Workbook

Sheet 特性表
A1: 特性ID | B1: 特性名词 | C1: 特性描述 | D1: 实现细节 | E1: 分类(用于美术分类） | F1: Icon
A2: 1 | B2: 入场 | C2: 进入战场时触发 | D2: 被召唤入场，发射入场，移出后移入等都会触发 | E2: 扳机
A3: 2 | B3: 持续 | C3: 每个我方回合触发 | E3: 扳机 | J3: 4
A4: 3 | B4: 临时 | C4: 使用卡牌后消失，不进入弃牌堆，回合结束未使用也消失 | E4: 卡片属性 | F4: =_xlfn.DISPIMG("ID_546E2A9585AC483F88F79B1B0FABC91A",1) -> =DISPIMG("ID_546E2A9585AC483F88F79B1B0FABC91A",1)
A5: 4 | B5: 消耗 | C5: 移出本场战斗，不再抽到 | D5: 进入消耗堆，消耗堆不展示给玩家 | E5: 卡片属性 | F5: =_xlfn.DISPIMG("ID_41892C5987A24E9D8B5B91A5BF98D2B7",1) -> =DISPIMG("ID_41892C5987A24E9D8B5B91A5BF98D2B7",1)
A6: 5 | B6: 弹射 | C6: 默认状态，可以和任何实体碰撞 | E6: 单位（固有机制）
A7: 6 | B7: 穿透 | C7: 可穿透生物单位继续前进，但会被场景物件阻挡并反弹 | E7: 单位（固有机制） | F7: =_xlfn.DISPIMG("ID_5FE4F3319B1340A0A1AA8B69BA6A64D9",1) -> =DISPIMG("ID_5FE4F3319B1340A0A1AA8B69BA6A64D9",1)
A8: 7 | B8: 穿透{0} | C8: 最多可穿透{0}个单位 | E8: 单位（固有机制）
A9: 8 | B9: 场景穿透 | C9: 可穿透任何东西，永远是一条直线 | D9: 隐藏属性，不展示给玩家，会有宽度参数 | E9: 单位（固有机制） | F9: =_xlfn.DISPIMG("ID_379C38818A72462381D5A5FA72F2772D",1) -> =DISPIMG("ID_379C38818A72462381D5A5FA72F2772D",1)
A10: 9 | B10: 触发 | C10: 命中首个单位时触发效果 | E10: 扳机
A11: 10 | B11: 跟随 | C11: 打出时，跟随目标向打出方向位移 | D11: 位移力度根据不同情况配置 | E11: 单位（针对友方）
A12: 11 | B12: 停止 | C12: 首次发射停止后，产生XX效果 | D12: 最晚回合结束 | E12: 扳机
A13: 12 | B13: 圣盾 | C13: 抵挡一次伤害后消失，不可叠加 | D13: 抵挡伤害本质是将伤害变为0，仍算一次伤害，会触发伤害次数+1。本质为持续性效果，可被沉默等效果移除 | E13: 单位（针对友方） | F13: =_xlfn.DISPIMG("ID_C8C750FDD3534A9889D7EE7B2118CEA7",1) -> =DISPIMG("ID_C8C750FDD3534A9889D7EE7B2118CEA7",1)
A14: 13 | B14: 吸血 | C14: 造成伤害会为自身回复等量血量 | E14: 单位（针对敌方） | F14: =_xlfn.DISPIMG("ID_CA739DAFEB6E440EA04AC5D75AD83F16",1) -> =DISPIMG("ID_CA739DAFEB6E440EA04AC5D75AD83F16",1)
A15: 14 | B15: 剧毒 | C15: 造成伤害时直接消灭对方随从单位（非英雄） | D15: 攻击圣盾时不触发 | E15: 单位（针对敌方）
A16: 15 | B16: 回归 | C16: 满足特定条件，可以回到手牌 | D16: 重置为初始状态 | E16: 单位（固有机制）
A17: 16 | B17: 连发{0} | C17: 当前回合已经打出{0}张牌时生效该效果 | D17: 不算本身 | E17: 扳机
A18: 17 | B18: 激励 | C18: 在场时释放英雄技能时触发该效果 | E18: 扳机
A19: 18 | B19: 过载{0} | C19: 下回合英雄能量获取下降{0} | E19: 卡片属性
A20: 19 | B20: 任务 | C20: 完成任务后会获得奖励 | E20: 单位（无针对）
A21: 20 | B21: 招募 | C21: 从牌库中召唤一个特定条件的生物 | E21: 单位（无针对）
A22: 21 | B22: 复活 | C22: 首次死亡后以一点血量复活 | E22: 单位（固有机制）
A23: 22 | B23: 技能触发 | C23: 打出技能牌后触发效果，每回合只能触发一次 | E23: 扳机
A24: 23 | B24: 变形 | C24: 变形为一个指定对象 | D24: 不算死亡，等于替换为另一个单位，也不触发入场效果 | E24: 单位（无针对）
A25: 24 | B25: 发现 | C25: 从三张特定类型的卡中选择一张 | E25: 卡片属性
A26: 25 | B26: 沉默 | C26: 移除生物牌上的效果，包括所有增益和减益效果 | D26: 不影响当前血量，相当于一个初始进入场上的不带技能的版本 | E26: 单位（无针对）
A27: 26 | B27: 控制 | C27: 获得对方生物的控制权 | E27: 单位（针对敌方）
A28: 27 | B28: 移回手牌 | C28: 卡牌以初始状态移回手牌 | E28: 单位（无针对）
A29: 28 | B29: 移回牌库 | C29: 卡牌以初始状态移回抽牌库 | E29: 单位（无针对）
A30: 29 | B30: 丢弃卡牌 | C30: 选择特定卡牌丢入弃牌库 | D30: （可以是手牌或抽牌库） | E30: 卡片属性
A31: 30 | B31: 磨灭卡牌 | C31: 将特定卡牌移出本场战斗 | E31: 卡片属性
A32: 31 | B32: 技能免疫 | C32: 无视技能卡效果 | E32: 单位（针对友方）
A33: 32 | B33: 恐惧 | C33: 每回合首次开始移动时，施加一个随机方向的力 | D33: （移动方向变得随机） | E33: 单位（无针对）
A34: 33 | B34: 揭示{0} | C34: 随机从牌库中抽{0}张展示给双方 | D34: ，若没有其他操作，就洗回牌库。对该牌有其他操作，则打断洗回牌库 | E34: 卡片属性
A35: 34 | B35: 复制 | C35: 复制单位继承本体的特性和持续效果 | D35: 复制的卡牌同理，一模一样，只是多一个复制标签，表现也稍有不同，名字也改为XX的复制，额外的，复制有一个复制标签，用做某些逻辑判断。例如复制标签无法被复制 | E35: 卡片属性 | F35: =_xlfn.DISPIMG("ID_D40DEA4F8DA541AAB8904B6DA3B28089",1) -> =DISPIMG("ID_D40DEA4F8DA541AAB8904B6DA3B28089",1)
A36: 35 | B36: 亡语 | C36: 死亡时触发效果 | D36: 死亡是指血量归零或被消灭，放逐变形等不算 | E36: 单位（固有机制）
A37: 36 | B37: 保留 | C37: 回合结束时保留在手牌中 | D37: 不进弃牌堆 | E37: 卡片属性 | F37: =_xlfn.DISPIMG("ID_580FBEEFD99F44A1ADCF432152D5E945",1) -> =DISPIMG("ID_580FBEEFD99F44A1ADCF432152D5E945",1)
A38: 37 | B38: 铁壁{0} | C38: 每层抵消一次碰撞伤害 | D38: 非碰撞伤害无效，0攻碰撞不消除铁壁 | E38: 单位（针对友方）
A39: 38 | B39: 引导 | C39: 碰到的第一个单位停下时，目标向其位移 | E39: 单位（无针对）
A40: 39 | B40: 激怒 | C40: 向最近的敌方单位移动 | D40: 没有其他前缀限定时，即时生效 | E40: 单位（针对敌方）
A41: 40 | B41: 唯一 | C41: 我方场上存在同名单位时，无法抽到该卡 | D41: 暂时移到一个隐藏的牌堆，不参与抽卡即可，该单位死亡时，移回弃牌堆即可。加入三选一后，买到唯一卡直接给战场中的对应单位升级
A42: 41 | B42: 指定 | C42: 拖拽到战场指定位置生效 | D42: 需要检测位置是否合法 | E42: 单位（无针对） | F42: =_xlfn.DISPIMG("ID_94AAB0458B7F420EA76325C64E01B6C2",1) -> =DISPIMG("ID_94AAB0458B7F420EA76325C64E01B6C2",1)
A43: 42 | B43: 献祭{0} | C43: 入场时随机牺牲{0}个友方随从单位，触发效果，若不足{0}个则不触发 | D43: 可以有多个不同参数的献祭词条，达成都触发
A44: 43 | B44: 点燃 | C44: 点燃状态，每个回合结束时，受到最大生命值百分之{0}的伤害 | D44: 单位碰撞会传导点燃状态。隐藏参数{1}个回合后结束buff，数值可配系统表，并且未来战中和战前可变化，再次挂上同一个状态会刷新结束条件。当目标单位身上有buff时尝试挂另一个buff的规则，具体见涌现设计 | E44: 单位（针对敌方） | F44: =_xlfn.DISPIMG("ID_F489C4BF30134C3991056A3BA6E6744F",1) -> =DISPIMG("ID_F489C4BF30134C3991056A3BA6E6744F",1)
A45: 44 | B45: 冻结 | C45: 冻结状态，无法移动，受到所有碰撞伤害增加百分之{0} | D45: 隐藏参数{1}次碰撞后结束冻结状态，当挂上新的冻结时会刷新这个次数，同上，元素反应参考涌现设计 | E45: 单位（针对友方） | F45: =_xlfn.DISPIMG("ID_6A9F6F2B73774BBB8E85C5D052B66669",1) -> =DISPIMG("ID_6A9F6F2B73774BBB8E85C5D052B66669",1)
A46: 45 | B46: 潮湿 | C46: 潮湿状态，将和各种元素产生一定反应 | D46: 隐藏参数{0}个回合后结束buff，元素反应参考涌现设计 | E46: 单位（针对友方） | F46: =_xlfn.DISPIMG("ID_5D02346217D34DD3AA142E19E19C49B1",1) -> =DISPIMG("ID_5D02346217D34DD3AA142E19E19C49B1",1)
A47: 46 | B47: 漏油 | C47: 漏油状态，每移动{0}米，受到最大生命值百分之{1}的伤害 | D47: 隐藏参数受到{2}次漏油伤害后结束漏油状态，并会在移动路径上留下有一定宽度的油地面。元素反应参考涌现设计 | E47: 单位（针对敌方） | F47: =_xlfn.DISPIMG("ID_B59C8A0334E143E69F78107819AC970F",1) -> =DISPIMG("ID_B59C8A0334E143E69F78107819AC970F",1)
A48: 47 | B48: 电击伤害 | C48: 电击伤害会对所有同一片液体地面上的单位造成连锁伤害 | D48: 伤害暂定一致；相连的地面就算是一片，不需要类型相同。冻结的冰地面算固态地面，不会导电。元素反应参考涌现设计 | E48: 单位（无针对） | F48: =_xlfn.DISPIMG("ID_60A86A4091584061A8A219D0DED6E6BC",1) -> =DISPIMG("ID_60A86A4091584061A8A219D0DED6E6BC",1)
A49: 48 | B49: 水地面 | C49: 液态地面，导电，进入水地面的单位尝试挂上潮湿buff，摩擦减少{0} | D49: 元素反应参考涌现设计
A50: 49 | B50: 血液地面 | C50: 液态地面，导电，进入血液地面的单位尝试挂上潮湿buff，摩擦减少{0} | D50: 元素反应参考涌现设计
A51: 50 | B51: 冰地面 | C51: 固态地面，不导电，进入冰地面，摩擦减少{0} | D51: 元素反应参考涌现设计
A52: 51 | B52: 火焰地面 | C52: 气态地面，不导电，进入火焰地面的单位尝试挂上点燃buff | D52: 元素反应参考涌现设计
A53: 52 | B53: 眩晕 | C53: 禁用单位效果，碰撞{0}次后恢复 | D53: 单位特性描述中的效果，不包含已有的属性增减益，眩晕可叠加，敌我双方和撞墙都算，每次碰撞减去一层眩晕 | E53: 卡片属性 | F53: =_xlfn.DISPIMG("ID_49B353FE784746EEBA3A25227A63675F",1) -> =DISPIMG("ID_49B353FE784746EEBA3A25227A63675F",1)
A54: 53 | B54: 连击 | C54: 单回合内，我方碰撞敌方的总次数 | E54: 单位（固有机制） | F54: =_xlfn.DISPIMG("ID_5840427C5BC4479E846340751E4FA305",1) -> =DISPIMG("ID_5840427C5BC4479E846340751E4FA305",1)
A55: 54 | B55: 雨天 | C55: 潮湿的雨天，似乎对元素反应有一些影响 | D55: 元素反应参考涌现设计 | E55: 单位（无针对） | F55: =_xlfn.DISPIMG("ID_A912E88FF780433784976E04CB4BEC01",1) -> =DISPIMG("ID_A912E88FF780433784976E04CB4BEC01",1)
A56: 55 | B56: 雷雨天 | C56: 打雷的雨天，似乎有些危险 | D56: 元素反应参考涌现设计
A57: 56 | B57: 连射 | C57: 拖拽入场选择方向，即可连续发射弹药 | D57: 发射前有固定延迟前摇{0}，子弹发射间隔{1}，弹药耗尽则卡牌使用完毕，松手时，按该方向继续发射弹药，再次点击屏幕，则方向移到点击处。移回卡牌时，保留当前弹药，下次发射继续。 | E57: 卡片属性 | F57: =_xlfn.DISPIMG("ID_86A9089201EC4ED993A9CDC6AFD773C6",1) -> =DISPIMG("ID_86A9089201EC4ED993A9CDC6AFD773C6",1)
A58: 57 | B58: 继承 | C58: 打出时场上如果存在同名友方，吸收其所有当前属性 | D58: 所有同名，攻击血量都吸收，注意是当前属性，并且杀死这些友方 | E58: 单位（针对友方） | F58: =_xlfn.DISPIMG("ID_5F374BE24E2A4C4DA1EC5D86BE28ABC7",1) -> =DISPIMG("ID_5F374BE24E2A4C4DA1EC5D86BE28ABC7",1)
A59: 58 | B59: 先锋 | C59: 开始战斗首个回合优先抽取 | D59: 若带多张，超过首回合抽牌数，则从这几张里随机
A60: 59 | B60: 英雄 | C60: 英雄死亡，英雄卡会回归牌库，可再次抽到 | E60: 单位（无针对） | F60: =_xlfn.DISPIMG("ID_F50943464F0B42649FF9DA6E09D9AB71",1) -> =DISPIMG("ID_F50943464F0B42649FF9DA6E09D9AB71",1)
A61: 60 | B61: 油地面 | C61: 遇到火焰或爆炸，产生爆炸，单位进入油地面，摩擦减少{0} | D61: 爆炸伤害{1}，爆炸范围{2}，每单个地面触发一次爆炸，触发爆炸有所延迟，延迟时间{3}
A62: 61 | B62: 爆炸 | C62: 造成范围伤害，并推开四周单位 | D62: 每个爆炸自己配自己的力 · 爆炸归属： 我方回合，无论爆炸的来源为何，所有爆炸均属于我 敌方回合，无论……，属于敌方 示例：我方回合，我放置了炸药桶，该炸药桶在敌方回合引爆，则此爆炸属于敌方 · 属于我的爆炸： 1. 敌方单位受到伤害、推力，我方单位不受伤，但受到推力 2. 爆炸相关参数受我方正面效果、敌方负面效果（无）影响，如我方露娜增加爆炸范围、我方电池焦耳增加爆炸伤害。敌方露娜、敌方电池焦耳是无关项 3. 只触发我方的爆炸收益，如露娜的“每触发一次爆炸，爆炸范围增加”、蜡烛的“每有一次爆炸，英雄生命增加” | E62: 单位（无针对） | F62: =_xlfn.DISPIMG("ID_C2EE5D420A984757BAD39E8AA79301B6",1) -> =DISPIMG("ID_C2EE5D420A984757BAD39E8AA79301B6",1)
A63: 62 | B63: 分裂 | C63: 分裂体无技能效果，和本体均分属性，本体死亡时，随机分裂体变为本体 | D63: 常见效果描述为“某人分裂出N个分裂体”，某人=分裂对象，N=分裂数量 · 分裂： 1个本体替代分裂对象，场上新增N个分裂体 本体保留分裂对象的卡牌效果、位置、状态；分裂体分布在本体周围（缺），初始无卡牌效果与状态 分裂体攻击 = MAX(1,分裂对象攻击/(N+1))，四舍五入取整 本体攻击 = MAX(1, 分裂对象攻击 - 分裂体攻击*N) 分裂体生命上限、当前生命计算同攻击 本体和分裂体的物理属性均与分裂对象相同，但受战力影响，大小和质量会被缩放 若分裂对象分裂时正在运动，（缺） 分裂出的分裂体是新入场单位，可触发形如“我方单位入场时获得圣盾”的效果；本体不是新入场单位，不可触发 · 示例： 37攻击、247/333生命的电池焦耳（在场时爆炸伤害增加）分裂出5个分裂体 分裂后，分裂体属性6攻击、41/56生命；本体属性7攻击、42/53生命 本体名为“电池焦耳”，身上有在场时爆炸伤害增加的卡牌效果 分裂体名为“电池焦耳（分裂体）”，无卡牌效果 · 分裂体类型： 分裂对象是英雄或英雄的分裂体，分裂体属于随从 分裂对象是随从，分裂体属于随从 分裂对象是雇佣兵，分裂体属于雇佣兵 · 分裂对象是分裂体： 分裂对象可以是任何单位（英雄、随从、雇佣兵、分裂体） 分裂体被分裂时，计算属性的方法如常，但新的本体/分裂体均记为老本体的分裂体 接上文案例，电池焦耳已被分成： 本体：电池焦耳，7攻击、42/53生命 5个分裂体：电池焦耳（分裂体），6攻击、41/56生命 某一电池焦耳（分裂体）受到效果“分裂出1个分裂体”的影响后，场面上有： （不变）本体：电池焦耳，7攻击、42/53生命 4个大分裂体：电池焦耳（分裂体），6攻击、41/56生命 1个小分裂体：电池焦耳（分裂体），3攻击、21/28生命 —— 由分裂体的属性公式算出 另1个小分裂体：电池焦耳（分裂体），3攻击、20/28生命 —— 由本体的属性公式算出 · 分裂对象是英雄： 1. 直接对英雄造成的增益或负面效果，只对本体有效，如“从我方血量最高随从转移{0}生命到我方英雄身上”、“燃烧英雄10点生命”、“我方英雄获得连击数翻倍”、“我方英雄攻击+3”、“敌方英雄攻击-3” 2. 需要选取目标的效果，以本体作为目标，如“回合开始时向敌方英雄开炮”、“以我方英雄为中心，对范围内……”、“所有我方单位粘合到英雄上” 3. 以英雄数据作为判定条件的，只判定本体，如“我方英雄首次生命将至一半以下时，……”、“我方英雄每次受伤，……” · 收回： 默认将所有分裂体回收到本体，暂不考虑只收回部分的情况 “收回”后的分裂对象，保留本体的卡牌效果、位置、状态（流血/潮湿/被吞噬等），丢弃分裂体的上述信息 攻击 = 本体攻击 + ∑所有分裂体的攻击，当前生命、生命上限同理 在分裂到收回期间，若有本体或分裂体死亡，分裂对象会相应损失一部分属性 分裂体被收回属于离场，可触发形如“每有一个我方单位离场……”的效果，但不属于死亡。本体只有死亡时算作离场 · 死亡： 分裂期间，本体死亡，则随机分裂体成为本体，获得分裂对象的卡牌效果 · 复制： 被复制的本体，视作一个全新单位 被复制的分裂体，若阵营未变，仍视作对应本体的分裂体；若阵营变更（如夺魂），则视作全新单位 若为“原始版复制”，则都视作全新单位 · 吞噬： 被吞者是分裂对象，分裂后本体保留被吞状态，分裂体脱离被吞，分布在吞噬者周围 被吞者是本体，触发收回时保留被吞状态，等于所有分裂体主动进吞噬者的肚子 被吞者是分裂体，收回时摆脱吞噬 | E63: 卡片属性 | F63: =_xlfn.DISPIMG("ID_2126AC54262D45F1AC0F44F92328BA7C",1) -> =DISPIMG("ID_2126AC54262D45F1AC0F44F92328BA7C",1)
A64: 63 | B64: 吞噬 | C64: 被吞噬单位效果仍在，每次只能吞噬一个单位，吞噬了其他单位后不能被吞噬 | D64: 1.吞噬对象： 注意吞噬限定的对象 制作吞噬类的技能时，需要特别限定可以被吞噬的对象，防止出现问题 吞噬雇佣兵，雇佣兵会在回合结束时离场，结束吞噬状态 2.吞噬后，被吞噬单位和吞噬单位的机制： 被吞噬单位和吞噬单位的机制都会继续生效 每次只能吞噬一个单位，吞噬了其他单位后不能被吞噬 3.吞噬后的属性、伤害等计算规则： 对单体的指向性攻击，如果通过吞噬的单位与被吞噬的单位交互，就能参与外界的运算 如果是全场的AOE技能，被吞噬的单位就无法与外界进行交互 情况1：刀鞘（10068）吞噬了一个单位A，获得他的攻击，接力棒会碰撞刀鞘时会获得（刀鞘+单位A）的部分攻击，单位A被吐出来后，是被接力棒偷走攻击后的基础属性 情况2：玩家使用核武对全场进行伤害，被吞噬的单位A不会受到这个伤害 4.吞噬时，被吞噬单位的位置处理 吞噬时不影响位移方向和力度 5.吞噬结束后，被吞噬单位的位置处理 单位死亡时吐出，不施加额外的力，在附近生成即可 如果需要施加额外的力，则需要在技能上额外加描述以突出 6.两个都带有吞噬效果的单位，互相首次碰撞，算谁吞谁 情况1：如果一张牌A在手牌中，一张牌B在场上，则手牌后打出的吞噬场上先打出的 情况2：如果两个都在场上，利用类似引力炸弹这类技能触发碰撞，需要和程序确认下碰撞器的先后逻辑，先触发吞噬效果的吞噬后触发效果的 7.复制 情况1：单位A吞噬单位B，使用有丝分裂复制单位A时，为了保持和20063统一，单位B不跟随一起复制，只复制A，这样会有一个单位A吞噬单位B，另外一个单位A没有吞噬对象 情况2：单位A吞噬单位B，使用复制（20063）复制单位A时，因为需要复制到手牌里，所以单位B不跟随复制 8.融合 情况1：使用20068集合时，单位A1吞噬了单位B，单位A2吞噬了单位C，单位A3吞噬了单位D，使用后随机选取一个单位A，吸取其他单位A的属性，然后杀死其他的单位A，解放对应吞噬的单位，但是被选中的单位A仍然吞噬着原来的单位 情况2：使用20068集合时，B吞了A1，C吞A2，D吞A3，集合对A无效，不能融合。因为吞噬相当于把单位移除场内，不能被直接调用生效 9.单位装填炮 情况1：单位A吞噬单位B，也有概率被装填到炮弹里被发射出去，此时被视为1个单位 10.吞噬后的单位状态 吞噬后的单位算作离场状态，需要触发离场相关的效果 | E64: 单位（无针对） | F64: =_xlfn.DISPIMG("ID_F3D14E0C2D634E0F9D818550D406F768",1) -> =DISPIMG("ID_F3D14E0C2D634E0F9D818550D406F768",1)
A65: 64 | B65: 虚化 | C65: 无法碰撞或被碰撞，但受到双倍伤害，下个我方回合开始时恢复 | E65: 单位（无针对）
B72: 抗魔力场 | C72: 只会受到碰撞伤害
B73: 缓冲护盾 | C73: 免疫碰撞伤害
B74: 超载 | C74: 使用后从牌库移除

Sheet check_info
A1: 一级ID | B1: 是否注释 | C1: 卡牌名 | D1: 技能效果
A2: 10010 | C2: 电吉他 和鸣 | D2: 回合结束时：我方每有一个在场单位，为我方英雄永久+{0}生命
A3: 10011 | C3: 纸巾 缠缠 | D3: 对同一敌方单位每多碰撞一次，伤害增加{0}%
A4: 10012 | C4: 摩托 赤狸 塞琳娜 | D4: 首次碰撞友方时，对其施加推力
A5: 10013 | C5: 雨伞 守心 布洛莉Brolly | D5: 碰撞友方时，为其添加圣盾
A6: 10014 | C6: 茶壶 灵愈 波西娅Potsia | D6: 碰撞友方时，为其恢复{0}点生命
A7: 10015 | C7: 留声机 回音 玛利亚 | D7: 回合结束时：对随机敌方单位造成{0}点伤害，每有{1}连击，伤害+{2}
A8: 10016 | C8: 电扇 彩虹 | D8: 在场时：我方打出的卡牌发射速度增加{0}%
A9: 10017 | C9: 电池 欧姆 | D9: 在场时：我方每获得{0}次连击数，额外获得{1}次连击
A10: 10018 | C10: 萨克斯 莉莉（Lily was here） | D10: 我方回合：每有我方单位离场时，我方英雄回复{0}点生命
A11: 10019 | C11: 电池 焦耳 | D11: 在场时：我方所有爆炸伤害增加{0}%
A12: 10020 | C12: 时钟 晨曦 | D12: 本局战斗：每打出一次，攻击力永久+{0}
A13: 10021 | C13: 自动铅笔 追忆 | D13: 在场时：每有一个我方单位入场，对随机敌方单位造成{0}伤害
A14: 10022 | B14: ## | C14: 橡皮 忘怀 | D14: 继承，我方回合，牺牲所有碰到的友方随从单位，获得其{0}%的当前属性
A15: 10023 | C15: 牙膏 露洁 爱丽儿（Ariel 小美人鱼） | D15: 回合结束时：分裂出{0}个分裂体
A16: 10024 | C16: 书 幻梦 仙蒂瑞拉 | D16: 回合结束时：牺牲英雄{0}点生命，抽{1}张牌
A17: 10025 | C17: 电池 伏特 | D17: 在场时：我方英雄获得连击数翻倍
A18: 10026 | C18: 功能饮料 牛红 | D18: 碰撞友方时：为该友方永久增加{0}点攻击力
A19: 10027 | B19: ## | C19: 牛奶 银河 | D19: 在场时：我方英雄获得吸血，每回合吸血上限为{1}
A20: 10028 | C20: 羽毛球 拉丽（英文就rally连续得分的意思） | D20: 打出时：有{0}%几率回到手牌，每次打出几率下降{1}%
A21: 10029 | C21: 姨妈巾 玫瑰 | D21: 回合结束时：根据我方牺牲总生命的{0}%，为我方英雄永久增加生命
A22: 10030 | C22: 军鼓 震声 | D22: 回合结束时：每有一个我方单位，对随机敌方单位造成一次{0}点伤害
A23: 10031 | C23: 注射器 针妮 佩妮（英文penny，联想小针） | D23: 每次碰撞我方：牺牲其{0}点生命，并为我方英雄永久加{1}生命
A24: 10032 | B24: ## | C24: 自行车 闪电 | D24: 首次碰撞随从单位时，施加一个较大的力
A25: 10033 | C25: 蜡烛 热泪 | D25: 在场时：每有一次爆炸，我方英雄生命+{0}
A26: 10034 | C26: 电钻 螺旋 | D26: 使碰撞到的敌方单位漏油
A27: 10035 | C27: 纯净水 浅浅 | D27: 无
A28: 10036 | C28: 纯净水 满满 | D28: 无
A29: 10037 | C29: 红汽水 浅浅 | D29: 无
A30: 10038 | B30: ## | C30: 红汽水 满满 | D30: 无
A31: 10039 | C31: 绿汽水 浅浅 | D31: 无
A32: 10040 | B32: ## | C32: 绿汽水 满满 | D32: 无
A33: 10041 | B33: ## | C33: 肥皂 滑滑 | D33: 降低自身摩擦力{0}%
A34: 10042 | C34: 刀 藏锋 | D34: 回合结束时：若连击数是单数，为我方英雄增加连击数*{0}%的攻击，若是双数，增加连击数{1}%的生命
A35: 10043 | C35: 刀 百炼 | D35: 每达成{0}连击，为生命百分比最低的我方回复{1}生命
A36: 10044 | C36: 煤油灯 流露 | D36: 首次碰撞后漏油，移动时留下油地面
A37: 10045 | C37: 盔甲 怀抱 | D37: 在场时：为所有我方分担{0}%的伤害，场上每有一个我方，自身忽略{1}%的伤害，最高忽略{2}%
A38: 10046 | C38: 啤酒瓶 破碎 | D38: 自身造成的连击数增加{0}%
A39: 10047 | B39: ## | C39: 暂时不做 | D39: 0
A40: 10048 | B40: ## | C40: 储蓄罐 珠珠 | D40: 0
A41: 10049 | B41: ## | C41: 夹子 瑾瑾 | D41: 对方舟和场景物件造成的伤害额外增加{0}%
A42: 10050 | C42: 茶包 小茗 | D42: 每碰撞一次友方，牺牲自身{0}%最大生命，为友方回复对应生命
A43: 10051 | C43: 气球 飘舞 | D43: 蓄力{0}回合后爆炸，造成{1}伤害
A44: 10052 | C44: 传奇飞行员 舰长 | D44: 每打出{0}张卡，获得一张炸蛋
A45: 10053 | C45: 黏黏女王 宁芙（Nymph） | D45: 打出时，回合开始时：收回自身分裂体，再分裂出{0}个分裂体
A46: 10054 | C46: 最强盗贼王 露娜（Luna） | D46: 回合结束时：对随机敌方单位发射导弹造成{0}点爆炸伤害。我方每触发一次爆炸，范围永久增加{3}
A47: 10055 | C47: 轻灵跃影 乔艾塔（Joetta） | D47: 我方回合开始时：向最近的敌方单位冲刺，回合结束时，每有{1}连击，自身攻击加{2}，生命加{3}
A48: 10056 | C48: 致命拥抱 维纳斯（Venus） | D48: 打出时：化作无法移动的花朵形态，我方回合盛开，无视吞噬规则吞噬碰到的任意单位，对敌方造成攻击力{0}%的伤害，为友方恢复攻击力{1}%的生命，然后吐出
A49: 10057 | C49: 环绕之蛇 娜吉尼（Nagini） | D49: 打出时：化作大蛇，我方回合每击杀一个单位，生命+{0}，并发射超电磁炮，伤害为自身攻击的{1}%
A50: 10058 | C50: 群蜂之母 梅丽莎（Melissa） | D50: 额外获得自身已损失生命{0}%的攻击，每次碰撞敌方单位，根据造成伤害的{1}%回复自身生命
A51: 10059 | C51: 鞭炮 噼啪 | D51: 我方回合：每个我方首次被爆炸击中，该我方位置触发一次爆炸，伤害为{0}
A52: 10060 | C52: 爆米花 酥脆 | D52: 我方回合：我方每被爆炸击中一次，该我方回复{0}点生命
A53: 10061 | C53: 红汽水 满满（复用） | D53: 每次碰撞敌方单位触发一次爆炸，伤害为{0}
... A65: 10073 | C65: 储蓄罐 珠珠（复用） | D65: 在场时：我方每有一次吞噬，我方英雄获得{0}点攻击，{1}点生命，被吞噬时，效果翻倍
A66: 10074 | B66: ## | C66: 扫把 | D66: 我方回合我方单位离场时，我方英雄回复{0}点生命
A67: 10075 | C67: 菠菜罐头 大力 | D67: 在场时：所有我方攻击增加{0}，被吞噬时，效果翻倍
A68: 10076 | C68: 仓鼠 囤囤 | D68: 回合结束时：我方已吞噬别人和被吞噬的单位生命永久增加{0}，被吞噬时，效果翻倍
A69: 10077 | C69: 接力棒 传承 | D69: 首次碰到友方时：获得其{0}%的攻击力
A70: 10078 | C70: 冰淇淋 甜霜 | D70: 经过液体地面时：将地面冻结
A71: 10079 | C71: 炸蛋 | D71: 碰到敌方后爆炸，对周围敌方和自身造成{0}点伤害
A72: 10080 | C72: 安全帽 小橘 | D72: 我方单位入场时：入场单位获得一个圣盾
A73: 20010 | C73: 切分 | D73: 场景穿透，将经过的我方非复制随从单位切成两个较小的复制单位，属性为原单位的{2}%
A74: 20011 | C74: 魅惑 | D74: 指定战场任意位置，敌方英雄向该位置位移
A75: 20012 | C75: 弹射锯片 | D75: 穿透，造成{0}伤害，每穿透一个单位伤害增加{1}%
A76: 20013 | C76: 自制手雷 | D76: 碰到首个敌方时，对范围内的敌方造成{0}伤害
A77: 20014 | C77: 见证我！ | D77: 杀死我方生命最低的随从，对周围敌方造成{0}点伤害
A78: 20015 | B78: ## | C78: 英勇祝福 | D78: 本回合，所有我方单位攻击力临时提升{0}，回合结束恢复
A79: 20016 | C79: 引力炸弹 | D79: 以我方英雄位置为中心，产生一个引力
A80: 20017 | C80: 精准爆破 | D80: 指定战场位置，生成{1}个爆炸桶，爆炸伤害为{2}
A81: 20018 | B81: ## | C81: 引导 | D81: 碰到首个单位时，我方英雄向其位移
A82: 20019 | B82: ## | C82: 变大！ | D82: 使碰撞的首个单位变大{0}%
A83: 20020 | B83: ## | C83: 缩小！ | D83: 使碰撞的首个单位变小{0}%
A84: 20021 | C84: 精准引导 | D84: 指定战场任意位置，我方英雄向该位置位移
A85: 20022 | B85: ## | C85: 蓄力 | D85: 下一张打出的卡牌，发射速度增加{0}%
A86: 20023 | C86: 弹簧安装 | D86: 指定战场位置，生成一个弹簧，被单位碰撞到时施加弹力
A87: 20024 | C87: 裂地斩 | D87: 场景穿透，路径上产生一条裂缝，受到{1}点伤害后消失
A88: 20025 | C88: 修建工事 | D88: 在战场中间产生一堵由障碍物组成的墙，墙体血量为{1}
A89: 20026 | C89: 风暴针刺 | D89: 根据本回合已打出的牌数，发射数根能量针，每个造成{0}点伤害
A90: 20027 | B90: ## | C90: 嗜血杀戮 | D90: 保留，本回合接下来的时间，我方英雄每杀死一个单位，攻击力永久增加{0}
A91: 20028 | B91: ## | C91: 冰冻炸弹 | D91: 碰到首个敌方时，对范围内的敌方单位造成{0}点伤害并冻结
A92: 20029 | B92: ## | C92: 人工降雨 | D92: 召唤雨天天气，回合结束消散
A93: 20030 | C93: 雷枪 | D93: 指定位置，召唤一道雷电，对最近的敌方单位造成一次{0}点电击伤害
A94: 20031 | B94: ## | C94: 滋水 | D94: 对触碰的首个敌方单位造成{0}点伤害，并赋予潮湿状态
A95: 20034 | C95: 补水计划 | D95: 保留，打出时每有一个敌方单位，手牌中生成一张临时的纯净水-浅浅
A96: 20035 | C96: 冰霜新星 | D96: 冻结场上的所有单位
A97: 20036 | C97: 巨雷枪 | D97: 场景穿透，对敌方单位造成{0}点电击伤害，每穿过一个敌方，生成一张临时的雷枪
A98: 20037 | C98: 投石支援 | D98: 指定战场任意位置，对范围内的敌方单位造成{0}点伤害并眩晕{1}层
A99: 20038 | C99: 飞砖 | D99: 碰到首个敌方单位时，对其造成{0}点伤害并眩晕{1}层
A100: 20039 | C100: 战术核武 | D100: 保留，对所有单位和场景物件造成{0}点伤害并点燃
A101: 20040 | B101: ## | C101: 混乱补给 | D101: 在随机空地召唤{0}个礼物盒，被碰撞若干次后打开，打开的玩家获得随机奖励
A102: 20041 | C102: 冰冻陷阱 | D102: 在随机空地召唤{0}个陷阱，将敌方单位推入时造成{1}伤害，眩晕{2}层并冻结，陷阱触发后消失
A103: 20042 | B103: ## | C103: 协力攻击 | D103: 穿透，对碰到的第一个敌方单位，造成路径上经过所有我方单位攻击{0}%的伤害
A104: 20043 | C104: 爆裂药瓶 | D104: 碰到首个单位时，回复范围内的我方单位{0}点生命
A105: 20044 | C105: 胡乱抓挠 | D105: 对随机敌方单位造成{0}次{1}点伤害，同一敌方单位每被击中一次，该伤害增加{2}%
A106: 20045 | B106: ## | C106: 接力 | D106: 穿透，碰到的第二个我方随从单位，吸收碰到的第一个我方随从单位{0}%的当前属性
A107: 20046 | C107: 重新出发 | D107: 碰到首个我方随从单位时，将其牺牲，并获得一张相同随从的临时卡
A108: 20047 | C108: 临摹 | D108: 保留，随机获得一张敌方手牌的临时复制
A109: 20048 | C109: 超电磁炮 | D109: 场景穿透，对敌方单位造成{0}点电击伤害
A110: 20049 | C110: 尖刺墙 | D110: 在我方方舟前生成一堵尖刺墙，墙体血量为{1}
A111: 20050 | C111: 海浪冲击 | D111: 召唤海浪
...

Sheet HUDBUFF表
C1: 📁 | D1: \\sznas\fileshare\战略孵化部\FrozenCats工作室\美术素材\切图（交付）\I 图标Icon\C 词条图标
A2: 对应ID | B2: Buff/DeBuff名词 | C2: Icon/表现 | D2: 显示权重 | E2: 展示位置 | F2: 计数方式 | G2: 计数逻辑 | H2: 作用目标 | I2: 技能效果
A3: 13 | B3: 吸血 | D3: 4 | E3: HUD栏 | F3: 不计数 | G3: 通用buff，单位拥有吸血状态时显示
A4: 43 | B4: 点燃 | D4: 3 | E4: HUD栏 | F4: 计算层数(倒数) | G4: 通用buff，用于计算燃烧状态的剩余回合数，角标数字显示剩余回合数
A5: 44 | B5: 冻结 | D5: 3 | E5: HUD栏 | F5: 计算层数(倒数) | G5: 通用buff，用于计算冻结状态解除所需的剩余碰撞次数
A6: 45 | B6: 潮湿 | D6: 2 | E6: HUD栏 | F6: 不计数 | G6: 通用buff，被附加潮湿状态时显示
A7: 46 | B7: 漏油 | D7: 3 | E7: HUD栏 | F7: 计算层数(倒数) | G7: 通用buff，用于计算漏油状态剩余可生效漏油伤害的次数
A8: 52 | B8: 眩晕 | D8: 3 | E8: HUD栏 | F8: 计算层数(倒数) | G8: 通用buff，用于计算眩晕状态解除所需的剩余碰撞次数
A9: 20015 | B9: 英勇祝福 | D9: 5 | E9: UIBUFF栏 | F9: 计时 | G9: 技能buff，用于计算英勇祝福剩余时间，使用倒计时方式计数
A10: 20022 | B10: 蓄力 | D10: 5 | E10: UIBUFF栏 | F10: 计算层数(倒数) | G10: 技能buff，用于计算蓄力剩余的生效次数
A11: 61 | B11: 露娜BUFF | D11: 6 | E11: HUD栏 | F11: 计算层数(正数) | G11: 角色buff，仅用于统计英雄露娜 Hero_2 的技能累计的爆炸伤害层数 | H11: 角色自己 | I11: =单位卡分表!P55 -> 回合结束时：对随机敌方单位发射导弹造成{0}点爆炸伤害。我方每触发一次爆炸，范围永久增加{3}
A12: 30002 | B12: 能量 | D12: 6 | E12: HUD栏 | F12: 计算层数(倒数) | G12: 角色buff，仅用于单位电池伏特 Card_Creature_25 的技能生效所需的出牌数，计数累加，每{0}层归0一次并发动技能
A13: 20003 | B13: 禁止移动 | D13: 1 | E13: HUD栏 | F13: 计算层数 | G13: 通用buff，仅用于处于禁止位移的单位，例如当前版本的英雄维纳斯 Hero_4
A14: 30003 | B14: 后攻 | D14: 6 | E14: UIBUFF栏 | F14: 计算层数(倒数) | G14: 后攻专属buff，计数写死固定5层，每次加能量演出时减少1层，也可根据当前回合数计算
A15: 30004 | B15: 纸巾 缠缠 增伤标记 | D15: 3 | E15: HUD栏 | F15: 计算层数(正数) | G15: 角色附加在别的单位上的临时buff，仅用于计算纸巾 Creature_10011 的技能对碰撞到的单位附加的伤害增加层数，回合结束后消失。 | H15: 纸巾 撞击的目标 | I15: =单位卡分表!P12 -> 对同一敌方单位每多碰撞一次，伤害增加{0}%
A16: 62 | B16: 分裂体 | D16: 4 | E16: HUD栏 | F16: 不计数 | G16: 通用buff，所有分裂体附带此buff，变为本体后buff消失。 | H16: 分裂体自己
A17: 30005 | B17: 军鼓 触发次数统计 | D17: 6 | E17: HUD栏 | F17: 计算层数(正数) | G17: Creature_10030 角色buff，仅在我方回合显示，我方回合内，实时更新计算当前场上我方单位数量（回合结束时会触发的攻击次数） | H17: 角色自己 | I17: =单位卡分表!P31 -> 回合结束时：每有一个我方单位，对随机敌方单位造成一次{0}点伤害
A18: 30006 | B18: 刀 百炼 连击触发计数 | D18: 6 | E18: HUD栏 | F18: 计算层数(倒数) | G18: Creature_10043 角色buff，仅在我方回合显示，我方回合内，计算触发技能效果所需的剩余连击次数。（到0时触发并刷新） | H18: 角色自己 | I18: =单位卡分表!P44 -> 每达成{0}连击，为生命百分比最低的我方回复{1}生命
A19: 30007 | B19: 气球 飘舞 爆炸倒计时 | D19: 6 | E19: HUD栏 | F19: 计算层数(倒数) | G19: Creature_10051 角色buff，持续展示，计算剩余的蓄力结束回合数。（到0时爆炸） | H19: 角色自己 | I19: =单位卡分表!P52 -> 蓄力{0}回合后爆炸，造成{1}伤害
A20: 30008 | B20: 舰长 炸弹获得计数 | D20: 6 | E20: HUD栏 | F20: 计算层数(倒数) | G20: Hero_10000 角色buff，持续展示，计算获得炸弹卡牌所需的剩余出牌张数。（到0时获得并刷新） | H20: 角色自己 | I20: =单位卡分表!P53 -> 每打出{0}张卡，获得一张炸蛋
A22: 63 | B22: 吞噬中 | D22: 4 | E22: HUD栏 | F22: 计算层数(正数) | G22: 通用buff，角色具有吞噬特性，且当前已有吞噬单位时，显示此Icon。 | H22: 角色自己 | I22: 0为未吞噬，非0为已吞噬，未吞噬Icon为632
A23: 30009 | B23: 电吉他 标记数 | D23: 6 | E23: HUD栏 | F23: 计算层数(正数) | G23: Creature_10010 角色buff，仅在我方回合显示，我方回合内，实时计算在场我方单位数量，回合结束触发技能时消失。 | H23: 角色自己 | I23: =单位卡分表!P11 -> 回合结束时：我方每有一个在场单位，为我方英雄永久+{0}生命
A24: 34 | B24: 复制体 | D24: 2 | E24: HUD栏 | F24: 不计数 | G24: 通用buff，角色是复制体。 | H24: 复制体自己

Sheet 单位卡分表
A1: 卡牌ID | B1: 卡牌名 | C1: 卡牌类型 | D1: 选项类型 | E1: 射击类型 | F1: 职业 | G1: 费用 | H1: 稀有度 | I1: 获取方式类型 | J1: AI目标规划 | K1: 瞄准线类型 | L1: 牌序规划标签 | M1: 等级上限 | N1: 英雄卡ID | O1: 版本过滤 | P1: 卡牌效果 | Q1: 效果备注 | R1: 卡牌效果2级 | S1: 2级效果备注 | T1: 卡牌效果3级 | U1: 3级效果备注 | V1: 流派归类（后续用作职业划分） | W1: 特性列表（特性ID） | Z1: Demo版本 技能表现 | AA1: 特效已加入？ | AB1: Demo版本 包装 | AC1: 一测版本 包装 | AE1: 失效次数 | AF1: 失效参数 | AG1: 技能类型 | AL1: 是否需要物理模拟
A2: 10001 | B2: 模版生物1 | C2: 1 | F2: 无 | G2: 1 | J2: 常规碰撞 | K2: 1 | L2: 5 | M2: 3 | O2: 0 | P2: 无 | Q2: 无 | AB2: 电视
A3: 10002 | B3: 模版生物2 | C3: 1 | F3: 无 | G3: 2 | J3: 常规碰撞 | K3: 1 | L3: 5 | M3: 3 | O3: 0 | P3: 无 | Q3: 无 | AB3: 水壶
A4: 10003 | B4: 模版生物3 | C4: 1 | F4: 无 | G4: 3 | J4: 常规碰撞 | K4: 1 | L4: 5 | M4: 3 | O4: 0 | P4: 无 | Q4: 无 | AB4: 剪刀
A5: 10004 | B5: 模版生物4 | C5: 1 | F5: 无 | G5: 4 | J5: 常规碰撞 | K5: 1 | L5: 5 | M5: 3 | O5: 0 | P5: 无 | Q5: 无 | AB5: 牙膏
A6: 10005 | B6: 模版生物5 | C6: 1 | F6: 无 | G6: 5 | J6: 常规碰撞 | K6: 1 | L6: 5 | M6: 3 | O6: 0 | P6: 无 | Q6: 无 | AB6: 鼠标
A7: 10006 | B7: 模版生物6 | C7: 1 | F7: 无 | G7: 6 | J7: 常规碰撞 | K7: 1 | L7: 5 | M7: 3 | O7: 0 | P7: 无 | Q7: 无
A8: 10007 | B8: 模版生物7 | C8: 1 | F8: 无 | G8: 7 | J8: 常规碰撞 | K8: 1 | L8: 5 | M8: 3 | O8: 0 | P8: 无 | Q8: 无
A9: 10008 | B9: 模版生物8 | C9: 1 | F9: 无 | G9: 8 | J9: 常规碰撞 | K9: 1 | L9: 5 | M9: 3 | O9: 0 | P9: 无 | Q9: 无
A10: 10009 | B10: 模版生物9 | C10: 1 | F10: 无 | G10: 9 | J10: 常规碰撞 | K10: 1 | L10: 5 | M10: 3 | O10: 0 | P10: 无 | Q10: 无
A11: 10010 | B11: 电吉他 和鸣 | C11: 1 | D11: 1 | E11: 1 | F11: 4 | G11: 5 | H11: 3 | I11: 0 | J11: 更多我方单位 | K11: 1 | L11: 5 | M11: 3 | O11: 1 | P11: 回合结束时：我方每有一个在场单位，为我方英雄永久+{0}生命 | Q11: 注意统一以造成的实际伤害论，打到1血单位，算造成1伤害 | V11: 1，5 | Z11: 每次触发对随机敌方造成伤害效果时，在受伤单位球处生成一个跟随球位移的攻击特效，并跳出伤害数字，特效播放完成后销毁 📦Effect_Creature15_Hit | AA11: 0 | AB11: 蜡烛（火苗） | AC11: 电吉他 | AG11: CollisionCauseDamage2RandomEnemy | AJ11: 2 | AL11: 1 | AM11: 1
A12: 10011 | B12: 纸巾 缠缠 | C12: 6 | D12: 1 | E12: 1 | F12: 3 | G12: 5 | H12: 3 | I12: 0 | J12: 常规碰撞（多次碰一个人加分） | K12: 1 | L12: 5 | M12: 3 | O12: 1 | P12: 对同一敌方单位每多碰撞一次，伤害增加{0}% | Q12: 可以加上标记，伤害向上取整，先加后乘。每回合最多触发{1}次 | V12: 0 | Z12: 每次碰撞敌方触发攻击伤害增加效果时，在该敌方球body位置播放1次📦Effect_Creature11_Hit特效并跟随敌方球进行移动 | AB12: 纸卷（纠缠） | AC12: 纸巾 | AG12: CauseDamageByCollisionTimes | AJ12: 2 | AL12: 1 | AM12: 1
A13: 10012 | B13: 摩托 赤狸 塞琳娜 | C13: 6 | D13: 1 | E13: 1 | F13: 4 | G13: 5 | H13: 3 | I13: 1 | J13: 我方英雄 | K13: 1 | L13: 7 | M13: 3 | O13: 1 | P13: 首次碰撞友方时，对其施加推力 | Q13: 隐藏推力{0} | V13: 3，4，5 | Z13: 触发该效果时，在碰撞位置播放一个曝气特效，播放完成后销毁 📦Effect_Creature13_Crash，该特效不跟随单位球移动 | AB13: 电吉他（音爆） | AC13: 摩托 | AE13: Times | AF13: 1 | AG13: CollisionHeroAddForceOnce | AJ13: 2 | AK13: 1 | AL13: 1 | AM13: 1
A14: 10013 | B14: 雨伞 守心 布洛莉Brolly | C14: 6 | D14: 1 | E14: 1 | F14: 2 | G14: 4 | H14: 3 | I14: 0 | J14: 更多我方单位 | K14: 1 | L14: 6 | M14: 3 | O14: 1 | P14: 碰撞友方时，为其添加圣盾 | Q14: 隐藏触发上限{0}次 | W14: 12 | Z14: （通用效果——圣盾： 被附加圣盾效果的单位，在该单位球处生成并播放📦Effect_ShieldUP，该特效跟随单位球body缩放，该特效跟随单位球移动 失去圣盾效果的单位，销毁该单位的📦Effect_ShieldUP 特效，并同时在该单位球Body处播放1次📦Effect_ShieldBreak 特效，该特效不跟随单位球移动和缩放） | AB14: 电风扇（吹风） | AC14: 雨伞 | AG14: AddShieldToCollisionTeammate | AK14: 1 | AL14: 1 | AM14: 1
A15: 10014 | B15: 茶壶 灵愈 波西娅Potsia | C15: 6 | D15: 1 | E15: 1 | F15: 2 | G15: 5 | H15: 3 | I15: 0 | J15: 我方高价值单位 | K15: 1 | L15: 6 | M15: 3 | O15: 1 | P15: 碰撞友方时，为其恢复{0}点生命 | Q15: 敌方回合也生效。隐藏触发上限{1}次 | AB15: 书（多张） | AC15: 茶壶 | AG15: CollisionTeammateRecoverHp | AL15: 1 | AM15: 1
A16: 10015 | B16: 留声机 回音 玛利亚 | C16: 1 | D16: 1 | E16: 1 | F16: 3 | G16: 5 | H16: 3 | I16: 0 | J16: 常规碰撞 | K16: 1 | L16: 5 | M16: 3 | O16: 1 | P16: 回合结束时：对随机敌方单位造成{0}点伤害，每有{1}连击，伤害+{2} | V16: 0 | W16: 53 | Z16: 该单位始终循环附带通用攻击光环特效 📦Effect_SustainableBuff_PowerLoop 触发回合结束的造成伤害效果时，在目标单位处播放攻击特效 📦Effect_Creature12_Hit，该特效跟随单位球移动 | AB16: 留声机（留声） | AC16: 留声机 | AE16: Times | AF16: 1 | AG16: CausePercentAttackDamageByComboCounts | AJ16: 2 | AL16: 1 | AM16: 1
A17: 10016 | B17: 电扇 彩虹 | C17: 1 | D17: 1 | E17: 1 | F17: 1 | G17: 5 | H17: 2 | I17: 0 | J17: 常规碰撞 | K17: 1 | L17: 2 | M17: 3 | O17: 1 | P17: 在场时：我方打出的卡牌发射速度增加{0}% | Q17: 可叠加，所有百分比加成，先加后乘，AddShootCardSpeedPercent | V17: 0 | Z17: 该单位始终循环附带通用增益光环特效 📦Effect_SustainableBuff_Loop | AB17: 牛奶（大补） | AC17: 电风扇（吹风） | AG17: CreatureAddShootCardSpeed | AJ17: 2 | AL17: 1 | AM17: 1
A18: 10017 | B18: 电池 欧姆 | C18: 1 | D18: 1 | E18: 1 | F18: 1 | G18: 7 | H18: 4 | I18: 1 | J18: 常规碰撞 | K18: 1 | L18: 2 | M18: 3 | O18: 1 | P18: 在场时：我方每获得{0}次连击数，额外获得{1}次连击 | Q18: 多个欧姆不叠加 | V18: 0 | W18: 53 | Z18: 该单位始终循环附带通用增益光环特效 📦Effect_SustainableBuff_Loop 生成能量时，从本体单位处生成一个📦Effect_EnergyTail飞至对应方能量条处后消失 | AC18: 电池1 | AG18: AddEnergyForHeroAtRoundOver | AJ18: 2 | AL18: 1
A19: 10018 | B19: 萨克斯 莉莉（Lily was here） | C19: 1 | D19: 1 | E19: 1 | F19: 1 | G19: 6 | H19: 3 | I19: 0 | J19: 常规碰撞（击杀权重大大增加） | K19: 1 | L19: 2.5 | M19: 3 | O19: 1 | P19: 我方回合：每有我方单位离场时，我方英雄回复{0}点生命 | Q19: （死亡，被吞噬，雇佣兵都算），被吞噬后，被吞噬单位死亡，只算一次离场（因为吞噬已经算离场了） | V19: 0 | Z19: 该单位始终循环附带通用攻击光环特效 📦Effect_SustainableBuff_PowerLoop 每次触发对随机敌方造成伤害的效果时，从本体单位位置生成一个📦Effect_Creature18_Fly，0.3s内飞至随机攻击的单位处，飞至终点时，在目标单位球处播放1次📦Effect_Creature15_Hit并跟随球移动 | AC19: 乐器娘2（萨克斯） | AG19: CauseDamageWhenKillEnemy | AJ19: 2 | AL19: 1 | AM19: 1
A20: 10019 | B20: 电池 焦耳 | C20: 1 | D20: 1 | E20: 1 | F20: 1 | G20: 5 | H20: 3 | I20: 1 | J20: 常规碰撞 | K20: 1 | L20: 2 | M20: 3 | O20: 1 | P20: 在场时：我方所有爆炸伤害增加{0}% | V20: 0 | W20: 61 | Z20: 该单位始终循环附带通用增益光环特效 📦Effect_SustainableBuff_Loop 生成能量时，从本体单位处生成一个📦Effect_EnergyTail飞至对应方能量条处后消失 | AC20: 电池2 | AG20: AddEnergyWhenKillEnemy | AJ20: 2 | AL20: 1
A21: 10020 | B21: 时钟 晨曦 | C21: 6 | D21: 1 | E21: 1 | F21: 3 | G21: 5 | H21: 3 | I21: 0 | J21: 常规碰撞 | K21: 1 | L21: 5 | M21: 3 | O21: 1 | P21: 本局战斗：每打出一次，攻击力永久+{0} | V21: 2 | Z21: 打出该单位后，在该单位body处生成一个📦Effect_AttackUp特效播放1次，并跟随该单位球进行移动 （通用特效：当前攻击力大于原始攻击力的单位，body处始终循环播放📦Effect_AttackUp_Loop特效，并跟随单位球移动，直到不满足条件或死亡） | AC21: 时钟（时间） | AE21: Times | AF21: 1 | AG21: AddAttackWhenShootCard | AJ21: 2 | AK21: 1 | AL21: 1 | AM21: 1
A22: 10021 | B22: 自动铅笔 追忆 | C22: 1 | D22: 1 | E22: 1 | F22: 1 | G22: 7 | H22: 3 | I22: 0 | J22: 常规碰撞 | K22: 1 | L22: 2 | M22: 3 | O22: 1 | P22: 在场时：每有一个我方单位入场，对随机敌方单位造成{0}伤害 | V22: 1 | Z22: 该单位始终循环附带通用攻击光环特效 📦Effect_SustainableBuff_PowerLoop 每次触发对随机敌方造成伤害的效果时，在本体单位球处生成并播放1次📦Effect_Creature21_Line，播放特效后0.1s再触发实际的法术效果，该特效需要计算目标单位球与本体单位球的角度并旋转Y值 | AC22: 铅笔 | AG22: ShootCardCauseDamageWhenAlive | AJ22: 2 | AK22: 1 | AL22: 1 | AM22: 1
A23: 10022 | B23: 橡皮 忘怀 | C23: 1 | D23: 1 | E23: 1 | F23: 4 | G23: 4 | H23: 3 | I23: 0 | J23: 更多我方随从单位 | K23: 1 | L23: 6.7 | M23: 3 | O23: 0 | P23: 继承，我方回合，牺牲所有碰到的友方随从单位，获得其{0}%的当前属性 | Q23: 改为继承特性 | V23: 1 | W23: 57 | Z23: 触发牺牲单位效果时，走常规击杀单位的流程，且在被击杀的单位处播放1次📦Effect_Creature22_Hit，该特效不跟随尸体移动 | AC23: 橡皮 | AG23: SacrificeCollisionCreature | AJ23: 2 | AK23: 1 | AL23: 1 | AM23: 1
A24: 10023 | B24: 牙膏 露洁 爱丽儿（Ariel 小美人鱼） | C24: 1 | D24: 1 | E24: 1 | F24: 1 | G24: 4 | H24: 4 | I24: 0 | J24: 常规碰撞 | K24: 1 | L24: 5 | M24: 3 | O24: 1 | P24: 回合结束时：分裂出{0}个分裂体 | V24: 1 | W24: 62 | Z24: （通用特效：召唤单位和生成物，在要召唤单位的位置播放📦Effect_Summon） | AC24: 牙膏 | AG24: SplitSelf | AJ24: 2 | AL24: 1 | AM24: 1
A25: 10024 | B25: 书 幻梦 仙蒂瑞拉 | C25: 1 | D25: 1 | E25: 1 | F25: 1 | G25: 6 | H25: 3 | I25: 1 | J25: 常规碰撞 | K25: 1 | L25: 5 | M25: 3 | O25: 1 | P25: 回合结束时：牺牲英雄{0}点生命，抽{1}张牌 | Q25: 在抽牌之前触发 | V25: 2 | Z25: 该单位始终循环附带通用增益光环特效 📦Effect_SustainableBuff_Loop 触发效果时，在对应英雄球位置播放1次📦Effect_LossLife_Flash，该特效跟随球移动 | AC25: 书 | AG25: GetMoreHandCard | AJ25: 2（待确认，牌堆无牌可抽也扣血） | AK25: 1 | AL25: 1 | AM25: 1
A26: 10025 | B26: 电池 伏特 | C26: 1 | D26: 1 | E26: 1 | F26: 1 | G26: 7 | H26: 3 | I26: 1 | J26: 常规碰撞 | K26: 1 | L26: 2 | M26: 3 | O26: 1 | P26: 在场时：我方英雄获得连击数翻倍 | Q26: 多个同时在场没用，都只是翻倍 | V26: 2 | W26: 53 | Z26: 该单位始终循环附带通用增益光环特效 📦Effect_SustainableBuff_Loop 生成能量时，从本体单位处生成一个📦Effect_EnergyTail飞至对应方能量条处后消失 | AC26: 电池3 | AG26: AddEnergyWhenShootCard | AJ26: 2 | AL26: 1
A27: 10026 | B27: 功能饮料 牛红 | C27: 6 | D27: 1 | E27: 1 | F27: 2 | G27: 5 | H27: 3 | I27: 0 | J27: 我方英雄 | K27: 1 | L27: 6 | M27: 3 | O27: 1 | P27: 碰撞友方时：为该友方永久增加{0}点攻击力 | Q27: 注意AI碰大蛇的处理。最多触发{1}次 | V27: 5 | Z27: 该单位始终循环附带通用增益光环特效 📦Effect_SustainableBuff_Loop 每次触发为英雄提升攻击力效果时，在对应英雄单位body处生成一个📦Effect_AttackUp特效播放1次，并跟随该单位球进行移动 （通用特效：当前攻击力大于原始攻击力的单位，body处始终循环播放📦Effect_AttackUp_Loop特效，并跟随单位球移动，直到不满足条件或死亡） | AC27: 爆米花 | AG27: CollisionHeroAddAttack | AJ27: 2 | AL27: 1 | AM27: 1
A28: 10027 | B28: 牛奶 银河 | C28: 1 | D28: 1 | E28: 1 | F28: 1 | G28: 5 | H28: 4 | I28: 0 | J28: 常规碰撞 | K28: 1 | L28: 2 | M28: 3 | O28: 0 | P28: 在场时：我方英雄获得吸血，每回合吸血上限为{1} | Q28: 吸血buff ID xxx。吸血特性{0} | V28: 3,5 | W28: 13 | Z28: 该单位始终循环附带通用增益光环特效 📦Effect_SustainableBuff_Loop （通用效果：吸血，触发时从被吸血的单位球处生成1个📦Effect_Lifesteal_Fly，飞至发动吸血的单位处后消失） （通用效果：回复血量，单位回复生命时，无论是否满血，都在该单位球处生成1个📦Effect_Health_Hit，跟随单位球移动，播放完成后消失） | AC28: 牛奶 | AG28: AddBuffToHeroWhenAlive | AJ28: 2 | AL28: 1 | AM28: 1
A29: 10028 | B29: 羽毛球 拉丽（英文就rally连续得分的意思） | C29: 6 | D29: 1 | E29: 1 | F29: 3 | G29: 5 | H29: 2 | I29: 0 | J29: 常规碰撞 | K29: 1 | L29: 5 | M29: 3 | O29: 1 | P29: 打出时：有{0}%几率回到手牌，每次打出几率下降{1}% | V29: 1，2 | Z29: 需要Spine配合 | AC29: 羽毛球 | AG29: RebackHandCard | AJ29: 2 | AK29: 1 | AL29: 1 | AM29: 1
A30: 10029 | B30: 姨妈巾 玫瑰 | C30: 1 | D30: 1 | E30: 1 | F30: 3 | G30: 5 | H30: 4 | I30: 0 | J30: 常规碰撞 | K30: 1 | L30: 5 | M30: 3 | O30: 1 | P30: 回合结束时：根据我方牺牲总生命的{0}%，为我方英雄永久增加生命 | Q30: 当前生命值。我方回合我方损失 | V30: 0 | Z30: 打出时，从被吸取生命的英雄Body位置生成飞行道具📦Effect_Creature29_Fly，飞行1s飞至姨妈巾处，飞至姨妈巾处后在姨妈巾的Body位置播放一次📦Effect_Creature29_Hit，该特效跟随单位球移动 特效部分仅作为表现存在，实际卡牌效果在打出瞬间立即生效 | AC30: 姨妈巾 | AE30: Times | AF30: 1 | AG30: AuntTowel | AJ30: 2 | AL30: 1 | AM30: 1
A31: 10030 | B31: 军鼓 震声 | C31: 1 | D31: 1 | E31: 1 | F31: 3 | G31: 7 | H31: 3 | I31: 1 | J31: 常规碰撞 | K31: 1 | L31: 5 | M31: 3 | O31: 1 | P31: 回合结束时：每有一个我方单位，对随机敌方单位造成一次{0}点伤害 | V31: 1 | Z31: 触发该效果时，每次对敌方造成伤害，在对应受伤害的单位球处生成并播放1次📦Effect_Creature30_Hit，造成伤害间隔为0.1s | AC31: 鼠标 | AG31: CauseDamageAccordOurActorNumAtRoundOver | AJ31: 2 | AL31: 1 | AM31: 1
A32: 10031 | B32: 注射器 针妮 佩妮（英文penny，联想小针） | C32: 6 | D32: 1 | E32: 1 | F32: 3 | G32: 7 | H32: 3 | I32: 0 | J32: 常规碰撞 | K32: 1 | L32: 6 | M32: 3 | O32: 1 | P32: 每次碰撞我方：牺牲其{0}点生命，并为我方英雄永久加{1}生命 | Q32: 可以吸死 | V32: 3，5 | Z32: 打出时，从所有被吸取生命的单位Body位置生成飞行道具📦Effect_Creature29_Fly，飞行1s飞至姨妈巾处，飞至姨妈巾处后在姨妈巾的Body位置播放一次📦Effect_Creature29_Hit，该特效跟随单位球移动 特效部分仅作为表现存在，实际卡牌效果在打出瞬间立即生效 | AB32: 76 | AC32: 注射器 | AE32: Times | AF32: 1 | AG32: Syringe | AJ32: 2 | AL32: 1 | AM32: 1
A33: 10032 | B33: 自行车 闪电 | C33: 6 | D33: 1 | E33: 1 | F33: 3 | G33: 4 | H33: 1 | I33: 0 | J33: 高价值敌方单位 | K33: 1 | L33: 5 | M33: 3 | O33: 0 | P33: 首次碰撞随从单位时，施加一个较大的力 | Q33: 敌我都行，隐藏参数力大小{0} | V33: 0 | Z33: 触发该效果时，在碰撞位置播放一个曝气特效，播放完成后销毁 📦Effect_Creature13_Crash | AC33: 自行车 | AE33: Times | AF33: 1 | AG33: CollisionRetinueAddForceOnce | AJ33: 2 | AL33: 1 | AM33: 1
A34: 10033 | B34: 蜡烛 热泪 | C34: 1 | D34: 1 | E34: 1 | F34: 3 | G34: 3 | H34: 3 | I34: 0 | J34: 高价值敌方单位 | K34: 1 | L34: 2 | M34: 3 | O34: 1 | P34: 在场时：每有一次爆炸，我方英雄生命+{0} | V34: 0 | W34: 61 | AC34: 蜡烛 | AE34: Times | AF34: 1 | AG34: FireSelfButImmunityDamage | AJ34: 2 | AL34: 1 | AM34: 1
A35: 10034 | B35: 电钻 螺旋 | C35: 6 | D35: 1 | E35: 1 | F35: 3 | G35: 5 | H35: 4 | I35: 0 | J35: 高价值敌方单位 | K35: 1 | L35: 6 | M35: 3 | O35: 1 | P35: 使碰撞到的敌方单位漏油 | Q35: 漏油特性ID{0}，隐藏敌方漏油格数上限{1}，漏油上限指，被碰撞到的敌方运动后，最多在{1}个地面留下漏油单元格 | V35: 0 | W35: 46 | Z35: 该单位每次碰撞敌方，仅触发流血时，在碰撞位置生成一个📦Effect_Creature34_Hit，播放一次，不跟随球移动 | AC35: 剪刀 | AG35: CollisionAddBuffToOthers | AJ35: 2 | AL35: 1 | AM35: 1
A36: 10035 | B36: 纯净水 浅浅 | C36: 1 | D36: 1 | E36: 1 | F36: 3 | G36: 2 | H36: 1 | I36: 0 | J36: 高价值敌方单位 | K36: 1 | L36: 5 | M36: 3 | O36: 1 | P36: 无 | Q36: 凑数属性怪，白水瓶娘浅，均衡攻血 | V36: 0 | AC36: 白水瓶娘浅 | AL36: 1 | AM36: 1
A37: 10036 | B37: 纯净水 满满 | C37: 1 | D37: 1 | E37: 1 | F37: 3 | G37: 4 | H37: 1 | I37: 0 | J37: 高价值敌方单位 | K37: 1 | L37: 5 | M37: 3 | O37: 1 | P37: 无 | Q37: 凑数属性怪，白水瓶娘满，均衡攻血 | V37: 0 | AC37: 白水瓶娘满 | AL37: 1 | AM37: 1
A38: 10037 | B38: 红汽水 浅浅 | C38: 1 | D38: 1 | E38: 1 | F38: 3 | G38: 3 | H38: 1 | I38: 0 | J38: 高价值敌方单位 | K38: 1 | L38: 5 | M38: 3 | O38: 1 | P38: 无 | Q38: 凑数属性怪，红水瓶娘浅，高攻低血 | V38: 0 | AC38: 红水瓶娘浅 | AL38: 1 | AM38: 1
A39: 10038 | B39: 红汽水 满满 | C39: 1 | D39: 1 | E39: 1 | F39: 3 | G39: 5 | H39: 1 | I39: 0 | J39: 高价值敌方单位 | K39: 1 | L39: 5 | M39: 3 | O39: 0 | P39: 无 | Q39: 凑数属性怪，红水瓶娘满，高攻低血 | V39: 0 | AC39: 红水瓶娘满 | AL39: 1 | AM39: 1
A40: 10039 | B40: 绿汽水 浅浅 | C40: 1 | D40: 1 | E40: 1 | F40: 3 | G40: 4 | H40: 1 | I40: 0 | J40: 高价值敌方单位 | K40: 1 | L40: 5 | M40: 3 | O40: 1 | P40: 无 | Q40: 凑数属性怪，绿水瓶娘浅，低攻高血 | V40: 0 | AC40: 绿水瓶娘浅 | AL40: 1 | AM40: 1
A41: 10040 | B41: 绿汽水 满满 | C41: 1 | D41: 1 | E41: 1 | F41: 3 | G41: 6 | H41: 1 | I41: 0 | J41: 高价值敌方单位 | K41: 1 | L41: 5 | M41: 3 | O41: 0 | P41: 无 | Q41: 凑数属性怪，绿水瓶娘满，低攻高血 | V41: 0 | AC41: 绿水瓶娘满 | AL41: 1 | AM41: 1
A42: 10041 | B42: 肥皂 滑滑 | C42: 1 | D42: 1 | E42: 1 | F42: 3 | G42: 5 | H42: 2 | I42: 0 | J42: 常规碰撞 | K42: 1 | L42: 5 | M42: 3 | O42: 0 | P42: 降低自身摩擦力{0}% | AC42: 肥皂 | AE42: Times | AF42: 1 | AG42: ReduceSelfFriction | AL42: 1 | AM42: 1
A43: 10042 | B43: 刀 藏锋 | C43: 1 | D43: 1 | E43: 1 | F43: 3 | G43: 7 | H43: 3 | I43: 0 | J43: 常规碰撞 | K43: 1 | L43: 5 | M43: 3 | O43: 1 | P43: 回合结束时：若连击数是单数，为我方英雄增加连击数*{0}%的攻击，若是双数，增加连击数{1}%的生命 | Q43: 我方回合 | W43: 57 | X43: 53 | AG43: AddAttackEachRound | AL43: 1 | AM43: 1
A44: 10043 | B44: 刀 百炼 | C44: 1 | D44: 1 | E44: 1 | F44: 3 | G44: 7 | H44: 3 | I44: 0 | J44: 常规碰撞 | K44: 1 | L44: 2 | M44: 3 | O44: 1 | P44: 每达成{0}连击，为生命百分比最低的我方回复{1}生命 | W44: 57 | X44: 12 | AG44: AddHpEachRound | AL44: 1 | AM44: 1
A45: 10044 | B45: 煤油灯 流露 | C45: 6 | D45: 1 | E45: 1 | F45: 2 | G45: 4 | H45: 3 | I45: 0 | J45: 常规碰撞 | K45: 1 | L45: 3 | M45: 3 | O45: 1 | P45: 首次碰撞后漏油，移动时留下油地面 | Q45: 隐藏参数产生油地面上限数量{0} | AA45: 0 | AC45: 火柴 | AG45: FireTerrainWhenMove | AL45: 1 | AM45: 1
A46: 10045 | B46: 盔甲 怀抱 | C46: 1 | D46: 1 | E46: 1 | F46: 1 | G46: 5 | H46: 4 | I46: 0 | J46: 常规碰撞 | K46: 1 | L46: 4 | M46: 3 | O46: 1 | P46: 在场时：为所有我方分担{0}%的伤害，场上每有一个我方，自身忽略{1}%的伤害，最高忽略{2}% | Q46: 分担后伤害向上取整，所有分担后的伤害标记为分担伤害，不会再次触发任何其他单位的分担。多个存在时，分担后的剩余伤害再进行分担，例100伤害，两个分担50%，就是75% | AA46: 0 | AC46: 盔甲娘 | AG46: ShareDamageForHero | AL46: 1 | AM46: 1
A47: 10046 | B47: 啤酒瓶 破碎 | C47: 6 | D47: 1 | E47: 1 | F47: 3 | G47: 5 | H47: 4 | I47: 0 | J47: 常规碰撞 | K47: 1 | L47: 5 | M47: 3 | O47: 1 | P47: 自身造成的连击数增加{0}% | Q47: 永久增加 | W47: 53 | AA47: 0 | AC47: 梨球 | AG47: AddAttackEachSufferedDamage | AL47: 1 | AM47: 1
A48: 10047 | B48: 暂时不做 | C48: 1 | D48: 1 | E48: 1 | F48: 3 | G48: 5 | H48: 1 | J48: 常规碰撞 | K48: 1 | L48: 5 | M48: 3 | O48: 0 | AL48: 1 | AM48: 1
A49: 10048 | B49: 储蓄罐 珠珠 | C49: 1 | D49: 1 | E49: 1 | F49: 3 | G49: 6 | H49: 4 | I49: 1 | J49: 常规碰撞 | K49: 1 | L49: 5 | M49: 3 | O49: 0 | AG49: PiggyBank | AL49: 1 | AM49: 1
A50: 10049 | B50: 夹子 瑾瑾 | C50: 6 | D50: 1 | E50: 1 | F50: 3 | G50: 6 | H50: 4 | I50: 0 | J50: 敌方方舟核心 | K50: 1 | L50: 5 | M50: 3 | O50: 0 | P50: 对方舟和场景物件造成的伤害额外增加{0}% | AG50: Clip | AL50: 1 | AM50: 1
A51: 10050 | B51: 茶包 小茗 | C51: 1 | D51: 1 | E51: 1 | F51: 3 | G51: 6 | H51: 3 | I51: 0 | J51: 常规碰撞 | K51: 1 | L51: 5 | M51: 3 | O51: 1 | P51: 每碰撞一次友方，牺牲自身{0}%最大生命，为友方回复对应生命 | W51: 57 | AG51: Tea | AL51: 1 | AM51: 1
A52: 10051 | B52: 气球 飘舞 | C52: 1 | D52: 1 | E52: 1 | F52: 1 | G52: 5 | H52: 2 | I52: 0 | J52: 敌方方舟核心 | K52: 1 | L52: 5 | M52: 3 | O52: 1 | P52: 蓄力{0}回合后爆炸，造成{1}伤害 | Q52: 隐藏参数范围{2}，爆炸推力{3}，我方回合开始时爆炸 | W52: 61 | AG52: Balloon | AL52: 1 | AM52: 1
A53: 10052 | B53: 传奇飞行员 舰长 | C53: 4 | D53: 1 | E53: 1 | F53: 3 | G53: 5 | H53: 4 | I53: 6 | J53: 常规碰撞 | K53: 1 | L53: 2.1 | M53: 3 | N53: 10000 | O53: 1 | P53: 每打出{0}张卡，获得一张炸蛋 | Q53: 炸蛋ID{1} | W53: 59 | AG53: Captain | AL53: 1 | AM53: 1
A54: 10053 | B54: 黏黏女王 宁芙（Nymph） | C54: 4 | D54: 1 | E54: 1 | F54: 3 | G54: 5 | H54: 4 | I54: 6 | J54: 常规碰撞 | K54: 1 | L54: 2.1 | M54: 3 | N54: 10001 | O54: 1 | P54: 打出时，回合开始时：收回自身分裂体，再分裂出{0}个分裂体 | Q54: 摆成倒三角，配置6个 | W54: 62 | AG54: HeroSummonCreature | AL54: 1 | AM54: 1
A55: 10054 | B55: 最强盗贼王 露娜（Luna） | C55: 4 | D55: 1 | E55: 1 | F55: 3 | G55: 5 | H55: 4 | I55: 6 | J55: 常规碰撞 | K55: 1 | L55: 2.1 | M55: 3 | N55: 10002 | O55: 1 | P55: 回合结束时：对随机敌方单位发射导弹造成{0}点爆炸伤害。我方每触发一次爆炸，范围永久增加{3} | Q55: 隐藏爆炸范围{1}，隐藏力{2} | W55: 59 | X55: 61 | AG55: Bullet | AL55: 1 | AM55: 1
A56: 10055 | B56: 轻灵跃影 乔艾塔（Joetta） | C56: 4 | D56: 1 | E56: 1 | F56: 3 | G56: 5 | H56: 4 | I56: 6 | J56: 常规碰撞 | K56: 1 | L56: 2.1 | M56: 3 | N56: 10003 | O56: 1 | P56: 我方回合开始时：向最近的敌方单位冲刺，回合结束时，每有{1}连击，自身攻击加{2}，生命加{3} | Q56: 力{0} | W56: 59 | AG56: MoveToNearestEnemy | AL56: 1 | AM56: 1
A57: 10056 | B57: 致命拥抱 维纳斯（Venus） | C57: 4 | D57: 1 | E57: 1 | F57: 3 | G57: 5 | H57: 4 | I57: 6 | J57: 常规碰撞 | K57: 1 | L57: 2.1 | M57: 3 | N57: 10004 | O57: 1 | P57: 打出时：化作无法移动的花朵形态，我方回合盛开，无视吞噬规则吞噬碰到的任意单位，对敌方造成攻击力{0}%的伤害，为友方恢复攻击力{1}%的生命，然后吐出 | Q57: 隐藏参数吐出力度{2}。食人花本身无法被吞噬，依次吐出。隐藏延迟吐出的时间参数{3} | W57: 59 | AG57: HeroDevourEnemy | AL57: 1 | AM57: 1
A58: 10057 | B58: 环绕之蛇 娜吉尼（Nagini） | C58: 4 | D58: 1 | E58: 1 | F58: 3 | G58: 5 | H58: 4 | I58: 6 | J58: 常规碰撞 | K58: 1 | L58: 2.1 | M58: 3 | N58: 10005 | O58: 1 | P58: 打出时：化作大蛇，我方回合每击杀一个单位，生命+{0}，并发射超电磁炮，伤害为自身攻击的{1}% | Q58: 从大蛇中心发射，随机角度，打得到方舟的角度里随机即可。超电磁炮ID{2} | W58: 59 | AG58: Nagini | AL58: 1 | AM58: 1
A59: 10058 | B59: 群蜂之母 梅丽莎（Melissa） | C59: 4 | D59: 1 | E59: 1 | F59: 3 | G59: 5 | H59: 4 | I59: 6 | J59: 常规碰撞 | K59: 1 | L59: 2.1 | M59: 3 | N59: 10006 | O59: 1 | P59: 额外获得自身已损失生命{0}%的攻击，每次碰撞敌方单位，根据造成伤害的{1}%回复自身生命 | W59: 59 | AG59: FusionPreUnits | AL59: 1 | AM59: 1
A60: 10059 | B60: 鞭炮 噼啪 | C60: 1 | D60: 1 | E60: 1 | F60: 3 | G60: 5 | H60: 4 | I60: 0 | J60: 常规碰撞 | K60: 1 | L60: 2.5 | M60: 3 | O60: 1 | P60: 我方回合：每个我方首次被爆炸击中，该我方位置触发一次爆炸，伤害为{0} | Q60: 隐藏参数范围{1}，爆炸推力{2} | W60: 61 | AG60: Firecracker
A61: 10060 | B61: 爆米花 酥脆 | C61: 1 | D61: 1 | E61: 1 | F61: 3 | G61: 5 | H61: 3 | I61: 0 | J61: 常规碰撞 | K61: 1 | L61: 2.5 | M61: 3 | O61: 1 | P61: 我方回合：我方每被爆炸击中一次，该我方回复{0}点生命 | Q61: 我方回合 | W61: 61 | AG61: Popcorn
A62: 10061 | B62: 红汽水 满满（复用） | C62: 6 | D62: 1 | E62: 1 | F62: 3 | G62: 5 | H62: 2 | I62: 0 | J62: 常规碰撞 | K62: 1 | L62: 5 | M62: 3 | O62: 1 | P62: 每次碰撞敌方单位触发一次爆炸，伤害为{0} | Q62: 我方回合的雇佣兵，隐藏参数范围{1}，爆炸推力{2} | W62: 61 | AG62: RedSoda
A63: 10062 | B63: 绿汽水 满满（复用） | C63: 1 | D63: 1 | E63: 1 | F63: 3 | G63: 5 | H63: 4 | I63: 0 | J63: 常规碰撞 | K63: 1 | L63: 5 | M63: 3 | O63: 1 | P63: 我方回合结束时：所有我方攻击+{0} | AG63: GreenSoda
A64: 10063 | B64: 篮球框 三分 | C64: 1 | D64: 1 | E64: 1 | F64: 3 | G64: 5 | H64: 3 | I64: 0 | J64: 常规碰撞 | K64: 1 | L64: 2 | M64: 3 | O64: 1 | P64: 每有一个我方入场：为血量百分比最低的友方回复{0}点生命 | AG64: BasketballHoop
A65: 10064 | B65: 飞刀 小李 | C65: 6 | D65: 1 | E65: 1 | F65: 3 | G65: 5 | H65: 3 | I65: 0 | J65: 常规碰撞 | K65: 1 | L65: 5 | M65: 3 | O65: 1 | P65: 碰到首个我方随从时：使其分裂出{0}个分裂体 | Q65: 分裂流雇佣兵 | W65: 62 | AG65: FlyKnife
A66: 10065 | B66: 磨刀石 霍霍 | C66: 1 | D66: 1 | E66: 1 | F66: 3 | G66: 5 | H66: 3 | I66: 0 | J66: 常规碰撞 | K66: 1 | L66: 2.2 | M66: 3 | O66: 1 | P66: 我方回合，我方英雄每次碰撞时：本单位牺牲最大生命{0}%的生命，英雄本次伤害额外增加{1}% | AG66: Whetstone
A67: 10066 | B67: 乌龟 壳壳 | C67: 1 | D67: 1 | E67: 1 | F67: 3 | G67: 5 | H67: 3 | I67: 0 | J67: 常规碰撞 | K67: 1 | L67: 5 | M67: 3 | O67: 1 | P67: 吞噬首个碰到的友方随从，自身死亡时，为被吞噬单位添加一个圣盾 | W67: 63 | X67: 12 | AG67: Turtle
A68: 10067 | B68: 复印机 复原 | C68: 1 | D68: 1 | E68: 1 | F68: 3 | G68: 5 | H68: 4 | I68: 0 | J68: 常规碰撞 | K68: 1 | L68: 5 | M68: 3 | O68: 1 | P68: 吞噬首个碰撞的随从，回合结束时，吐出一个该单位的我方原始版复制 | Q68: 敌方也能吞 | AG68: Copier
A69: 10068 | B69: 刀鞘 护刃 | C69: 1 | D69: 1 | E69: 1 | F69: 3 | G69: 5 | H69: 2 | I69: 0 | J69: 常规碰撞 | K69: 1 | L69: 5 | M69: 3 | O69: 1 | P69: 吞噬首个碰到的友方随从，吞噬期间获得其攻击 | AG69: Knife
A70: 10069 | B70: 绷带 包扎 | C70: 1 | D70: 1 | E70: 1 | F70: 3 | G70: 5 | H70: 2 | I70: 0 | J70: 常规碰撞 | K70: 1 | L70: 5 | M70: 3 | O70: 1 | P70: 吞噬首个碰到的友方随从，自身每被碰撞一次，为被吞噬单位回复{0}点生命 | AG70: Bandage
A71: 10070 | B71: 捕蝇草 夹子 | C71: 1 | D71: 1 | E71: 1 | F71: 3 | G71: 5 | H71: 4 | I71: 0 | J71: 常规碰撞 | K71: 1 | L71: 5 | M71: 3 | O71: 1 | P71: 吞噬首个碰撞的敌方随从，禁用其技能效果，每个我方回合结束对其造成{0}点伤害 | AG71: Flytrap
A72: 10071 | B72: 鳄鱼 沼泽 | C72: 1 | D72: 1 | E72: 1 | F72: 3 | G72: 5 | H72: 3 | I72: 0 | J72: 常规碰撞 | K72: 1 | L72: 5 | M72: 3 | O72: 1 | P72: 吞噬首个碰撞的随从，回合结束对被吞噬单位造成{0}伤害，若该随从死亡，则获取其基础属性 | AG72: Crocodile
A73: 10072 | B73: 鲨鱼 利齿 | C73: 6 | D73: 1 | E73: 1 | F73: 3 | G73: 5 | H73: 3 | I73: 0 | J73: 常规碰撞 | K73: 1 | L73: 5 | M73: 3 | O73: 1 | P73: 每回合首次碰撞敌方方舟时，可以吞噬一块船体，本场战斗每有一次吞噬，效果增强 | Q73: 看做造成伤害，但是用规整的伤害蔓延算法即可 | AG73: Pelican
A74: 10073 | B74: 储蓄罐 珠珠（复用） | C74: 1 | D74: 1 | E74: 1 | F74: 3 | G74: 5 | H74: 3 | I74: 0 | J74: 常规碰撞 | K74: 1 | L74: 4 | M74: 3 | O74: 1 | P74: 在场时：我方每有一次吞噬，我方英雄获得{0}点攻击，{1}点生命，被吞噬时，效果翻倍 | AG74: PiggyBank
A75: 10074 | B75: 扫把 | C75: 1 | D75: 1 | E75: 1 | F75: 3 | G75: 5 | H75: 1 | I75: 0 | J75: 常规碰撞 | K75: 1 | L75: 5 | M75: 3 | O75: 0 | P75: 我方回合我方单位离场时，我方英雄回复{0}点生命 | Q75: 死亡，被吞噬，雇佣兵离场都算
A76: 10075 | B76: 菠菜罐头 大力 | C76: 1 | D76: 1 | E76: 1 | F76: 3 | G76: 5 | H76: 2 | I76: 0 | J76: 常规碰撞 | K76: 1 | L76: 4 | M76: 3 | O76: 1 | P76: 在场时：所有我方攻击增加{0}，被吞噬时，效果翻倍 | AG76: CannedSpinach
A77: 10076 | B77: 仓鼠 囤囤 | C77: 1 | D77: 1 | E77: 1 | F77: 3 | G77: 5 | H77: 3 | I77: 0 | J77: 常规碰撞 | K77: 1 | L77: 5 | M77: 3 | O77: 1 | P77: 回合结束时：我方已吞噬别人和被吞噬的单位生命永久增加{0}，被吞噬时，效果翻倍 | AG77: Hamster
A78: 10077 | B78: 接力棒 传承 | C78: 6 | D78: 1 | E78: 1 | F78: 3 | G78: 5 | H78: 3 | I78: 0 | J78: 常规碰撞 | K78: 1 | L78: 6 | M78: 3 | O78: 1 | P78: 首次碰到友方时：获得其{0}%的攻击力 | AG78: Baton
A79: 10078 | B79: 冰淇淋 甜霜 | C79: 6 | D79: 1 | E79: 1 | F79: 3 | G79: 5 | H79: 2 | I79: 0 | J79: 常规碰撞 | K79: 1 | L79: 5 | M79: 3 | O79: 1 | P79: 经过液体地面时：将地面冻结 | AG79: Refrigerator
A80: 10079 | B80: 炸蛋 | C80: 6 | D80: 1 | E80: 1 | F80: 3 | G80: 5 | H80: 2 | I80: 0 | J80: 常规碰撞 | K80: 1 | L80: 6 | M80: 3 | O80: 1 | P80: 碰到敌方后爆炸，对周围敌方和自身造成{0}点伤害 | Q80: 隐藏参数范围{1}，推力{2} | W80: 61 | AG80: Egg
A81: 10080 | B81: 安全帽 小橘 | C81: 1 | D81: 1 | E81: 1 | F81: 3 | G81: 5 | H81: 3 | I81: 0 | J81: 常规碰撞 | K81: 1 | L81: 2 | M81: 3 | O81: 1 | P81: 我方单位入场时：入场单位获得一个圣盾 | W81: 12 | AG81: SafeHat
P84: 下面为备选技能
P85: 我方回合，获得首个死亡单位的临时复制，但打出时属性只有1-1 | AA85: 0
P86: 每个回合，我方首个受到致命伤害的单位，忽略本次伤害，生命变为1点 | AA86: 0
P87: 在场时，每回合开始时获得一张临时的XX技能 | AA87: 0
P88: 在场时受到{0}次爆炸后孵化，给与{1}张炸蛋 | AA88: 0
P89: 对方方舟受损度越高，自身越强 | AA89: 0
P90: 在场时，我方回合我方英雄每受一次碰撞，对随机敌方造成{0}点伤害 | Q90: 敌我碰撞都算，配合大蛇 | AA90: 0
P91: 冻结碰到的所有敌方单位 | AA91: 0
P92: 碰到首个敌方时，对范围内的敌方造成{0}点伤害并冻结 | AA92: 0
P93: 碰到的首个友方，在本回合获得临时的吸血 | AA93: 0
P94: 方舟被破坏时，为自身回复血量 | AA94: 0
P95: 临时吸收 | AA95: 0
P96: 吸收所有圣盾，冰冻等等 | AA96: 0
P97: 逆转海浪（或者英雄产生一个吸力） | AA97: 0
P98: 标记每次碰到的单位，回合结束时，标记单位对周围产生一个吸力，标记数越多，吸力越强 | Q98: 回合结束清除标记 | AA98: 0
P99: 每有一个我方单位入场，为其添加圣盾 | AA99: 0
P100: 吞噬敌方，吞噬我方来保护或者限制 | Q100: 吞噬机制，也可以减少场上单位，甚至可以套娃 | AA100: 0
AA101: 0
P102: 本单位碰撞到的敌方单位，下一次碰撞会对对方方舟造成伤害 | AA102: 0 | AL102: 1
...

Sheet 技能卡分表
A1: 卡牌ID | B1: 名称 | C1: 卡牌类型 | D1: 选项类型 | E1: 射击类型 | F1: 职业 | G1: 费用 | H1: 稀有度 | I1: 获取方式类型 | J1: AI目标规划 | K1: 瞄准线类型 | L1: 牌序规划标签 | M1: 等级上限 | N1: 废弃 | O1: 不放入商店 | P1: 卡牌效果 | Q1: 效果备注 | R1: 卡牌效果2级 | S1: 2级效果备注 | T1: 卡牌效果3级 | U1: 3级效果备注 | V1: 流派归类（后续用作职业划分） | W1: 特性列表（特性ID） | Z1: 引用交互物列表（交互物ID） | AB1: 技能表现 | AC1: 额外备注 | AD1: 特效已加入？ | AE1: 失效次数 | AF1: 失效参数 | AG1: 技能类型 | AJ1: 是否需要物理模拟
A2: 20001 | B2: 模版法术1 | C2: 2 | D2: 1 | F2: 无 | G2: 1 | J2: 高价值敌方单位 | K2: 3 | L2: 5 | N2: 1 | O2: 1 | P2: 命中首个敌方单位时，对其造成X点伤害 | Q2: 无
A3: 20002 | B3: 模版法术2 | C3: 2 | D3: 1 | F3: 无 | G3: 2 | J3: 高价值敌方单位 | K3: 3 | L3: 5 | N3: 1 | O3: 1 | P3: 命中首个敌方单位时，对其造成X点伤害 | Q3: 无
A4: 20003 | B4: 模版法术3 | C4: 2 | D4: 1 | F4: 无 | G4: 3 | J4: 高价值敌方单位 | K4: 3 | L4: 5 | N4: 1 | O4: 1 | P4: 命中首个敌方单位时，对其造成X点伤害 | Q4: 无
A5: 20004 | B5: 模版法术4 | C5: 2 | D5: 1 | F5: 无 | G5: 4 | J5: 高价值敌方单位 | K5: 3 | L5: 5 | N5: 1 | O5: 1 | P5: 命中首个敌方单位时，对其造成X点伤害 | Q5: 无
A6: 20005 | B6: 模版法术5 | C6: 2 | D6: 1 | F6: 无 | G6: 5 | J6: 高价值敌方单位 | K6: 3 | L6: 5 | N6: 1 | O6: 1 | P6: 命中首个敌方单位时，对其造成X点伤害 | Q6: 无
A7: 20006 | B7: 模版法术6 | C7: 2 | D7: 1 | F7: 无 | G7: 6 | J7: 高价值敌方单位 | K7: 3 | L7: 5 | N7: 1 | O7: 1 | P7: 命中首个敌方单位时，对其造成X点伤害 | Q7: 无
A8: 20007 | B8: 模版法术7 | C8: 2 | D8: 1 | F8: 无 | G8: 7 | J8: 高价值敌方单位 | K8: 3 | L8: 5 | N8: 1 | O8: 1 | P8: 命中首个敌方单位时，对其造成X点伤害 | Q8: 无
A9: 20008 | B9: 模版法术8 | C9: 2 | D9: 1 | F9: 无 | G9: 8 | J9: 高价值敌方单位 | K9: 3 | L9: 5 | N9: 1 | O9: 1 | P9: 命中首个敌方单位时，对其造成X点伤害 | Q9: 无
A10: 20009 | B10: 模版法术9 | C10: 2 | D10: 1 | F10: 无 | G10: 9 | J10: 高价值敌方单位 | K10: 3 | L10: 5 | N10: 1 | O10: 1 | P10: 命中首个敌方单位时，对其造成X点伤害 | Q10: 无
A11: 20010 | B11: 切分 | C11: 2 | D11: 2 | E11: 1 | F11: 4 | G11: 5 | H11: 4 | I11: 3 | J11: 更多我方随从单位 | K11: 7 | L11: 6.3 | M11: 1 | P11: 场景穿透，将经过的我方非复制随从单位切成两个较小的复制单位，属性为原单位的{2}% | Q11: 属性百分比可配，向上取整，隐藏参数，体积减小{0}%，质量减少{1}% | V11: 0 | W11: 8 | X11: 34 | AB11: 发动法术后，从发射点位置生成并播放1次📦Effect_Magic10_Shoot，生成时的旋转角度与操作发射角度相同，触发效果时，在每个被击中的单位球Body处生成并播放1次📦Effect_Magic10_Hit | AE11: Times | AF11: 1 | AG11: SplitCollisionCreature | AJ11: 0 | AK11: 1
A12: 20011 | B12: 魅惑 | C12: 2 | D12: 2 | E12: 1 | F12: 4 | G12: 4 | H12: 4 | I12: 3 | J12: 高价值我方单位 | K12: 6 | L12: 7.1 | M12: 3 | P12: 指定战场任意位置，敌方英雄向该位置位移 | Q12: 隐藏参数位移力度{0}，不能移动的英雄不生效 | R12: 指定战场任意位置，敌方英雄向该位置位移，位移力量更大 | S12: 隐藏参数位移力度{0}，不能移动的英雄不生效 | T12: 指定战场任意位置，敌方英雄向该位置位移，位移力量最大 | U12: 隐藏参数位移力度{0}，不能移动的英雄不生效 | V12: 0 | W12: 41 | AB12: 发动法术后，在指定的战场位置生成一个📦Effect_Magic11，英雄在延迟0.4s后向目标方向位移 | AE12: Times | AF12: 1 | AG12: CharmHero | AJ12: 0 | AK12: 1
A13: 20012 | B13: 弹射锯片 | C13: 2 | D13: 2 | E13: 1 | F13: 3 | G13: 4 | H13: 5 | I13: 0 | J13: 更多敌方单位 （飞行路径敌方伤害价值取最高） | K13: 2 | L13: 5 | M13: 3 | P13: 穿透，造成{0}伤害，每穿透一个单位伤害增加{1}% | Q13: 计算友方单位，先加后乘，隐藏参数最小伤害间隔{2}秒 | V13: 1 | W13: 6 | AB13: 生成一个飞行道具特效按照技能规则进行移动 📦Effect_Magic12_Fly 对造成伤害的单位，球位置处，播放一个受击特效 📦Effect_Magic12_Hit | AC13: 无敌风火轮 | AE13: Times | AF13: 1 | AG13: CollisionCauseDamage | AJ13: 1 | AK13: 1
A14: 20013 | B14: 自制手雷 | C14: 2 | D14: 2 | E14: 1 | F14: 3 | G14: 3 | H14: 3 | I14: 0 | J14: 高价值敌方单位 （所有单位圆形范围敌方伤害价值取最高） | K14: 4 | L14: 5 | M14: 3 | P14: 碰到首个敌方时，对范围内的敌方造成{0}伤害 | Q14: 隐藏参数范围大小{1}，隐藏参数中心点向四周的推力{2} | V14: 0 | AB14: 生成一个飞行道具特效按照技能规则进行移动 📦Effect_Magic13_Fly 在接触点位置生成爆炸特效，该特效跟随范围数值缩放 📦Effect_Magic13_Hit | AC14: 火球术 | AE14: Times | AF14: 1 | AG14: CollisionCauseRangeDamageOnce | AJ14: 1 | AK14: 1
A15: 20014 | B15: 见证我！ | C15: 2 | D15: 2 | E15: 1 | F15: 4 | G15: 3 | H15: 2 | I15: 0 | J15: 无目标 | K15: 5 | L15: 5 | M15: 3 | P15: 杀死我方生命最低的随从，对周围敌方造成{0}点伤害 | Q15: 隐藏参数范围大小{1}，推力参数{2}，如果有多个血量相同的单位例如牙膏，则都爆炸，多个爆炸做个小延时。拖出去时提示一下哪些单位会爆炸 | V15: 1 | W15: 36 | AB15: 以0.1s为间隔，顺序在爆炸球坐标处播放爆炸特效，该特效跟随范围数值缩放 📦Effect_Magic14 | AC15: 自爆 | AE15: Times | AF15: 1 | AG15: SelfDestructCauseRangeDamage | AJ15: 0 | AK15: 1
A16: 20015 | B16: 英勇祝福 | C16: 2 | D16: 2 | E16: 1 | F16: 2 | G16: 4 | H16: 2 | I16: 0 | J16: 无目标 | K16: 5 | L16: 6 | M16: 3 | N16: 1 | O16: 1 | P16: 本回合，所有我方单位攻击力临时提升{0}，回合结束恢复 | Q16: 固定值，目的是配合单位数量流派，如果有多次使用，可以叠加 | V16: 0 | AB16: 打出该法术后的生效时间内，所有新打出的单位球在body处生成一个📦Effect_AttackUp特效播放1次，并跟随该单位球进行移动 （通用特效：当前攻击力大于原始攻击力的单位，body处始终循环播放📦Effect_AttackUp_Loop特效，并跟随单位球移动，直到不满足条件或死亡） | AC16: 英勇祝福之类的 | AE16: Times | AF16: 1 | AG16: ContinueAddBuffToSelf | AJ16: 0
A17: 20016 | B17: 引力炸弹 | C17: 2 | D17: 2 | E17: 1 | F17: 4 | G17: 4 | H17: 4 | I17: 0 | J17: 无目标 | K17: 5 | L17: 6.4 | M17: 3 | P17: 以我方英雄位置为中心，产生一个引力 | Q17: 隐藏参数力大小{0} | V17: 3,4 | AB17: 法术发动时，在对应英雄球body位置生成一个📦Effect_Magic16_Flash播放1次，引力效果在特效播放后0.2s发动，该特效不跟随球移动 | AC17: 引力 | AE17: Times | AF17: 1 | AG17: AddGravitationToHero | AJ17: 0 | AK17: 1
A18: 20017 | B18: 精准爆破 | C18: 2 | D18: 2 | E18: 1 | F18: 3 | G18: 4 | H18: 2 | I18: 3 | J18: 随机位置 （敌方单位几何圆心重心） | K18: 6 | L18: 5 | M18: 1 | P18: 指定战场位置，生成{1}个爆炸桶，爆炸伤害为{2} | Q18: 指定位置有单位和场景物件时尝试推开单位，或推开自身，该推开做成通用功能。交互物{0} | V18: 4,5 | W18: 41 | X18: 61 | Z18: 10001 | AB18: （通用特效：召唤单位和生成物，在要召唤单位的位置播放📦Effect_Summon） （通用爆炸桶特效：爆炸桶触发效果或摧毁时，在爆炸桶位置生成并播放一个📦DamageDebrisParticle； 爆炸桶触发爆炸效果时，在爆炸桶位置播放1个📦Effect_BlastBarrel_Bomb，该特效跟随范围数值缩放） | AC18: 84 | AE18: Times | AF18: 1 | AG18: AddInteractiveObjectAppointPosition | AJ18: 0 | AK18: 1
A19: 20018 | B19: 引导 | C19: 2 | D19: 2 | E19: 1 | F19: 4 | G19: 3 | H19: 2 | I19: 0 | J19: 高价值敌方单位 | K19: 3 | L19: 7 | M19: 3 | N19: 1 | O19: 1 | P19: 碰到首个单位时，我方英雄向其位移 | Q19: 隐藏参数力大小{0}，回合结束标记消失 | V19: 3 | AB19: 发射飞行道具📦Effect_Magic18_Fly,触碰到首个可触发的单位时消失，在碰撞到的单位Body位置生成一个标记特效📦Effect_Magic18_Mark循环播放，跟随移动，回合结束消失 | AC19: 108 | AE19: Times | AF19: 1 | AG19: HeroMove2Collider | AJ19: 1 | AK19: 1
A20: 20019 | B20: 变大！ | C20: 2 | D20: 2 | E20: 1 | F20: 2 | G20: 2 | H20: 1 | I20: 3 | J20: 高价值敌方单位 | K20: 3 | L20: 2 | M20: 1 | N20: 1 | O20: 1 | P20: 使碰撞的首个单位变大{0}% | Q20: 隐藏参数质量增大{1}%，可加法叠加，敌我方都可，英雄注意大蛇，直接变宽，未来可以隐藏设定统一的变大变小的极限值 | V20: 3,4,5 | AB20: 发射飞行道具📦Effect_Magic19_Fly,触碰到首个可触发的单位时消失，在碰撞到的单位Body位置生成一个特效📦Effect_Magic19播放1次后消失，不跟随移动 飞行道具触碰到首个可触发单位的同时，该单位球0.3s内ease out插值缩放至效果大小 | AC20: 98 | AE20: Times | AF20: 1 | AG20: CollisionChangeVolume | AJ20: 1 | AK20: 1
A21: 20020 | B21: 缩小！ | C21: 2 | D21: 2 | E21: 1 | F21: 2 | G21: 2 | H21: 1 | I21: 3 | J21: 高价值我方单位 | K21: 3 | L21: 2 | M21: 1 | N21: 1 | O21: 1 | P21: 使碰撞的首个单位变小{0}% | Q21: 隐藏参数质量减小{1}%，其他同上 | V21: 0 | AB21: 发射飞行道具📦Effect_Magic20_Fly,触碰到首个可触发的单位时消失，在碰撞到的单位Body位置生成一个特效📦Effect_Magic19播放1次后消失，不跟随移动 飞行道具触碰到首个可触发单位的同时，该单位球0.3s内ease out插值缩放至效果大小 | AC21: 98 | AE21: Times | AF21: 1 | AG21: CollisionChangeVolume | AJ21: 1 | AK21: 1
A22: 20021 | B22: 精准引导 | C22: 2 | D22: 2 | E22: 1 | F22: 4 | G22: 4 | H22: 4 | I22: 3 | J22: 高价值敌方单位 | K22: 6 | L22: 7 | M22: 3 | P22: 指定战场任意位置，我方英雄向该位置位移 | Q22: 隐藏参数位移力度{0}，不能移动的英雄不生效 | V22: 3 | W22: 41 | AB22: 发动法术后，在指定的战场位置生成一个📦Effect_Magic21_Mark，英雄在延迟0.4s后向目标方向位移，该标记存在3s后消失 | AC22: 109 | AE22: Times | AF22: 1 | AG22: HeroMove2AppointPosition | AJ22: 0 | AK22: 1
A23: 20022 | B23: 蓄力 | C23: 2 | D23: 2 | E23: 1 | F23: 2 | G23: 1 | H23: 2 | I23: 3 | J23: 无目标 | K23: 5 | L23: 2 | M23: 1 | N23: 1 | O23: 1 | P23: 下一张打出的卡牌，发射速度增加{0}% | V23: 0 | AB23: 下一张打出若是单位牌，单位移动时会在Body位置附带📦Effect_Magic22_Trail特效跟随单位球移动，生成特效时，将单位球的当前帧图像应用至🌍Effect_Magic22_Trail材质球的MainTex 该特效在此单位球首次停止移动后消失 下一张打出的若是法术牌，则暂时只应用速度增加效果，不附带额外特效 | AC23: 117 | AE23: Times | AF23: 1 | AG23: SkillCardAddShootCardSpeed | AJ23: 0
A24: 20023 | B24: 弹簧安装 | C24: 2 | D24: 2 | E24: 1 | F24: 2 | G24: 2 | H24: 3 | I24: 3 | J24: 随机空地 （敌方或场上单位几何圆心重心） | K24: 6 | L24: 2 | M24: 1 | P24: 指定战场位置，生成一个弹簧，被单位碰撞到时施加弹力 | Q24: 同上推开规则。场景要素默认都是敌我方都有效，增加推力参数{1}，覆盖交互物的设置.交互物{0}.碰撞{2}次后消失 | V24: 4,5 | W24: 41 | Z24: 10002 | AB24: （通用特效：召唤单位和生成物，在要召唤单位的位置播放📦Effect_Summon） （通用弹簧特效：弹簧摧毁时，在弹簧位置生成并播放一个📦DamageDebrisParticle） | AE24: Times | AF24: 1 | AG24: InstallSpring | AJ24: 0 | AK24: 1
A25: 20024 | B25: 裂地斩 | C25: 2 | D25: 2 | E25: 1 | F25: 2 | G25: 4 | H25: 4 | I25: 0 | J25: 高价值敌方单位 （所有单位几何重心或圆心） | K25: 7 | L25: 2 | M25: 3 | P25: 场景穿透，路径上产生一条裂缝，受到{1}点伤害后消失 | Q25: 单位碰到裂缝反弹跟墙一样特性，投射物可以穿过，裂缝可以叠着，可以跨回合存在，发射时注意底边裂缝处理，产生裂缝时挤开单位，增加产生裂缝时向两边的力。隐藏参数力大小{0} | V25: 5 | W25: 8 | AB25: 发动法术后，从发射点位置生成并播放📦Effect_Magic24_Wall，生成时的旋转角度与操作发射角度相同，同时生成碰撞体，回合结束时特效和碰撞体消失 | AC25: 97 | AE25: Times | AF25: 1 | AG25: AddInteractiveObject | AJ25: 0 | AK25: 1
A26: 20025 | B26: 修建工事 | C26: 2 | D26: 2 | E26: 1 | F26: 2 | G26: 3 | H26: 3 | I26: 1 | J26: 无目标 | K26: 5 | L26: 2 | M26: 3 | P26: 在战场中间产生一堵由障碍物组成的墙，墙体血量为{1} | Q26: 尝试用障碍物场景物件横向排列而成，排不下则停下，例如大蛇存在时战场变小，相应墙也会缩短。交互物ID{0} | V26: 5 | Z26: 10005 | AB26: 从战场（0,0）位置开始向两侧以0.05s每个的速度生成障碍物，直至无法生成为止 （通用特效：召唤单位和生成物，在要召唤单位的位置播放📦Effect_Summon） （通用障碍物特效：障碍物摧毁时，在障碍物位置生成并播放一个📦DamageDebrisParticle） | AE26: Times | AF26: 1 | AG26: AddInteractiveObjectToSpecialPosition | AJ26: 0 | AK26: 1
A27: 20026 | B27: 风暴针刺 | C27: 2 | D27: 2 | E27: 1 | F27: 4 | G27: 4 | H27: 3 | I27: 0 | J27: 高价值敌方单位 | K27: 7 | L27: 8.5 | M27: 3 | P27: 根据本回合已打出的牌数，发射数根能量针，每个造成{0}点伤害 | Q27: 投射物首次碰到敌方单位或墙就会消失，隐藏参数宽度{1}，宽度决定投射物随机生成的左右范围 | V27: 2 | W27: 8 | AB27: 发动法术后，从随机出来的发射点位置生成并播放📦Effect_Magic26_Shoot，生成时的旋转角度与操作发射角度相同，发射间隔为0.35s/个；每次发射的特效播放0.15s后，，若对路径上的首个单位造成了伤害，则在受到伤害的单位Body处播放1个📦Effect_Magic26_Hit | AC27: 62 | AE27: Times | AF27: 1 | AG27: MultiRaycastCauseDamage | AJ27: 0 | AK27: 1
A28: 20027 | B28: 嗜血杀戮 | C28: 2 | D28: 2 | E28: 1 | F28: 2 | G28: 5 | H28: 3 | I28: 0 | J28: 无目标 | K28: 5 | L28: 2 | M28: 3 | N28: 1 | O28: 1 | P28: 保留，本回合接下来的时间，我方英雄每杀死一个单位，攻击力永久增加{0} | V28: 3,4,5 | W28: 36 | AB28: 发动法术后，在获得效果的对应英雄球处生成并播放1次📦Effect_Magic27 每次触发提升攻击力效果时，在自身球body处生成一个📦Effect_AttackUp特效播放1次，并跟随该单位球进行移动 （通用特效：当前攻击力大于原始攻击力的单位，body处始终循环播放📦Effect_AttackUp_Loop特效，并跟随单位球移动，直到不满足条件或死亡） | AC28: 53 76 | AE28: Times | AF28: 1 | AG28: HeroKillEnemyAddAttack | AJ28: 0 | AK28: 1
A29: 20028 | B29: 冰冻炸弹 | C29: 2 | D29: 2 | E29: 1 | F29: 3 | G29: 3 | H29: 3 | I29: 0 | J29: 高价值敌方单位 （所有单位周围伤害价值中取最高） | K29: 4 | L29: 5 | M29: 3 | N29: 1 | O29: 1 | P29: 碰到首个敌方时，对范围内的敌方单位造成{0}点伤害并冻结 | Q29: 隐藏参数范围大小{1}，对场景也生效，包括水地面，会变成冰地面。 | V29: 0 | W29: 44 | AB29: 发动法术后，从发射点生成飞行道具📦Effect_Magic28_Fly，按照操作发射方向飞出，触发效果后消失，触发效果时，在触发位置生成并播放1次📦Effect_Magic28_Boom，该特效跟随范围数值缩放 | AC29: 68 109 | AE29: Times | AF29: 1 | AG29: CollisionCauseRangeDamageAndAddBuffOnce | AJ29: 1 | AK29: 1
A30: 20029 | B30: 人工降雨 | C30: 2 | D30: 2 | E30: 1 | F30: 2 | G30: 2 | H30: 3 | I30: 3 | J30: 无目标 | K30: 5 | L30: 2 | M30: 1 | N30: 1 | O30: 1 | P30: 召唤雨天天气，回合结束消散 | Q30: 熄灭（去掉点燃buff）场上所有单位尝试挂上潮湿buff，隐藏参数天气类型{0}，这个技能本回合结束就消失，若是有多个天气时，后出者覆盖前出者 | R30: 召唤雨天天气，生成{0}个水面，{1}回合后消失 | S30: 熄灭（去掉点燃buff）场上所有单位尝试挂上潮湿buff，隐藏参数天气类型{2}，若是有多个天气时，后出者覆盖前出者 | T30: 召唤雨天天气，生成{0}个水面，{1}回合后消失 | U30: 熄灭（去掉点燃buff）场上所有单位尝试挂上潮湿buff，隐藏参数天气类型{2}，若是有多个天气时，后出者覆盖前出者 | V30: 0 | W30: 54 | AB30: 发动法术后，在战场（0,0）位置生成一个特效📦Effect_Weather_Rain，回合结束时消失 | AC30: 113rain | AE30: Times | AF30: 1 | AG30: SummonWeather | AJ30: 0 | AK30: 1
A31: 20030 | B31: 雷枪 | C31: 2 | D31: 1 | E31: 1 | F31: 3 | G31: 3 | H31: 2 | I31: 0 | J31: 高价值敌方单位 | K31: 6 | L31: 5 | M31: 3 | P31: 指定位置，召唤一道雷电，对最近的敌方单位造成一次{0}点电击伤害 | Q31: 隐藏效果，打出时若是雨天，则将天气转化成雷雨天 | V31: 0 | W31: 41 | X31: 47 | AB31: 对选定位置最近的敌方单位Body处生成一道雷击特效📦Effect_Magic30_Hit播放特效后0.1s再触发实际的法术效果（伤害和电击） | AC31: 转换为雷雨天气时，销毁原本的雨天特效，在战场（0,0）位置生成一个特效📦Effect_Weather_Thunderstorm 雷雨天气的攻击特效使用雷击特效📦Effect_Magic30_Hit播放特效后0.1s再触发实际的法术效果（伤害和电击） 液体地面液体地面感电特效为：在触发感电效果的所有液体地面地块中心点播放一个📦Effect_Electrocution1 | AE31: Times | AF31: 1 | AG31: SummonThunder | AJ31: 0 | AK31: 1
A32: 20031 | B32: 滋水 | C32: 2 | D32: 2 | E32: 1 | F32: 3 | G32: 3 | H32: 1 | I32: 0 | J32: 高价值敌方单位 | K32: 7 | L32: 5 | M32: 3 | N32: 1 | O32: 1 | P32: 对触碰的首个敌方单位造成{0}点伤害，并赋予潮湿状态 | Q32: 凑数技能，水瓶娘滋水，对碰到的我方也会赋予潮湿 | R32: 场景穿透，对触碰的所有敌方单位造成{0}点伤害，并赋予潮湿状态 | S32: 隐藏参数宽度{1}，递进第二级滋水。隐藏效果，对碰到的我方赋予潮湿 | T32: 场景穿透，发射水柱击退路径上的所有敌方单位，造成{0}点伤害，并赋予潮湿状态 | U32: 隐藏参数宽度{1}，隐藏参数击退力度{2}，留下水地面，第三级递进滋水。隐藏效果，对碰到的我方赋予潮湿和一样的推力 | V32: 0 | W32: 8 | X32: 45 | AB32: 发动法术后，从发射点生成飞行道具📦Effect_Magic31_Fly，按照操作发射方向飞出，触发效果后消失，触发效果时，在被击中的单位球Body处生成并播放1次📦Effect_Water_Hit，该特效跟随单位球移动 | AC32: 80 | AE32: Times | AF32: 1 | AG32: SceneThroughCauseDamageAndAddBuffOnce | AH32: SceneThroughCauseDamageAndAddBuff | AI32: SceneThroughCauseDamageAddForceAndAddBuff | AJ32: 0
A33: 20034 | B33: 补水计划 | C33: 2 | D33: 2 | E33: 1 | F33: 3 | G33: 6 | H33: 4 | I33: 3 | J33: 无目标 | K33: 5 | L33: 5 | M33: 1 | P33: 保留，打出时每有一个敌方单位，手牌中生成一张临时的纯净水-浅浅 | Q33: 隐藏参数生成卡ID{0} | V33: 1，2 | W33: 36 | X33: 3 | AB33: 发动法术后，从每个敌方单位Body位置生成一个📦Effect_Magic34_Fly，0.5s内ease in out插值飞至对应方手牌区域中心位置，到达终点后消失 | AC33: 80 | AE33: Times | AF33: 1 | AG33: AddHandCard | AJ33: 0 | AK33: 1
A34: 20035 | B34: 冰霜新星 | C34: 2 | D34: 2 | E34: 1 | F34: 2 | G34: 5 | H34: 4 | I34: 3 | J34: 无目标 | K34: 5 | L34: 5 | M34: 1 | P34: 冻结场上的所有单位 | Q34: 同样冻结所有液体地面和可冻结场景物件 | W34: 44 | AB34: 发动法术后，在战场(0,0)丶位置生成一个📦Effect_Magic35特效播放1次，播放特效后0.45s再触发实际的法术效果（冰冻这些） | AC34: 112 | AE34: Times | AF34: 1 | AG34: AddBuffToAllEntity | AJ34: 0 | AK34: 1
A35: 20036 | B35: 巨雷枪 | C35: 2 | D35: 2 | E35: 1 | F35: 4 | G35: 4 | H35: 4 | I35: 0 | J35: 覆盖更多敌方单位 （最多击杀） | K35: 7 | L35: 5 | M35: 3 | P35: 场景穿透，对敌方单位造成{0}点电击伤害，每穿过一个敌方，生成一张临时的雷枪 | Q35: 蔓延的电击伤害击杀也算，隐藏效果，打出时若是雨天，则将天气转化成雷雨天，隐藏参数生成卡ID{1}，隐藏参数宽度{2}，增加对经过的场景物件的伤害 | V35: 2 | W35: 8 | X35: 47 | Y35: 3 | AB35: 发动法术后，从发射点位置生成并播放1次📦Effect_Magic36_Shoot，生成时的旋转角度与操作发射角度相同，特效播放0.15s后，在受到此技能伤害判定的所有单位球处播放1次📦Effect_Magic36_Hit，此特效不跟随单位球移动，同时造成伤害 | AC35: 转换为雷雨天气时，销毁原本的雨天特效，在战场（0,0）位置生成一个特效📦Effect_Weather_Thunderstorm 雷雨天气的攻击特效使用雷击特效📦Effect_Magic30_Hit播放特效后0.1s再触发实际的法术效果（伤害和电击） 液体地面液体地面感电特效为：在触发感电效果的所有液体地面地块中心点播放一个📦Effect_Electrocution1 | AE35: Times | AF35: 1 | AG35: SceneThroughCauseElectricshock | AJ35: 0 | AK35: 1
A36: 20037 | B36: 投石支援 | C36: 2 | D36: 2 | E36: 1 | F36: 3 | G36: 4 | H36: 4 | I36: 0 | J36: 覆盖更多敌方单位 （圆形范围敌方最多） | K36: 6 | L36: 5 | M36: 3 | P36: 指定战场任意位置，对范围内的敌方单位造成{0}点伤害并眩晕{1}层 | Q36: 隐藏参数范围{2}，敌我双方都生效,眩晕ID{3} | R36: 指定战场任意位置，掉落石头对较大范围内的敌方单位造成{0}点伤害并眩晕{1}层 | S36: 隐藏参数范围{2}，敌我双方都生效，眩晕ID{3} | T36: 指定战场任意位置，掉落石头对大范围内的敌方单位造成{0}点伤害并眩晕{1}层 | U36: 隐藏参数范围{2}，敌我双方都生效，眩晕ID{3} | V36: 0 | W36: 41 | X36: 52 | AB36: 发动法术后，在指定的位置播放📦Effect_Magic37_Hit特效1次，特效播放0.2s后触发范围伤害及眩晕效果，该特效跟随范围配置进行缩放 | AC36: 60 | AE36: Times | AF36: 1 | AG36: CauseDamageAndAddBuffAtAppointPosition | AJ36: 0 | AK36: 1
A37: 20038 | B37: 飞砖 | C37: 2 | D37: 2 | E37: 1 | F37: 3 | G37: 2 | H37: 2 | I37: 0 | J37: 高价值敌方单位 | K37: 3 | L37: 5 | M37: 3 | P37: 碰到首个敌方单位时，对其造成{0}点伤害并眩晕{1}层 | Q37: 眩晕技能ID{2} | V37: 0 | W37: 52 | AB37: 发动法术后，从发射点生成飞行道具📦Effect_Magic38_Fly，按照操作发射方向飞出，触发效果后消失，触发效果时，在触发位置生成并播放1次📦Effect_Magic38_Hit | AC37: 68zhuan | AE37: Times | AF37: 1 | AG37: CollisionCauseDamageAndAddBuffOnce | AJ37: 1 | AK37: 1
A38: 20039 | B38: 战术核武 | C38: 2 | D38: 2 | E38: 1 | F38: 4 | G38: 4 | H38: 4 | I38: 1 | J38: 无目标 | K38: 5 | L38: 5 | M38: 3 | P38: 保留，对所有单位和场景物件造成{0}点伤害并点燃 | Q38: 敌我双方都受伤，位置为战场中心，并且有力向周围，隐藏参数推动力{1} | V38: 4,5 | W38: 36 | X38: 43 | AB38: 发动法术后，在战场(0,0)丶位置生成一个📦Effect_Magic39_Boom特效播放1次，播放特效后0.3s再触发实际的法术效果（伤害和推力） | AC38: 82 | AE38: Times | AF38: 1 | AG38: CauseDamageAndAddBuffToAllEntity | AJ38: 0 | AK38: 1
A39: 20040 | B39: 混乱补给 | C39: 2 | D39: 2 | E39: 1 | F39: 2 | G39: 2 | H39: 2 | I39: 3 | J39: 无目标 | K39: 5 | L39: 5 | M39: 1 | N39: 1 | O39: 1 | P39: 在随机空地召唤{0}个礼物盒，被碰撞若干次后打开，打开的玩家获得随机奖励 | Q39: 局外货币，全体回血，全体加攻等等都可，预期三回合打开 | V39: 0 | Z39: 10004 | AB39: （通用特效：召唤单位和生成物，在要召唤单位的位置播放📦Effect_Summon） （通用礼物盒特效：礼物盒摧毁时，在礼物盒位置生成并播放一个📦DamageDebrisParticle） 礼物盒被摧毁时，根据随机效果在礼物盒位置生成对应动画 全体加攻时：所有被加攻的单位播放通用加攻效果 全体回复时：所有被回复的单位播放通用恢复效果 | AE39: Times | AF39: 1 | AG39: ChaosSupply | AJ39: 0 | AK39: 1
A40: 20041 | B40: 冰冻陷阱 | C40: 2 | D40: 2 | E40: 1 | F40: 2 | G40: 2 | H40: 3 | I40: 0 | J40: 无目标 | K40: 5 | L40: 3 | M40: 3 | P40: 在随机空地召唤{0}个陷阱，将敌方单位推入时造成{1}伤害，眩晕{2}层并冻结，陷阱触发后消失 | Q40: 回合结束不消失，直到一方推入另一方。我的回合，敌方会触发陷阱，反过来敌方回合就是我方触发陷阱。非主动回合一方会触发陷阱 | V40: 0 | Z40: 10003 | AB40: （通用特效：召唤单位和生成物，在要召唤单位的位置播放📦Effect_Summon） （通用陷阱特效：礼物盒摧毁时，在礼物盒位置生成并播放一个📦DamageDebrisParticle 陷阱触发伤害效果时，陷阱播放触发动画，同时在受到陷阱伤害的单位球处生成并播放1次📦Effect_Trap_Hit特效，该特效跟随单位球移动） | AC40: 108 | AE40: Times | AF40: 1 | AG40: AddInteractiveObjectAtRandomPosition | AJ40: 0 | AK40: 1
A41: 20042 | B41: 协力攻击 | C41: 2 | D41: 2 | E41: 1 | F41: 4 | G41: 4 | H41: 4 | I41: 0 | J41: 覆盖更多敌方单位（起点到终点间伤害价值取最高） | K41: 2 | L41: 6.3 | M41: 3 | N41: 1 | O41: 1 | P41: 穿透，对碰到的第一个敌方单位，造成路径上经过所有我方单位攻击{0}%的伤害 | Q41: 注意大蛇弹墙壁，算一次还是两次，得测了告诉我，数值有所调整 | V41: 1,5 | W41: 6 | AB41: 发动法术后，从发射点生成飞行道具📦Effect_Magic42_Fly，按照操作发射方向飞出，触发伤害效果后消失，触发效果时，在触发位置生成并播放1次📦Effect_Magic42_Hit | AC41: 110 001 | AE41: Times | AF41: 1 | AG41: CollisionStackAttackCauseDamage | AJ41: 1 | AK41: 1
A42: 20043 | B42: 爆裂药瓶 | C42: 2 | D42: 2 | E42: 1 | F42: 4 | G42: 4 | H42: 3 | I42: 0 | J42: 高价值我方单位（所有单位圆形范围回血价值取最高） | K42: 4 | L42: 5 | M42: 3 | P42: 碰到首个单位时，回复范围内的我方单位{0}点生命 | Q42: 隐藏参数范围大小{1} | V42: 0 | AB42: 发动法术后，从发射点生成飞行道具📦Effect_Magic43_Fly，按照操作发射方向飞出，触发效果后消失，触发效果时，在触发位置生成并播放1次📦Effect_Magic43_Boom，该特效跟随范围数值缩放 （通用效果：回复血量，单位回复生命时，无论是否满血，都在该单位球处生成1个📦Effect_Health_Hit，跟随单位球移动，播放完成后消失） | AC42: 56 | AE42: Times | AF42: 1 | AG42: CollisionRecoverHp | AJ42: 1 | AK42: 1
A43: 20044 | B43: 胡乱抓挠 | C43: 2 | D43: 2 | E43: 1 | F43: 4 | G43: 4 | H43: 2 | I43: 0 | J43: 无目标 | K43: 5 | L43: 8 | M43: 3 | P43: 对随机敌方单位造成{0}次{1}点伤害，同一敌方单位每被击中一次，该伤害增加{2}% | Q43: 克制单体随从的教程牌，不同单位独立计算重复次数，每次伤害增加为先加后乘 | AB43: 发动法术后，以0.15s为间隔随机目标造成伤害，每次造成伤害时，在受到伤害的目标单位球处播放📦Effect_Magic44_Hit | AC43: 2 | AE43: Times | AF43: 1 | AG43: MultiCauseDamage2RandomEnemy | AJ43: 0 | AK43: 1
A44: 20045 | B44: 接力 | C44: 2 | D44: 2 | E44: 1 | F44: 4 | G44: 3 | H44: 5 | I44: 0 | J44: 高价值我方单位 | K44: 2 | L44: 6.4 | M44: 3 | N44: 1 | O44: 1 | P44: 穿透，碰到的第二个我方随从单位，吸收碰到的第一个我方随从单位{0}%的当前属性 | Q44: 注意是随从，英雄不算，和橡皮类似，第一个单位攻血属性扣掉对应的百分比，最大值也会，第二个单位血量上限也会增加。若第二个单位没打中，则不触发效果，第一个单位也不扣属性。 | W44: 6 | AB44: 发动法术后，从发射点生成飞行道具📦Effect_Magic45_Fly，按照操作发射方向飞出， 完成了整个技能的飞行判断流程后，进行以下流程： 在属性下降的单位球处播放📦Effect_Magic45_Hit1 该特效跟随单位球移动； 在属性提升的单位球处播放📦Effect_Magic45_Hit2 该特效跟随单位球移动 | AE44: Times | AF44: 1 | AG44: ReduceCreatureAttribute2Others | AJ44: 1 | AK44: 1
A45: 20046 | B45: 重新出发 | C45: 2 | D45: 2 | E45: 1 | F45: 4 | G45: 3 | H45: 3 | I45: 3 | J45: 高价值我方单位 | K45: 3 | L45: 8 | M45: 1 | P45: 碰到首个我方随从单位时，将其牺牲，并获得一张相同随从的临时卡 | Q45: 等于一张新卡，不继承场中单位的任何属性 | W45: 3 | AB45: 发动法术后，从发射点生成飞行道具📦Effect_Magic46_Fly，按照操作发射方向飞出，触发伤害效果后消失，触发效果时，在触发位置生成并播放1次📦Effect_Magic46_Hit | AE45: Times | AF45: 1 | AG45: SacrificeCollisionCreatureGetCardOnce | AJ45: 1 | AK45: 1
A46: 20047 | B46: 临摹 | C46: 2 | D46: 2 | E46: 1 | F46: 2 | G46: 3 | H46: 4 | I46: 3 | J46: 无目标 | K46: 5 | L46: 2 | M46: 3 | P46: 保留，随机获得一张敌方手牌的临时复制 | Q46: 临时优先级高于保留，若同时存在两个特性，优先临时。临摹复制过来的牌与自身等级一致，例如1级临摹复制了3级的纯净水，但是玩家只能获得1级的纯净水 | W46: 36 | X46: 3 | Y46: 34 | AB46: 无特效，后续补充 | AE46: Times | AF46: 1 | AG46: GetEnemyHandCard | AJ46: 0 | AK46: 1
A47: 20048 | B47: 超电磁炮 | C47: 2 | D47: 2 | E47: 1 | F47: 3 | G47: 4 | H47: 3 | I47: 0 | J47: 高价值敌方单位 | K47: 7 | L47: 5 | M47: 3 | P47: 场景穿透，对敌方单位造成{0}点电击伤害 | Q47: 和巨雷枪效果一致，包括引起雷雨，蔓延伤害这些，隐藏参数宽度{1}，增加对经过的场景物件的伤害 | W47: 8 | X47: 47 | AB47: 发动法术后，从发射点位置生成并播放1次📦Effect_Magic48_Shoot，生成时的旋转角度与操作发射角度相同，特效播放1s后，对路径上的所有敌方造成伤害 | AE47: Times | AF47: 1 | AG47: SceneThroughCauseElectricshockDontRebackCard | AJ47: 0 | AK47: 1
A48: 20049 | B48: 尖刺墙 | C48: 2 | D48: 2 | E48: 1 | F48: 2 | G48: 4 | H48: 4 | I48: 3 | J48: 无目标 | K48: 5 | L48: 3 | M48: 3 | P48: 在我方方舟前生成一堵尖刺墙，墙体血量为{1} | Q48: 在敌方半场最远处墙壁前生成一行，由尖刺墙交互物组成的墙，推开其他单位，若有大蛇，则在大蛇下方整数格子生成。交互物ID{0} | Z48: 10007 | AB48: 通用summon | AE48: Times | AF48: 1 | AG48: AddInteractiveUponScene | AJ48: 0 | AK48: 1
A49: 20050 | B49: 海浪冲击 | C49: 2 | D49: 2 | E49: 1 | F49: 4 | G49: 5 | H49: 5 | I49: 0 | J49: 无目标 | K49: 5 | L49: 8 | M49: 3 | P49: 召唤海浪 | Q49: 对所有单位赋予一个自下而上的力，隐藏参数力大小{0}，随机留下{1}个水地面，尝试赋予所有单位潮湿，去除所有火焰地面.{2}海浪次数，{3}海浪间隔 | R49: 召唤{2}次海浪，留下{1}个水地面 | S49: 对所有单位赋予一个自下而上的力，隐藏参数力大小{0}，随机留下{1}个水地面，尝试赋予所有单位潮湿，去除所有火焰地面.{2}海浪次数，{3}海浪间隔 | T49: 召唤{2}次海浪，留下{1}个水地面 | U49: 对所有单位赋予一个自下而上的力，隐藏参数力大小{0}，随机留下{1}个水地面，尝试赋予所有单位潮湿，去除所有火焰地面.{2}海浪次数，{3}海浪间隔 | AB49: 发动法术后，在战场(0,0)丶位置生成一个📦Effect_Magic50特效播放1次，播放特效后0.5s内，从下到上依次发动实际效果 | AE49: Times | AF49: 1 | AG49: SummonWaves | AJ49: 1 | AK49: 1
A50: 20051 | B50: 修建阵地 | C50: 2 | D50: 2 | E50: 1 | F50: 4 | G50: 3 | H50: 2 | I50: 1 | J50: 无目标 | K50: 5 | L50: 8 | M50: 3 | P50: 在我方英雄周围生成{0}个掩体，掩体血量为{2} | Q50: 尽量靠近英雄的随机空地，生成掩体，去掉炸药桶生成。交互物ID{1} | Z50: 10008 | AB50: 通用summon | AE50: Times | AF50: 1 | AG50: AddInteractiveAroundHero | AJ50: 0 | AK50: 1
A51: 20052 | B51: 机关枪 | C51: 2 | D51: 1 | E51: 2 | F51: 4 | G51: 2 | H51: 3 | I51: 0 | J51: 高价值敌方单位 | K51: 3 | L51: 6 | M51: 3 | N51: 1 | O51: 1 | P51: 连射，向瞄准方向发射子弹，伤害{0}{1}，弹药数量{2} | Q51: 隐藏参数发射延迟{3}，子弹飞行间隔{4}，子弹类型{5}，子弹最大存在时间{6}。子弹规则为场景物件反弹，打中第一个敌方单位或中立单位生效伤害并结束飞行。 | W51: 56 | AB51: Effect_Magic52_Fly Effect_Magic52_Hit | AE51: Times | AF51: 1 | AG51: MachineGun
A52: 20053 | B52: 连击机关枪 | C52: 2 | D52: 1 | E52: 2 | F52: 4 | G52: 5 | H52: 3 | I52: 0 | J52: 高价值敌方单位 | K52: 3 | L52: 8 | M52: 3 | N52: 1 | O52: 1 | P52: 连射，向瞄准方向发射子弹，伤害{0}{1}，弹药数量等于当前连击数的{2}% | Q52: 隐藏参数发射延迟{3}，子弹飞行间隔{4}，子弹类型{5}，子弹最大存在时间{6}。首次发射后弹药数固定，打到一半连击增加，弹药数也不再受影响。 | W52: 56 | AB52: Effect_Magic53_Fly Effect_Magic53_Hit | AE52: Times | AF52: 1 | AG52: MachineGun
A53: 20054 | B53: 回收 | C53: 2 | D53: 2 | E53: 1 | F53: 1 | G53: 4 | H53: 4 | I53: 3 | J53: 无目标 | K53: 5 | L53: 5 | M53: 1 | P53: 下一张打出的卡牌，从自身牌库中移除 | Q53: 根据对应星级，折算成1星卡数量，返还到总商店库中 | AE53: Times | AF53: 1 | AG53: RecycleNextCard
A54: 20055 | B54: 连击炮 | C54: 2 | D54: 1 | E54: 1 | F54: 4 | G54: 4 | H54: 3 | I54: 0 | J54: 高价值敌方单位 | K54: 3 | L54: 8 | M54: 3 | N54: 1 | O54: 1 | P54: 碰到首个敌方时，造成当前连击数*{0}的伤害 | Q54: 场景反弹 | AB54: Effect_Magic55_Fly Effect_Magic55_Hit | AE54: Times | AF54: 1 | AG54: CollisionCauseDamageOnce | AJ54: 1
A55: 20056 | B55: 协力炮 | C55: 2 | D55: 1 | E55: 1 | F55: 4 | G55: 4 | H55: 3 | I55: 1 | J55: 高价值敌方单位 | K55: 3 | L55: 8 | M55: 3 | N55: 1 | O55: 1 | P55: 碰到首个敌方时，造成当前我方单位数*{0}的伤害 | Q55: 场景反弹 | AB55: Effect_Magic56_Fly Effect_Magic56_Hit | AE55: Times | AF55: 1 | AG55: CollisionCauseDamageOnce | AJ55: 1
A56: 20057 | B56: 金币炮 | C56: 2 | D56: 1 | E56: 1 | F56: 4 | G56: 5 | H56: 3 | I56: 1 | J56: 高价值敌方单位 | K56: 3 | L56: 8 | M56: 3 | N56: 1 | O56: 1 | P56: 碰到首个敌方时，造成当前金币数*{0}的伤害 | Q56: 本回合金币数 | AB56: Effect_Magic57_Fly Effect_Magic57_Hit | AE56: Times | AF56: 1 | AG56: CollisionCauseDamageOnce | AJ56: 1
A57: 20058 | B57: 单位机关枪 | C57: 2 | D57: 1 | E57: 2 | F57: 4 | G57: 5 | H57: 3 | I57: 0 | J57: 高价值敌方单位 | K57: 3 | L57: 8 | M57: 3 | N57: 1 | O57: 1 | P57: 连射，向瞄准方向发射子弹，伤害{0}{1}，弹药数量等于当前我方单位数的{2}% | Q57: 隐藏参数发射延迟{3}，子弹飞行间隔{4}，子弹最大存在时间{5}。首次发射后弹药数固定，打到一半单位数变化，弹药数也不再受影响。 | W57: 56 | AB57: Effect_Magic58_Fly Effect_Magic58_Hit | AE57: Times | AF57: 1 | AG57: MachineGun
A58: 20059 | B58: 机关枪子弹 | C58: 3 | D58: 1 | E58: 1 | F58: 3 | G58: 1 | H58: 3 | I58: 0 | J58: 更多敌方单位 （飞行路径敌方伤害价值取最高） | K58: 2 | L58: 5 | M58: 3 | N58: 1 | O58: 1 | P58: 伤害{0} | AE58: Times | AF58: 1 | AG58: NormalBullet | AJ58: 1
A59: 20060 | B59: 连击机关枪子弹 | C59: 3 | D59: 1 | E59: 1 | F59: 3 | G59: 1 | H59: 3 | I59: 0 | J59: 更多敌方单位 （飞行路径敌方伤害价值取最高） | K59: 2 | L59: 5 | M59: 3 | N59: 1 | O59: 1 | P59: 伤害{0} | AE59: Times | AF59: 1 | AG59: NormalBullet | AJ59: 1
A60: 20061 | B60: 单位机关枪子弹 | C60: 3 | D60: 1 | E60: 1 | F60: 3 | G60: 1 | H60: 3 | I60: 0 | J60: 更多敌方单位 （飞行路径敌方伤害价值取最高） | K60: 2 | L60: 5 | M60: 3 | N60: 1 | O60: 1 | P60: 伤害{0} | AE60: Times | AF60: 1 | AG60: NormalBullet | AJ60: 1
A61: 20062 | B61: 瞬移 | C61: 2 | D61: 2 | E61: 1 | F61: 1 | G61: 4 | H61: 5 | I61: 5 | J61: 高价值敌方单位 | K61: 6 | L61: 2 | M61: 3 | O61: 1 | P61: 指定战场位置，我方英雄瞬移到该位置 | Q61: 食人花专属，对大蛇无用，其他英雄也可以用.复制过来的牌与自身等级一致，例如1级复制了3级的纯净水，但是玩家只能获得1级的纯净水 | W61: 41 | AB61: 暂无特效 | AE61: Times | AF61: 1 | AG61: Teleport
A62: 20063 | B62: 复制 | C62: 2 | D62: 2 | E62: 1 | F62: 1 | G62: 4 | H62: 5 | I62: 5 | J62: 无目标 | K62: 5 | L62: 2 | M62: 3 | P62: 打出时，随机获得战场上{0}个随从单位的临时复制 | Q62: 单位牌到手上，类似临摹 | W62: 3 | X62: 34 | AB62: 暂无特效 | AE62: Times | AF62: 1 | AG62: GetOurUnitCard
A63: 20064 | B63: 猎杀标记 | C63: 2 | D63: 2 | E63: 1 | F63: 1 | G63: 4 | H63: 2 | I63: 0 | J63: 低血量敌方单位 | K63: 3 | L63: 2 | M63: 3 | P63: 标记碰到的首个敌方单位，并对其造成{0}伤害，标记单位死亡时，再次获取本卡，回合结束标记消失 | Q63: 本卡的临时复制，英雄也能标记 | AB63: Effect_Magic64_Fly，飞行道具 Effect_Magic64_Mark，同20018 | AE63: Times | AF63: 1 | AG63: HuntingMark | AJ63: 1
A64: 20065 | B64: 回旋镖 | C64: 2 | D64: 2 | E64: 1 | F64: 1 | G64: 4 | H64: 2 | I64: 5 | J64: 无目标 | K64: 5 | L64: 5 | M64: 3 | P64: 对随机敌方单位造成{0}点伤害，打出时有{1}%概率回到手牌，每次打出概率下降{2}% | Q64: 技能版羽毛球 | AB64: Effect_Magic65_Hit： 受到攻击的敌方位置播放 | AE64: Times | AF64: 1 | AG64: ConsecutiveKill | AJ64: 1
A65: 20066 | B65: 协力恢复 | C65: 2 | D65: 2 | E65: 1 | F65: 1 | G65: 4 | H65: 4 | I65: 0 | J65: 无目标 | K65: 5 | L65: 2 | M65: 3 | P65: 打出时，我方单位比敌方单位每少一个，为所有我方单位回复{0}生命 | W65: 36 | AB65: 通用回复 | AE65: Times | AF65: 1 | AG65: CooperativeRecovery
A66: 20067 | B66: 金币机关枪 | C66: 2 | D66: 1 | E66: 2 | F66: 1 | G66: 5 | H66: 3 | I66: 1 | J66: 高价值敌方单位 | K66: 3 | L66: 8 | M66: 3 | N66: 1 | O66: 1 | P66: 连射，向瞄准方向发射子弹，伤害{0}{1}，弹药数量等于当前可用金币数的{2}% | W66: 56 | AE66: Times | AF66: 1 | AG66: MachineGun
A67: 20068 | B67: 集合 | C67: 2 | D67: 2 | E67: 1 | F67: 1 | G67: 4 | H67: 3 | I67: 0 | J67: 无目标 | K67: 5 | L67: 8 | M67: 3 | P67: 保留，打出时，将场上所有我方同名随从融合成一个，属性继承{0}% | Q67: 随机选择其中一个作为载体即可，属性为当前属性。例如场上三个羽毛球，随机挑其中一个，获得另外两个{0}%属性，另外两个杀死 | W67: 36 | AB67: 暂无特效 | AE67: Times | AF67: 1 | AG67: Fusion
A68: 20069 | B68: 剥削 | C68: 2 | D68: 2 | E68: 1 | F68: 1 | G68: 4 | H68: 3 | I68: 1 | J68: 无目标 | K68: 5 | L68: 6 | M68: 3 | N68: 1 | O68: 1 | P68: 对随机{0}个我方单位造成{1}点伤害，获得{2}个金币 | Q68: 若场上没有击中友方，就不生效，若击中友方但是因为圣盾这些没造成伤害，还是生效的 | AB68: Effect_Magic69_Hit： 受伤的单位位置播 这个 | AE68: Times | AF68: 1 | AG68: DonateBlood
A69: 20070 | B69: 夺魂 | C69: 2 | D69: 2 | E69: 1 | F69: 1 | G69: 5 | H69: 3 | I69: 0 | J69: 低血量敌方单位 | K69: 3 | L69: 8 | M69: 3 | P69: 碰到首个敌方单位时，对其造成{0}伤害，若击杀，则召唤一个该单位的我方复制 | Q69: 不保留属性和buff，相当于一张新卡，重新召唤在原地，敌方变我方 | W69: 34 | AB69: Effect_Magic70_Fly： 飞行道具 | AE69: Times | AF69: 1 | AG69: Induce2Capitulate | AJ69: 1
A70: 20071 | B70: 金币机关枪子弹 | C70: 3 | D70: 1 | E70: 1 | F70: 3 | G70: 1 | H70: 3 | I70: 0 | J70: 更多敌方单位 （飞行路径敌方伤害价值取最高） | K70: 2 | L70: 5 | M70: 3 | N70: 1 | O70: 1 | P70: 伤害{0} | AB70: Effect_Magic71_Fly： 飞行道具 Effect_Magic71_Hit | AE70: Times | AF70: 1 | AG70: NormalBullet
A71: 20072 | B71: 瞄准 | C71: 2 | D71: 2 | E71: 1 | F71: 1 | G71: 4 | H71: 3 | I71: 3 | J71: 高价值敌方单位 | K71: 3 | L71: 2 | M71: 1 | P71: 保留，碰到首个单位时，为其添加一个定向标记，所有随机选择目标的技能，都优先以该单位为目标 | Q71: 英雄也算，敌我的优先级更高，随机我方的技能不会选到敌方去，反之同理，若有多个定向标记，则在其中随机，标记持久保存，直到单位死亡 | W71: 36 | AB71: Effect_Magic72_Fly，飞行道具 Effect_Magic72_Mark，同20018
A72: 20073 | B72: 镭射光束 | C72: 2 | D72: 2 | E72: 1 | F72: 1 | G72: 4 | H72: 5 | I72: 0 | J72: 高价值敌方单位 | K72: 7 | L72: 5 | M72: 3 | P72: 场景穿透，持续对敌方造成{0}点伤害，持续{1}秒 | Q72: 隐藏参数伤害间隔{2}，光束宽度{3}，克制方舟的技能，方舟像素破坏后，会继续破坏后面的像素 做一张发镭射光束的单位卡 | AB72: Effect_Magic73_Line： 激光本体，分为2层效果，均使用Line Renderer实现，生成时需要实时获取激光的起始坐标与结束坐标，赋给Line Renderer的PostionIndex的X值，技能结束时禁用或销毁 Effect_Magic73_Hit： 在激光结束点的位置生成并跟随结束点移动，技能结束时禁用或销毁 | AE72: Duration | AF72: 2 | AG72: LaserBeam
A73: 20074 | B73: 随机升星 | C73: 2 | D73: 2 | E73: 1 | F73: 1 | G73: 4 | H73: 4 | I73: 3 | J73: 无目标 | K73: 5 | L73: 5 | M73: 1 | N73: 1 | O73: 1 | P73: 保留，打出时，牌组里的随机一张牌升{0}星 | Q73: 不会选英雄专属卡 | W73: 36 | AB73: 暂无特效 | AE73: Times | AF73: 1 | AG73: RandomStarUp
A74: 20075 | B74: 定向升星 | C74: 2 | D74: 2 | E74: 1 | F74: 1 | G74: 4 | H74: 4 | I74: 3 | J74: 无目标 | K74: 5 | L74: 5 | M74: 1 | N74: 1 | O74: 1 | P74: 保留，打出后，使你打出的下一张牌升{0}星 | Q74: 若该卡牌无法升星或者是英雄专属卡，跳过，下一张卡再生效，可以加一个最多跳过次数。打出这张就让其升星成功，即时反馈 | W74: 36 | AB74: 暂无特效 | AE74: Times | AF74: 1 | AG74: NextStarUp
A75: 20076 | B75: 主炮子弹 | C75: 3 | D75: 1 | E75: 1 | F75: 3 | G75: 1 | H75: 3 | I75: 0 | J75: 更多敌方单位 （飞行路径敌方伤害价值取最高） | K75: 2 | L75: 5 | M75: 3 | N75: 1 | O75: 1 | P75: 伤害{0} | AB75: Effect_Magic76_Fly： 飞行道具 Effect_Magic76_Hit | AE75: Times | AF75: 1 | AG75: GunBullet
A76: 20077 | B76: 副炮子弹 | C76: 3 | D76: 1 | E76: 1 | F76: 3 | G76: 1 | H76: 3 | I76: 0 | J76: 更多敌方单位 （飞行路径敌方伤害价值取最高） | K76: 2 | L76: 5 | M76: 3 | N76: 1 | O76: 1 | P76: 伤害{0} | AB76: Effect_Magic77_Fly： 飞行道具 Effect_Magic77_Hit | AE76: Times | AF76: 1 | AG76: GunBullet
A77: 20078 | B77: 应急英雄 | C77: 2 | D77: 2 | E77: 1 | F77: 1 | G77: 4 | H77: 2 | I77: 3 | L77: 2.2 | P77: 从牌库抽取我方英雄，打出时英雄生命为1 | AE77: Times | AF77: 1 | AG77: EmergencyHero
A78: 20079 | B78: 召唤英雄 | C78: 2 | D78: 2 | E78: 1 | F78: 1 | G78: 4 | H78: 4 | I78: 3 | L78: 2.2 | P78: 从牌库抽取我方英雄 | AE78: Times | AF78: 1 | AG78: SummonHero
A79: 20080 | B79: 尾针开刃 | C79: 2 | D79: 2 | E79: 1 | F79: 1 | G79: 4 | H79: 5 | I79: 5 | L79: 5 | O79: 1 | P79: 打出时燃烧英雄{0}%当前血量，为其永久增加燃烧血量{1}%的攻击 | Q79: 新版本梅丽莎专属卡 | AE79: Times | AF79: 1 | AG79: TailNeedle
A80: 20081 | B80: 合众为一 | C80: 2 | D80: 2 | E80: 1 | F80: 1 | G80: 4 | H80: 5 | I80: 5 | L80: 8 | O80: 1 | P80: 将所有我方分裂体回收到本体 | Q80: 新版本宁芙专属卡 | AE80: Times | AF80: 1 | AG80: Merge
A81: 20082 | B81: 随机重塑 | C81: 2 | D81: 2 | E81: 1 | F81: 1 | G81: 4 | H81: 3 | I81: 3 | L81: 5 | P81: 将碰到的首个我方随从，变形成随机单位 | Q81: 雇佣兵卡也算 | AE81: Times | AF81: 1 | AG81: Deformation
A82: 20083 | B82: 同归于尽！ | C82: 2 | D82: 2 | E82: 1 | F82: 1 | G82: 4 | H82: 5 | I82: 3 | L82: 2 | P82: 保留，引爆我方本节方舟，对场上所有单位和敌方方舟造成{0}点伤害 | AE82: Times | AF82: 1 | AG82: TogetherDie
A83: 20084 | B83: 呕！ | C83: 2 | D83: 2 | E83: 1 | F83: 1 | G83: 4 | H83: 4 | I83: 3 | L83: 5 | P83: 让所有单位呕吐，留下水地面，吞噬单位吐出 | AE83: Times | AF83: 1 | AG83: Vomit
A84: 20085 | B84: 虚化 | C84: 2 | D84: 2 | E84: 1 | F84: 1 | G84: 4 | H84: 2 | I84: 3 | L84: 5 | P84: 使碰撞的首个单位虚化，无法碰撞或被碰撞，但受到双倍伤害，下个我方回合开始时恢复 | AE84: Times | AF84: 1 | AG84: Vitual
P88: 下面为备选技能
P89: 为方舟回复部分船体 | Q89: 隐藏参数回复像素数{0}，用默认的装饰像素块就行，从低到高回复
Q90: 五星大核弹，用于追回优劣势
P91: 额外抽{0}张牌
P92: 控制方舟冲撞
P93: 我方方舟所有炮台，向打出方向发射{0}次
P94: 为敌方生成单位，或往敌方手牌塞满卡，令对方无法买新牌
P95: 获得一张随机的，不高于{0}价格的/稀有度为{0}一次性卡
P97: 消耗血量获得金币的机制（加速战斗节奏）
P98: 本回合所有友方碰到场景物件，回复{0}生命值
P99: 穿透，标记穿过的敌方，技能消失时，对所有标记敌方造成标记数*{0}的伤害 | Q99: 回合结束还没消失的话，强制消失
P100: 在随机空地召唤小食人花，吞入触碰的敌方造成{0}点伤害并吐出，吞入{1}次后枯萎 | Q100: 隐藏参数吐出的力{2}，跟食人花娘机制一致，可以复用
P101: 消耗带入的{0}金币，XX
P102: 回合开始时若在手牌，则生成{0}张本卡
H104: 3 | I104: 0 | J104: 高价值敌方单位 | K104: 3 | L104: 3 | P104: 标记首个碰撞的敌人，该敌人本回合受伤增加{0}%
D105: 1 | F105: 2 | G105: 3
...

Sheet 组件分表
A1: 组件卡的组ID | B1: 对应组件卡ID | C1: 组件名 | D1: 卡牌类型 | E1: 组件类型 | F1: 价格 | G1: 初始星级 | H1: 最大星级 | I1: 获取方式类型 | J1: 废弃 | K1: 不放入商店 | L1: 组件主动效果，被破坏后失效 | M1: 效果备注 | N1: 2星效果 | O1: 3星效果 | P1: 4星效果 | Q1: 5星效果 | R1: 特性列表（特性ID） | T1: KeyID | U1: 引用交互物列表（交互物ID） | V1: 技能表现 | W1: 失效类型 | X1: 失效参数 | Y1: 射击操作类型 | Z1: 是否需要物理模拟 | AA1: 职业 | AB1: 瞄准线类型 | AC1: 牌序标签类型
A2: 4001 | B2: {=_xlfn.XLOOKUP(A2,组件ID生成表!B:B,组件ID生成表!C:C,"没配置")} -> 40011 | C2: 初始炮 | D2: 5 | E2: 2 | F2: 5 | G2: 1 | H2: 1 | I2: 3 | L2: 打出时，回合开始时：开炮，伤害为{0} | M2: 用作默认 | R2: ArkPartNormalGun | S2: {0:炮弹ID，1:偏移角度} | T2: 36
A3: 4002 | B3: {=_xlfn.XLOOKUP(A3,组件ID生成表!B:B,组件ID生成表!C:C,"没配置")} -> 40021 | C3: 过渡炮 | D3: 5 | E3: 2 | F3: 5 | G3: 1 | H3: 1 | I3: 3 | L3: 打出时，回合开始时：开炮，伤害为{0}，被替换时获得{2}金币 | M3: 替换的意思是再买一门炮时的替换，破坏不算 | N3: 伤害+ | R3: ArkPartTransitionGun | S3: {0:炮弹ID，1:偏移角度，2:金币数} | T3: 36
A4: 4003 | B4: {=_xlfn.XLOOKUP(A4,组件ID生成表!B:B,组件ID生成表!C:C,"没配置")} -> 40032 | C4: 英雄炮 | D4: 5 | E4: 2 | F4: 6 | G4: 2 | H4: 2 | I4: 3 | L4: 打出时，回合开始时：向敌方英雄开炮，伤害为{0} | M4: 无英雄时向前开炮 | O4: 伤害+ | P4: 伤害+ | R4: ArkPartHeroGun | S4: {0:炮弹ID} | T4: 36
A5: 4004 | B5: {=_xlfn.XLOOKUP(A5,组件ID生成表!B:B,组件ID生成表!C:C,"没配置")} -> 40043 | C5: 精英炮 | D5: 5 | E5: 2 | F5: 9 | G5: 3 | H5: 3 | I5: 3 | L5: 打出时，回合开始时：向敌方攻击最高单位开炮，伤害为{0} | O5: 伤害+ | P5: 伤害+ | R5: ArkPartCreatureGun | S5: {0:炮弹ID} | T5: 36
A6: 4005 | B6: {=_xlfn.XLOOKUP(A6,组件ID生成表!B:B,组件ID生成表!C:C,"没配置")} -> 40054 | C6: 方舟炮 | D6: 5 | E6: 2 | F6: 12 | G6: 4 | H6: 4 | I6: 3 | L6: 打出时，回合开始时：开炮，伤害为{0}，对方舟伤害增加{2}% | O6: 伤害+ | P6: 对方舟伤害++ | Q6: 伤害+，对方舟伤害+ | R6: ArkPartArkGun | S6: {0:炮弹ID，1:偏移角度，2:伤害增加百分比} | T6: 36
A7: 4006 | B7: {=_xlfn.XLOOKUP(A7,组件ID生成表!B:B,组件ID生成表!C:C,"没配置")} -> 40062 | C7: 打牌炮 | D7: 5 | E7: 2 | F7: 6 | G7: 2 | H7: 2 | I7: 3 | L7: 每打{1}张牌，向打牌方向开炮，伤害为{0} | P7: 门槛2 | Q7: 门槛1 | R7: ArkPartShootCardGun | S7: {0:炮弹ID，1:出牌数量} | T7: 36
A8: 4007 | B8: {=_xlfn.XLOOKUP(A8,组件ID生成表!B:B,组件ID生成表!C:C,"没配置")} -> 40074 | C8: 冰冻炮 | D8: 5 | E8: 2 | F8: 12 | G8: 4 | H8: 4 | I8: 3 | L8: 打出时，回合开始时：向{1}个敌方单位开炮，伤害为{0}，对击中的敌方赋予冰冻 | P8: 冰冻数量+1 | R8: ArkPartFreezeGun | S8: {0:炮弹ID，1:目标数量} | T8: 36
A9: 4008 | B9: {=_xlfn.XLOOKUP(A9,组件ID生成表!B:B,组件ID生成表!C:C,"没配置")} -> 40085 | C9: 一次性卡炮 | D9: 5 | E9: 2 | F9: 12 | G9: 5 | H9: 5 | I9: 3 | L9: 打出时，回合开始时：开炮，伤害为{0}，本局战斗，每获得过{2}张商店一次性卡，伤害增加{3} | M9: 前端可以显示一下当前总伤害累计多少 | P9: 伤害增量+ | Q9: 门槛2 | R9: ArkPartTempCardGun | S9: {0:炮弹ID，1:偏移角度，2：获得卡片数量，3：增加伤害} | T9: 36
A10: 4009 | B10: {=_xlfn.XLOOKUP(A10,组件ID生成表!B:B,组件ID生成表!C:C,"没配置")} -> 40093 | C10: 亡语商店炮 | D10: 5 | E10: 2 | F10: 9 | G10: 3 | H10: 3 | I10: 3 | L10: 打出时，回合开始时：开炮，伤害为{0}，被替换时，获得一张比本组件星级高{2}级的一次性卡 | M10: 最大不超过5星 | O10: 售价++，拿5星卡 | R10: ArkPartReplaceGun | S10: {0:炮弹ID，1:偏移角度，2：高多少级} | T10: 36
A11: 4010 | B11: {=_xlfn.XLOOKUP(A11,组件ID生成表!B:B,组件ID生成表!C:C,"没配置")} -> 40105 | C11: 冲刺引擎 | D11: 5 | E11: 5 | F11: 12 | G11: 5 | H11: 5 | I11: 3 | L11: 我方方舟回合开始多冲撞{0}次，伤害增加{1}% | Q11: 次数+ | R11: ArkPartClashEngine | S11: {0:冲撞次数，1：伤害百分比} | T11: 36
A12: 4011 | B12: {=_xlfn.XLOOKUP(A12,组件ID生成表!B:B,组件ID生成表!C:C,"没配置")} -> 40114 | C12: 单位装填炮 | D12: 5 | E12: 2 | F12: 12 | G12: 4 | H12: 4 | I12: 3 | L12: 我方回合结束时：将{0}个随机友方单位装填进炮，我方开始时发射出去 | M12: 暂时移出战场，敌方打破这个炮，单位就掉出来，隐藏参数发射速度大小{1}，英雄跳过大蛇和花 | O12: 治疗被装填单位 | P12: 打出力道++（初始打出力道较弱） | R12: ArkPartEquipUnitGun | S12: {0:随从个数，1:力大小} | T12: 36
A13: 4012 | B13: {=_xlfn.XLOOKUP(A13,组件ID生成表!B:B,组件ID生成表!C:C,"没配置")} -> 40123 | C13: 自动打牌炮 | D13: 5 | E13: 2 | F13: 9 | G13: 3 | H13: 3 | I13: 3 | L13: 我方回合结束时：将未打且非保留的单位牌发射出去，其攻击增加{1} | M13: 和上一个实现类似，只有英雄卡，单位卡和雇佣兵卡增加属性 | O13: 增加等量生命上限 | P13: 增加更多生命 | R13: ArkPartAutoShootCardGun | S13: {0:偏移角度，1：加成百分比} | T13: 36
A14: 4013 | B14: {=_xlfn.XLOOKUP(A14,组件ID生成表!B:B,组件ID生成表!C:C,"没配置")} -> 40134 | C14: 烟雾导弹 | D14: 5 | E14: 3 | F14: 12 | G14: 4 | H14: 4 | I14: 3 | L14: 回合结束时：在随机位置产生一片烟雾，烟雾中看不到单位并且瞄准线失效 | M14: 导弹，我方回合开始时消散，隐藏参数范围{0} | P14: 范围+ | R14: ArkPartOverloadGun | S14: {0:范围大小} | T14: 36
A15: 4014 | B15: {=_xlfn.XLOOKUP(A15,组件ID生成表!B:B,组件ID生成表!C:C,"没配置")} -> 40141 | C15: 初始导弹 | D15: 5 | E15: 3 | F15: 5 | G15: 1 | H15: 1 | I15: 3 | L15: 打出时，回合开始时：对随机范围区域造成{0}伤害 | M15: 用作默认，隐藏参数范围大小{1} | R15: ArkPartNormalMissile | S15: {0:伤害，1:范围} | T15: 36
A16: 4015 | B16: {=_xlfn.XLOOKUP(A16,组件ID生成表!B:B,组件ID生成表!C:C,"没配置")} -> 40151 | C16: 过渡导弹 | D16: 5 | E16: 3 | F16: 5 | G16: 1 | H16: 1 | I16: 3 | L16: 打出时，回合开始时：对随机范围区域造成{0}伤害，被替换时获得{2}金币 | M16: 隐藏参数范围大小{1} | N16: 伤害+ | R16: ArkPartPassMissile | S16: {0:伤害，1:范围，2：获得金币数} | T16: 36
A17: 4016 | B17: {=_xlfn.XLOOKUP(A17,组件ID生成表!B:B,组件ID生成表!C:C,"没配置")} -> 40163 | C17: 蓄力核武 | D17: 5 | E17: 3 | F17: 9 | G17: 3 | H17: 3 | I17: 3 | L17: 蓄力{0}回合，回合开始时：发射一颗毁天灭地的核弹，核弹伤害为{1} | M17: 复用战术核武，伤害不同，组件被破坏则蓄力清零 | P17: 蓄力- | R17: ArkPartAccumulatePowerMissile | S17: {0:回合间隔，1:伤害} | T17: 36
A18: 4017 | B18: {=_xlfn.XLOOKUP(A18,组件ID生成表!B:B,组件ID生成表!C:C,"没配置")} -> 40173 | C18: 智能导弹 | D18: 5 | E18: 3 | F18: 9 | G18: 3 | H18: 3 | I18: 3 | L18: 打出时，回合开始时：向单位最多的位置发射炮弹，对其中的敌方造成{0}伤害，我方治疗{1}生命 | M18: 隐藏参数范围大小{2} | O18: 伤害+ | P18: 范围+ | Q18: 伤害+，范围+ | R18: ArkPartAutoMissile | S18: {0:伤害，1:恢复血量，2：范围} | T18: 36
A19: 4018 | B19: {=_xlfn.XLOOKUP(A19,组件ID生成表!B:B,组件ID生成表!C:C,"没配置")} -> 40185 | C19: 英雄导弹 | D19: 5 | E19: 3 | F19: 12 | G19: 5 | H19: 5 | I19: 3 | L19: 打出时，回合开始时：以我方英雄为中心，对范围内敌方和英雄自身造成{0}伤害 | M19: 隐藏参数范围大小{1} | P19: 范围+ | Q19: 伤害+，范围+ | R19: ArkPartHeroMissile | S19: {0:伤害，1:范围} | T19: 36
A20: 4019 | B20: {=_xlfn.XLOOKUP(A20,组件ID生成表!B:B,组件ID生成表!C:C,"没配置")} -> 40192 | C20: 液体导弹 | D20: 5 | E20: 3 | F20: 6 | G20: 2 | H20: 2 | I20: 3 | L20: 打出时，回合开始时：对随机范围区域，造成{0}伤害，赋予潮湿，并留下水地面 | M20: 敌我都潮湿，只有敌方受伤，隐藏参数范围大小{1} | O20: 伤害+ | R20: ArkPartWaterMissile | S20: {0:伤害，1:范围} | T20: 36
A21: 4020 | B21: {=_xlfn.XLOOKUP(A21,组件ID生成表!B:B,组件ID生成表!C:C,"没配置")} -> 40204 | C21: 加速导弹 | D21: 5 | E21: 3 | F21: 12 | G21: 4 | H21: 4 | I21: 3 | L21: 打出时，回合开始时：在随机区域生成{0}个加速地面 | M21: 加速地面新场景物件，经过的单位加速并且加速地面消失 | P21: 数量+ | R21: ArkPartAccelerateMissile | S21: {0：地面数量，1:范围半径，2:力} | T21: 36
A22: 4021 | B22: {=_xlfn.XLOOKUP(A22,组件ID生成表!B:B,组件ID生成表!C:C,"没配置")} -> 40212 | C22: 掩体导弹 | D22: 5 | E22: 3 | F22: 6 | G22: 2 | H22: 2 | I22: 3 | L22: 回合结束时：围绕我方生命最低单位召唤{0}个掩体，掩体生命为{2}，我方回合开始时移除 | M22: 导弹，数量较多，高星可以比修建阵地夸张一些，影响对方碰撞来保护单位 | P22: 掩体数量+ | R22: ArkPartAddInteractiveAircraft | S22: {0：交互物数量，1:交互物ID，2:掩体血量} | T22: 36
A23: 4022 | B23: {=_xlfn.XLOOKUP(A23,组件ID生成表!B:B,组件ID生成表!C:C,"没配置")} -> 40221 | C23: 初始治疗引擎 | D23: 5 | E23: 5 | F23: 5 | G23: 1 | H23: 1 | I23: 3 | L23: 打出时，回合开始时：治疗生命比例最低的我方{0}点生命 | M23: 初始默认 | R23: ArkPartCureEngine | S23: {0：恢复血量} | T23: 36
A24: 4023 | B24: {=_xlfn.XLOOKUP(A24,组件ID生成表!B:B,组件ID生成表!C:C,"没配置")} -> 40232 | C24: 转运无人机 | D24: 5 | E24: 4 | F24: 6 | G24: 2 | H24: 2 | I24: 3 | L24: 打出时，回合开始时：从我方生命最高随从转移{0}生命上限到我方英雄身上 | O24: 转移量+ | P24: 转移量+ | R24: ArkPartTransportAircraft | S24: {0：转移血量} | T24: 36
A25: 4024 | B25: {=_xlfn.XLOOKUP(A25,组件ID生成表!B:B,组件ID生成表!C:C,"没配置")} -> 40242 | C25: 猎杀无人机 | D25: 5 | E25: 4 | F25: 6 | G25: 2 | H25: 2 | I25: 3 | L25: 我方回合：将生命最低的敌方单位变大{0}% | M25: 质量也对应变大{1}%，过程中生命最低单位变化则切换，包括击杀，敌方回合恢复 | R25: ArkPartHuntingAircraft | S25: {0：增加百分比} | T25: 36
A26: 4025 | B26: {=_xlfn.XLOOKUP(A26,组件ID生成表!B:B,组件ID生成表!C:C,"没配置")} -> 40255 | C26: 目标无人机 | D26: 5 | E26: 4 | F26: 12 | G26: 5 | H26: 5 | I26: 3 | L26: 打出时，回合开始时：随机标记{0}个敌方单位，标记单位受伤增加{1}%，最大叠加{2}层 | M26: 回合结束移除标记 | P26: 标记数量2，标记可叠加2层 | Q26: 标记数量4，标记可叠加3层 | R26: ArkPartTargetAircraft | S26: {0：标记敌方数，1:伤害增加百分比，2:最大叠加层数} | T26: 36
A27: 4026 | B27: {=_xlfn.XLOOKUP(A27,组件ID生成表!B:B,组件ID生成表!C:C,"没配置")} -> 40263 | C27: 变强无人机 | D27: 5 | E27: 4 | F27: 9 | G27: 3 | H27: 3 | I27: 3 | L27: 每当我方单位（分裂体除外）死亡或离场，他在本局对战中的攻击永久增加{0} | M27: 包括英雄 | O27: 攻击+ | P27: 攻击++ | R27: ArkPartStrongAircraft | S27: {0：攻击值} | T27: 36
A28: 4027 | B28: {=_xlfn.XLOOKUP(A28,组件ID生成表!B:B,组件ID生成表!C:C,"没配置")} -> 40274 | C28: 粘合无人机 | D28: 5 | E28: 4 | F28: 12 | G28: 4 | H28: 4 | I28: 3 | L28: 我方回合结束时，将所有我方单位粘合到英雄上，我方回合开始时弹走黏合单位 | M28: 尝试黏上英雄直到放不下，没有英雄则失效，敌方仍旧能正常碰到不同部位，只是我方会一起行动 | P28: 英雄临时变小 | Q28: 回合开始时弹走黏合单位 | R28: ArkPartMixAircraft | T28: 36
A29: 4028 | B29: {=_xlfn.XLOOKUP(A29,组件ID生成表!B:B,组件ID生成表!C:C,"没配置")} -> 40283 | C29: 汲取无人机 | D29: 5 | E29: 4 | F29: 9 | G29: 3 | H29: 3 | I29: 3 | L29: 我方回合：我方英雄碰到雇佣兵时，吸取其{0}点攻击力 | M29: 吸到0，雇佣兵攻击不足时有多少吸多少。英雄攻击为永久增加，雇佣兵攻击减少持续至离场 | N29: 售价- | R29: ArkPartDrawAircraft | S29: {0：攻击值} | T29: 36
A30: 4029 | B30: {=_xlfn.XLOOKUP(A30,组件ID生成表!B:B,组件ID生成表!C:C,"没配置")} -> 40295 | C30: 抽卡引擎 | D30: 5 | E30: 5 | F30: 12 | G30: 5 | H30: 5 | I30: 3 | L30: 每回合抽卡数量加{0} | R30: ArkPartDrawCardEngine | S30: {0：数量} | T30: 36
A31: 4030 | B31: {=_xlfn.XLOOKUP(A31,组件ID生成表!B:B,组件ID生成表!C:C,"没配置")} -> 40302 | C31: 圣盾引擎 | D31: 5 | E31: 5 | F31: 6 | G31: 2 | H31: 2 | I31: 3 | L31: 回合结束时：为随机{0}个我方添加圣盾 | M31: 最低到1 | N31: 数量+ | O31: 数量+ | R31: ArkPartRandomAddShieldEngine | S31: {0：数量} | T31: 36
A32: 4031 | B32: {=_xlfn.XLOOKUP(A32,组件ID生成表!B:B,组件ID生成表!C:C,"没配置")} -> 40313 | C32: 生命引擎 | D32: 5 | E32: 5 | F32: 9 | G32: 3 | H32: 3 | I32: 3 | L32: 回合结束时：为所有我方永久增加{0}生命 | P32: 生命成长+ | R32: ArkPartHealthEngine | S32: {0：生命值} | T32: 36
A33: 4032 | B33: {=_xlfn.XLOOKUP(A33,组件ID生成表!B:B,组件ID生成表!C:C,"没配置")} -> 40323 | C33: 过载引擎 | D33: 5 | E33: 5 | F33: 9 | G33: 3 | H33: 3 | I33: 3 | L33: 回合开始时：对我方方舟造成一定伤害，抽{0}张卡 | M33: 和过载炮一个机制，改到这边，隐藏参数对方舟伤害{1} | O33: 自残- | R33: ArkPartOverloadEngine | S33: {0：抽卡数，1：方舟伤害像素个数，2：方舟伤害} | T33: 36
A34: 4033 | B34: {=_xlfn.XLOOKUP(A34,组件ID生成表!B:B,组件ID生成表!C:C,"没配置")} -> 40331 | C34: 猎杀引擎 | D34: 5 | E34: 5 | F34: 5 | G34: 1 | H34: 1 | I34: 3 | L34: 击杀敌方时：为所有我方回复{0}生命 | N34: 治疗+ | R34: ArkPartHuntingEngine | S34: {0：回复生命值} | T34: 36
A35: 4034 | B35: {=_xlfn.XLOOKUP(A35,组件ID生成表!B:B,组件ID生成表!C:C,"没配置")} -> 40342 | C35: 组件破坏引擎 | D35: 5 | E35: 5 | F35: 6 | G35: 2 | H35: 2 | I35: 3 | L35: 每破坏一个敌方组件，抽{0}张卡 | O35: 售价- | P35: 售价--，收益+ | R35: ArkPartDestoryArkPartEngine | S35: {0：抽卡数} | T35: 36
A36: 4035 | B36: {=_xlfn.XLOOKUP(A36,组件ID生成表!B:B,组件ID生成表!C:C,"没配置")} -> 40354 | C36: 临时卡引擎 | D36: 5 | E36: 5 | F36: 12 | G36: 4 | H36: 4 | I36: 3 | L36: 每打出{0}张临时卡，抽{1}张卡 | Q36: 门槛-（标准体验） | R36: ArkPartTempCardEngine | S36: {0：打牌数，1：抽卡数} | T36: 36
A37: 4036 | B37: {=_xlfn.XLOOKUP(A37,组件ID生成表!B:B,组件ID生成表!C:C,"没配置")} -> 40362 | C37: 急救引擎 | D37: 5 | E37: 5 | F37: 6 | G37: 2 | H37: 2 | I37: 3 | L37: 每个我方回合和敌方回合：我方英雄首次血量降至一半以下，对我方方舟造成一定伤害，为英雄回复{0}生命 | M37: 隐藏参数对方舟伤害{1} | O37: 治疗+ | P37: 自残- | R37: ArkPartFrstAidEngine | S37: {0：回复生命值，1：方舟伤害像素个数，2：方舟伤害} | T37: 36
A38: 4037 | B38: {=_xlfn.XLOOKUP(A38,组件ID生成表!B:B,组件ID生成表!C:C,"没配置")} -> 40374 | C38: 商店引擎 | D38: 5 | E38: 5 | F38: 12 | G38: 4 | H38: 4 | I38: 3 | L38: 打出时，每回合开始时：给与{0}张随机同星一次性卡 | M38: 本组件几星，给的一次性卡就是几星 | O38: 星级提升 | P38: 星级提升 | R38: ArkPartShopEngine | S38: {0：数量} | T38: 36
A39: 4038 | B39: {=_xlfn.XLOOKUP(A39,组件ID生成表!B:B,组件ID生成表!C:C,"没配置")} -> 40383 | C39: 转移引擎 | D39: 5 | E39: 5 | F39: 9 | G39: 3 | H39: 3 | I39: 3 | L39: 回合结束时：对我方英雄造成{0}伤害，为所有我方随从永久+{1}生命 | M39: 临时生命换永久加成，雇佣兵离场后生效 | O39: 生命成长+ | R39: ArkPartTransferEngine | S39: {0：英雄伤害 1：随从生命} | T39: 36
A40: 4039 | B40: {=_xlfn.XLOOKUP(A40,组件ID生成表!B:B,组件ID生成表!C:C,"没配置")} -> 40394 | C40: 方舟炮弹 | D40: 3 | E40: 0 | F40: 0 | G40: =G6 -> 4 | H40: =H6 -> 4 | I40: 3 | K40: 1 | L40: 方舟炮的炮弹 | R40: GunBullet | W40: Times | X40: 1 | Y40: 1 | Z40: 0 | AA40: 3 | AB40: 2 | AC40: 5
A41: 4040 | B41: {=_xlfn.XLOOKUP(A41,组件ID生成表!B:B,组件ID生成表!C:C,"没配置")} -> 40404 | C41: 冰冻炮弹 | D41: 3 | E41: 0 | F41: 0 | G41: =G8 -> 4 | H41: =H8 -> 4 | I41: 3 | K41: 1 | L41: 冰冻炮的炮弹 | R41: GunBullet | W41: Times | X41: 1 | Y41: 1 | Z41: 0 | AA41: 3 | AB41: 2 | AC41: 5
A42: 4041 | B42: {=_xlfn.XLOOKUP(A42,组件ID生成表!B:B,组件ID生成表!C:C,"没配置")} -> 40412 | C42: 承伤引擎 | D42: 5 | E42: 5 | F42: 6 | G42: 2 | H42: 2 | I42: 3 | L42: 我方英雄每次受伤：本组件受到{0}点伤害，使我方英雄减免{1}点伤害 | M42: 英雄固定减伤，嘲讽，被高攻克制 | R42: ArkPartProtectEngine | S42: {0：组件伤害 1：减伤值} | T42: 36
A43: 4042 | B43: {=_xlfn.XLOOKUP(A43,组件ID生成表!B:B,组件ID生成表!C:C,"没配置")} -> 40421 | C43: 初始无人机 | D43: 5 | E43: 4 | F43: 5 | G43: 1 | H43: 1 | I43: 3 | L43: 打出时，回合开始时：随机选择一个我方，为其增加{0}攻击，回合结束恢复 | R43: ArkPartNormalAircraft | S43: {0：攻击} | T43: 36
A44: 4043 | B44: {=_xlfn.XLOOKUP(A44,组件ID生成表!B:B,组件ID生成表!C:C,"没配置")} -> 40431 | C44: 初始炮炮弹 | D44: 3 | E44: 0 | F44: 0 | G44: =G2 -> 1 | H44: =H2 -> 1 | I44: 3 | K44: 1 | L44: 初始炮炮弹，伤害{0} | R44: GunBullet | W44: Times | X44: 1 | Y44: 1 | Z44: 0 | AA44: 3 | AB44: 2 | AC44: 5
A45: 4044 | B45: {=_xlfn.XLOOKUP(A45,组件ID生成表!B:B,组件ID生成表!C:C,"没配置")} -> 40441 | C45: 过渡炮炮弹 | D45: 3 | E45: 0 | F45: 0 | G45: =G3 -> 1 | H45: =H3 -> 1 | I45: 3 | K45: 1 | L45: 过渡炮炮弹，伤害{0} | R45: GunBullet | W45: Times | X45: 1 | Y45: 1 | Z45: 0 | AA45: 3 | AB45: 2 | AC45: 5
A46: 4045 | B46: {=_xlfn.XLOOKUP(A46,组件ID生成表!B:B,组件ID生成表!C:C,"没配置")} -> 40452 | C46: 英雄炮炮弹 | D46: 3 | E46: 0 | F46: 0 | G46: =G4 -> 2 | H46: =H4 -> 2 | I46: 3 | K46: 1 | L46: 英雄炮炮弹，伤害{0} | R46: GunBullet | W46: Times | X46: 1 | Y46: 1 | Z46: 0 | AA46: 3 | AB46: 2 | AC46: 5
A47: 4046 | B47: {=_xlfn.XLOOKUP(A47,组件ID生成表!B:B,组件ID生成表!C:C,"没配置")} -> 40463 | C47: 精英炮炮弹 | D47: 3 | E47: 0 | F47: 0 | G47: =G5 -> 3 | H47: =H5 -> 3 | I47: 3 | K47: 1 | L47: 精英炮炮弹，伤害{0} | R47: GunBullet | W47: Times | X47: 1 | Y47: 1 | Z47: 0 | AA47: 3 | AB47: 2 | AC47: 5
A48: 4047 | B48: {=_xlfn.XLOOKUP(A48,组件ID生成表!B:B,组件ID生成表!C:C,"没配置")} -> 40472 | C48: 打牌炮炮弹 | D48: 3 | E48: 0 | F48: 0 | G48: =G7 -> 2 | H48: =H7 -> 2 | I48: 3 | K48: 1 | L48: 打牌炮炮弹，伤害{0} | R48: GunBullet | W48: Times | X48: 1 | Y48: 1 | Z48: 0 | AA48: 3 | AB48: 2 | AC48: 5
A49: 4048 | B49: {=_xlfn.XLOOKUP(A49,组件ID生成表!B:B,组件ID生成表!C:C,"没配置")} -> 40485 | C49: 一次性卡炮弹 | D49: 3 | E49: 0 | F49: 0 | G49: =G9 -> 5 | H49: =H9 -> 5 | I49: 3 | K49: 1 | L49: 一次性卡炮，伤害{0} | R49: GunBullet | W49: Times | X49: 1 | Y49: 1 | Z49: 0 | AA49: 3 | AB49: 2 | AC49: 5
A50: 4049 | B50: {=_xlfn.XLOOKUP(A50,组件ID生成表!B:B,组件ID生成表!C:C,"没配置")} -> 40493 | C50: 亡语商店炮炮弹 | D50: 3 | E50: 0 | F50: 0 | G50: =G10 -> 3 | H50: =H10 -> 3 | I50: 3 | K50: 1 | L50: 亡语商店炮炮弹，伤害{0} | R50: GunBullet | W50: Times | X50: 1 | Y50: 1 | Z50: 0 | AA50: 3 | AB50: 2 | AC50: 5

Sheet 特性表检索
A1: 特性名词 | B1: 临时版icon | C1: 特性描述 | D1: 实现细节
A2: 入场 | C2: 进入战场时触发 | D2: 被召唤入场，发射入场，移出后移入等都会触发
A3: 持续 | C3: 每个我方回合触发
A4: 临时 | C4: 使用卡牌后消失，不进入弃牌堆，回合结束未使用也消失
A5: 消耗 | C5: 使用后不进入弃牌堆，进入消耗堆，不再参与接下来的抽牌 | D5: 消耗堆不展示给玩家
A6: 弹射 | C6: 默认状态，可以和任何实体碰撞
A7: 穿透 | C7: 可穿透生物单位继续前进，但会被场景物件阻挡并反弹 | D7: 穿透后面若带数字，则意思是最多穿透几次就消失
A8: 强穿透 | C8: 可穿透除战场墙壁外的任何东西
A9: 极致穿透 | C9: 可穿透任何东西，永远是一条直线 | D9: 隐藏属性，不展示给玩家
A10: 生物触发 | C10: 命中首个生物时触发效果
A11: 跟随 | C11: 打出时，目标向打出方向位移 | D11: 位移力度根据不同情况配置
A12: 停止 | C12: 首次发射停止后，产生XX效果 | D12: 最晚回合结束
A13: 圣盾 | C13: 抵挡一次伤害后消失，圣盾不可叠加 | D13: 抵挡伤害本质是将伤害变为0，仍算一次伤害，会触发伤害次数+1。本质为持续性效果，可被沉默等效果移除
A14: 吸血 | C14: 造成伤害会为自身回复等量血量
A15: 剧毒 | C15: 造成伤害时直接消灭对方生物（非英雄） | D15: 攻击圣盾时不触发
A16: 回归 | C16: 打出的回合满足特定条件，可以回到手牌 | D16: 重置为初始状态
A17: 连击 | C17: 当前回合已经打出N张牌时生效该效果 | D17: 不算本身
A18: 激励 | C18: 在场时释放英雄技能时触发该效果
A19: 过载 | C19: 下回合英雄能量获取下降N
A20: 任务/奖励 | C20: 完成任务后会获得奖励
A21: 招募 | C21: 从牌库中召唤一个特定条件的生物
A22: 复活 | C22: 首次死亡后以一点血量复活
A23: 法术触发 | C23: 打出法术牌后触发效果，每回合只能触发一次
A24: 变形 | C24: 变形为一个指定对象 | D24: 不算死亡，等于替换为另一个单位，也不触发入场效果
A25: 发现 | C25: 从三张特定类型的卡中选择一张
A26: 沉默 | C26: 移除生物牌上的效果，包括所有增益和减益效果 | D26: 不影响当前血量，相当于一个初始进入场上的不带技能的版本
A27: 控制 | C27: 获得对方生物的控制权
A28: 移回手牌 | C28: 卡牌以初始状态移回手牌
A29: 移回抽牌库 | C29: 卡牌以初始状态移回抽牌库
A30: 丢弃卡牌 | C30: 选择特定卡牌丢入弃牌库（可以是手牌或抽牌库）
A31: 磨灭卡牌 | C31: 将特定卡牌移出本场战斗
A32: 魔免 | C32: 无视法术效果
A33: 恐惧 | C33: 每回合首次开始移动时，施加一个随机方向的力（移动方向变得随机）
A34: 揭示 | C34: 随机从牌库中抽N张展示给双方，若没有其他操作，就洗回牌库 | D34: 对该牌有其他操作，则打断洗回牌库
A35: 复制 | C35: 复制的随从拥有和本体一致的基础特性和属性，复制的卡牌同理，一模一样，只是多一个复制标签，表现也稍有不同，名字也改为XX的复制 | D35: 额外的，复制有一个复制标签，用做某些逻辑判断。例如复制标签无法被复制
A36: 亡语 | C36: 死亡时触发效果 | D36: 死亡是指血量归零或被消灭，放逐变形等不算
A37: 保留 | C37: 回合结束时保留在手牌中
A38: 铁壁X | C38: 每一层铁壁可以抵消一次碰撞伤害 | D38: 非碰撞伤害无效，0攻碰撞不消除铁壁
A39: 引导 | C39: 碰到的第一个单位停下时，目标向其位移
A40: 激怒 | C40: 向最近的敌方单位移动 | D40: 没有其他前缀限定时，即时生效

Sheet 英雄卡分表
A1: 卡牌ID | B1: 卡牌名 | C1: 称号 | D1: 星级 | E1: 卡牌类型 | F1: 选项类型 | G1: 射击类型 | H1: 英雄类型 | I1: 职业 | J1: 费用 | K1: 稀有度 | L1: 获取方式类型 | M1: AI目标规划 | N1: 瞄准线类型 | O1: 牌序规划标签 | P1: 是否需要物理模拟 | Q1: 等级上限 | R1: 英雄专属卡ID | S1: 卡牌效果 | T1: 效果备注 | U1: 卡牌效果2级 | V1: 2级效果备注 | W1: 卡牌效果3级 | X1: 3级效果备注 | Y1: 流派归类（后续用作职业划分） | Z1: 特性列表（特性ID） | AC1: Demo版本 技能表现 | AD1: 美术表现 | AF1: 卡组上限 | AG1: 卡组下限 | AH1: Demo版本 包装 | AI1: 一测版本 包装 | AK1: 失效次数 | AL1: 失效参数 | AM1: 技能类型
A2: 10000 | B2: 舰长 | C2: 传奇飞行员 | D2: 1 | E2: 4 | F2: 1 | G2: 1 | H2: Normal | I2: 1 | J2: 13 | K2: 4 | L2: 6 | M2: 常规碰撞 | N2: 1 | O2: 5 | P2: 1 | Q2: 15 | R2: 20026 | S2: 每打出{0}张卡，获得一张炸蛋 | AF2: 12 | AG2: 12
A3: 10001 | B3: 梅莉（Meli） | C3: 黏黏女王 | D3: 1 | E3: 4 | F3: 1 | G3: 1 | H3: Normal | I3: 1 | J3: 23 | K3: 4 | L3: 6 | M3: 常规碰撞 | N3: 1 | O3: 5 | P3: 1 | Q3: 15 | R3: 20081 | S3: 融合碰撞到的前{0}个友方随从，获得其当前属性和技能效果 | AC3: 触发该英雄的召唤单位效果时，不使用通用召唤特效，改为使用📦Effect_Hero1_Summon | AF3: 12 | AG3: 12 | AM3: FusionPreUnits
A4: 10002 | B4: 露娜（Luna） | C4: 最强盗贼王 | D4: 1 | E4: 4 | F4: 1 | G4: 1 | H4: Normal | I4: 1 | J4: 15 | K4: 4 | L4: 6 | M4: 常规碰撞 | N4: 1 | O4: 5 | P4: 1 | Q4: 15 | R4: 20017 | S4: 回合开始时，对随机敌方发射导弹造成{0}点爆炸伤害，我方每触发一次爆炸，所有爆炸伤害永久加{1}，范围永久增加{2} | T4: 打出N张牌累计 | AC4: 触发对随机敌方造成伤害效果时，在Hero_2英雄球位置生成一个📦Effect_Hero2_Shoot特效，该特效不跟随英雄球移动，生成时计算英雄球与目标球的角度并旋转该特效的Y值，特效播放0.05s后，在目标球位置播放一个📦Effect_Hero2_Hit并造成伤害，该特效跟随目标球移动。 | AF4: 12 | AG4: 12 | AM4: Bullet
A5: 10003 | B5: 乔艾塔（Joetta） | C5: 轻灵跃影 | D5: 1 | E5: 4 | F5: 1 | G5: 1 | H5: Normal | I5: 1 | J5: 18 | K5: 4 | L5: 6 | M5: 常规碰撞 | N5: 1 | O5: 5 | P5: 1 | Q5: 15 | R5: 20021 | S5: 每个我方回合开始时，向最近的敌方单位冲刺，回合结束时，每有{1}连击，自身攻击加{2}，生命加{3} | T5: 隐藏参数位移力{0} | AC5: 这个英雄需要游戏开始后2.3s后再发动技能 | AF5: 12 | AG5: 12 | AM5: MoveToNearestEnemy
A6: 10004 | B6: 维纳斯（Venus） | C6: 致命拥抱 | D6: 1 | E6: 4 | F6: 1 | G6: 1 | H6: Chomper | I6: 1 | J6: 18 | K6: 4 | L6: 6 | M6: 常规碰撞 | N6: 1 | O6: 5 | P6: 1 | Q6: 15 | R6: 20062 | S6: 打出时化作无法移动的花朵形态，我方回合盛开，吞噬碰到的敌方单位造成英雄攻击{0}%的伤害后吐出 | T6: 隐藏参数吐出时的位移力{1}，吐出时方向随机，吞噬单位被杀死就吐出尸体。不会造成碰撞伤害，直接吞噬 | AF6: 12 | AG6: 12 | AM6: HeroDevourEnemy
A7: 10005 | B7: 娜吉尼（Nagini） | C7: 环绕之蛇 | D7: 1 | E7: 4 | F7: 1 | G7: 1 | H7: Snake | I7: 1 | J7: 15 | K7: 4 | L7: 6 | M7: 常规碰撞 | N7: 1 | O7: 5 | P7: 1 | Q7: 15 | R7: 20016 | S7: 打出时在战场底边化作大蛇形态 | T7: 敌方回合敌方撞墙，就扣我方英雄血量，我方回合敌方撞墙，就是按英雄攻击扣其血量 | AF7: 12 | AG7: 12
A8: 10006 | B8: 梅丽莎（Melissa） | C8: 群蜂之母 | D8: 1 | E8: 4 | F8: 1 | G8: 1 | H8: Normal | I8: 1 | J8: 23 | K8: 4 | L8: 6 | M8: 常规碰撞 | N8: 1 | O8: 5 | P8: 1 | Q8: 15 | R8: 20080 | S8: 每个我方回合结束，对自身造成{0}点伤害，为所有友方随从增加{1}点生命上限 | T8: 圣盾可以抵挡自身的伤害，该效果对自身血量最低伤害到1 | AF8: 12 | AG8: 12 | AM8: AddHp2AllUnit

Sheet 场景物件表及数值
A1: 场景物件ID | B1: 场景物件名字 | C1: 场景物件效果 | D1: 效果备注 | E1: 是否受碰撞伤害 | F1: 是否免疫伤害 | G1: 是否可移动 | H1: 是否可燃 | I1: 是否导电 | J1: 是否受到电击伤害 | K1: 是否可冰冻 | L1: 血量 | M1: 参数1 | N1: 参数2 | O1: 参数3 | P1: 参数4
A2: Scene_Item_1 | B2: 爆炸桶 | C2: 被破坏时爆炸，对周围的单位和场景物件造成伤害和推力 | D2: 隐藏参数爆炸力大小{0}，爆炸伤害{1}，爆炸范围{2} | E2: 1 | F2: 0 | G2: 0 | H2: 1 | I2: 0 | J2: 0 | K2: 1 | L2: 1 | M2: 6 | N2: 80 | O2: 1.5 | P2: 0
A3: Scene_Item_2 | B3: 弹簧 | C3: 单位碰撞弹簧反弹时，额外获得一个推力 | D3: 隐藏参数推力{0}，隐藏参数碰撞{1}次后破坏 | E3: 1 | F3: 0 | G3: 0 | H3: 1 | I3: 0 | J3: 0 | K3: 1 | L3: 30 | M3: 6 | N3: 3 | O3: 0 | P3: 0
A4: Scene_Item_3 | B4: 陷阱 | C4: 将敌方推入时造成{1}伤害，冻结并眩晕{2}层，陷阱触发后消失 | D4: 非主动回合的一方触发 | E4: 0 | F4: 0 | G4: 0 | H4: 1 | I4: 0 | J4: 0 | K4: 1 | L4: 5 | M4: 150 | N4: 3 | O4: 0 | P4: 0
A5: Scene_Item_4 | B5: 礼物盒 | C5: 被碰撞{0}次后打开，随机获得一种奖励 | D5: 随机获得以下三种奖励中的一种：1获得{1}局外货币，2全体友方增加{2}点攻击，3全体友方回复{3}点血量。局外货币获得量未来做一个上限限制，以免玩家刷 | E5: 1 | F5: 0 | G5: 0 | H5: 1 | I5: 0 | J5: 0 | K5: 1 | L5: 30 | M5: 10 | N5: 10 | O5: 10 | P5: 30
A6: Scene_Item_5 | B6: 障碍物 | C6: 多碰撞几次就会被破坏 | D6: 0 | E6: 1 | F6: 0 | G6: 0 | H6: 1 | I6: 0 | J6: 0 | K6: 1 | L6: 20 | M6: 0 | N6: 0 | O6: 0 | P6: 0
A7: Scene_Item_6 | B7: 裂缝 | C7: 0 | D7: 0 | E7: 1 | F7: 0 | G7: 0 | H7: 1 | I7: 0 | J7: 0 | K7: 1 | L7: 300 | M7: 0 | N7: 0 | O7: 0 | P7: 0
A8: Scene_Item_7 | B8: 尖刺墙 | C8: 碰到尖刺墙的单位受到自身最大生命{0}%的伤害 | D8: 0 | E8: 1 | F8: 0 | G8: 0 | H8: 0 | I8: 0 | J8: 0 | K8: 0 | L8: 50 | M8: 2 | N8: 0 | O8: 0 | P8: 0
A9: Scene_Item_8 | B9: 掩体 | C9: 多碰撞几次就会被破坏 | D9: 0 | E9: 1 | F9: 0 | G9: 0 | H9: 0 | I9: 0 | J9: 0 | K9: 0 | L9: 10 | M9: 0 | N9: 0 | O9: 0 | P9: 0
A10: Scene_Item_9
A11: Scene_Item_10
A12: Scene_Item_11

Sheet 机制总表（参考）
A1: 卡牌类型 | B1: 流派归类（后续用作职业划分） | C1: 设计归类 | D1: 生效类型（1弹射参与碰撞，2弹射穿透，3直接生效，4拖选目标） | E1: 卡牌效果 | F1: 衍生牌数
A2: 生物 | B2: 人海流 | C2: 生物数量 | D2: 1 | E2: 每个回合开始时，生成一个自身的复制体，血量继承 | F2: 1 | H2: 卡牌设计原则：
A3: 生物 | B3: 人海流 | C3: 生物数量 | D3: 1 | E3: 当场上我方单位大于等于5时，攻击力提升 | F3: 1 | H3: 1持续备战类，需要高能耗，且低攻击。来控制玩家整体带的数量在一个合理范围内。核心目的是保证场上需要理解学习的持续重要单位，保持在一个合理数量之内
A4: 生物 | B4: 人海流 | C4: 生物数量，位移，弹射 | D4: 1 | E4: 对碰撞到的我方单位施加一个较大的力 | F4: 1
A5: 生物 | B5: 人海流 | C5: 生物数量，燃血 | D5: 1 | E5: 我方回合碰到我方英雄时，扣除英雄一定血量，生成一个新单位 | F5: 1
A6: 法术 | B6: 人海流 | C6: 生物数量，穿透 | D6: 2 | E6: 发射一个穿透的刀，将经过的我方单位切成两个较小的单位，属性对半分 | F6: 1
A7: 生物 | B7: 人海流 | C7: 生物数量，弹射 | D7: 1 | E7: 我方回合，每次碰到我方单位，对随机敌方造成一次伤害 | F7: 1
A8: 生物 | B8: 人海流 | C8: 生物数量，精英，弹射 | D8: 1 | E8: 吞噬每回合首个碰撞到的我方单位，获得其X%的基础属性
A9: 法术 | B9: 人海流 | C9: 生物数量，精英，穿透 | D9: 2 | E9: 将穿过的所有单位属性变为首个穿过单位的属性，回合结束后恢复
A10: 法术 | B10: 弹射流 | C10: 弹射，时机把控 | D10: 1 | E10: 中子对撞A，打出后速度较慢，碰到中子对撞B时发生大爆炸，造成伤害
A11: 法术 | B11: 弹射流 | C11: 弹射，时机把控 | D11: 1 | E11: 中子对撞B，打出后速度较快，碰到中子对撞A时发生大爆炸，造成伤害
A12: 生物 | B12: 弹射流 | C12: 弹射 | D12: 1 | E12: 单回合内，对同一个单位碰撞多次伤害增加 | F12: 1
A13: 生物 | B13: 弹射流 | C13: 弹射，时机把控 | D13: 1 | E13: 击中位移状态的敌方单位时，伤害增加
A14: 生物 | B14: 弹射流 | C14: 弹射，标记 | D14: 1 | E14: 标记每回合首次碰到的敌人，该敌人受到伤害增加 | F14: 1
A15: 生物 | B15: 弹射流 | C15: 弹射 | D15: 1 | E15: 单回合内，每碰撞一次，攻击增加，回合结束时恢复 | F15: 1
A16: 法术 | B16: 穿透流 | C16: 穿透 | D16: 2 | E16: 初始低伤害，每穿透一个伤害增加 | F16: 1
A17: 法术 | B17: 穿透流 | C17: 穿透，路径 | D17: 2 | E17: 留下路径，若路径闭合则对其中的单位造成大量伤害，回合结束路径消失
A18: 法术 | B18: 穿透流 | C18: 穿透，范围 | D18: 2 | E18: 敌方切分，将经过的敌方单位切成两个较小的单位，属性对半分 | F18: 1
A19: 法术 | B19: 穿透流 | C19: 穿透 | D19: 2 | E19: 分裂箭，每穿透一个单位，分裂成两道箭，最多分裂N次
A20: 法术 | B20: 穿透流 | C20: 穿透 | D20: 2 | E20: 借力打力，对经过的第二个单位，造成第一个单位攻击力的伤害 | F20: 1
A21: 法术 | B21: 穿透流 | C21: 穿透，标记 | D21: 2 | E21: 对经过的单位附上XX标记
A22: 法术 | B22: 穿透流 | C22: 穿透，链接 | D22: 2 | E22: 按顺序链接经过的单位
A23: 法术 | B23: 穿透流 | C23: 穿透，链接 | D23: 2 | E23: 穿过链接线时对链接的单位造成伤害
A24: 生物 | B24: 英雄流 | C24: 英雄，标记 | D24: 1 | E24: 标记碰撞的首个敌方单位，回合结束时，我方英雄向其位移 | F24: 1
A25: 生物 | B25: 英雄流 | C25: 英雄，弹射 | D25: 1 | E25: 碰到英雄后，获得属性加成 | F25: 1
A26: 生物 | B26: 英雄流 | C26: 英雄，亡语 | D26: 1 | E26: 该单位死亡时，为英雄增加攻击力 | F26: 1
A27: 生物 | B27: 英雄流 | C27: 英雄，弹射 | D27: 1 | E27: 每回合首次碰撞英雄时，对施加一个较大的力 | F27: 1
A28: 生物 | B28: 英雄流 | C28: 英雄，弹射，亡语 | D28: 1 | E28: 碰到我方英雄，使该生物牺牲，将属性按比例加到英雄上 | F28: 1
A29: 法术 | B29: 英雄流 | C29: 英雄，穿透，燃血 | D29: 2 | E29: 牺牲穿过的我方单位，将其属性按比例加到英雄上 | F29: 1
A30: 法术 | B30: 英雄流 | C30: 英雄，弹射 | D30: 2 | E30: 打出时，英雄按同一个方向进行位移 | F30: 1
A31: 生物 | B31: 过牌流 | C31: 过牌，燃血 | D31: 1 | E31: 每回合燃烧英雄血量，进行抽牌 | F31: 1
A32: 生物 | B32: 过牌流 | C32: 过牌 | D32: 1 | E32: 每回合生成一张临时牌
A33: 生物 | B33: 过牌流 | C33: 过牌，击杀，精英 | D33: 1 | E33: 该生物每击杀一个敌人，我方英雄增加N点能量 | F33: 1
A34: 生物 | B34: 过牌流 | C34: 生物数量，弹射，过牌 | D34: 1 | E34: 我方回合，首次碰撞敌方英雄时，生成一张临时该卡，场上最多存在N个 | F34: 1
A35: 生物 | B35: 通用 | C35: 过牌 | D35: 1 | E35: 连发增幅系列，例如连续打出三张同名卡，则获得X收益 | F35: 1
A36: 法术 | B36: 通用 | C36: 牌序，弹射 | D36: 3 | E36: 加速器，下一张打出的卡牌，发射速度增加 | F36: 2
A37: 法术 | B37: 通用 | C37: 牌序 | D37: 3 | E37: 减速力场，下一张打出的卡牌，发射速度减少，摩擦力也降低
A38: 法术 | B38: 通用 | C38: 牌序 | D38: 3 | E38: 连发步枪，间隔一小段时间，连续打出后两张卡牌
A39: 法术 | B39: 通用 | C39: 弹射 | D39: 2 | E39: 单位控制器，释放时，攻击最高的单位按释放方向进行移动 | F39: 1
A40: 法术 | B40: 通用 | C40: 穿透 | D40: 2 | E40: 通用穿透，每穿透一个单位伤害减少 | F40: 1
A41: 法术 | B41: 通用 | C41: 穿透 | D41: 2 | E41: 对穿透的单位施加力 | F41: 1
A42: 法术 | B42: 通用 | C42: 穿透，回收 | D42: 2 | E42: 收回场上的生物，可以再次发射出去
A43: 生物 | B43: 通用 | C43: 资源 | D43: 1 | E43: 每回合为英雄生成一点能量 | F43: 1
A44: 生物 | B44: 通用 | C44: 过牌，标记 | D44: 1 | E44: 标记碰撞的目标，同名卡牌对其造成伤害时额外增加，可叠加，回合结束时重置
A45: 法术 | B45: 通用 | C45: 过牌 | D45: 3 | E45: 销毁并复制2次手上所有卡牌
A46: 生物 | B46: 通用 | C46: 圣盾 | D46: 1 | E46: 为碰撞到的单位增加圣盾 | F46: 1
A47: 生物 | B47: 通用 | C47: 成长 | D47: 1 | E47: 每打出一次，攻击力/血量增加 | F47: 1
A48: 法术 | B48: 通用 | C48: 场景 | D48: 4 | E48: 在特定地点召唤场景物件
A49: 法术 | B49: 通用 | C49: 范围 | D49: 4 | E49: 在选定位置释放圆形范围AOE伤害 | F49: 1
A50: 法术 | B50: 通用 | C50: 物理变化 | D50: 2 | E50: 本回合，使碰到的首个单位变大 | F50: 1
A51: 法术 | B51: 通用 | C51: 物理变化 | D51: 2 | E51: 使穿过的所有单位永久缩小，不可叠加
A52: 生物 | B52: 通用 | C52: 负面 | D52: 1 | E52: 每回合首次碰到敌方英雄，扣除其1点能量 | F52: 2
A53: 法术 | B53: 场景流 | C53: 场景 | D53: 2 | E53: 经过的路径生成墙壁
A54: 生物 | B54: 场景流 | C54: 场景，元素 | D54: 1 | E54: 单位死亡后化作火焰地面
A55: 生物 | B55: 场景流 | C55: 场景，元素 | D55: 1 | E55: 单位进入火焰地面时，产生爆炸并被点燃
A56: 生物 | B56: 场景流 | C56: 场景，掉落物 | D56: 1 | E56: 移动时随机生成N个掉落物，若本回合全部被拾取，则获得一个大增益
A57: 生物 | B57: 人海流 | C57: 精英，弹射 | D57: 1 | E57: 融合碰到的所有我方生物，获得X%的基础属性 | F57: 1
A58: 法术 | B58: 场景流 | C58: 场景，持续 | D58: 1 | E58: 产生全场持续吹向敌方的风（加快我方出牌速度，增加敌方出牌难度，敌方可以抵消）
A59: 生物 | B59: 数字流 | C59: 数字 | D59: 1 | E59: 扑克牌数字1-13*4
E61: 英雄技能冷却减少/充能加速
E62: 吸血，碰撞时回复等量生命值 | F62: 1
E63: 抽取能耗值最高/最低的牌 | F63: 1
E64: 抽到时自动释放，选择目标/特定方向
E65: 入场，发射时触发
E66: 法术伤害增加X
E67: 抉择，两个选择中选一个
E68: 发现，随机三选一
E69: 从牌库中召唤特定（法力值小于，攻击力等于等等）生物 | F69: 1
E70: 造成等同于该生物攻击力的伤害，随机分配到所有敌人身上
E71: 在手牌中时，触发XX效果
E72: 如果牌库中没有相同的牌，则XX
E73: 将特定牌洗入我方/敌方牌库
E74: 将特定牌塞入我方/敌方手牌
E75: 召唤本局中已经死亡的特定随从
E76: 入场时触发另一个在场生物的入场/xx效果
E77: 对该生物使用XX时，触发一个效果
E78: 根据种族进行特定操作
E79: 在手牌中根据特定条件变形 | F79: 1
E80: 获得额外回合
E81: 获取对手随机手牌的复制 | F81: 1
E82: 召唤随从的N攻N血版本
E83: 复制对手的手牌，洗入自己的牌库
E84: 使用上回合对手使用的卡牌
E85: 复制对手的操作
E86: 在手牌中时，每个回合变成对手手牌中的一张牌 | F86: 1
E87: 将所有生物变形为法力值增加N点的生物
E88: 释放法术时，召唤一个法力值相同的生物
E89: 每回合结束时，偷取对方英雄血量至我方英雄
E90: 在我方回合受到伤害，获得XX增益（燃血流）
E91: 弃牌相关增益
E92: 将对手手牌中一个随机生物拉入战场 | F92: 1
E93: 替换自身牌库或部分牌库为XX
E94: 检测双方英雄血量，触发效果
E95: 检测双方牌库，触发效果
E96: 法力奇数偶数等数字检测，触发效果
E97: 和战场相关，碰墙时获得XX效果等
E98: 法术消灭了随从，则召唤该随从 | F98: 1
E99: 双方同时生效的，例如同时抽牌到5张等
E100: 猜测，例如抽牌，若猜中下一张牌法力值是大还是小，则获得这张牌
E101: 将法力上限转化成生物，生物死亡时回复上限 | F101: 1
...

Sheet AI阵容搭配规划
A1: bot_type | B1: hero_id | D1: card_list | Q1: ##var | R1: id | S1: bot_type | T1: hero_id | U1: card_list
A2: int | B2: int | D2: list,int | Q2: ##type | R2: int | S2: int | T2: int | U2: list,int
A3: ai类型 | B3: 英雄id | D3: 卡组 | Q3: ## | R3: id | S3: ai类型 | T3: 英雄id | U3: 卡组
A4: s | B4: s | D4: s | Q4: ##group | S4: s | T4: s | U4: s
A5: 0 | B5: 10000 | C5: 卡组ID | D5: 10021 | E5: 10030 | F5: 10080 | G5: 10036 | H5: 10035 | I5: 10037 | J5: 10012 | K5: 10031 | L5: 10026 | M5: 10020
B6: =IF(ISNUMBER(MATCH(B5,单位卡分表!$N:$N,0)),INDEX(单位卡分表!$B:$B,MATCH(B5,单位卡分表!$N:$N,0)),INDEX(技能卡分表!$B:$B,MATCH(B5,技能卡分表!$A:$A,0))) -> 传奇飞行员 舰长 | C6: 名字 | D6: =IF(ISNUMBER(MATCH(D5,单位卡分表!$A:$A,0)),INDEX(单位卡分表!$B:$B,MATCH(D5,单位卡分表!$A:$A,0)),INDEX(技能卡分表!$B:$B,MATCH(D5,技能卡分表!$A:$A,0))) -> 自动铅笔 追忆 | E6: =IF(ISNUMBER(MATCH(E5,单位卡分表!$A:$A,0)),INDEX(单位卡分表!$B:$B,MATCH(E5,单位卡分表!$A:$A,0)),INDEX(技能卡分表!$B:$B,MATCH(E5,技能卡分表!$A:$A,0))) -> 军鼓 震声 | F6: =IF(ISNUMBER(MATCH(F5,单位卡分表!$A:$A,0)),INDEX(单位卡分表!$B:$B,MATCH(F5,单位卡分表!$A:$A,0)),INDEX(技能卡分表!$B:$B,MATCH(F5,技能卡分表!$A:$A,0))) -> 安全帽 小橘 | G6: =IF(ISNUMBER(MATCH(G5,单位卡分表!$A:$A,0)),INDEX(单位卡分表!$B:$B,MATCH(G5,单位卡分表!$A:$A,0)),INDEX(技能卡分表!$B:$B,MATCH(G5,技能卡分表!$A:$A,0))) -> 纯净水 满满 | H6: =IF(ISNUMBER(MATCH(H5,单位卡分表!$A:$A,0)),INDEX(单位卡分表!$B:$B,MATCH(H5,单位卡分表!$A:$A,0)),INDEX(技能卡分表!$B:$B,MATCH(H5,技能卡分表!$A:$A,0))) -> 纯净水 浅浅 | I6: =IF(ISNUMBER(MATCH(I5,单位卡分表!$A:$A,0)),INDEX(单位卡分表!$B:$B,MATCH(I5,单位卡分表!$A:$A,0)),INDEX(技能卡分表!$B:$B,MATCH(I5,技能卡分表!$A:$A,0))) -> 红汽水 浅浅 | J6: =IF(ISNUMBER(MATCH(J5,单位卡分表!$A:$A,0)),INDEX(单位卡分表!$B:$B,MATCH(J5,单位卡分表!$A:$A,0)),INDEX(技能卡分表!$B:$B,MATCH(J5,技能卡分表!$A:$A,0))) -> 摩托 赤狸 塞琳娜 | K6: =IF(ISNUMBER(MATCH(K5,单位卡分表!$A:$A,0)),INDEX(单位卡分表!$B:$B,MATCH(K5,单位卡分表!$A:$A,0)),INDEX(技能卡分表!$B:$B,MATCH(K5,技能卡分表!$A:$A,0))) -> 注射器 针妮 佩妮（英文penny，联想小针） | ... M6: =IF(ISNUMBER(MATCH(M5,单位卡分表!$A:$A,0)),INDEX(单位卡分表!$B:$B,MATCH(M5,单位卡分表!$A:$A,0)),INDEX(技能卡分表!$B:$B,MATCH(M5,技能卡分表!$A:$A,0))) -> 时钟 晨曦 | N6: =IF(SUMPRODUCT(COUNTIF(D6:M6,D6:M6))>COLUMNS(D6:M6),"有重复","无重复") -> 无重复
A7: 0 | B7: 10000 | C7: 卡组ID | D7: 10039 | E7: 10030 | F7: 10050 | G7: 10036 | H7: 10035 | I7: 10037 | J7: 10079 | K7: 10044 | L7: 10026 | M7: 10020
B8: =IF(ISNUMBER(MATCH(B7,单位卡分表!$N:$N,0)),INDEX(单位卡分表!$B:$B,MATCH(B7,单位卡分表!$N:$N,0)),INDEX(技能卡分表!$B:$B,MATCH(B7,技能卡分表!$A:$A,0))) -> 传奇飞行员 舰长 | C8: 名字 | D8: =IF(ISNUMBER(MATCH(D7,单位卡分表!$A:$A,0)),INDEX(单位卡分表!$B:$B,MATCH(D7,单位卡分表!$A:$A,0)),INDEX(技能卡分表!$B:$B,MATCH(D7,技能卡分表!$A:$A,0))) -> 绿汽水 浅浅 | E8: =IF(ISNUMBER(MATCH(E7,单位卡分表!$A:$A,0)),INDEX(单位卡分表!$B:$B,MATCH(E7,单位卡分表!$A:$A,0)),INDEX(技能卡分表!$B:$B,MATCH(E7,技能卡分表!$A:$A,0))) -> 军鼓 震声 | F8: =IF(ISNUMBER(MATCH(F7,单位卡分表!$A:$A,0)),INDEX(单位卡分表!$B:$B,MATCH(F7,单位卡分表!$A:$A,0)),INDEX(技能卡分表!$B:$B,MATCH(F7,技能卡分表!$A:$A,0))) -> 茶包 小茗 | G8: =IF(ISNUMBER(MATCH(G7,单位卡分表!$A:$A,0)),INDEX(单位卡分表!$B:$B,MATCH(G7,单位卡分表!$A:$A,0)),INDEX(技能卡分表!$B:$B,MATCH(G7,技能卡分表!$A:$A,0))) -> 纯净水 满满 | H8: =IF(ISNUMBER(MATCH(H7,单位卡分表!$A:$A,0)),INDEX(单位卡分表!$B:$B,MATCH(H7,单位卡分表!$A:$A,0)),INDEX(技能卡分表!$B:$B,MATCH(H7,技能卡分表!$A:$A,0))) -> 纯净水 浅浅 | I8: =IF(ISNUMBER(MATCH(I7,单位卡分表!$A:$A,0)),INDEX(单位卡分表!$B:$B,MATCH(I7,单位卡分表!$A:$A,0)),INDEX(技能卡分表!$B:$B,MATCH(I7,技能卡分表!$A:$A,0))) -> 红汽水 浅浅 | J8: =IF(ISNUMBER(MATCH(J7,单位卡分表!$A:$A,0)),INDEX(单位卡分表!$B:$B,MATCH(J7,单位卡分表!$A:$A,0)),INDEX(技能卡分表!$B:$B,MATCH(J7,技能卡分表!$A:$A,0))) -> 炸蛋 | K8: =IF(ISNUMBER(MATCH(K7,单位卡分表!$A:$A,0)),INDEX(单位卡分表!$B:$B,MATCH(K7,单位卡分表!$A:$A,0)),INDEX(技能卡分表!$B:$B,MATCH(K7,技能卡分表!$A:$A,0))) -> 煤油灯 流露 | ... M8: =IF(ISNUMBER(MATCH(M7,单位卡分表!$A:$A,0)),INDEX(单位卡分表!$B:$B,MATCH(M7,单位卡分表!$A:$A,0)),INDEX(技能卡分表!$B:$B,MATCH(M7,技能卡分表!$A:$A,0))) -> 时钟 晨曦 | N8: =IF(SUMPRODUCT(COUNTIF(D8:M8,D8:M8))>COLUMNS(D8:M8),"有重复","无重复") -> 无重复
A9: 0 | B9: 10002 | C9: 卡组ID | D9: 10033 | E9: 10060 | F9: 10051 | G9: 10036 | H9: 10035 | I9: 10037 | J9: 10079 | K9: 10044 | L9: 10026 | M9: 10020
B10: =IF(ISNUMBER(MATCH(B9,单位卡分表!$N:$N,0)),INDEX(单位卡分表!$B:$B,MATCH(B9,单位卡分表!$N:$N,0)),INDEX(技能卡分表!$B:$B,MATCH(B9,技能卡分表!$A:$A,0))) -> 最强盗贼王 露娜（Luna） | C10: 名字 | D10: =IF(ISNUMBER(MATCH(D9,单位卡分表!$A:$A,0)),INDEX(单位卡分表!$B:$B,MATCH(D9,单位卡分表!$A:$A,0)),INDEX(技能卡分表!$B:$B,MATCH(D9,技能卡分表!$A:$A,0))) -> 蜡烛 热泪 | E10: =IF(ISNUMBER(MATCH(E9,单位卡分表!$A:$A,0)),INDEX(单位卡分表!$B:$B,MATCH(E9,单位卡分表!$A:$A,0)),INDEX(技能卡分表!$B:$B,MATCH(E9,技能卡分表!$A:$A,0))) -> 爆米花 酥脆 | F10: =IF(ISNUMBER(MATCH(F9,单位卡分表!$A:$A,0)),INDEX(单位卡分表!$B:$B,MATCH(F9,单位卡分表!$A:$A,0)),INDEX(技能卡分表!$B:$B,MATCH(F9,技能卡分表!$A:$A,0))) -> 气球 飘舞 | G10: =IF(ISNUMBER(MATCH(G9,单位卡分表!$A:$A,0)),INDEX(单位卡分表!$B:$B,MATCH(G9,单位卡分表!$A:$A,0)),INDEX(技能卡分表!$B:$B,MATCH(G9,技能卡分表!$A:$A,0))) -> 纯净水 满满 | H10: =IF(ISNUMBER(MATCH(H9,单位卡分表!$A:$A,0)),INDEX(单位卡分表!$B:$B,MATCH(H9,单位卡分表!$A:$A,0)),INDEX(技能卡分表!$B:$B,MATCH(H9,技能卡分表!$A:$A,0))) -> 纯净水 浅浅 | I10: =IF(ISNUMBER(MATCH(I9,单位卡分表!$A:$A,0)),INDEX(单位卡分表!$B:$B,MATCH(I9,单位卡分表!$A:$A,0)),INDEX(技能卡分表!$B:$B,MATCH(I9,技能卡分表!$A:$A,0))) -> 红汽水 浅浅 | J10: =IF(ISNUMBER(MATCH(J9,单位卡分表!$A:$A,0)),INDEX(单位卡分表!$B:$B,MATCH(J9,单位卡分表!$A:$A,0)),INDEX(技能卡分表!$B:$B,MATCH(J9,技能卡分表!$A:$A,0))) -> 炸蛋 | K10: =IF(ISNUMBER(MATCH(K9,单位卡分表!$A:$A,0)),INDEX(单位卡分表!$B:$B,MATCH(K9,单位卡分表!$A:$A,0)),INDEX(技能卡分表!$B:$B,MATCH(K9,技能卡分表!$A:$A,0))) -> 煤油灯 流露 | ... M10: =IF(ISNUMBER(MATCH(M9,单位卡分表!$A:$A,0)),INDEX(单位卡分表!$B:$B,MATCH(M9,单位卡分表!$A:$A,0)),INDEX(技能卡分表!$B:$B,MATCH(M9,技能卡分表!$A:$A,0))) -> 时钟 晨曦 | N10: =IF(SUMPRODUCT(COUNTIF(D10:M10,D10:M10))>COLUMNS(D10:M10),"有重复","无重复") -> 无重复
A11: 0 | B11: 10002 | C11: 卡组ID | D11: 10015 | E11: 10017 | F11: 10050 | G11: 10036 | H11: 10035 | I11: 10037 | J11: 10011 | K11: 10012 | L11: 10026 | M11: 10020
B12: =IF(ISNUMBER(MATCH(B11,单位卡分表!$N:$N,0)),INDEX(单位卡分表!$B:$B,MATCH(B11,单位卡分表!$N:$N,0)),INDEX(技能卡分表!$B:$B,MATCH(B11,技能卡分表!$A:$A,0))) -> 最强盗贼王 露娜（Luna） | C12: 名字 | D12: =IF(ISNUMBER(MATCH(D11,单位卡分表!$A:$A,0)),INDEX(单位卡分表!$B:$B,MATCH(D11,单位卡分表!$A:$A,0)),INDEX(技能卡分表!$B:$B,MATCH(D11,技能卡分表!$A:$A,0))) -> 留声机 回音 玛利亚 | E12: =IF(ISNUMBER(MATCH(E11,单位卡分表!$A:$A,0)),INDEX(单位卡分表!$B:$B,MATCH(E11,单位卡分表!$A:$A,0)),INDEX(技能卡分表!$B:$B,MATCH(E11,技能卡分表!$A:$A,0))) -> 电池 欧姆 | F12: =IF(ISNUMBER(MATCH(F11,单位卡分表!$A:$A,0)),INDEX(单位卡分表!$B:$B,MATCH(F11,单位卡分表!$A:$A,0)),INDEX(技能卡分表!$B:$B,MATCH(F11,技能卡分表!$A:$A,0))) -> 茶包 小茗 | G12: =IF(ISNUMBER(MATCH(G11,单位卡分表!$A:$A,0)),INDEX(单位卡分表!$B:$B,MATCH(G11,单位卡分表!$A:$A,0)),INDEX(技能卡分表!$B:$B,MATCH(G11,技能卡分表!$A:$A,0))) -> 纯净水 满满 | H12: =IF(ISNUMBER(MATCH(H11,单位卡分表!$A:$A,0)),INDEX(单位卡分表!$B:$B,MATCH(H11,单位卡分表!$A:$A,0)),INDEX(技能卡分表!$B:$B,MATCH(H11,技能卡分表!$A:$A,0))) -> 纯净水 浅浅 | I12: =IF(ISNUMBER(MATCH(I11,单位卡分表!$A:$A,0)),INDEX(单位卡分表!$B:$B,MATCH(I11,单位卡分表!$A:$A,0)),INDEX(技能卡分表!$B:$B,MATCH(I11,技能卡分表!$A:$A,0))) -> 红汽水 浅浅 | J12: =IF(ISNUMBER(MATCH(J11,单位卡分表!$A:$A,0)),INDEX(单位卡分表!$B:$B,MATCH(J11,单位卡分表!$A:$A,0)),INDEX(技能卡分表!$B:$B,MATCH(J11,技能卡分表!$A:$A,0))) -> 纸巾 缠缠 | K12: =IF(ISNUMBER(MATCH(K11,单位卡分表!$A:$A,0)),INDEX(单位卡分表!$B:$B,MATCH(K11,单位卡分表!$A:$A,0)),INDEX(技能卡分表!$B:$B,MATCH(K11,技能卡分表!$A:$A,0))) -> 摩托 赤狸 塞琳娜 | ... M12: =IF(ISNUMBER(MATCH(M11,单位卡分表!$A:$A,0)),INDEX(单位卡分表!$B:$B,MATCH(M11,单位卡分表!$A:$A,0)),INDEX(技能卡分表!$B:$B,MATCH(M11,技能卡分表!$A:$A,0))) -> 时钟 晨曦 | N12: =IF(SUMPRODUCT(COUNTIF(D12:M12,D12:M12))>COLUMNS(D12:M12),"有重复","无重复") -> 无重复
A13: 0 | B13: 10003 | C13: 卡组ID | D13: 10021 | E13: 10062 | F13: 10016 | G13: 10036 | H13: 10035 | I13: 10037 | J13: 10077 | K13: 10013 | L13: 10026 | M13: 10020
B14: =IF(ISNUMBER(MATCH(B13,单位卡分表!$N:$N,0)),INDEX(单位卡分表!$B:$B,MATCH(B13,单位卡分表!$N:$N,0)),INDEX(技能卡分表!$B:$B,MATCH(B13,技能卡分表!$A:$A,0))) -> 轻灵跃影 乔艾塔（Joetta） | C14: 名字 | D14: =IF(ISNUMBER(MATCH(D13,单位卡分表!$A:$A,0)),INDEX(单位卡分表!$B:$B,MATCH(D13,单位卡分表!$A:$A,0)),INDEX(技能卡分表!$B:$B,MATCH(D13,技能卡分表!$A:$A,0))) -> 自动铅笔 追忆 | E14: =IF(ISNUMBER(MATCH(E13,单位卡分表!$A:$A,0)),INDEX(单位卡分表!$B:$B,MATCH(E13,单位卡分表!$A:$A,0)),INDEX(技能卡分表!$B:$B,MATCH(E13,技能卡分表!$A:$A,0))) -> 绿汽水 满满（复用） | F14: =IF(ISNUMBER(MATCH(F13,单位卡分表!$A:$A,0)),INDEX(单位卡分表!$B:$B,MATCH(F13,单位卡分表!$A:$A,0)),INDEX(技能卡分表!$B:$B,MATCH(F13,技能卡分表!$A:$A,0))) -> 电扇 彩虹 | G14: =IF(ISNUMBER(MATCH(G13,单位卡分表!$A:$A,0)),INDEX(单位卡分表!$B:$B,MATCH(G13,单位卡分表!$A:$A,0)),INDEX(技能卡分表!$B:$B,MATCH(G13,技能卡分表!$A:$A,0))) -> 纯净水 满满 | H14: =IF(ISNUMBER(MATCH(H13,单位卡分表!$A:$A,0)),INDEX(单位卡分表!$B:$B,MATCH(H13,单位卡分表!$A:$A,0)),INDEX(技能卡分表!$B:$B,MATCH(H13,技能卡分表!$A:$A,0))) -> 纯净水 浅浅 | I14: =IF(ISNUMBER(MATCH(I13,单位卡分表!$A:$A,0)),INDEX(单位卡分表!$B:$B,MATCH(I13,单位卡分表!$A:$A,0)),INDEX(技能卡分表!$B:$B,MATCH(I13,技能卡分表!$A:$A,0))) -> 红汽水 浅浅 | J14: =IF(ISNUMBER(MATCH(J13,单位卡分表!$A:$A,0)),INDEX(单位卡分表!$B:$B,MATCH(J13,单位卡分表!$A:$A,0)),INDEX(技能卡分表!$B:$B,MATCH(J13,技能卡分表!$A:$A,0))) -> 接力棒 传承 | K14: =IF(ISNUMBER(MATCH(K13,单位卡分表!$A:$A,0)),INDEX(单位卡分表!$B:$B,MATCH(K13,单位卡分表!$A:$A,0)),INDEX(技能卡分表!$B:$B,MATCH(K13,技能卡分表!$A:$A,0))) -> 雨伞 守心 布洛莉Brolly | ... M14: =IF(ISNUMBER(MATCH(M13,单位卡分表!$A:$A,0)),INDEX(单位卡分表!$B:$B,MATCH(M13,单位卡分表!$A:$A,0)),INDEX(技能卡分表!$B:$B,MATCH(M13,技能卡分表!$A:$A,0))) -> 时钟 晨曦 | N14: =IF(SUMPRODUCT(COUNTIF(D14:M14,D14:M14))>COLUMNS(D14:M14),"有重复","无重复") -> 无重复
A15: 0 | B15: 10003 | C15: 卡组ID | D15: 10025 | E15: 10016 | F15: 10030 | G15: 10036 | H15: 10035 | I15: 10037 | J15: 10028 | K15: 10012 | L15: 10026 | M15: 10020
B16: =IF(ISNUMBER(MATCH(B15,单位卡分表!$N:$N,0)),INDEX(单位卡分表!$B:$B,MATCH(B15,单位卡分表!$N:$N,0)),INDEX(技能卡分表!$B:$B,MATCH(B15,技能卡分表!$A:$A,0))) -> 轻灵跃影 乔艾塔（Joetta） | C16: 名字 | D16: =IF(ISNUMBER(MATCH(D15,单位卡分表!$A:$A,0)),INDEX(单位卡分表!$B:$B,MATCH(D15,单位卡分表!$A:$A,0)),INDEX(技能卡分表!$B:$B,MATCH(D15,技能卡分表!$A:$A,0))) -> 电池 伏特 | E16: =IF(ISNUMBER(MATCH(E15,单位卡分表!$A:$A,0)),INDEX(单位卡分表!$B:$B,MATCH(E15,单位卡分表!$A:$A,0)),INDEX(技能卡分表!$B:$B,MATCH(E15,技能卡分表!$A:$A,0))) -> 电扇 彩虹 | F16: =IF(ISNUMBER(MATCH(F15,单位卡分表!$A:$A,0)),INDEX(单位卡分表!$B:$B,MATCH(F15,单位卡分表!$A:$A,0)),INDEX(技能卡分表!$B:$B,MATCH(F15,技能卡分表!$A:$A,0))) -> 军鼓 震声 | G16: =IF(ISNUMBER(MATCH(G15,单位卡分表!$A:$A,0)),INDEX(单位卡分表!$B:$B,MATCH(G15,单位卡分表!$A:$A,0)),INDEX(技能卡分表!$B:$B,MATCH(G15,技能卡分表!$A:$A,0))) -> 纯净水 满满 | H16: =IF(ISNUMBER(MATCH(H15,单位卡分表!$A:$A,0)),INDEX(单位卡分表!$B:$B,MATCH(H15,单位卡分表!$A:$A,0)),INDEX(技能卡分表!$B:$B,MATCH(H15,技能卡分表!$A:$A,0))) -> 纯净水 浅浅 | I16: =IF(ISNUMBER(MATCH(I15,单位卡分表!$A:$A,0)),INDEX(单位卡分表!$B:$B,MATCH(I15,单位卡分表!$A:$A,0)),INDEX(技能卡分表!$B:$B,MATCH(I15,技能卡分表!$A:$A,0))) -> 红汽水 浅浅 | J16: =IF(ISNUMBER(MATCH(J15,单位卡分表!$A:$A,0)),INDEX(单位卡分表!$B:$B,MATCH(J15,单位卡分表!$A:$A,0)),INDEX(技能卡分表!$B:$B,MATCH(J15,技能卡分表!$A:$A,0))) -> 羽毛球 拉丽（英文就rally连续得分的意思） | K16: =IF(ISNUMBER(MATCH(K15,单位卡分表!$A:$A,0)),INDEX(单位卡分表!$B:$B,MATCH(K15,单位卡分表!$A:$A,0)),INDEX(技能卡分表!$B:$B,MATCH(K15,技能卡分表!$A:$A,0))) -> 摩托 赤狸 塞琳娜 | ... M16: =IF(ISNUMBER(MATCH(M15,单位卡分表!$A:$A,0)),INDEX(单位卡分表!$B:$B,MATCH(M15,单位卡分表!$A:$A,0)),INDEX(技能卡分表!$B:$B,MATCH(M15,技能卡分表!$A:$A,0))) -> 时钟 晨曦 | N16: =IF(SUMPRODUCT(COUNTIF(D16:M16,D16:M16))>COLUMNS(D16:M16),"有重复","无重复") -> 无重复
A17: 1 | B17: 10000 | C17: 卡组ID | D17: 10021 | E17: 10030 | F17: 10080 | G17: 10036 | H17: 10035 | I17: 10037 | J17: 10012 | K17: 10031 | L17: 10026 | M17: 10020
B18: =IF(ISNUMBER(MATCH(B17,单位卡分表!$N:$N,0)),INDEX(单位卡分表!$B:$B,MATCH(B17,单位卡分表!$N:$N,0)),INDEX(技能卡分表!$B:$B,MATCH(B17,技能卡分表!$A:$A,0))) -> 传奇飞行员 舰长 | C18: 名字 | D18: =IF(ISNUMBER(MATCH(D17,单位卡分表!$A:$A,0)),INDEX(单位卡分表!$B:$B,MATCH(D17,单位卡分表!$A:$A,0)),INDEX(技能卡分表!$B:$B,MATCH(D17,技能卡分表!$A:$A,0))) -> 自动铅笔 追忆 | E18: =IF(ISNUMBER(MATCH(E17,单位卡分表!$A:$A,0)),INDEX(单位卡分表!$B:$B,MATCH(E17,单位卡分表!$A:$A,0)),INDEX(技能卡分表!$B:$B,MATCH(E17,技能卡分表!$A:$A,0))) -> 军鼓 震声 | F18: =IF(ISNUMBER(MATCH(F17,单位卡分表!$A:$A,0)),INDEX(单位卡分表!$B:$B,MATCH(F17,单位卡分表!$A:$A,0)),INDEX(技能卡分表!$B:$B,MATCH(F17,技能卡分表!$A:$A,0))) -> 安全帽 小橘 | G18: =IF(ISNUMBER(MATCH(G17,单位卡分表!$A:$A,0)),INDEX(单位卡分表!$B:$B,MATCH(G17,单位卡分表!$A:$A,0)),INDEX(技能卡分表!$B:$B,MATCH(G17,技能卡分表!$A:$A,0))) -> 纯净水 满满 | H18: =IF(ISNUMBER(MATCH(H17,单位卡分表!$A:$A,0)),INDEX(单位卡分表!$B:$B,MATCH(H17,单位卡分表!$A:$A,0)),INDEX(技能卡分表!$B:$B,MATCH(H17,技能卡分表!$A:$A,0))) -> 纯净水 浅浅 | I18: =IF(ISNUMBER(MATCH(I17,单位卡分表!$A:$A,0)),INDEX(单位卡分表!$B:$B,MATCH(I17,单位卡分表!$A:$A,0)),INDEX(技能卡分表!$B:$B,MATCH(I17,技能卡分表!$A:$A,0))) -> 红汽水 浅浅 | J18: =IF(ISNUMBER(MATCH(J17,单位卡分表!$A:$A,0)),INDEX(单位卡分表!$B:$B,MATCH(J17,单位卡分表!$A:$A,0)),INDEX(技能卡分表!$B:$B,MATCH(J17,技能卡分表!$A:$A,0))) -> 摩托 赤狸 塞琳娜 | K18: =IF(ISNUMBER(MATCH(K17,单位卡分表!$A:$A,0)),INDEX(单位卡分表!$B:$B,MATCH(K17,单位卡分表!$A:$A,0)),INDEX(技能卡分表!$B:$B,MATCH(K17,技能卡分表!$A:$A,0))) -> 注射器 针妮 佩妮（英文penny，联想小针） | ... M18: =IF(ISNUMBER(MATCH(M17,单位卡分表!$A:$A,0)),INDEX(单位卡分表!$B:$B,MATCH(M17,单位卡分表!$A:$A,0)),INDEX(技能卡分表!$B:$B,MATCH(M17,技能卡分表!$A:$A,0))) -> 时钟 晨曦 | N18: =IF(SUMPRODUCT(COUNTIF(D18:M18,D18:M18))>COLUMNS(D18:M18),"有重复","无重复") -> 无重复
A19: 1 | B19: 10002 | C19: 卡组ID | D19: 10033 | E19: 10060 | F19: 10051 | G19: 10036 | H19: 10035 | I19: 10037 | J19: 10079 | K19: 10044 | L19: 10026 | M19: 10020
B20: =IF(ISNUMBER(MATCH(B19,单位卡分表!$N:$N,0)),INDEX(单位卡分表!$B:$B,MATCH(B19,单位卡分表!$N:$N,0)),INDEX(技能卡分表!$B:$B,MATCH(B19,技能卡分表!$A:$A,0))) -> 最强盗贼王 露娜（Luna） | C20: 名字 | D20: =IF(ISNUMBER(MATCH(D19,单位卡分表!$A:$A,0)),INDEX(单位卡分表!$B:$B,MATCH(D19,单位卡分表!$A:$A,0)),INDEX(技能卡分表!$B:$B,MATCH(D19,技能卡分表!$A:$A,0))) -> 蜡烛 热泪 | E20: =IF(ISNUMBER(MATCH(E19,单位卡分表!$A:$A,0)),INDEX(单位卡分表!$B:$B,MATCH(E19,单位卡分表!$A:$A,0)),INDEX(技能卡分表!$B:$B,MATCH(E19,技能卡分表!$A:$A,0))) -> 爆米花 酥脆 | F20: =IF(ISNUMBER(MATCH(F19,单位卡分表!$A:$A,0)),INDEX(单位卡分表!$B:$B,MATCH(F19,单位卡分表!$A:$A,0)),INDEX(技能卡分表!$B:$B,MATCH(F19,技能卡分表!$A:$A,0))) -> 气球 飘舞 | G20: =IF(ISNUMBER(MATCH(G19,单位卡分表!$A:$A,0)),INDEX(单位卡分表!$B:$B,MATCH(G19,单位卡分表!$A:$A,0)),INDEX(技能卡分表!$B:$B,MATCH(G19,技能卡分表!$A:$A,0))) -> 纯净水 满满 | H20: =IF(ISNUMBER(MATCH(H19,单位卡分表!$A:$A,0)),INDEX(单位卡分表!$B:$B,MATCH(H19,单位卡分表!$A:$A,0)),INDEX(技能卡分表!$B:$B,MATCH(H19,技能卡分表!$A:$A,0))) -> 纯净水 浅浅 | I20: =IF(ISNUMBER(MATCH(I19,单位卡分表!$A:$A,0)),INDEX(单位卡分表!$B:$B,MATCH(I19,单位卡分表!$A:$A,0)),INDEX(技能卡分表!$B:$B,MATCH(I19,技能卡分表!$A:$A,0))) -> 红汽水 浅浅 | J20: =IF(ISNUMBER(MATCH(J19,单位卡分表!$A:$A,0)),INDEX(单位卡分表!$B:$B,MATCH(J19,单位卡分表!$A:$A,0)),INDEX(技能卡分表!$B:$B,MATCH(J19,技能卡分表!$A:$A,0))) -> 炸蛋 | K20: =IF(ISNUMBER(MATCH(K19,单位卡分表!$A:$A,0)),INDEX(单位卡分表!$B:$B,MATCH(K19,单位卡分表!$A:$A,0)),INDEX(技能卡分表!$B:$B,MATCH(K19,技能卡分表!$A:$A,0))) -> 煤油灯 流露 | ... M20: =IF(ISNUMBER(MATCH(M19,单位卡分表!$A:$A,0)),INDEX(单位卡分表!$B:$B,MATCH(M19,单位卡分表!$A:$A,0)),INDEX(技能卡分表!$B:$B,MATCH(M19,技能卡分表!$A:$A,0))) -> 时钟 晨曦 | N20: =IF(SUMPRODUCT(COUNTIF(D20:M20,D20:M20))>COLUMNS(D20:M20),"有重复","无重复") -> 无重复
A21: 1 | B21: 10002 | C21: 卡组ID | D21: 10015 | E21: 10017 | F21: 10050 | G21: 10036 | H21: 10035 | I21: 10037 | J21: 10011 | K21: 10012 | L21: 10026 | M21: 10020
B22: =IF(ISNUMBER(MATCH(B21,单位卡分表!$N:$N,0)),INDEX(单位卡分表!$B:$B,MATCH(B21,单位卡分表!$N:$N,0)),INDEX(技能卡分表!$B:$B,MATCH(B21,技能卡分表!$A:$A,0))) -> 最强盗贼王 露娜（Luna） | C22: 名字 | D22: =IF(ISNUMBER(MATCH(D21,单位卡分表!$A:$A,0)),INDEX(单位卡分表!$B:$B,MATCH(D21,单位卡分表!$A:$A,0)),INDEX(技能卡分表!$B:$B,MATCH(D21,技能卡分表!$A:$A,0))) -> 留声机 回音 玛利亚 | E22: =IF(ISNUMBER(MATCH(E21,单位卡分表!$A:$A,0)),INDEX(单位卡分表!$B:$B,MATCH(E21,单位卡分表!$A:$A,0)),INDEX(技能卡分表!$B:$B,MATCH(E21,技能卡分表!$A:$A,0))) -> 电池 欧姆 | F22: =IF(ISNUMBER(MATCH(F21,单位卡分表!$A:$A,0)),INDEX(单位卡分表!$B:$B,MATCH(F21,单位卡分表!$A:$A,0)),INDEX(技能卡分表!$B:$B,MATCH(F21,技能卡分表!$A:$A,0))) -> 茶包 小茗 | G22: =IF(ISNUMBER(MATCH(G21,单位卡分表!$A:$A,0)),INDEX(单位卡分表!$B:$B,MATCH(G21,单位卡分表!$A:$A,0)),INDEX(技能卡分表!$B:$B,MATCH(G21,技能卡分表!$A:$A,0))) -> 纯净水 满满 | H22: =IF(ISNUMBER(MATCH(H21,单位卡分表!$A:$A,0)),INDEX(单位卡分表!$B:$B,MATCH(H21,单位卡分表!$A:$A,0)),INDEX(技能卡分表!$B:$B,MATCH(H21,技能卡分表!$A:$A,0))) -> 纯净水 浅浅 | I22: =IF(ISNUMBER(MATCH(I21,单位卡分表!$A:$A,0)),INDEX(单位卡分表!$B:$B,MATCH(I21,单位卡分表!$A:$A,0)),INDEX(技能卡分表!$B:$B,MATCH(I21,技能卡分表!$A:$A,0))) -> 红汽水 浅浅 | J22: =IF(ISNUMBER(MATCH(J21,单位卡分表!$A:$A,0)),INDEX(单位卡分表!$B:$B,MATCH(J21,单位卡分表!$A:$A,0)),INDEX(技能卡分表!$B:$B,MATCH(J21,技能卡分表!$A:$A,0))) -> 纸巾 缠缠 | K22: =IF(ISNUMBER(MATCH(K21,单位卡分表!$A:$A,0)),INDEX(单位卡分表!$B:$B,MATCH(K21,单位卡分表!$A:$A,0)),INDEX(技能卡分表!$B:$B,MATCH(K21,技能卡分表!$A:$A,0))) -> 摩托 赤狸 塞琳娜 | ... M22: =IF(ISNUMBER(MATCH(M21,单位卡分表!$A:$A,0)),INDEX(单位卡分表!$B:$B,MATCH(M21,单位卡分表!$A:$A,0)),INDEX(技能卡分表!$B:$B,MATCH(M21,技能卡分表!$A:$A,0))) -> 时钟 晨曦 | N22: =IF(SUMPRODUCT(COUNTIF(D22:M22,D22:M22))>COLUMNS(D22:M22),"有重复","无重复") -> 无重复
A23: 1 | B23: 10003 | C23: 卡组ID | D23: 10021 | E23: 10062 | F23: 10016 | G23: 10036 | H23: 10035 | I23: 10037 | J23: 10077 | K23: 10013 | L23: 10026 | M23: 10020
B24: =IF(ISNUMBER(MATCH(B23,单位卡分表!$N:$N,0)),INDEX(单位卡分表!$B:$B,MATCH(B23,单位卡分表!$N:$N,0)),INDEX(技能卡分表!$B:$B,MATCH(B23,技能卡分表!$A:$A,0))) -> 轻灵跃影 乔艾塔（Joetta） | C24: 名字 | D24: =IF(ISNUMBER(MATCH(D23,单位卡分表!$A:$A,0)),INDEX(单位卡分表!$B:$B,MATCH(D23,单位卡分表!$A:$A,0)),INDEX(技能卡分表!$B:$B,MATCH(D23,技能卡分表!$A:$A,0))) -> 自动铅笔 追忆 | E24: =IF(ISNUMBER(MATCH(E23,单位卡分表!$A:$A,0)),INDEX(单位卡分表!$B:$B,MATCH(E23,单位卡分表!$A:$A,0)),INDEX(技能卡分表!$B:$B,MATCH(E23,技能卡分表!$A:$A,0))) -> 绿汽水 满满（复用） | F24: =IF(ISNUMBER(MATCH(F23,单位卡分表!$A:$A,0)),INDEX(单位卡分表!$B:$B,MATCH(F23,单位卡分表!$A:$A,0)),INDEX(技能卡分表!$B:$B,MATCH(F23,技能卡分表!$A:$A,0))) -> 电扇 彩虹 | G24: =IF(ISNUMBER(MATCH(G23,单位卡分表!$A:$A,0)),INDEX(单位卡分表!$B:$B,MATCH(G23,单位卡分表!$A:$A,0)),INDEX(技能卡分表!$B:$B,MATCH(G23,技能卡分表!$A:$A,0))) -> 纯净水 满满 | H24: =IF(ISNUMBER(MATCH(H23,单位卡分表!$A:$A,0)),INDEX(单位卡分表!$B:$B,MATCH(H23,单位卡分表!$A:$A,0)),INDEX(技能卡分表!$B:$B,MATCH(H23,技能卡分表!$A:$A,0))) -> 纯净水 浅浅 | I24: =IF(ISNUMBER(MATCH(I23,单位卡分表!$A:$A,0)),INDEX(单位卡分表!$B:$B,MATCH(I23,单位卡分表!$A:$A,0)),INDEX(技能卡分表!$B:$B,MATCH(I23,技能卡分表!$A:$A,0))) -> 红汽水 浅浅 | J24: =IF(ISNUMBER(MATCH(J23,单位卡分表!$A:$A,0)),INDEX(单位卡分表!$B:$B,MATCH(J23,单位卡分表!$A:$A,0)),INDEX(技能卡分表!$B:$B,MATCH(J23,技能卡分表!$A:$A,0))) -> 接力棒 传承 | K24: =IF(ISNUMBER(MATCH(K23,单位卡分表!$A:$A,0)),INDEX(单位卡分表!$B:$B,MATCH(K23,单位卡分表!$A:$A,0)),INDEX(技能卡分表!$B:$B,MATCH(K23,技能卡分表!$A:$A,0))) -> 雨伞 守心 布洛莉Brolly | ... M24: =IF(ISNUMBER(MATCH(M23,单位卡分表!$A:$A,0)),INDEX(单位卡分表!$B:$B,MATCH(M23,单位卡分表!$A:$A,0)),INDEX(技能卡分表!$B:$B,MATCH(M23,技能卡分表!$A:$A,0))) -> 时钟 晨曦 | N24: =IF(SUMPRODUCT(COUNTIF(D24:M24,D24:M24))>COLUMNS(D24:M24),"有重复","无重复") -> 无重复
A25: 1 | B25: 10003 | C25: 卡组ID | D25: 10025 | E25: 10016 | F25: 10030 | G25: 10036 | H25: 10035 | I25: 10037 | J25: 10028 | K25: 10012 | L25: 10026 | M25: 10020
B26: =IF(ISNUMBER(MATCH(B25,单位卡分表!$N:$N,0)),INDEX(单位卡分表!$B:$B,MATCH(B25,单位卡分表!$N:$N,0)),INDEX(技能卡分表!$B:$B,MATCH(B25,技能卡分表!$A:$A,0))) -> 轻灵跃影 乔艾塔（Joetta） | C26: 名字 | D26: =IF(ISNUMBER(MATCH(D25,单位卡分表!$A:$A,0)),INDEX(单位卡分表!$B:$B,MATCH(D25,单位卡分表!$A:$A,0)),INDEX(技能卡分表!$B:$B,MATCH(D25,技能卡分表!$A:$A,0))) -> 电池 伏特 | E26: =IF(ISNUMBER(MATCH(E25,单位卡分表!$A:$A,0)),INDEX(单位卡分表!$B:$B,MATCH(E25,单位卡分表!$A:$A,0)),INDEX(技能卡分表!$B:$B,MATCH(E25,技能卡分表!$A:$A,0))) -> 电扇 彩虹 | F26: =IF(ISNUMBER(MATCH(F25,单位卡分表!$A:$A,0)),INDEX(单位卡分表!$B:$B,MATCH(F25,单位卡分表!$A:$A,0)),INDEX(技能卡分表!$B:$B,MATCH(F25,技能卡分表!$A:$A,0))) -> 军鼓 震声 | G26: =IF(ISNUMBER(MATCH(G25,单位卡分表!$A:$A,0)),INDEX(单位卡分表!$B:$B,MATCH(G25,单位卡分表!$A:$A,0)),INDEX(技能卡分表!$B:$B,MATCH(G25,技能卡分表!$A:$A,0))) -> 纯净水 满满 | H26: =IF(ISNUMBER(MATCH(H25,单位卡分表!$A:$A,0)),INDEX(单位卡分表!$B:$B,MATCH(H25,单位卡分表!$A:$A,0)),INDEX(技能卡分表!$B:$B,MATCH(H25,技能卡分表!$A:$A,0))) -> 纯净水 浅浅 | I26: =IF(ISNUMBER(MATCH(I25,单位卡分表!$A:$A,0)),INDEX(单位卡分表!$B:$B,MATCH(I25,单位卡分表!$A:$A,0)),INDEX(技能卡分表!$B:$B,MATCH(I25,技能卡分表!$A:$A,0))) -> 红汽水 浅浅 | J26: =IF(ISNUMBER(MATCH(J25,单位卡分表!$A:$A,0)),INDEX(单位卡分表!$B:$B,MATCH(J25,单位卡分表!$A:$A,0)),INDEX(技能卡分表!$B:$B,MATCH(J25,技能卡分表!$A:$A,0))) -> 羽毛球 拉丽（英文就rally连续得分的意思） | K26: =IF(ISNUMBER(MATCH(K25,单位卡分表!$A:$A,0)),INDEX(单位卡分表!$B:$B,MATCH(K25,单位卡分表!$A:$A,0)),INDEX(技能卡分表!$B:$B,MATCH(K25,技能卡分表!$A:$A,0))) -> 摩托 赤狸 塞琳娜 | ... M26: =IF(ISNUMBER(MATCH(M25,单位卡分表!$A:$A,0)),INDEX(单位卡分表!$B:$B,MATCH(M25,单位卡分表!$A:$A,0)),INDEX(技能卡分表!$B:$B,MATCH(M25,技能卡分表!$A:$A,0))) -> 时钟 晨曦 | N26: =IF(SUMPRODUCT(COUNTIF(D26:M26,D26:M26))>COLUMNS(D26:M26),"有重复","无重复") -> 无重复
A27: 1 | B27: 10004 | C27: 卡组ID | D27: 10072 | E27: 10073 | F27: 10036 | G27: 10075 | H27: 10039 | I27: 10066 | J27: 10028 | K27: 10026 | L27: 10020 | M27: 10012
B28: =IF(ISNUMBER(MATCH(B27,单位卡分表!$N:$N,0)),INDEX(单位卡分表!$B:$B,MATCH(B27,单位卡分表!$N:$N,0)),INDEX(技能卡分表!$B:$B,MATCH(B27,技能卡分表!$A:$A,0))) -> 致命拥抱 维纳斯（Venus） | C28: 名字 | D28: =IF(ISNUMBER(MATCH(D27,单位卡分表!$A:$A,0)),INDEX(单位卡分表!$B:$B,MATCH(D27,单位卡分表!$A:$A,0)),INDEX(技能卡分表!$B:$B,MATCH(D27,技能卡分表!$A:$A,0))) -> 鲨鱼 利齿 | E28: =IF(ISNUMBER(MATCH(E27,单位卡分表!$A:$A,0)),INDEX(单位卡分表!$B:$B,MATCH(E27,单位卡分表!$A:$A,0)),INDEX(技能卡分表!$B:$B,MATCH(E27,技能卡分表!$A:$A,0))) -> 储蓄罐 珠珠（复用） | F28: =IF(ISNUMBER(MATCH(F27,单位卡分表!$A:$A,0)),INDEX(单位卡分表!$B:$B,MATCH(F27,单位卡分表!$A:$A,0)),INDEX(技能卡分表!$B:$B,MATCH(F27,技能卡分表!$A:$A,0))) -> 纯净水 满满 | G28: =IF(ISNUMBER(MATCH(G27,单位卡分表!$A:$A,0)),INDEX(单位卡分表!$B:$B,MATCH(G27,单位卡分表!$A:$A,0)),INDEX(技能卡分表!$B:$B,MATCH(G27,技能卡分表!$A:$A,0))) -> 菠菜罐头 大力 | H28: =IF(ISNUMBER(MATCH(H27,单位卡分表!$A:$A,0)),INDEX(单位卡分表!$B:$B,MATCH(H27,单位卡分表!$A:$A,0)),INDEX(技能卡分表!$B:$B,MATCH(H27,技能卡分表!$A:$A,0))) -> 绿汽水 浅浅 | I28: =IF(ISNUMBER(MATCH(I27,单位卡分表!$A:$A,0)),INDEX(单位卡分表!$B:$B,MATCH(I27,单位卡分表!$A:$A,0)),INDEX(技能卡分表!$B:$B,MATCH(I27,技能卡分表!$A:$A,0))) -> 乌龟 壳壳 | J28: =IF(ISNUMBER(MATCH(J27,单位卡分表!$A:$A,0)),INDEX(单位卡分表!$B:$B,MATCH(J27,单位卡分表!$A:$A,0)),INDEX(技能卡分表!$B:$B,MATCH(J27,技能卡分表!$A:$A,0))) -> 羽毛球 拉丽（英文就rally连续得分的意思） | K28: =IF(ISNUMBER(MATCH(K27,单位卡分表!$A:$A,0)),INDEX(单位卡分表!$B:$B,MATCH(K27,单位卡分表!$A:$A,0)),INDEX(技能卡分表!$B:$B,MATCH(K27,技能卡分表!$A:$A,0))) -> 功能饮料 牛红 | ... M28: =IF(ISNUMBER(MATCH(M27,单位卡分表!$A:$A,0)),INDEX(单位卡分表!$B:$B,MATCH(M27,单位卡分表!$A:$A,0)),INDEX(技能卡分表!$B:$B,MATCH(M27,技能卡分表!$A:$A,0))) -> 摩托 赤狸 塞琳娜 | N28: =IF(SUMPRODUCT(COUNTIF(D28:M28,D28:M28))>COLUMNS(D28:M28),"有重复","无重复") -> 无重复
A29: 2 | B29: 10000 | C29: 卡组ID | D29: 10021 | E29: 10030 | F29: 10080 | G29: 10036 | H29: 10035 | I29: 10037 | J29: 10012 | K29: 10031 | L29: 10026 | M29: 10020
B30: =IF(ISNUMBER(MATCH(B29,单位卡分表!$N:$N,0)),INDEX(单位卡分表!$B:$B,MATCH(B29,单位卡分表!$N:$N,0)),INDEX(技能卡分表!$B:$B,MATCH(B29,技能卡分表!$A:$A,0))) -> 传奇飞行员 舰长 | C30: 名字 | D30: =IF(ISNUMBER(MATCH(D29,单位卡分表!$A:$A,0)),INDEX(单位卡分表!$B:$B,MATCH(D29,单位卡分表!$A:$A,0)),INDEX(技能卡分表!$B:$B,MATCH(D29,技能卡分表!$A:$A,0))) -> 自动铅笔 追忆 | E30: =IF(ISNUMBER(MATCH(E29,单位卡分表!$A:$A,0)),INDEX(单位卡分表!$B:$B,MATCH(E29,单位卡分表!$A:$A,0)),INDEX(技能卡分表!$B:$B,MATCH(E29,技能卡分表!$A:$A,0))) -> 军鼓 震声 | F30: =IF(ISNUMBER(MATCH(F29,单位卡分表!$A:$A,0)),INDEX(单位卡分表!$B:$B,MATCH(F29,单位卡分表!$A:$A,0)),INDEX(技能卡分表!$B:$B,MATCH(F29,技能卡分表!$A:$A,0))) -> 安全帽 小橘 | G30: =IF(ISNUMBER(MATCH(G29,单位卡分表!$A:$A,0)),INDEX(单位卡分表!$B:$B,MATCH(G29,单位卡分表!$A:$A,0)),INDEX(技能卡分表!$B:$B,MATCH(G29,技能卡分表!$A:$A,0))) -> 纯净水 满满 | H30: =IF(ISNUMBER(MATCH(H29,单位卡分表!$A:$A,0)),INDEX(单位卡分表!$B:$B,MATCH(H29,单位卡分表!$A:$A,0)),INDEX(技能卡分表!$B:$B,MATCH(H29,技能卡分表!$A:$A,0))) -> 纯净水 浅浅 | I30: =IF(ISNUMBER(MATCH(I29,单位卡分表!$A:$A,0)),INDEX(单位卡分表!$B:$B,MATCH(I29,单位卡分表!$A:$A,0)),INDEX(技能卡分表!$B:$B,MATCH(I29,技能卡分表!$A:$A,0))) -> 红汽水 浅浅 | J30: =IF(ISNUMBER(MATCH(J29,单位卡分表!$A:$A,0)),INDEX(单位卡分表!$B:$B,MATCH(J29,单位卡分表!$A:$A,0)),INDEX(技能卡分表!$B:$B,MATCH(J29,技能卡分表!$A:$A,0))) -> 摩托 赤狸 塞琳娜 | K30: =IF(ISNUMBER(MATCH(K29,单位卡分表!$A:$A,0)),INDEX(单位卡分表!$B:$B,MATCH(K29,单位卡分表!$A:$A,0)),INDEX(技能卡分表!$B:$B,MATCH(K29,技能卡分表!$A:$A,0))) -> 注射器 针妮 佩妮（英文penny，联想小针） | ... M30: =IF(ISNUMBER(MATCH(M29,单位卡分表!$A:$A,0)),INDEX(单位卡分表!$B:$B,MATCH(M29,单位卡分表!$A:$A,0)),INDEX(技能卡分表!$B:$B,MATCH(M29,技能卡分表!$A:$A,0))) -> 时钟 晨曦 | N30: =IF(SUMPRODUCT(COUNTIF(D30:M30,D30:M30))>COLUMNS(D30:M30),"有重复","无重复") -> 无重复
A31: 2 | B31: 10002 | C31: 卡组ID | D31: 10033 | E31: 10060 | F31: 10051 | G31: 10036 | H31: 10035 | I31: 10037 | J31: 10079 | K31: 10044 | L31: 10026 | M31: 10020
B32: =IF(ISNUMBER(MATCH(B31,单位卡分表!$N:$N,0)),INDEX(单位卡分表!$B:$B,MATCH(B31,单位卡分表!$N:$N,0)),INDEX(技能卡分表!$B:$B,MATCH(B31,技能卡分表!$A:$A,0))) -> 最强盗贼王 露娜（Luna） | C32: 名字 | D32: =IF(ISNUMBER(MATCH(D31,单位卡分表!$A:$A,0)),INDEX(单位卡分表!$B:$B,MATCH(D31,单位卡分表!$A:$A,0)),INDEX(技能卡分表!$B:$B,MATCH(D31,技能卡分表!$A:$A,0))) -> 蜡烛 热泪 | E32: =IF(ISNUMBER(MATCH(E31,单位卡分表!$A:$A,0)),INDEX(单位卡分表!$B:$B,MATCH(E31,单位卡分表!$A:$A,0)),INDEX(技能卡分表!$B:$B,MATCH(E31,技能卡分表!$A:$A,0))) -> 爆米花 酥脆 | F32: =IF(ISNUMBER(MATCH(F31,单位卡分表!$A:$A,0)),INDEX(单位卡分表!$B:$B,MATCH(F31,单位卡分表!$A:$A,0)),INDEX(技能卡分表!$B:$B,MATCH(F31,技能卡分表!$A:$A,0))) -> 气球 飘舞 | G32: =IF(ISNUMBER(MATCH(G31,单位卡分表!$A:$A,0)),INDEX(单位卡分表!$B:$B,MATCH(G31,单位卡分表!$A:$A,0)),INDEX(技能卡分表!$B:$B,MATCH(G31,技能卡分表!$A:$A,0))) -> 纯净水 满满 | H32: =IF(ISNUMBER(MATCH(H31,单位卡分表!$A:$A,0)),INDEX(单位卡分表!$B:$B,MATCH(H31,单位卡分表!$A:$A,0)),INDEX(技能卡分表!$B:$B,MATCH(H31,技能卡分表!$A:$A,0))) -> 纯净水 浅浅 | I32: =IF(ISNUMBER(MATCH(I31,单位卡分表!$A:$A,0)),INDEX(单位卡分表!$B:$B,MATCH(I31,单位卡分表!$A:$A,0)),INDEX(技能卡分表!$B:$B,MATCH(I31,技能卡分表!$A:$A,0))) -> 红汽水 浅浅 | J32: =IF(ISNUMBER(MATCH(J31,单位卡分表!$A:$A,0)),INDEX(单位卡分表!$B:$B,MATCH(J31,单位卡分表!$A:$A,0)),INDEX(技能卡分表!$B:$B,MATCH(J31,技能卡分表!$A:$A,0))) -> 炸蛋 | K32: =IF(ISNUMBER(MATCH(K31,单位卡分表!$A:$A,0)),INDEX(单位卡分表!$B:$B,MATCH(K31,单位卡分表!$A:$A,0)),INDEX(技能卡分表!$B:$B,MATCH(K31,技能卡分表!$A:$A,0))) -> 煤油灯 流露 | ... M32: =IF(ISNUMBER(MATCH(M31,单位卡分表!$A:$A,0)),INDEX(单位卡分表!$B:$B,MATCH(M31,单位卡分表!$A:$A,0)),INDEX(技能卡分表!$B:$B,MATCH(M31,技能卡分表!$A:$A,0))) -> 时钟 晨曦 | N32: =IF(SUMPRODUCT(COUNTIF(D32:M32,D32:M32))>COLUMNS(D32:M32),"有重复","无重复") -> 无重复
A33: 2 | B33: 10002 | C33: 卡组ID | D33: 10015 | E33: 10017 | F33: 10050 | G33: 10036 | H33: 10035 | I33: 10037 | J33: 10011 | K33: 10012 | L33: 10026 | M33: 10020
B34: =IF(ISNUMBER(MATCH(B33,单位卡分表!$N:$N,0)),INDEX(单位卡分表!$B:$B,MATCH(B33,单位卡分表!$N:$N,0)),INDEX(技能卡分表!$B:$B,MATCH(B33,技能卡分表!$A:$A,0))) -> 最强盗贼王 露娜（Luna） | C34: 名字 | D34: =IF(ISNUMBER(MATCH(D33,单位卡分表!$A:$A,0)),INDEX(单位卡分表!$B:$B,MATCH(D33,单位卡分表!$A:$A,0)),INDEX(技能卡分表!$B:$B,MATCH(D33,技能卡分表!$A:$A,0))) -> 留声机 回音 玛利亚 | E34: =IF(ISNUMBER(MATCH(E33,单位卡分表!$A:$A,0)),INDEX(单位卡分表!$B:$B,MATCH(E33,单位卡分表!$A:$A,0)),INDEX(技能卡分表!$B:$B,MATCH(E33,技能卡分表!$A:$A,0))) -> 电池 欧姆 | F34: =IF(ISNUMBER(MATCH(F33,单位卡分表!$A:$A,0)),INDEX(单位卡分表!$B:$B,MATCH(F33,单位卡分表!$A:$A,0)),INDEX(技能卡分表!$B:$B,MATCH(F33,技能卡分表!$A:$A,0))) -> 茶包 小茗 | G34: =IF(ISNUMBER(MATCH(G33,单位卡分表!$A:$A,0)),INDEX(单位卡分表!$B:$B,MATCH(G33,单位卡分表!$A:$A,0)),INDEX(技能卡分表!$B:$B,MATCH(G33,技能卡分表!$A:$A,0))) -> 纯净水 满满 | H34: =IF(ISNUMBER(MATCH(H33,单位卡分表!$A:$A,0)),INDEX(单位卡分表!$B:$B,MATCH(H33,单位卡分表!$A:$A,0)),INDEX(技能卡分表!$B:$B,MATCH(H33,技能卡分表!$A:$A,0))) -> 纯净水 浅浅 | I34: =IF(ISNUMBER(MATCH(I33,单位卡分表!$A:$A,0)),INDEX(单位卡分表!$B:$B,MATCH(I33,单位卡分表!$A:$A,0)),INDEX(技能卡分表!$B:$B,MATCH(I33,技能卡分表!$A:$A,0))) -> 红汽水 浅浅 | J34: =IF(ISNUMBER(MATCH(J33,单位卡分表!$A:$A,0)),INDEX(单位卡分表!$B:$B,MATCH(J33,单位卡分表!$A:$A,0)),INDEX(技能卡分表!$B:$B,MATCH(J33,技能卡分表!$A:$A,0))) -> 纸巾 缠缠 | K34: =IF(ISNUMBER(MATCH(K33,单位卡分表!$A:$A,0)),INDEX(单位卡分表!$B:$B,MATCH(K33,单位卡分表!$A:$A,0)),INDEX(技能卡分表!$B:$B,MATCH(K33,技能卡分表!$A:$A,0))) -> 摩托 赤狸 塞琳娜 | ... M34: =IF(ISNUMBER(MATCH(M33,单位卡分表!$A:$A,0)),INDEX(单位卡分表!$B:$B,MATCH(M33,单位卡分表!$A:$A,0)),INDEX(技能卡分表!$B:$B,MATCH(M33,技能卡分表!$A:$A,0))) -> 时钟 晨曦 | N34: =IF(SUMPRODUCT(COUNTIF(D34:M34,D34:M34))>COLUMNS(D34:M34),"有重复","无重复") -> 无重复
A35: 2 | B35: 10003 | C35: 卡组ID | D35: 10021 | E35: 10062 | F35: 10016 | G35: 10036 | H35: 10035 | I35: 10037 | J35: 10077 | K35: 10013 | L35: 10026 | M35: 10020
B36: =IF(ISNUMBER(MATCH(B35,单位卡分表!$N:$N,0)),INDEX(单位卡分表!$B:$B,MATCH(B35,单位卡分表!$N:$N,0)),INDEX(技能卡分表!$B:$B,MATCH(B35,技能卡分表!$A:$A,0))) -> 轻灵跃影 乔艾塔（Joetta） | C36: 名字 | D36: =IF(ISNUMBER(MATCH(D35,单位卡分表!$A:$A,0)),INDEX(单位卡分表!$B:$B,MATCH(D35,单位卡分表!$A:$A,0)),INDEX(技能卡分表!$B:$B,MATCH(D35,技能卡分表!$A:$A,0))) -> 自动铅笔 追忆 | E36: =IF(ISNUMBER(MATCH(E35,单位卡分表!$A:$A,0)),INDEX(单位卡分表!$B:$B,MATCH(E35,单位卡分表!$A:$A,0)),INDEX(技能卡分表!$B:$B,MATCH(E35,技能卡分表!$A:$A,0))) -> 绿汽水 满满（复用） | F36: =IF(ISNUMBER(MATCH(F35,单位卡分表!$A:$A,0)),INDEX(单位卡分表!$B:$B,MATCH(F35,单位卡分表!$A:$A,0)),INDEX(技能卡分表!$B:$B,MATCH(F35,技能卡分表!$A:$A,0))) -> 电扇 彩虹 | G36: =IF(ISNUMBER(MATCH(G35,单位卡分表!$A:$A,0)),INDEX(单位卡分表!$B:$B,MATCH(G35,单位卡分表!$A:$A,0)),INDEX(技能卡分表!$B:$B,MATCH(G35,技能卡分表!$A:$A,0))) -> 纯净水 满满 | H36: =IF(ISNUMBER(MATCH(H35,单位卡分表!$A:$A,0)),INDEX(单位卡分表!$B:$B,MATCH(H35,单位卡分表!$A:$A,0)),INDEX(技能卡分表!$B:$B,MATCH(H35,技能卡分表!$A:$A,0))) -> 纯净水 浅浅 | I36: =IF(ISNUMBER(MATCH(I35,单位卡分表!$A:$A,0)),INDEX(单位卡分表!$B:$B,MATCH(I35,单位卡分表!$A:$A,0)),INDEX(技能卡分表!$B:$B,MATCH(I35,技能卡分表!$A:$A,0))) -> 红汽水 浅浅 | J36: =IF(ISNUMBER(MATCH(J35,单位卡分表!$A:$A,0)),INDEX(单位卡分表!$B:$B,MATCH(J35,单位卡分表!$A:$A,0)),INDEX(技能卡分表!$B:$B,MATCH(J35,技能卡分表!$A:$A,0))) -> 接力棒 传承 | K36: =IF(ISNUMBER(MATCH(K35,单位卡分表!$A:$A,0)),INDEX(单位卡分表!$B:$B,MATCH(K35,单位卡分表!$A:$A,0)),INDEX(技能卡分表!$B:$B,MATCH(K35,技能卡分表!$A:$A,0))) -> 雨伞 守心 布洛莉Brolly | ... M36: =IF(ISNUMBER(MATCH(M35,单位卡分表!$A:$A,0)),INDEX(单位卡分表!$B:$B,MATCH(M35,单位卡分表!$A:$A,0)),INDEX(技能卡分表!$B:$B,MATCH(M35,技能卡分表!$A:$A,0))) -> 时钟 晨曦 | N36: =IF(SUMPRODUCT(COUNTIF(D36:M36,D36:M36))>COLUMNS(D36:M36),"有重复","无重复") -> 无重复
A37: 2 | B37: 10004 | C37: 卡组ID | D37: 10073 | E37: 10070 | F37: 10071 | G37: 10069 | H37: 10068 | I37: 10066 | J37: 10028 | K37: 10026 | L37: 10014 | M37: 10013
B38: =IF(ISNUMBER(MATCH(B37,单位卡分表!$N:$N,0)),INDEX(单位卡分表!$B:$B,MATCH(B37,单位卡分表!$N:$N,0)),INDEX(技能卡分表!$B:$B,MATCH(B37,技能卡分表!$A:$A,0))) -> 致命拥抱 维纳斯（Venus） | C38: 名字 | D38: =IF(ISNUMBER(MATCH(D37,单位卡分表!$A:$A,0)),INDEX(单位卡分表!$B:$B,MATCH(D37,单位卡分表!$A:$A,0)),INDEX(技能卡分表!$B:$B,MATCH(D37,技能卡分表!$A:$A,0))) -> 储蓄罐 珠珠（复用） | E38: =IF(ISNUMBER(MATCH(E37,单位卡分表!$A:$A,0)),INDEX(单位卡分表!$B:$B,MATCH(E37,单位卡分表!$A:$A,0)),INDEX(技能卡分表!$B:$B,MATCH(E37,技能卡分表!$A:$A,0))) -> 捕蝇草 夹子 | F38: =IF(ISNUMBER(MATCH(F37,单位卡分表!$A:$A,0)),INDEX(单位卡分表!$B:$B,MATCH(F37,单位卡分表!$A:$A,0)),INDEX(技能卡分表!$B:$B,MATCH(F37,技能卡分表!$A:$A,0))) -> 鳄鱼 沼泽 | G38: =IF(ISNUMBER(MATCH(G37,单位卡分表!$A:$A,0)),INDEX(单位卡分表!$B:$B,MATCH(G37,单位卡分表!$A:$A,0)),INDEX(技能卡分表!$B:$B,MATCH(G37,技能卡分表!$A:$A,0))) -> 绷带 包扎 | H38: =IF(ISNUMBER(MATCH(H37,单位卡分表!$A:$A,0)),INDEX(单位卡分表!$B:$B,MATCH(H37,单位卡分表!$A:$A,0)),INDEX(技能卡分表!$B:$B,MATCH(H37,技能卡分表!$A:$A,0))) -> 刀鞘 护刃 | I38: =IF(ISNUMBER(MATCH(I37,单位卡分表!$A:$A,0)),INDEX(单位卡分表!$B:$B,MATCH(I37,单位卡分表!$A:$A,0)),INDEX(技能卡分表!$B:$B,MATCH(I37,技能卡分表!$A:$A,0))) -> 乌龟 壳壳 | J38: =IF(ISNUMBER(MATCH(J37,单位卡分表!$A:$A,0)),INDEX(单位卡分表!$B:$B,MATCH(J37,单位卡分表!$A:$A,0)),INDEX(技能卡分表!$B:$B,MATCH(J37,技能卡分表!$A:$A,0))) -> 羽毛球 拉丽（英文就rally连续得分的意思） | K38: =IF(ISNUMBER(MATCH(K37,单位卡分表!$A:$A,0)),INDEX(单位卡分表!$B:$B,MATCH(K37,单位卡分表!$A:$A,0)),INDEX(技能卡分表!$B:$B,MATCH(K37,技能卡分表!$A:$A,0))) -> 功能饮料 牛红 | ... M38: =IF(ISNUMBER(MATCH(M37,单位卡分表!$A:$A,0)),INDEX(单位卡分表!$B:$B,MATCH(M37,单位卡分表!$A:$A,0)),INDEX(技能卡分表!$B:$B,MATCH(M37,技能卡分表!$A:$A,0))) -> 雨伞 守心 布洛莉Brolly | N38: =IF(SUMPRODUCT(COUNTIF(D38:M38,D38:M38))>COLUMNS(D38:M38),"有重复","无重复") -> 无重复
A39: 2 | B39: 10004 | C39: 卡组ID | D39: 10072 | E39: 10073 | F39: 10036 | G39: 10075 | H39: 10039 | I39: 10066 | J39: 10028 | K39: 10026 | L39: 10020 | M39: 10012
B40: =IF(ISNUMBER(MATCH(B39,单位卡分表!$N:$N,0)),INDEX(单位卡分表!$B:$B,MATCH(B39,单位卡分表!$N:$N,0)),INDEX(技能卡分表!$B:$B,MATCH(B39,技能卡分表!$A:$A,0))) -> 致命拥抱 维纳斯（Venus） | C40: 名字 | D40: =IF(ISNUMBER(MATCH(D39,单位卡分表!$A:$A,0)),INDEX(单位卡分表!$B:$B,MATCH(D39,单位卡分表!$A:$A,0)),INDEX(技能卡分表!$B:$B,MATCH(D39,技能卡分表!$A:$A,0))) -> 鲨鱼 利齿 | E40: =IF(ISNUMBER(MATCH(E39,单位卡分表!$A:$A,0)),INDEX(单位卡分表!$B:$B,MATCH(E39,单位卡分表!$A:$A,0)),INDEX(技能卡分表!$B:$B,MATCH(E39,技能卡分表!$A:$A,0))) -> 储蓄罐 珠珠（复用） | F40: =IF(ISNUMBER(MATCH(F39,单位卡分表!$A:$A,0)),INDEX(单位卡分表!$B:$B,MATCH(F39,单位卡分表!$A:$A,0)),INDEX(技能卡分表!$B:$B,MATCH(F39,技能卡分表!$A:$A,0))) -> 纯净水 满满 | G40: =IF(ISNUMBER(MATCH(G39,单位卡分表!$A:$A,0)),INDEX(单位卡分表!$B:$B,MATCH(G39,单位卡分表!$A:$A,0)),INDEX(技能卡分表!$B:$B,MATCH(G39,技能卡分表!$A:$A,0))) -> 菠菜罐头 大力 | H40: =IF(ISNUMBER(MATCH(H39,单位卡分表!$A:$A,0)),INDEX(单位卡分表!$B:$B,MATCH(H39,单位卡分表!$A:$A,0)),INDEX(技能卡分表!$B:$B,MATCH(H39,技能卡分表!$A:$A,0))) -> 绿汽水 浅浅 | I40: =IF(ISNUMBER(MATCH(I39,单位卡分表!$A:$A,0)),INDEX(单位卡分表!$B:$B,MATCH(I39,单位卡分表!$A:$A,0)),INDEX(技能卡分表!$B:$B,MATCH(I39,技能卡分表!$A:$A,0))) -> 乌龟 壳壳 | J40: =IF(ISNUMBER(MATCH(J39,单位卡分表!$A:$A,0)),INDEX(单位卡分表!$B:$B,MATCH(J39,单位卡分表!$A:$A,0)),INDEX(技能卡分表!$B:$B,MATCH(J39,技能卡分表!$A:$A,0))) -> 羽毛球 拉丽（英文就rally连续得分的意思） | K40: =IF(ISNUMBER(MATCH(K39,单位卡分表!$A:$A,0)),INDEX(单位卡分表!$B:$B,MATCH(K39,单位卡分表!$A:$A,0)),INDEX(技能卡分表!$B:$B,MATCH(K39,技能卡分表!$A:$A,0))) -> 功能饮料 牛红 | ... M40: =IF(ISNUMBER(MATCH(M39,单位卡分表!$A:$A,0)),INDEX(单位卡分表!$B:$B,MATCH(M39,单位卡分表!$A:$A,0)),INDEX(技能卡分表!$B:$B,MATCH(M39,技能卡分表!$A:$A,0))) -> 摩托 赤狸 塞琳娜 | N40: =IF(SUMPRODUCT(COUNTIF(D40:M40,D40:M40))>COLUMNS(D40:M40),"有重复","无重复") -> 无重复
A41: 3 | B41: 10000 | C41: 卡组ID | D41: 10021 | E41: 10030 | F41: 10080 | G41: 10036 | H41: 10035 | I41: 10037 | J41: 10012 | K41: 10031 | L41: 10026 | M41: 10020
B42: =IF(ISNUMBER(MATCH(B41,单位卡分表!$N:$N,0)),INDEX(单位卡分表!$B:$B,MATCH(B41,单位卡分表!$N:$N,0)),INDEX(技能卡分表!$B:$B,MATCH(B41,技能卡分表!$A:$A,0))) -> 传奇飞行员 舰长 | C42: 名字 | D42: =IF(ISNUMBER(MATCH(D41,单位卡分表!$A:$A,0)),INDEX(单位卡分表!$B:$B,MATCH(D41,单位卡分表!$A:$A,0)),INDEX(技能卡分表!$B:$B,MATCH(D41,技能卡分表!$A:$A,0))) -> 自动铅笔 追忆 | E42: =IF(ISNUMBER(MATCH(E41,单位卡分表!$A:$A,0)),INDEX(单位卡分表!$B:$B,MATCH(E41,单位卡分表!$A:$A,0)),INDEX(技能卡分表!$B:$B,MATCH(E41,技能卡分表!$A:$A,0))) -> 军鼓 震声 | F42: =IF(ISNUMBER(MATCH(F41,单位卡分表!$A:$A,0)),INDEX(单位卡分表!$B:$B,MATCH(F41,单位卡分表!$A:$A,0)),INDEX(技能卡分表!$B:$B,MATCH(F41,技能卡分表!$A:$A,0))) -> 安全帽 小橘 | G42: =IF(ISNUMBER(MATCH(G41,单位卡分表!$A:$A,0)),INDEX(单位卡分表!$B:$B,MATCH(G41,单位卡分表!$A:$A,0)),INDEX(技能卡分表!$B:$B,MATCH(G41,技能卡分表!$A:$A,0))) -> 纯净水 满满 | H42: =IF(ISNUMBER(MATCH(H41,单位卡分表!$A:$A,0)),INDEX(单位卡分表!$B:$B,MATCH(H41,单位卡分表!$A:$A,0)),INDEX(技能卡分表!$B:$B,MATCH(H41,技能卡分表!$A:$A,0))) -> 纯净水 浅浅 | I42: =IF(ISNUMBER(MATCH(I41,单位卡分表!$A:$A,0)),INDEX(单位卡分表!$B:$B,MATCH(I41,单位卡分表!$A:$A,0)),INDEX(技能卡分表!$B:$B,MATCH(I41,技能卡分表!$A:$A,0))) -> 红汽水 浅浅 | J42: =IF(ISNUMBER(MATCH(J41,单位卡分表!$A:$A,0)),INDEX(单位卡分表!$B:$B,MATCH(J41,单位卡分表!$A:$A,0)),INDEX(技能卡分表!$B:$B,MATCH(J41,技能卡分表!$A:$A,0))) -> 摩托 赤狸 塞琳娜 | K42: =IF(ISNUMBER(MATCH(K41,单位卡分表!$A:$A,0)),INDEX(单位卡分表!$B:$B,MATCH(K41,单位卡分表!$A:$A,0)),INDEX(技能卡分表!$B:$B,MATCH(K41,技能卡分表!$A:$A,0))) -> 注射器 针妮 佩妮（英文penny，联想小针） | ... M42: =IF(ISNUMBER(MATCH(M41,单位卡分表!$A:$A,0)),INDEX(单位卡分表!$B:$B,MATCH(M41,单位卡分表!$A:$A,0)),INDEX(技能卡分表!$B:$B,MATCH(M41,技能卡分表!$A:$A,0))) -> 时钟 晨曦 | N42: =IF(SUMPRODUCT(COUNTIF(D42:M42,D42:M42))>COLUMNS(D42:M42),"有重复","无重复") -> 无重复
A43: 3 | B43: 10002 | C43: 卡组ID | D43: 10033 | E43: 10060 | F43: 10051 | G43: 10036 | H43: 10035 | I43: 10037 | J43: 10079 | K43: 10044 | L43: 10026 | M43: 10020
B44: =IF(ISNUMBER(MATCH(B43,单位卡分表!$N:$N,0)),INDEX(单位卡分表!$B:$B,MATCH(B43,单位卡分表!$N:$N,0)),INDEX(技能卡分表!$B:$B,MATCH(B43,技能卡分表!$A:$A,0))) -> 最强盗贼王 露娜（Luna） | C44: 名字 | D44: =IF(ISNUMBER(MATCH(D43,单位卡分表!$A:$A,0)),INDEX(单位卡分表!$B:$B,MATCH(D43,单位卡分表!$A:$A,0)),INDEX(技能卡分表!$B:$B,MATCH(D43,技能卡分表!$A:$A,0))) -> 蜡烛 热泪 | E44: =IF(ISNUMBER(MATCH(E43,单位卡分表!$A:$A,0)),INDEX(单位卡分表!$B:$B,MATCH(E43,单位卡分表!$A:$A,0)),INDEX(技能卡分表!$B:$B,MATCH(E43,技能卡分表!$A:$A,0))) -> 爆米花 酥脆 | F44: =IF(ISNUMBER(MATCH(F43,单位卡分表!$A:$A,0)),INDEX(单位卡分表!$B:$B,MATCH(F43,单位卡分表!$A:$A,0)),INDEX(技能卡分表!$B:$B,MATCH(F43,技能卡分表!$A:$A,0))) -> 气球 飘舞 | G44: =IF(ISNUMBER(MATCH(G43,单位卡分表!$A:$A,0)),INDEX(单位卡分表!$B:$B,MATCH(G43,单位卡分表!$A:$A,0)),INDEX(技能卡分表!$B:$B,MATCH(G43,技能卡分表!$A:$A,0))) -> 纯净水 满满 | H44: =IF(ISNUMBER(MATCH(H43,单位卡分表!$A:$A,0)),INDEX(单位卡分表!$B:$B,MATCH(H43,单位卡分表!$A:$A,0)),INDEX(技能卡分表!$B:$B,MATCH(H43,技能卡分表!$A:$A,0))) -> 纯净水 浅浅 | I44: =IF(ISNUMBER(MATCH(I43,单位卡分表!$A:$A,0)),INDEX(单位卡分表!$B:$B,MATCH(I43,单位卡分表!$A:$A,0)),INDEX(技能卡分表!$B:$B,MATCH(I43,技能卡分表!$A:$A,0))) -> 红汽水 浅浅 | J44: =IF(ISNUMBER(MATCH(J43,单位卡分表!$A:$A,0)),INDEX(单位卡分表!$B:$B,MATCH(J43,单位卡分表!$A:$A,0)),INDEX(技能卡分表!$B:$B,MATCH(J43,技能卡分表!$A:$A,0))) -> 炸蛋 | K44: =IF(ISNUMBER(MATCH(K43,单位卡分表!$A:$A,0)),INDEX(单位卡分表!$B:$B,MATCH(K43,单位卡分表!$A:$A,0)),INDEX(技能卡分表!$B:$B,MATCH(K43,技能卡分表!$A:$A,0))) -> 煤油灯 流露 | ... M44: =IF(ISNUMBER(MATCH(M43,单位卡分表!$A:$A,0)),INDEX(单位卡分表!$B:$B,MATCH(M43,单位卡分表!$A:$A,0)),INDEX(技能卡分表!$B:$B,MATCH(M43,技能卡分表!$A:$A,0))) -> 时钟 晨曦 | N44: =IF(SUMPRODUCT(COUNTIF(D44:M44,D44:M44))>COLUMNS(D44:M44),"有重复","无重复") -> 无重复
A45: 3 | B45: 10003 | C45: 卡组ID | D45: 10021 | E45: 10062 | F45: 10016 | G45: 10036 | H45: 10035 | I45: 10037 | J45: 10077 | K45: 10013 | L45: 10026 | M45: 10020
B46: =IF(ISNUMBER(MATCH(B45,单位卡分表!$N:$N,0)),INDEX(单位卡分表!$B:$B,MATCH(B45,单位卡分表!$N:$N,0)),INDEX(技能卡分表!$B:$B,MATCH(B45,技能卡分表!$A:$A,0))) -> 轻灵跃影 乔艾塔（Joetta） | C46: 名字 | D46: =IF(ISNUMBER(MATCH(D45,单位卡分表!$A:$A,0)),INDEX(单位卡分表!$B:$B,MATCH(D45,单位卡分表!$A:$A,0)),INDEX(技能卡分表!$B:$B,MATCH(D45,技能卡分表!$A:$A,0))) -> 自动铅笔 追忆 | E46: =IF(ISNUMBER(MATCH(E45,单位卡分表!$A:$A,0)),INDEX(单位卡分表!$B:$B,MATCH(E45,单位卡分表!$A:$A,0)),INDEX(技能卡分表!$B:$B,MATCH(E45,技能卡分表!$A:$A,0))) -> 绿汽水 满满（复用） | F46: =IF(ISNUMBER(MATCH(F45,单位卡分表!$A:$A,0)),INDEX(单位卡分表!$B:$B,MATCH(F45,单位卡分表!$A:$A,0)),INDEX(技能卡分表!$B:$B,MATCH(F45,技能卡分表!$A:$A,0))) -> 电扇 彩虹 | G46: =IF(ISNUMBER(MATCH(G45,单位卡分表!$A:$A,0)),INDEX(单位卡分表!$B:$B,MATCH(G45,单位卡分表!$A:$A,0)),INDEX(技能卡分表!$B:$B,MATCH(G45,技能卡分表!$A:$A,0))) -> 纯净水 满满 | H46: =IF(ISNUMBER(MATCH(H45,单位卡分表!$A:$A,0)),INDEX(单位卡分表!$B:$B,MATCH(H45,单位卡分表!$A:$A,0)),INDEX(技能卡分表!$B:$B,MATCH(H45,技能卡分表!$A:$A,0))) -> 纯净水 浅浅 | I46: =IF(ISNUMBER(MATCH(I45,单位卡分表!$A:$A,0)),INDEX(单位卡分表!$B:$B,MATCH(I45,单位卡分表!$A:$A,0)),INDEX(技能卡分表!$B:$B,MATCH(I45,技能卡分表!$A:$A,0))) -> 红汽水 浅浅 | J46: =IF(ISNUMBER(MATCH(J45,单位卡分表!$A:$A,0)),INDEX(单位卡分表!$B:$B,MATCH(J45,单位卡分表!$A:$A,0)),INDEX(技能卡分表!$B:$B,MATCH(J45,技能卡分表!$A:$A,0))) -> 接力棒 传承 | K46: =IF(ISNUMBER(MATCH(K45,单位卡分表!$A:$A,0)),INDEX(单位卡分表!$B:$B,MATCH(K45,单位卡分表!$A:$A,0)),INDEX(技能卡分表!$B:$B,MATCH(K45,技能卡分表!$A:$A,0))) -> 雨伞 守心 布洛莉Brolly | ... M46: =IF(ISNUMBER(MATCH(M45,单位卡分表!$A:$A,0)),INDEX(单位卡分表!$B:$B,MATCH(M45,单位卡分表!$A:$A,0)),INDEX(技能卡分表!$B:$B,MATCH(M45,技能卡分表!$A:$A,0))) -> 时钟 晨曦 | N46: =IF(SUMPRODUCT(COUNTIF(D46:M46,D46:M46))>COLUMNS(D46:M46),"有重复","无重复") -> 无重复
A47: 3 | B47: 10004 | C47: 卡组ID | D47: 10072 | E47: 10073 | F47: 10036 | G47: 10075 | H47: 10039 | I47: 10066 | J47: 10028 | K47: 10026 | L47: 10020 | M47: 10012
B48: =IF(ISNUMBER(MATCH(B47,单位卡分表!$N:$N,0)),INDEX(单位卡分表!$B:$B,MATCH(B47,单位卡分表!$N:$N,0)),INDEX(技能卡分表!$B:$B,MATCH(B47,技能卡分表!$A:$A,0))) -> 致命拥抱 维纳斯（Venus） | C48: 名字 | D48: =IF(ISNUMBER(MATCH(D47,单位卡分表!$A:$A,0)),INDEX(单位卡分表!$B:$B,MATCH(D47,单位卡分表!$A:$A,0)),INDEX(技能卡分表!$B:$B,MATCH(D47,技能卡分表!$A:$A,0))) -> 鲨鱼 利齿 | E48: =IF(ISNUMBER(MATCH(E47,单位卡分表!$A:$A,0)),INDEX(单位卡分表!$B:$B,MATCH(E47,单位卡分表!$A:$A,0)),INDEX(技能卡分表!$B:$B,MATCH(E47,技能卡分表!$A:$A,0))) -> 储蓄罐 珠珠（复用） | F48: =IF(ISNUMBER(MATCH(F47,单位卡分表!$A:$A,0)),INDEX(单位卡分表!$B:$B,MATCH(F47,单位卡分表!$A:$A,0)),INDEX(技能卡分表!$B:$B,MATCH(F47,技能卡分表!$A:$A,0))) -> 纯净水 满满 | G48: =IF(ISNUMBER(MATCH(G47,单位卡分表!$A:$A,0)),INDEX(单位卡分表!$B:$B,MATCH(G47,单位卡分表!$A:$A,0)),INDEX(技能卡分表!$B:$B,MATCH(G47,技能卡分表!$A:$A,0))) -> 菠菜罐头 大力 | H48: =IF(ISNUMBER(MATCH(H47,单位卡分表!$A:$A,0)),INDEX(单位卡分表!$B:$B,MATCH(H47,单位卡分表!$A:$A,0)),INDEX(技能卡分表!$B:$B,MATCH(H47,技能卡分表!$A:$A,0))) -> 绿汽水 浅浅 | I48: =IF(ISNUMBER(MATCH(I47,单位卡分表!$A:$A,0)),INDEX(单位卡分表!$B:$B,MATCH(I47,单位卡分表!$A:$A,0)),INDEX(技能卡分表!$B:$B,MATCH(I47,技能卡分表!$A:$A,0))) -> 乌龟 壳壳 | J48: =IF(ISNUMBER(MATCH(J47,单位卡分表!$A:$A,0)),INDEX(单位卡分表!$B:$B,MATCH(J47,单位卡分表!$A:$A,0)),INDEX(技能卡分表!$B:$B,MATCH(J47,技能卡分表!$A:$A,0))) -> 羽毛球 拉丽（英文就rally连续得分的意思） | K48: =IF(ISNUMBER(MATCH(K47,单位卡分表!$A:$A,0)),INDEX(单位卡分表!$B:$B,MATCH(K47,单位卡分表!$A:$A,0)),INDEX(技能卡分表!$B:$B,MATCH(K47,技能卡分表!$A:$A,0))) -> 功能饮料 牛红 | ... M48: =IF(ISNUMBER(MATCH(M47,单位卡分表!$A:$A,0)),INDEX(单位卡分表!$B:$B,MATCH(M47,单位卡分表!$A:$A,0)),INDEX(技能卡分表!$B:$B,MATCH(M47,技能卡分表!$A:$A,0))) -> 摩托 赤狸 塞琳娜 | N48: =IF(SUMPRODUCT(COUNTIF(D48:M48,D48:M48))>COLUMNS(D48:M48),"有重复","无重复") -> 无重复
A49: 3 | B49: 10006 | C49: 卡组ID
B50: =IF(ISNUMBER(MATCH(B49,单位卡分表!$N:$N,0)),INDEX(单位卡分表!$B:$B,MATCH(B49,单位卡分表!$N:$N,0)),INDEX(技能卡分表!$B:$B,MATCH(B49,技能卡分表!$A:$A,0))) -> 群蜂之母 梅丽莎（Melissa） | C50: 名字 | D50: =IF(ISNUMBER(MATCH(D49,单位卡分表!$A:$A,0)),INDEX(单位卡分表!$B:$B,MATCH(D49,单位卡分表!$A:$A,0)),INDEX(技能卡分表!$B:$B,MATCH(D49,技能卡分表!$A:$A,0))) -> #N/A | E50: =IF(ISNUMBER(MATCH(E49,单位卡分表!$A:$A,0)),INDEX(单位卡分表!$B:$B,MATCH(E49,单位卡分表!$A:$A,0)),INDEX(技能卡分表!$B:$B,MATCH(E49,技能卡分表!$A:$A,0))) -> #N/A | F50: =IF(ISNUMBER(MATCH(F49,单位卡分表!$A:$A,0)),INDEX(单位卡分表!$B:$B,MATCH(F49,单位卡分表!$A:$A,0)),INDEX(技能卡分表!$B:$B,MATCH(F49,技能卡分表!$A:$A,0))) -> #N/A | G50: =IF(ISNUMBER(MATCH(G49,单位卡分表!$A:$A,0)),INDEX(单位卡分表!$B:$B,MATCH(G49,单位卡分表!$A:$A,0)),INDEX(技能卡分表!$B:$B,MATCH(G49,技能卡分表!$A:$A,0))) -> #N/A | H50: =IF(ISNUMBER(MATCH(H49,单位卡分表!$A:$A,0)),INDEX(单位卡分表!$B:$B,MATCH(H49,单位卡分表!$A:$A,0)),INDEX(技能卡分表!$B:$B,MATCH(H49,技能卡分表!$A:$A,0))) -> #N/A | I50: =IF(ISNUMBER(MATCH(I49,单位卡分表!$A:$A,0)),INDEX(单位卡分表!$B:$B,MATCH(I49,单位卡分表!$A:$A,0)),INDEX(技能卡分表!$B:$B,MATCH(I49,技能卡分表!$A:$A,0))) -> #N/A | J50: =IF(ISNUMBER(MATCH(J49,单位卡分表!$A:$A,0)),INDEX(单位卡分表!$B:$B,MATCH(J49,单位卡分表!$A:$A,0)),INDEX(技能卡分表!$B:$B,MATCH(J49,技能卡分表!$A:$A,0))) -> #N/A | K50: =IF(ISNUMBER(MATCH(K49,单位卡分表!$A:$A,0)),INDEX(单位卡分表!$B:$B,MATCH(K49,单位卡分表!$A:$A,0)),INDEX(技能卡分表!$B:$B,MATCH(K49,技能卡分表!$A:$A,0))) -> #N/A | ... M50: =IF(ISNUMBER(MATCH(M49,单位卡分表!$A:$A,0)),INDEX(单位卡分表!$B:$B,MATCH(M49,单位卡分表!$A:$A,0)),INDEX(技能卡分表!$B:$B,MATCH(M49,技能卡分表!$A:$A,0))) -> #N/A | N50: =IF(SUMPRODUCT(COUNTIF(D50:M50,D50:M50))>COLUMNS(D50:M50),"有重复","无重复") -> 有重复
A51: 3 | B51: 10006 | C51: 卡组ID
B52: =IF(ISNUMBER(MATCH(B51,单位卡分表!$N:$N,0)),INDEX(单位卡分表!$B:$B,MATCH(B51,单位卡分表!$N:$N,0)),INDEX(技能卡分表!$B:$B,MATCH(B51,技能卡分表!$A:$A,0))) -> 群蜂之母 梅丽莎（Melissa） | C52: 名字 | D52: =IF(ISNUMBER(MATCH(D51,单位卡分表!$A:$A,0)),INDEX(单位卡分表!$B:$B,MATCH(D51,单位卡分表!$A:$A,0)),INDEX(技能卡分表!$B:$B,MATCH(D51,技能卡分表!$A:$A,0))) -> #N/A | E52: =IF(ISNUMBER(MATCH(E51,单位卡分表!$A:$A,0)),INDEX(单位卡分表!$B:$B,MATCH(E51,单位卡分表!$A:$A,0)),INDEX(技能卡分表!$B:$B,MATCH(E51,技能卡分表!$A:$A,0))) -> #N/A | F52: =IF(ISNUMBER(MATCH(F51,单位卡分表!$A:$A,0)),INDEX(单位卡分表!$B:$B,MATCH(F51,单位卡分表!$A:$A,0)),INDEX(技能卡分表!$B:$B,MATCH(F51,技能卡分表!$A:$A,0))) -> #N/A | G52: =IF(ISNUMBER(MATCH(G51,单位卡分表!$A:$A,0)),INDEX(单位卡分表!$B:$B,MATCH(G51,单位卡分表!$A:$A,0)),INDEX(技能卡分表!$B:$B,MATCH(G51,技能卡分表!$A:$A,0))) -> #N/A | H52: =IF(ISNUMBER(MATCH(H51,单位卡分表!$A:$A,0)),INDEX(单位卡分表!$B:$B,MATCH(H51,单位卡分表!$A:$A,0)),INDEX(技能卡分表!$B:$B,MATCH(H51,技能卡分表!$A:$A,0))) -> #N/A | I52: =IF(ISNUMBER(MATCH(I51,单位卡分表!$A:$A,0)),INDEX(单位卡分表!$B:$B,MATCH(I51,单位卡分表!$A:$A,0)),INDEX(技能卡分表!$B:$B,MATCH(I51,技能卡分表!$A:$A,0))) -> #N/A | J52: =IF(ISNUMBER(MATCH(J51,单位卡分表!$A:$A,0)),INDEX(单位卡分表!$B:$B,MATCH(J51,单位卡分表!$A:$A,0)),INDEX(技能卡分表!$B:$B,MATCH(J51,技能卡分表!$A:$A,0))) -> #N/A | K52: =IF(ISNUMBER(MATCH(K51,单位卡分表!$A:$A,0)),INDEX(单位卡分表!$B:$B,MATCH(K51,单位卡分表!$A:$A,0)),INDEX(技能卡分表!$B:$B,MATCH(K51,技能卡分表!$A:$A,0))) -> #N/A | ... M52: =IF(ISNUMBER(MATCH(M51,单位卡分表!$A:$A,0)),INDEX(单位卡分表!$B:$B,MATCH(M51,单位卡分表!$A:$A,0)),INDEX(技能卡分表!$B:$B,MATCH(M51,技能卡分表!$A:$A,0))) -> #N/A | N52: =IF(SUMPRODUCT(COUNTIF(D52:M52,D52:M52))>COLUMNS(D52:M52),"有重复","无重复") -> 有重复
A53: 4 | B53: 10000 | C53: 卡组ID
C54: 名字 | D54: =IF(ISNUMBER(MATCH(D53,单位卡分表!$A:$A,0)),INDEX(单位卡分表!$B:$B,MATCH(D53,单位卡分表!$A:$A,0)),INDEX(技能卡分表!$B:$B,MATCH(D53,技能卡分表!$A:$A,0))) -> #N/A | E54: =IF(ISNUMBER(MATCH(E53,单位卡分表!$A:$A,0)),INDEX(单位卡分表!$B:$B,MATCH(E53,单位卡分表!$A:$A,0)),INDEX(技能卡分表!$B:$B,MATCH(E53,技能卡分表!$A:$A,0))) -> #N/A | F54: =IF(ISNUMBER(MATCH(F53,单位卡分表!$A:$A,0)),INDEX(单位卡分表!$B:$B,MATCH(F53,单位卡分表!$A:$A,0)),INDEX(技能卡分表!$B:$B,MATCH(F53,技能卡分表!$A:$A,0))) -> #N/A | G54: =IF(ISNUMBER(MATCH(G53,单位卡分表!$A:$A,0)),INDEX(单位卡分表!$B:$B,MATCH(G53,单位卡分表!$A:$A,0)),INDEX(技能卡分表!$B:$B,MATCH(G53,技能卡分表!$A:$A,0))) -> #N/A | H54: =IF(ISNUMBER(MATCH(H53,单位卡分表!$A:$A,0)),INDEX(单位卡分表!$B:$B,MATCH(H53,单位卡分表!$A:$A,0)),INDEX(技能卡分表!$B:$B,MATCH(H53,技能卡分表!$A:$A,0))) -> #N/A | I54: =IF(ISNUMBER(MATCH(I53,单位卡分表!$A:$A,0)),INDEX(单位卡分表!$B:$B,MATCH(I53,单位卡分表!$A:$A,0)),INDEX(技能卡分表!$B:$B,MATCH(I53,技能卡分表!$A:$A,0))) -> #N/A | J54: =IF(ISNUMBER(MATCH(J53,单位卡分表!$A:$A,0)),INDEX(单位卡分表!$B:$B,MATCH(J53,单位卡分表!$A:$A,0)),INDEX(技能卡分表!$B:$B,MATCH(J53,技能卡分表!$A:$A,0))) -> #N/A | K54: =IF(ISNUMBER(MATCH(K53,单位卡分表!$A:$A,0)),INDEX(单位卡分表!$B:$B,MATCH(K53,单位卡分表!$A:$A,0)),INDEX(技能卡分表!$B:$B,MATCH(K53,技能卡分表!$A:$A,0))) -> #N/A | ... M54: =IF(ISNUMBER(MATCH(M53,单位卡分表!$A:$A,0)),INDEX(单位卡分表!$B:$B,MATCH(M53,单位卡分表!$A:$A,0)),INDEX(技能卡分表!$B:$B,MATCH(M53,技能卡分表!$A:$A,0))) -> #N/A | N54: =IF(SUMPRODUCT(COUNTIF(D54:M54,D54:M54))>COLUMNS(D54:M54),"有重复","无重复") -> 有重复
A55: 4 | B55: 10002 | C55: 卡组ID
C56: 名字 | D56: =IF(ISNUMBER(MATCH(D55,单位卡分表!$A:$A,0)),INDEX(单位卡分表!$B:$B,MATCH(D55,单位卡分表!$A:$A,0)),INDEX(技能卡分表!$B:$B,MATCH(D55,技能卡分表!$A:$A,0))) -> #N/A | E56: =IF(ISNUMBER(MATCH(E55,单位卡分表!$A:$A,0)),INDEX(单位卡分表!$B:$B,MATCH(E55,单位卡分表!$A:$A,0)),INDEX(技能卡分表!$B:$B,MATCH(E55,技能卡分表!$A:$A,0))) -> #N/A | F56: =IF(ISNUMBER(MATCH(F55,单位卡分表!$A:$A,0)),INDEX(单位卡分表!$B:$B,MATCH(F55,单位卡分表!$A:$A,0)),INDEX(技能卡分表!$B:$B,MATCH(F55,技能卡分表!$A:$A,0))) -> #N/A | G56: =IF(ISNUMBER(MATCH(G55,单位卡分表!$A:$A,0)),INDEX(单位卡分表!$B:$B,MATCH(G55,单位卡分表!$A:$A,0)),INDEX(技能卡分表!$B:$B,MATCH(G55,技能卡分表!$A:$A,0))) -> #N/A | H56: =IF(ISNUMBER(MATCH(H55,单位卡分表!$A:$A,0)),INDEX(单位卡分表!$B:$B,MATCH(H55,单位卡分表!$A:$A,0)),INDEX(技能卡分表!$B:$B,MATCH(H55,技能卡分表!$A:$A,0))) -> #N/A | I56: =IF(ISNUMBER(MATCH(I55,单位卡分表!$A:$A,0)),INDEX(单位卡分表!$B:$B,MATCH(I55,单位卡分表!$A:$A,0)),INDEX(技能卡分表!$B:$B,MATCH(I55,技能卡分表!$A:$A,0))) -> #N/A | J56: =IF(ISNUMBER(MATCH(J55,单位卡分表!$A:$A,0)),INDEX(单位卡分表!$B:$B,MATCH(J55,单位卡分表!$A:$A,0)),INDEX(技能卡分表!$B:$B,MATCH(J55,技能卡分表!$A:$A,0))) -> #N/A | K56: =IF(ISNUMBER(MATCH(K55,单位卡分表!$A:$A,0)),INDEX(单位卡分表!$B:$B,MATCH(K55,单位卡分表!$A:$A,0)),INDEX(技能卡分表!$B:$B,MATCH(K55,技能卡分表!$A:$A,0))) -> #N/A | ... M56: =IF(ISNUMBER(MATCH(M55,单位卡分表!$A:$A,0)),INDEX(单位卡分表!$B:$B,MATCH(M55,单位卡分表!$A:$A,0)),INDEX(技能卡分表!$B:$B,MATCH(M55,技能卡分表!$A:$A,0))) -> #N/A | N56: =IF(SUMPRODUCT(COUNTIF(D56:M56,D56:M56))>COLUMNS(D56:M56),"有重复","无重复") -> 有重复
A57: 4 | B57: 10003 | C57: 卡组ID
C58: 名字 | D58: =IF(ISNUMBER(MATCH(D57,单位卡分表!$A:$A,0)),INDEX(单位卡分表!$B:$B,MATCH(D57,单位卡分表!$A:$A,0)),INDEX(技能卡分表!$B:$B,MATCH(D57,技能卡分表!$A:$A,0))) -> #N/A | E58: =IF(ISNUMBER(MATCH(E57,单位卡分表!$A:$A,0)),INDEX(单位卡分表!$B:$B,MATCH(E57,单位卡分表!$A:$A,0)),INDEX(技能卡分表!$B:$B,MATCH(E57,技能卡分表!$A:$A,0))) -> #N/A | F58: =IF(ISNUMBER(MATCH(F57,单位卡分表!$A:$A,0)),INDEX(单位卡分表!$B:$B,MATCH(F57,单位卡分表!$A:$A,0)),INDEX(技能卡分表!$B:$B,MATCH(F57,技能卡分表!$A:$A,0))) -> #N/A | G58: =IF(ISNUMBER(MATCH(G57,单位卡分表!$A:$A,0)),INDEX(单位卡分表!$B:$B,MATCH(G57,单位卡分表!$A:$A,0)),INDEX(技能卡分表!$B:$B,MATCH(G57,技能卡分表!$A:$A,0))) -> #N/A | H58: =IF(ISNUMBER(MATCH(H57,单位卡分表!$A:$A,0)),INDEX(单位卡分表!$B:$B,MATCH(H57,单位卡分表!$A:$A,0)),INDEX(技能卡分表!$B:$B,MATCH(H57,技能卡分表!$A:$A,0))) -> #N/A | I58: =IF(ISNUMBER(MATCH(I57,单位卡分表!$A:$A,0)),INDEX(单位卡分表!$B:$B,MATCH(I57,单位卡分表!$A:$A,0)),INDEX(技能卡分表!$B:$B,MATCH(I57,技能卡分表!$A:$A,0))) -> #N/A | J58: =IF(ISNUMBER(MATCH(J57,单位卡分表!$A:$A,0)),INDEX(单位卡分表!$B:$B,MATCH(J57,单位卡分表!$A:$A,0)),INDEX(技能卡分表!$B:$B,MATCH(J57,技能卡分表!$A:$A,0))) -> #N/A | K58: =IF(ISNUMBER(MATCH(K57,单位卡分表!$A:$A,0)),INDEX(单位卡分表!$B:$B,MATCH(K57,单位卡分表!$A:$A,0)),INDEX(技能卡分表!$B:$B,MATCH(K57,技能卡分表!$A:$A,0))) -> #N/A | ... M58: =IF(ISNUMBER(MATCH(M57,单位卡分表!$A:$A,0)),INDEX(单位卡分表!$B:$B,MATCH(M57,单位卡分表!$A:$A,0)),INDEX(技能卡分表!$B:$B,MATCH(M57,技能卡分表!$A:$A,0))) -> #N/A | N58: =IF(SUMPRODUCT(COUNTIF(D58:M58,D58:M58))>COLUMNS(D58:M58),"有重复","无重复") -> 有重复
A59: 4 | B59: 10004 | C59: 卡组ID
C60: 名字 | D60: =IF(ISNUMBER(MATCH(D59,单位卡分表!$A:$A,0)),INDEX(单位卡分表!$B:$B,MATCH(D59,单位卡分表!$A:$A,0)),INDEX(技能卡分表!$B:$B,MATCH(D59,技能卡分表!$A:$A,0))) -> #N/A | E60: =IF(ISNUMBER(MATCH(E59,单位卡分表!$A:$A,0)),INDEX(单位卡分表!$B:$B,MATCH(E59,单位卡分表!$A:$A,0)),INDEX(技能卡分表!$B:$B,MATCH(E59,技能卡分表!$A:$A,0))) -> #N/A | F60: =IF(ISNUMBER(MATCH(F59,单位卡分表!$A:$A,0)),INDEX(单位卡分表!$B:$B,MATCH(F59,单位卡分表!$A:$A,0)),INDEX(技能卡分表!$B:$B,MATCH(F59,技能卡分表!$A:$A,0))) -> #N/A | G60: =IF(ISNUMBER(MATCH(G59,单位卡分表!$A:$A,0)),INDEX(单位卡分表!$B:$B,MATCH(G59,单位卡分表!$A:$A,0)),INDEX(技能卡分表!$B:$B,MATCH(G59,技能卡分表!$A:$A,0))) -> #N/A | H60: =IF(ISNUMBER(MATCH(H59,单位卡分表!$A:$A,0)),INDEX(单位卡分表!$B:$B,MATCH(H59,单位卡分表!$A:$A,0)),INDEX(技能卡分表!$B:$B,MATCH(H59,技能卡分表!$A:$A,0))) -> #N/A | I60: =IF(ISNUMBER(MATCH(I59,单位卡分表!$A:$A,0)),INDEX(单位卡分表!$B:$B,MATCH(I59,单位卡分表!$A:$A,0)),INDEX(技能卡分表!$B:$B,MATCH(I59,技能卡分表!$A:$A,0))) -> #N/A | J60: =IF(ISNUMBER(MATCH(J59,单位卡分表!$A:$A,0)),INDEX(单位卡分表!$B:$B,MATCH(J59,单位卡分表!$A:$A,0)),INDEX(技能卡分表!$B:$B,MATCH(J59,技能卡分表!$A:$A,0))) -> #N/A | K60: =IF(ISNUMBER(MATCH(K59,单位卡分表!$A:$A,0)),INDEX(单位卡分表!$B:$B,MATCH(K59,单位卡分表!$A:$A,0)),INDEX(技能卡分表!$B:$B,MATCH(K59,技能卡分表!$A:$A,0))) -> #N/A | ... M60: =IF(ISNUMBER(MATCH(M59,单位卡分表!$A:$A,0)),INDEX(单位卡分表!$B:$B,MATCH(M59,单位卡分表!$A:$A,0)),INDEX(技能卡分表!$B:$B,MATCH(M59,技能卡分表!$A:$A,0))) -> #N/A | N60: =IF(SUMPRODUCT(COUNTIF(D60:M60,D60:M60))>COLUMNS(D60:M60),"有重复","无重复") -> 有重复
A61: 4 | B61: 10006 | C61: 卡组ID
C62: 名字 | D62: =IF(ISNUMBER(MATCH(D61,单位卡分表!$A:$A,0)),INDEX(单位卡分表!$B:$B,MATCH(D61,单位卡分表!$A:$A,0)),INDEX(技能卡分表!$B:$B,MATCH(D61,技能卡分表!$A:$A,0))) -> #N/A | E62: =IF(ISNUMBER(MATCH(E61,单位卡分表!$A:$A,0)),INDEX(单位卡分表!$B:$B,MATCH(E61,单位卡分表!$A:$A,0)),INDEX(技能卡分表!$B:$B,MATCH(E61,技能卡分表!$A:$A,0))) -> #N/A | F62: =IF(ISNUMBER(MATCH(F61,单位卡分表!$A:$A,0)),INDEX(单位卡分表!$B:$B,MATCH(F61,单位卡分表!$A:$A,0)),INDEX(技能卡分表!$B:$B,MATCH(F61,技能卡分表!$A:$A,0))) -> #N/A | G62: =IF(ISNUMBER(MATCH(G61,单位卡分表!$A:$A,0)),INDEX(单位卡分表!$B:$B,MATCH(G61,单位卡分表!$A:$A,0)),INDEX(技能卡分表!$B:$B,MATCH(G61,技能卡分表!$A:$A,0))) -> #N/A | H62: =IF(ISNUMBER(MATCH(H61,单位卡分表!$A:$A,0)),INDEX(单位卡分表!$B:$B,MATCH(H61,单位卡分表!$A:$A,0)),INDEX(技能卡分表!$B:$B,MATCH(H61,技能卡分表!$A:$A,0))) -> #N/A | I62: =IF(ISNUMBER(MATCH(I61,单位卡分表!$A:$A,0)),INDEX(单位卡分表!$B:$B,MATCH(I61,单位卡分表!$A:$A,0)),INDEX(技能卡分表!$B:$B,MATCH(I61,技能卡分表!$A:$A,0))) -> #N/A | J62: =IF(ISNUMBER(MATCH(J61,单位卡分表!$A:$A,0)),INDEX(单位卡分表!$B:$B,MATCH(J61,单位卡分表!$A:$A,0)),INDEX(技能卡分表!$B:$B,MATCH(J61,技能卡分表!$A:$A,0))) -> #N/A | K62: =IF(ISNUMBER(MATCH(K61,单位卡分表!$A:$A,0)),INDEX(单位卡分表!$B:$B,MATCH(K61,单位卡分表!$A:$A,0)),INDEX(技能卡分表!$B:$B,MATCH(K61,技能卡分表!$A:$A,0))) -> #N/A | ... M62: =IF(ISNUMBER(MATCH(M61,单位卡分表!$A:$A,0)),INDEX(单位卡分表!$B:$B,MATCH(M61,单位卡分表!$A:$A,0)),INDEX(技能卡分表!$B:$B,MATCH(M61,技能卡分表!$A:$A,0))) -> #N/A | N62: =IF(SUMPRODUCT(COUNTIF(D62:M62,D62:M62))>COLUMNS(D62:M62),"有重复","无重复") -> 有重复
A63: 4 | B63: 10001 | C63: 卡组ID
C64: 名字 | D64: =IF(ISNUMBER(MATCH(D63,单位卡分表!$A:$A,0)),INDEX(单位卡分表!$B:$B,MATCH(D63,单位卡分表!$A:$A,0)),INDEX(技能卡分表!$B:$B,MATCH(D63,技能卡分表!$A:$A,0))) -> #N/A | E64: =IF(ISNUMBER(MATCH(E63,单位卡分表!$A:$A,0)),INDEX(单位卡分表!$B:$B,MATCH(E63,单位卡分表!$A:$A,0)),INDEX(技能卡分表!$B:$B,MATCH(E63,技能卡分表!$A:$A,0))) -> #N/A | F64: =IF(ISNUMBER(MATCH(F63,单位卡分表!$A:$A,0)),INDEX(单位卡分表!$B:$B,MATCH(F63,单位卡分表!$A:$A,0)),INDEX(技能卡分表!$B:$B,MATCH(F63,技能卡分表!$A:$A,0))) -> #N/A | G64: =IF(ISNUMBER(MATCH(G63,单位卡分表!$A:$A,0)),INDEX(单位卡分表!$B:$B,MATCH(G63,单位卡分表!$A:$A,0)),INDEX(技能卡分表!$B:$B,MATCH(G63,技能卡分表!$A:$A,0))) -> #N/A | H64: =IF(ISNUMBER(MATCH(H63,单位卡分表!$A:$A,0)),INDEX(单位卡分表!$B:$B,MATCH(H63,单位卡分表!$A:$A,0)),INDEX(技能卡分表!$B:$B,MATCH(H63,技能卡分表!$A:$A,0))) -> #N/A | I64: =IF(ISNUMBER(MATCH(I63,单位卡分表!$A:$A,0)),INDEX(单位卡分表!$B:$B,MATCH(I63,单位卡分表!$A:$A,0)),INDEX(技能卡分表!$B:$B,MATCH(I63,技能卡分表!$A:$A,0))) -> #N/A | J64: =IF(ISNUMBER(MATCH(J63,单位卡分表!$A:$A,0)),INDEX(单位卡分表!$B:$B,MATCH(J63,单位卡分表!$A:$A,0)),INDEX(技能卡分表!$B:$B,MATCH(J63,技能卡分表!$A:$A,0))) -> #N/A | K64: =IF(ISNUMBER(MATCH(K63,单位卡分表!$A:$A,0)),INDEX(单位卡分表!$B:$B,MATCH(K63,单位卡分表!$A:$A,0)),INDEX(技能卡分表!$B:$B,MATCH(K63,技能卡分表!$A:$A,0))) -> #N/A | ... M64: =IF(ISNUMBER(MATCH(M63,单位卡分表!$A:$A,0)),INDEX(单位卡分表!$B:$B,MATCH(M63,单位卡分表!$A:$A,0)),INDEX(技能卡分表!$B:$B,MATCH(M63,技能卡分表!$A:$A,0))) -> #N/A | N64: =IF(SUMPRODUCT(COUNTIF(D64:M64,D64:M64))>COLUMNS(D64:M64),"有重复","无重复") -> 有重复

Sheet 新手卡规划
A1: 卡牌ID | B1: 卡牌类型（1生物，2法术） | C1: 卡牌名 | D1: 费用 | E1: 稀有度 | F1: 卡牌效果 | G1: 效果备注 | I1: 默认卡组设计
I2: 初始赠送卡组
A3: 10018 | B3: 1 | C3: =IF(B3=1,INDEX(单位卡分表!B:B,MATCH(A3,单位卡分表!A:A,0)),IF(B3=2,INDEX(技能卡分表!B:B,MATCH(A3,技能卡分表!A:A,0)),0)) -> 萨克斯 莉莉（Lily was here） | D3: =IF(B3=1,INDEX(单位卡分表!G:G,MATCH(A3,单位卡分表!A:A,0)),IF(B3=2,INDEX(技能卡分表!G:G,MATCH(A3,技能卡分表!A:A,0)),0)) -> 6 | E3: =IF(B3=1,INDEX(单位卡分表!H:H,MATCH(A3,单位卡分表!A:A,0)),IF(B3=2,INDEX(技能卡分表!H:H,MATCH(A3,技能卡分表!A:A,0)),0)) -> 3 | F3: =IF(B3=1,INDEX(单位卡分表!P:P,MATCH(A3,单位卡分表!A:A,0)),IF(B3=2,INDEX(技能卡分表!P:P,MATCH(A3,技能卡分表!A:A,0)),0)) -> 我方回合：每有我方单位离场时，我方英雄回复{0}点生命 | G3: =IF(B3=1,INDEX(单位卡分表!Q:Q,MATCH(A3,单位卡分表!A:A,0)),IF(B3=2,INDEX(技能卡分表!Q:Q,MATCH(A3,技能卡分表!A:A,0)),"")) -> （死亡，被吞噬，雇佣兵都算），被吞噬后，被吞噬单位死亡，只算一次离场（因为吞噬已经算离场了） | J3: 英雄 | K3: 10000 | L3: 舰长 | N3: 英雄 | O3: 10002 | P3: 露娜 | R3: 英雄 | S3: 10001 | T3: 宁芙 | V3: 英雄 | W3: 10003 | X3: 乔艾塔 | Z3: 英雄 | AA3: 10004 | AB3: 维纳斯 | AD3: 英雄 | AE3: 10005 | AF3: 大蛇 | AH3: 英雄 | AI3: 10006 | AJ3: 蜂后
A4: 10028 | B4: 1 | C4: =IF(B4=1,INDEX(单位卡分表!B:B,MATCH(A4,单位卡分表!A:A,0)),IF(B4=2,INDEX(技能卡分表!B:B,MATCH(A4,技能卡分表!A:A,0)),0)) -> 羽毛球 拉丽（英文就rally连续得分的意思） | D4: =IF(B4=1,INDEX(单位卡分表!G:G,MATCH(A4,单位卡分表!A:A,0)),IF(B4=2,INDEX(技能卡分表!G:G,MATCH(A4,技能卡分表!A:A,0)),0)) -> 5 | E4: =IF(B4=1,INDEX(单位卡分表!H:H,MATCH(A4,单位卡分表!A:A,0)),IF(B4=2,INDEX(技能卡分表!H:H,MATCH(A4,技能卡分表!A:A,0)),0)) -> 2 | F4: =IF(B4=1,INDEX(单位卡分表!P:P,MATCH(A4,单位卡分表!A:A,0)),IF(B4=2,INDEX(技能卡分表!P:P,MATCH(A4,技能卡分表!A:A,0)),0)) -> 打出时：有{0}%几率回到手牌，每次打出几率下降{1}% | G4: =IF(B4=1,INDEX(单位卡分表!Q:Q,MATCH(A4,单位卡分表!A:A,0)),IF(B4=2,INDEX(技能卡分表!Q:Q,MATCH(A4,技能卡分表!A:A,0)),"")) -> 0 | J4: 10021 | K4: 1 | L4: =IF(K4=1,INDEX(单位卡分表!$B:$B,MATCH(J4,单位卡分表!$A:$A,0)),IF(K4=2,INDEX(技能卡分表!$B:$B,MATCH(J4,技能卡分表!$A:$A,0)),0)) -> 自动铅笔 追忆 | N4: 10033 | O4: 1 | P4: =IF(O4=1,INDEX(单位卡分表!$B:$B,MATCH(N4,单位卡分表!$A:$A,0)),IF(O4=2,INDEX(技能卡分表!$B:$B,MATCH(N4,技能卡分表!$A:$A,0)),0)) -> 蜡烛 热泪 | S4: 1 | T4: =IF(S4=1,INDEX(单位卡分表!$B:$B,MATCH(R4,单位卡分表!$A:$A,0)),IF(S4=2,INDEX(技能卡分表!$B:$B,MATCH(R4,技能卡分表!$A:$A,0)),0)) -> #N/A | V4: 10025 | W4: 1 | X4: =IF(W4=1,INDEX(单位卡分表!$B:$B,MATCH(V4,单位卡分表!$A:$A,0)),IF(W4=2,INDEX(技能卡分表!$B:$B,MATCH(V4,技能卡分表!$A:$A,0)),0)) -> 电池 伏特 | Z4: 10072 | AA4: 1 | AB4: =IF(AA4=1,INDEX(单位卡分表!$B:$B,MATCH(Z4,单位卡分表!$A:$A,0)),IF(AA4=2,INDEX(技能卡分表!$B:$B,MATCH(Z4,技能卡分表!$A:$A,0)),0)) -> 鲨鱼 利齿 | AD4: 10080 | AE4: 1 | AF4: =IF(AE4=1,INDEX(单位卡分表!$B:$B,MATCH(AD4,单位卡分表!$A:$A,0)),IF(AE4=2,INDEX(技能卡分表!$B:$B,MATCH(AD4,技能卡分表!$A:$A,0)),0)) -> 安全帽 小橘 | AH4: 10028 | AI4: 1 | AJ4: =IF(AI4=1,INDEX(单位卡分表!$B:$B,MATCH(AH4,单位卡分表!$A:$A,0)),IF(AI4=2,INDEX(技能卡分表!$B:$B,MATCH(AH4,技能卡分表!$A:$A,0)),0)) -> 羽毛球 拉丽（英文就rally连续得分的意思）
A5: 10032 | B5: 1 | C5: =IF(B5=1,INDEX(单位卡分表!B:B,MATCH(A5,单位卡分表!A:A,0)),IF(B5=2,INDEX(技能卡分表!B:B,MATCH(A5,技能卡分表!A:A,0)),0)) -> 自行车 闪电 | D5: =IF(B5=1,INDEX(单位卡分表!G:G,MATCH(A5,单位卡分表!A:A,0)),IF(B5=2,INDEX(技能卡分表!G:G,MATCH(A5,技能卡分表!A:A,0)),0)) -> 4 | E5: =IF(B5=1,INDEX(单位卡分表!H:H,MATCH(A5,单位卡分表!A:A,0)),IF(B5=2,INDEX(技能卡分表!H:H,MATCH(A5,技能卡分表!A:A,0)),0)) -> 1 | F5: =IF(B5=1,INDEX(单位卡分表!P:P,MATCH(A5,单位卡分表!A:A,0)),IF(B5=2,INDEX(技能卡分表!P:P,MATCH(A5,技能卡分表!A:A,0)),0)) -> 首次碰撞随从单位时，施加一个较大的力 | G5: =IF(B5=1,INDEX(单位卡分表!Q:Q,MATCH(A5,单位卡分表!A:A,0)),IF(B5=2,INDEX(技能卡分表!Q:Q,MATCH(A5,技能卡分表!A:A,0)),"")) -> 敌我都行，隐藏参数力大小{0} | J5: 10030 | K5: 1 | L5: =IF(K5=1,INDEX(单位卡分表!$B:$B,MATCH(J5,单位卡分表!$A:$A,0)),IF(K5=2,INDEX(技能卡分表!$B:$B,MATCH(J5,技能卡分表!$A:$A,0)),0)) -> 军鼓 震声 | N5: 10060 | O5: 1 | P5: =IF(O5=1,INDEX(单位卡分表!$B:$B,MATCH(N5,单位卡分表!$A:$A,0)),IF(O5=2,INDEX(技能卡分表!$B:$B,MATCH(N5,技能卡分表!$A:$A,0)),0)) -> 爆米花 酥脆 | S5: 1 | T5: =IF(S5=1,INDEX(单位卡分表!$B:$B,MATCH(R5,单位卡分表!$A:$A,0)),IF(S5=2,INDEX(技能卡分表!$B:$B,MATCH(R5,技能卡分表!$A:$A,0)),0)) -> #N/A | V5: 10016 | W5: 1 | X5: =IF(W5=1,INDEX(单位卡分表!$B:$B,MATCH(V5,单位卡分表!$A:$A,0)),IF(W5=2,INDEX(技能卡分表!$B:$B,MATCH(V5,技能卡分表!$A:$A,0)),0)) -> 电扇 彩虹 | Z5: 10073 | AA5: 1 | AB5: =IF(AA5=1,INDEX(单位卡分表!$B:$B,MATCH(Z5,单位卡分表!$A:$A,0)),IF(AA5=2,INDEX(技能卡分表!$B:$B,MATCH(Z5,技能卡分表!$A:$A,0)),0)) -> 储蓄罐 珠珠（复用） | AD5: 10021 | AE5: 1 | AF5: =IF(AE5=1,INDEX(单位卡分表!$B:$B,MATCH(AD5,单位卡分表!$A:$A,0)),IF(AE5=2,INDEX(技能卡分表!$B:$B,MATCH(AD5,技能卡分表!$A:$A,0)),0)) -> 自动铅笔 追忆 | AH5: 10035 | AI5: 1 | AJ5: =IF(AI5=1,INDEX(单位卡分表!$B:$B,MATCH(AH5,单位卡分表!$A:$A,0)),IF(AI5=2,INDEX(技能卡分表!$B:$B,MATCH(AH5,技能卡分表!$A:$A,0)),0)) -> 纯净水 浅浅
A6: 10035 | B6: 1 | C6: =IF(B6=1,INDEX(单位卡分表!B:B,MATCH(A6,单位卡分表!A:A,0)),IF(B6=2,INDEX(技能卡分表!B:B,MATCH(A6,技能卡分表!A:A,0)),0)) -> 纯净水 浅浅 | D6: =IF(B6=1,INDEX(单位卡分表!G:G,MATCH(A6,单位卡分表!A:A,0)),IF(B6=2,INDEX(技能卡分表!G:G,MATCH(A6,技能卡分表!A:A,0)),0)) -> 2 | E6: =IF(B6=1,INDEX(单位卡分表!H:H,MATCH(A6,单位卡分表!A:A,0)),IF(B6=2,INDEX(技能卡分表!H:H,MATCH(A6,技能卡分表!A:A,0)),0)) -> 1 | F6: =IF(B6=1,INDEX(单位卡分表!P:P,MATCH(A6,单位卡分表!A:A,0)),IF(B6=2,INDEX(技能卡分表!P:P,MATCH(A6,技能卡分表!A:A,0)),0)) -> 无 | G6: =IF(B6=1,INDEX(单位卡分表!Q:Q,MATCH(A6,单位卡分表!A:A,0)),IF(B6=2,INDEX(技能卡分表!Q:Q,MATCH(A6,技能卡分表!A:A,0)),"")) -> 凑数属性怪，白水瓶娘浅，均衡攻血 | J6: 10080 | K6: 1 | L6: =IF(K6=1,INDEX(单位卡分表!$B:$B,MATCH(J6,单位卡分表!$A:$A,0)),IF(K6=2,INDEX(技能卡分表!$B:$B,MATCH(J6,技能卡分表!$A:$A,0)),0)) -> 安全帽 小橘 | N6: 10051 | O6: 1 | P6: =IF(O6=1,INDEX(单位卡分表!$B:$B,MATCH(N6,单位卡分表!$A:$A,0)),IF(O6=2,INDEX(技能卡分表!$B:$B,MATCH(N6,技能卡分表!$A:$A,0)),0)) -> 气球 飘舞 | S6: 1 | T6: =IF(S6=1,INDEX(单位卡分表!$B:$B,MATCH(R6,单位卡分表!$A:$A,0)),IF(S6=2,INDEX(技能卡分表!$B:$B,MATCH(R6,技能卡分表!$A:$A,0)),0)) -> #N/A | V6: 10030 | W6: 1 | X6: =IF(W6=1,INDEX(单位卡分表!$B:$B,MATCH(V6,单位卡分表!$A:$A,0)),IF(W6=2,INDEX(技能卡分表!$B:$B,MATCH(V6,技能卡分表!$A:$A,0)),0)) -> 军鼓 震声 | Z6: 10036 | AA6: 1 | AB6: =IF(AA6=1,INDEX(单位卡分表!$B:$B,MATCH(Z6,单位卡分表!$A:$A,0)),IF(AA6=2,INDEX(技能卡分表!$B:$B,MATCH(Z6,技能卡分表!$A:$A,0)),0)) -> 纯净水 满满 | AD6: 10030 | AE6: 1 | AF6: =IF(AE6=1,INDEX(单位卡分表!$B:$B,MATCH(AD6,单位卡分表!$A:$A,0)),IF(AE6=2,INDEX(技能卡分表!$B:$B,MATCH(AD6,技能卡分表!$A:$A,0)),0)) -> 军鼓 震声 | AH6: 10038 | AI6: 1 | AJ6: =IF(AI6=1,INDEX(单位卡分表!$B:$B,MATCH(AH6,单位卡分表!$A:$A,0)),IF(AI6=2,INDEX(技能卡分表!$B:$B,MATCH(AH6,技能卡分表!$A:$A,0)),0)) -> 红汽水 满满
A7: 10036 | B7: 1 | C7: =IF(B7=1,INDEX(单位卡分表!B:B,MATCH(A7,单位卡分表!A:A,0)),IF(B7=2,INDEX(技能卡分表!B:B,MATCH(A7,技能卡分表!A:A,0)),0)) -> 纯净水 满满 | D7: =IF(B7=1,INDEX(单位卡分表!G:G,MATCH(A7,单位卡分表!A:A,0)),IF(B7=2,INDEX(技能卡分表!G:G,MATCH(A7,技能卡分表!A:A,0)),0)) -> 4 | E7: =IF(B7=1,INDEX(单位卡分表!H:H,MATCH(A7,单位卡分表!A:A,0)),IF(B7=2,INDEX(技能卡分表!H:H,MATCH(A7,技能卡分表!A:A,0)),0)) -> 1 | F7: =IF(B7=1,INDEX(单位卡分表!P:P,MATCH(A7,单位卡分表!A:A,0)),IF(B7=2,INDEX(技能卡分表!P:P,MATCH(A7,技能卡分表!A:A,0)),0)) -> 无 | G7: =IF(B7=1,INDEX(单位卡分表!Q:Q,MATCH(A7,单位卡分表!A:A,0)),IF(B7=2,INDEX(技能卡分表!Q:Q,MATCH(A7,技能卡分表!A:A,0)),"")) -> 凑数属性怪，白水瓶娘满，均衡攻血 | J7: 10036 | K7: 1 | L7: =IF(K7=1,INDEX(单位卡分表!$B:$B,MATCH(J7,单位卡分表!$A:$A,0)),IF(K7=2,INDEX(技能卡分表!$B:$B,MATCH(J7,技能卡分表!$A:$A,0)),0)) -> 纯净水 满满 | N7: 10036 | O7: 1 | P7: =IF(O7=1,INDEX(单位卡分表!$B:$B,MATCH(N7,单位卡分表!$A:$A,0)),IF(O7=2,INDEX(技能卡分表!$B:$B,MATCH(N7,技能卡分表!$A:$A,0)),0)) -> 纯净水 满满 | S7: 1 | T7: =IF(S7=1,INDEX(单位卡分表!$B:$B,MATCH(R7,单位卡分表!$A:$A,0)),IF(S7=2,INDEX(技能卡分表!$B:$B,MATCH(R7,技能卡分表!$A:$A,0)),0)) -> #N/A | V7: 10036 | W7: 1 | X7: =IF(W7=1,INDEX(单位卡分表!$B:$B,MATCH(V7,单位卡分表!$A:$A,0)),IF(W7=2,INDEX(技能卡分表!$B:$B,MATCH(V7,技能卡分表!$A:$A,0)),0)) -> 纯净水 满满 | Z7: 10075 | AA7: 1 | AB7: =IF(AA7=1,INDEX(单位卡分表!$B:$B,MATCH(Z7,单位卡分表!$A:$A,0)),IF(AA7=2,INDEX(技能卡分表!$B:$B,MATCH(Z7,技能卡分表!$A:$A,0)),0)) -> 菠菜罐头 大力 | AD7: 10036 | AE7: 1 | AF7: =IF(AE7=1,INDEX(单位卡分表!$B:$B,MATCH(AD7,单位卡分表!$A:$A,0)),IF(AE7=2,INDEX(技能卡分表!$B:$B,MATCH(AD7,技能卡分表!$A:$A,0)),0)) -> 纯净水 满满 | AH7: 10040 | AI7: 1 | AJ7: =IF(AI7=1,INDEX(单位卡分表!$B:$B,MATCH(AH7,单位卡分表!$A:$A,0)),IF(AI7=2,INDEX(技能卡分表!$B:$B,MATCH(AH7,技能卡分表!$A:$A,0)),0)) -> 绿汽水 满满
A8: 10037 | B8: 1 | C8: =IF(B8=1,INDEX(单位卡分表!B:B,MATCH(A8,单位卡分表!A:A,0)),IF(B8=2,INDEX(技能卡分表!B:B,MATCH(A8,技能卡分表!A:A,0)),0)) -> 红汽水 浅浅 | D8: =IF(B8=1,INDEX(单位卡分表!G:G,MATCH(A8,单位卡分表!A:A,0)),IF(B8=2,INDEX(技能卡分表!G:G,MATCH(A8,技能卡分表!A:A,0)),0)) -> 3 | E8: =IF(B8=1,INDEX(单位卡分表!H:H,MATCH(A8,单位卡分表!A:A,0)),IF(B8=2,INDEX(技能卡分表!H:H,MATCH(A8,技能卡分表!A:A,0)),0)) -> 1 | F8: =IF(B8=1,INDEX(单位卡分表!P:P,MATCH(A8,单位卡分表!A:A,0)),IF(B8=2,INDEX(技能卡分表!P:P,MATCH(A8,技能卡分表!A:A,0)),0)) -> 无 | G8: =IF(B8=1,INDEX(单位卡分表!Q:Q,MATCH(A8,单位卡分表!A:A,0)),IF(B8=2,INDEX(技能卡分表!Q:Q,MATCH(A8,技能卡分表!A:A,0)),"")) -> 凑数属性怪，红水瓶娘浅，高攻低血 | J8: 10035 | K8: 1 | L8: =IF(K8=1,INDEX(单位卡分表!$B:$B,MATCH(J8,单位卡分表!$A:$A,0)),IF(K8=2,INDEX(技能卡分表!$B:$B,MATCH(J8,技能卡分表!$A:$A,0)),0)) -> 纯净水 浅浅 | N8: 10035 | O8: 1 | P8: =IF(O8=1,INDEX(单位卡分表!$B:$B,MATCH(N8,单位卡分表!$A:$A,0)),IF(O8=2,INDEX(技能卡分表!$B:$B,MATCH(N8,技能卡分表!$A:$A,0)),0)) -> 纯净水 浅浅 | S8: 1 | T8: =IF(S8=1,INDEX(单位卡分表!$B:$B,MATCH(R8,单位卡分表!$A:$A,0)),IF(S8=2,INDEX(技能卡分表!$B:$B,MATCH(R8,技能卡分表!$A:$A,0)),0)) -> #N/A | V8: 10035 | W8: 1 | X8: =IF(W8=1,INDEX(单位卡分表!$B:$B,MATCH(V8,单位卡分表!$A:$A,0)),IF(W8=2,INDEX(技能卡分表!$B:$B,MATCH(V8,技能卡分表!$A:$A,0)),0)) -> 纯净水 浅浅 | Z8: 10039 | AA8: 1 | AB8: =IF(AA8=1,INDEX(单位卡分表!$B:$B,MATCH(Z8,单位卡分表!$A:$A,0)),IF(AA8=2,INDEX(技能卡分表!$B:$B,MATCH(Z8,技能卡分表!$A:$A,0)),0)) -> 绿汽水 浅浅 | AD8: 10037 | AE8: 1 | AF8: =IF(AE8=1,INDEX(单位卡分表!$B:$B,MATCH(AD8,单位卡分表!$A:$A,0)),IF(AE8=2,INDEX(技能卡分表!$B:$B,MATCH(AD8,技能卡分表!$A:$A,0)),0)) -> 红汽水 浅浅 | AH8: 10041 | AI8: 1 | AJ8: =IF(AI8=1,INDEX(单位卡分表!$B:$B,MATCH(AH8,单位卡分表!$A:$A,0)),IF(AI8=2,INDEX(技能卡分表!$B:$B,MATCH(AH8,技能卡分表!$A:$A,0)),0)) -> 肥皂 滑滑
A9: 10038 | B9: 1 | C9: =IF(B9=1,INDEX(单位卡分表!B:B,MATCH(A9,单位卡分表!A:A,0)),IF(B9=2,INDEX(技能卡分表!B:B,MATCH(A9,技能卡分表!A:A,0)),0)) -> 红汽水 满满 | D9: =IF(B9=1,INDEX(单位卡分表!G:G,MATCH(A9,单位卡分表!A:A,0)),IF(B9=2,INDEX(技能卡分表!G:G,MATCH(A9,技能卡分表!A:A,0)),0)) -> 5 | E9: =IF(B9=1,INDEX(单位卡分表!H:H,MATCH(A9,单位卡分表!A:A,0)),IF(B9=2,INDEX(技能卡分表!H:H,MATCH(A9,技能卡分表!A:A,0)),0)) -> 1 | F9: =IF(B9=1,INDEX(单位卡分表!P:P,MATCH(A9,单位卡分表!A:A,0)),IF(B9=2,INDEX(技能卡分表!P:P,MATCH(A9,技能卡分表!A:A,0)),0)) -> 无 | G9: =IF(B9=1,INDEX(单位卡分表!Q:Q,MATCH(A9,单位卡分表!A:A,0)),IF(B9=2,INDEX(技能卡分表!Q:Q,MATCH(A9,技能卡分表!A:A,0)),"")) -> 凑数属性怪，红水瓶娘满，高攻低血 | J9: 10037 | K9: 1 | L9: =IF(K9=1,INDEX(单位卡分表!$B:$B,MATCH(J9,单位卡分表!$A:$A,0)),IF(K9=2,INDEX(技能卡分表!$B:$B,MATCH(J9,技能卡分表!$A:$A,0)),0)) -> 红汽水 浅浅 | N9: 10037 | O9: 1 | P9: =IF(O9=1,INDEX(单位卡分表!$B:$B,MATCH(N9,单位卡分表!$A:$A,0)),IF(O9=2,INDEX(技能卡分表!$B:$B,MATCH(N9,技能卡分表!$A:$A,0)),0)) -> 红汽水 浅浅 | S9: 1 | T9: =IF(S9=1,INDEX(单位卡分表!$B:$B,MATCH(R9,单位卡分表!$A:$A,0)),IF(S9=2,INDEX(技能卡分表!$B:$B,MATCH(R9,技能卡分表!$A:$A,0)),0)) -> #N/A | V9: 10037 | W9: 1 | X9: =IF(W9=1,INDEX(单位卡分表!$B:$B,MATCH(V9,单位卡分表!$A:$A,0)),IF(W9=2,INDEX(技能卡分表!$B:$B,MATCH(V9,技能卡分表!$A:$A,0)),0)) -> 红汽水 浅浅 | Z9: 10066 | AA9: 1 | AB9: =IF(AA9=1,INDEX(单位卡分表!$B:$B,MATCH(Z9,单位卡分表!$A:$A,0)),IF(AA9=2,INDEX(技能卡分表!$B:$B,MATCH(Z9,技能卡分表!$A:$A,0)),0)) -> 乌龟 壳壳 | AD9: 10063 | AE9: 1 | AF9: =IF(AE9=1,INDEX(单位卡分表!$B:$B,MATCH(AD9,单位卡分表!$A:$A,0)),IF(AE9=2,INDEX(技能卡分表!$B:$B,MATCH(AD9,技能卡分表!$A:$A,0)),0)) -> 篮球框 三分 | AH9: 10049 | AI9: 1 | AJ9: =IF(AI9=1,INDEX(单位卡分表!$B:$B,MATCH(AH9,单位卡分表!$A:$A,0)),IF(AI9=2,INDEX(技能卡分表!$B:$B,MATCH(AH9,技能卡分表!$A:$A,0)),0)) -> 夹子 瑾瑾
A10: 10039 | B10: 1 | C10: =IF(B10=1,INDEX(单位卡分表!B:B,MATCH(A10,单位卡分表!A:A,0)),IF(B10=2,INDEX(技能卡分表!B:B,MATCH(A10,技能卡分表!A:A,0)),0)) -> 绿汽水 浅浅 | D10: =IF(B10=1,INDEX(单位卡分表!G:G,MATCH(A10,单位卡分表!A:A,0)),IF(B10=2,INDEX(技能卡分表!G:G,MATCH(A10,技能卡分表!A:A,0)),0)) -> 4 | E10: =IF(B10=1,INDEX(单位卡分表!H:H,MATCH(A10,单位卡分表!A:A,0)),IF(B10=2,INDEX(技能卡分表!H:H,MATCH(A10,技能卡分表!A:A,0)),0)) -> 1 | F10: =IF(B10=1,INDEX(单位卡分表!P:P,MATCH(A10,单位卡分表!A:A,0)),IF(B10=2,INDEX(技能卡分表!P:P,MATCH(A10,技能卡分表!A:A,0)),0)) -> 无 | G10: =IF(B10=1,INDEX(单位卡分表!Q:Q,MATCH(A10,单位卡分表!A:A,0)),IF(B10=2,INDEX(技能卡分表!Q:Q,MATCH(A10,技能卡分表!A:A,0)),"")) -> 凑数属性怪，绿水瓶娘浅，低攻高血 | J10: 10079 | K10: 1 | L10: =IF(K10=1,INDEX(单位卡分表!$B:$B,MATCH(J10,单位卡分表!$A:$A,0)),IF(K10=2,INDEX(技能卡分表!$B:$B,MATCH(J10,技能卡分表!$A:$A,0)),0)) -> 炸蛋 | N10: 10079 | O10: 1 | P10: =IF(O10=1,INDEX(单位卡分表!$B:$B,MATCH(N10,单位卡分表!$A:$A,0)),IF(O10=2,INDEX(技能卡分表!$B:$B,MATCH(N10,技能卡分表!$A:$A,0)),0)) -> 炸蛋 | S10: 1 | T10: =IF(S10=1,INDEX(单位卡分表!$B:$B,MATCH(R10,单位卡分表!$A:$A,0)),IF(S10=2,INDEX(技能卡分表!$B:$B,MATCH(R10,技能卡分表!$A:$A,0)),0)) -> #N/A | V10: 10028 | W10: 1 | X10: =IF(W10=1,INDEX(单位卡分表!$B:$B,MATCH(V10,单位卡分表!$A:$A,0)),IF(W10=2,INDEX(技能卡分表!$B:$B,MATCH(V10,技能卡分表!$A:$A,0)),0)) -> 羽毛球 拉丽（英文就rally连续得分的意思） | Z10: 10028 | AA10: 1 | AB10: =IF(AA10=1,INDEX(单位卡分表!$B:$B,MATCH(Z10,单位卡分表!$A:$A,0)),IF(AA10=2,INDEX(技能卡分表!$B:$B,MATCH(Z10,技能卡分表!$A:$A,0)),0)) -> 羽毛球 拉丽（英文就rally连续得分的意思） | AD10: 10028 | AE10: 1 | AF10: =IF(AE10=1,INDEX(单位卡分表!$B:$B,MATCH(AD10,单位卡分表!$A:$A,0)),IF(AE10=2,INDEX(技能卡分表!$B:$B,MATCH(AD10,技能卡分表!$A:$A,0)),0)) -> 羽毛球 拉丽（英文就rally连续得分的意思） | AH10: 10051 | AI10: 1 | AJ10: =IF(AI10=1,INDEX(单位卡分表!$B:$B,MATCH(AH10,单位卡分表!$A:$A,0)),IF(AI10=2,INDEX(技能卡分表!$B:$B,MATCH(AH10,技能卡分表!$A:$A,0)),0)) -> 气球 飘舞
A11: 10040 | B11: 1 | C11: =IF(B11=1,INDEX(单位卡分表!B:B,MATCH(A11,单位卡分表!A:A,0)),IF(B11=2,INDEX(技能卡分表!B:B,MATCH(A11,技能卡分表!A:A,0)),0)) -> 绿汽水 满满 | D11: =IF(B11=1,INDEX(单位卡分表!G:G,MATCH(A11,单位卡分表!A:A,0)),IF(B11=2,INDEX(技能卡分表!G:G,MATCH(A11,技能卡分表!A:A,0)),0)) -> 6 | E11: =IF(B11=1,INDEX(单位卡分表!H:H,MATCH(A11,单位卡分表!A:A,0)),IF(B11=2,INDEX(技能卡分表!H:H,MATCH(A11,技能卡分表!A:A,0)),0)) -> 1 | F11: =IF(B11=1,INDEX(单位卡分表!P:P,MATCH(A11,单位卡分表!A:A,0)),IF(B11=2,INDEX(技能卡分表!P:P,MATCH(A11,技能卡分表!A:A,0)),0)) -> 无 | G11: =IF(B11=1,INDEX(单位卡分表!Q:Q,MATCH(A11,单位卡分表!A:A,0)),IF(B11=2,INDEX(技能卡分表!Q:Q,MATCH(A11,技能卡分表!A:A,0)),"")) -> 凑数属性怪，绿水瓶娘满，低攻高血 | J11: 10044 | K11: 1 | L11: =IF(K11=1,INDEX(单位卡分表!$B:$B,MATCH(J11,单位卡分表!$A:$A,0)),IF(K11=2,INDEX(技能卡分表!$B:$B,MATCH(J11,技能卡分表!$A:$A,0)),0)) -> 煤油灯 流露 | N11: 10044 | O11: 1 | P11: =IF(O11=1,INDEX(单位卡分表!$B:$B,MATCH(N11,单位卡分表!$A:$A,0)),IF(O11=2,INDEX(技能卡分表!$B:$B,MATCH(N11,技能卡分表!$A:$A,0)),0)) -> 煤油灯 流露 | S11: 2 | T11: =IF(S11=1,INDEX(单位卡分表!$B:$B,MATCH(R11,单位卡分表!$A:$A,0)),IF(S11=2,INDEX(技能卡分表!$B:$B,MATCH(R11,技能卡分表!$A:$A,0)),0)) -> #N/A | V11: 10012 | W11: 1 | X11: =IF(W11=1,INDEX(单位卡分表!$B:$B,MATCH(V11,单位卡分表!$A:$A,0)),IF(W11=2,INDEX(技能卡分表!$B:$B,MATCH(V11,技能卡分表!$A:$A,0)),0)) -> 摩托 赤狸 塞琳娜 | Z11: 10026 | AA11: 1 | AB11: =IF(AA11=1,INDEX(单位卡分表!$B:$B,MATCH(Z11,单位卡分表!$A:$A,0)),IF(AA11=2,INDEX(技能卡分表!$B:$B,MATCH(Z11,技能卡分表!$A:$A,0)),0)) -> 功能饮料 牛红 | AD11: 10026 | AE11: 1 | AF11: =IF(AE11=1,INDEX(单位卡分表!$B:$B,MATCH(AD11,单位卡分表!$A:$A,0)),IF(AE11=2,INDEX(技能卡分表!$B:$B,MATCH(AD11,技能卡分表!$A:$A,0)),0)) -> 功能饮料 牛红 | AH11: 20050 | AI11: 2 | AJ11: =IF(AI11=1,INDEX(单位卡分表!$B:$B,MATCH(AH11,单位卡分表!$A:$A,0)),IF(AI11=2,INDEX(技能卡分表!$B:$B,MATCH(AH11,技能卡分表!$A:$A,0)),0)) -> 海浪冲击
A12: 10041 | B12: 1 | C12: =IF(B12=1,INDEX(单位卡分表!B:B,MATCH(A12,单位卡分表!A:A,0)),IF(B12=2,INDEX(技能卡分表!B:B,MATCH(A12,技能卡分表!A:A,0)),0)) -> 肥皂 滑滑 | D12: =IF(B12=1,INDEX(单位卡分表!G:G,MATCH(A12,单位卡分表!A:A,0)),IF(B12=2,INDEX(技能卡分表!G:G,MATCH(A12,技能卡分表!A:A,0)),0)) -> 5 | E12: =IF(B12=1,INDEX(单位卡分表!H:H,MATCH(A12,单位卡分表!A:A,0)),IF(B12=2,INDEX(技能卡分表!H:H,MATCH(A12,技能卡分表!A:A,0)),0)) -> 2 | F12: =IF(B12=1,INDEX(单位卡分表!P:P,MATCH(A12,单位卡分表!A:A,0)),IF(B12=2,INDEX(技能卡分表!P:P,MATCH(A12,技能卡分表!A:A,0)),0)) -> 降低自身摩擦力{0}% | G12: =IF(B12=1,INDEX(单位卡分表!Q:Q,MATCH(A12,单位卡分表!A:A,0)),IF(B12=2,INDEX(技能卡分表!Q:Q,MATCH(A12,技能卡分表!A:A,0)),"")) -> 0 | J12: 10026 | K12: 1 | L12: =IF(K12=1,INDEX(单位卡分表!$B:$B,MATCH(J12,单位卡分表!$A:$A,0)),IF(K12=2,INDEX(技能卡分表!$B:$B,MATCH(J12,技能卡分表!$A:$A,0)),0)) -> 功能饮料 牛红 | N12: 10026 | O12: 1 | P12: =IF(O12=1,INDEX(单位卡分表!$B:$B,MATCH(N12,单位卡分表!$A:$A,0)),IF(O12=2,INDEX(技能卡分表!$B:$B,MATCH(N12,技能卡分表!$A:$A,0)),0)) -> 功能饮料 牛红 | S12: 2 | T12: =IF(S12=1,INDEX(单位卡分表!$B:$B,MATCH(R12,单位卡分表!$A:$A,0)),IF(S12=2,INDEX(技能卡分表!$B:$B,MATCH(R12,技能卡分表!$A:$A,0)),0)) -> #N/A | V12: 10026 | W12: 1 | X12: =IF(W12=1,INDEX(单位卡分表!$B:$B,MATCH(V12,单位卡分表!$A:$A,0)),IF(W12=2,INDEX(技能卡分表!$B:$B,MATCH(V12,技能卡分表!$A:$A,0)),0)) -> 功能饮料 牛红 | Z12: 10020 | AA12: 1 | AB12: =IF(AA12=1,INDEX(单位卡分表!$B:$B,MATCH(Z12,单位卡分表!$A:$A,0)),IF(AA12=2,INDEX(技能卡分表!$B:$B,MATCH(Z12,技能卡分表!$A:$A,0)),0)) -> 时钟 晨曦 | AD12: 10020 | AE12: 1 | AF12: =IF(AE12=1,INDEX(单位卡分表!$B:$B,MATCH(AD12,单位卡分表!$A:$A,0)),IF(AE12=2,INDEX(技能卡分表!$B:$B,MATCH(AD12,技能卡分表!$A:$A,0)),0)) -> 时钟 晨曦 | AH12: 20073 | AI12: 2 | AJ12: =IF(AI12=1,INDEX(单位卡分表!$B:$B,MATCH(AH12,单位卡分表!$A:$A,0)),IF(AI12=2,INDEX(技能卡分表!$B:$B,MATCH(AH12,技能卡分表!$A:$A,0)),0)) -> 镭射光束
A13: 20018 | B13: 2 | C13: =IF(B13=1,INDEX(单位卡分表!B:B,MATCH(A13,单位卡分表!A:A,0)),IF(B13=2,INDEX(技能卡分表!B:B,MATCH(A13,技能卡分表!A:A,0)),0)) -> 引导 | D13: =IF(B13=1,INDEX(单位卡分表!G:G,MATCH(A13,单位卡分表!A:A,0)),IF(B13=2,INDEX(技能卡分表!G:G,MATCH(A13,技能卡分表!A:A,0)),0)) -> 3 | E13: =IF(B13=1,INDEX(单位卡分表!H:H,MATCH(A13,单位卡分表!A:A,0)),IF(B13=2,INDEX(技能卡分表!H:H,MATCH(A13,技能卡分表!A:A,0)),0)) -> 2 | F13: =IF(B13=1,INDEX(单位卡分表!P:P,MATCH(A13,单位卡分表!A:A,0)),IF(B13=2,INDEX(技能卡分表!P:P,MATCH(A13,技能卡分表!A:A,0)),0)) -> 碰到首个单位时，我方英雄向其位移 | G13: =IF(B13=1,INDEX(单位卡分表!Q:Q,MATCH(A13,单位卡分表!A:A,0)),IF(B13=2,INDEX(技能卡分表!Q:Q,MATCH(A13,技能卡分表!A:A,0)),"")) -> 隐藏参数力大小{0}，回合结束标记消失 | J13: 10020 | K13: 1 | L13: =IF(K13=1,INDEX(单位卡分表!$B:$B,MATCH(J13,单位卡分表!$A:$A,0)),IF(K13=2,INDEX(技能卡分表!$B:$B,MATCH(J13,技能卡分表!$A:$A,0)),0)) -> 时钟 晨曦 | N13: 10020 | O13: 1 | P13: =IF(O13=1,INDEX(单位卡分表!$B:$B,MATCH(N13,单位卡分表!$A:$A,0)),IF(O13=2,INDEX(技能卡分表!$B:$B,MATCH(N13,技能卡分表!$A:$A,0)),0)) -> 时钟 晨曦 | S13: 1 | T13: =IF(S13=1,INDEX(单位卡分表!$B:$B,MATCH(R13,单位卡分表!$A:$A,0)),IF(S13=2,INDEX(技能卡分表!$B:$B,MATCH(R13,技能卡分表!$A:$A,0)),0)) -> #N/A | V13: 10020 | W13: 1 | X13: =IF(W13=1,INDEX(单位卡分表!$B:$B,MATCH(V13,单位卡分表!$A:$A,0)),IF(W13=2,INDEX(技能卡分表!$B:$B,MATCH(V13,技能卡分表!$A:$A,0)),0)) -> 时钟 晨曦 | Z13: 10012 | AA13: 1 | AB13: =IF(AA13=1,INDEX(单位卡分表!$B:$B,MATCH(Z13,单位卡分表!$A:$A,0)),IF(AA13=2,INDEX(技能卡分表!$B:$B,MATCH(Z13,技能卡分表!$A:$A,0)),0)) -> 摩托 赤狸 塞琳娜 | AD13: 10031 | AE13: 1 | AF13: =IF(AE13=1,INDEX(单位卡分表!$B:$B,MATCH(AD13,单位卡分表!$A:$A,0)),IF(AE13=2,INDEX(技能卡分表!$B:$B,MATCH(AD13,技能卡分表!$A:$A,0)),0)) -> 注射器 针妮 佩妮（英文penny，联想小针） | AH13: 10032 | AI13: 1 | AJ13: =IF(AI13=1,INDEX(单位卡分表!$B:$B,MATCH(AH13,单位卡分表!$A:$A,0)),IF(AI13=2,INDEX(技能卡分表!$B:$B,MATCH(AH13,技能卡分表!$A:$A,0)),0)) -> 自行车 闪电
A14: 20021 | B14: 2 | C14: =IF(B14=1,INDEX(单位卡分表!B:B,MATCH(A14,单位卡分表!A:A,0)),IF(B14=2,INDEX(技能卡分表!B:B,MATCH(A14,技能卡分表!A:A,0)),0)) -> 精准引导 | D14: =IF(B14=1,INDEX(单位卡分表!G:G,MATCH(A14,单位卡分表!A:A,0)),IF(B14=2,INDEX(技能卡分表!G:G,MATCH(A14,技能卡分表!A:A,0)),0)) -> 4 | E14: =IF(B14=1,INDEX(单位卡分表!H:H,MATCH(A14,单位卡分表!A:A,0)),IF(B14=2,INDEX(技能卡分表!H:H,MATCH(A14,技能卡分表!A:A,0)),0)) -> 4 | F14: =IF(B14=1,INDEX(单位卡分表!P:P,MATCH(A14,单位卡分表!A:A,0)),IF(B14=2,INDEX(技能卡分表!P:P,MATCH(A14,技能卡分表!A:A,0)),0)) -> 指定战场任意位置，我方英雄向该位置位移 | G14: =IF(B14=1,INDEX(单位卡分表!Q:Q,MATCH(A14,单位卡分表!A:A,0)),IF(B14=2,INDEX(技能卡分表!Q:Q,MATCH(A14,技能卡分表!A:A,0)),"")) -> 隐藏参数位移力度{0}，不能移动的英雄不生效
A15: 20022 | B15: 2 | C15: =IF(B15=1,INDEX(单位卡分表!B:B,MATCH(A15,单位卡分表!A:A,0)),IF(B15=2,INDEX(技能卡分表!B:B,MATCH(A15,技能卡分表!A:A,0)),0)) -> 蓄力 | D15: =IF(B15=1,INDEX(单位卡分表!G:G,MATCH(A15,单位卡分表!A:A,0)),IF(B15=2,INDEX(技能卡分表!G:G,MATCH(A15,技能卡分表!A:A,0)),0)) -> 1 | E15: =IF(B15=1,INDEX(单位卡分表!H:H,MATCH(A15,单位卡分表!A:A,0)),IF(B15=2,INDEX(技能卡分表!H:H,MATCH(A15,技能卡分表!A:A,0)),0)) -> 2 | F15: =IF(B15=1,INDEX(单位卡分表!P:P,MATCH(A15,单位卡分表!A:A,0)),IF(B15=2,INDEX(技能卡分表!P:P,MATCH(A15,技能卡分表!A:A,0)),0)) -> 下一张打出的卡牌，发射速度增加{0}% | G15: =IF(B15=1,INDEX(单位卡分表!Q:Q,MATCH(A15,单位卡分表!A:A,0)),IF(B15=2,INDEX(技能卡分表!Q:Q,MATCH(A15,技能卡分表!A:A,0)),"")) -> 0
A16: 20028 | B16: 2 | C16: =IF(B16=1,INDEX(单位卡分表!B:B,MATCH(A16,单位卡分表!A:A,0)),IF(B16=2,INDEX(技能卡分表!B:B,MATCH(A16,技能卡分表!A:A,0)),0)) -> 冰冻炸弹 | D16: =IF(B16=1,INDEX(单位卡分表!G:G,MATCH(A16,单位卡分表!A:A,0)),IF(B16=2,INDEX(技能卡分表!G:G,MATCH(A16,技能卡分表!A:A,0)),0)) -> 3 | E16: =IF(B16=1,INDEX(单位卡分表!H:H,MATCH(A16,单位卡分表!A:A,0)),IF(B16=2,INDEX(技能卡分表!H:H,MATCH(A16,技能卡分表!A:A,0)),0)) -> 3 | F16: =IF(B16=1,INDEX(单位卡分表!P:P,MATCH(A16,单位卡分表!A:A,0)),IF(B16=2,INDEX(技能卡分表!P:P,MATCH(A16,技能卡分表!A:A,0)),0)) -> 碰到首个敌方时，对范围内的敌方单位造成{0}点伤害并冻结 | G16: =IF(B16=1,INDEX(单位卡分表!Q:Q,MATCH(A16,单位卡分表!A:A,0)),IF(B16=2,INDEX(技能卡分表!Q:Q,MATCH(A16,技能卡分表!A:A,0)),"")) -> 隐藏参数范围大小{1}，对场景也生效，包括水地面，会变成冰地面。
A17: 20030 | B17: 2 | C17: =IF(B17=1,INDEX(单位卡分表!B:B,MATCH(A17,单位卡分表!A:A,0)),IF(B17=2,INDEX(技能卡分表!B:B,MATCH(A17,技能卡分表!A:A,0)),0)) -> 雷枪 | D17: =IF(B17=1,INDEX(单位卡分表!G:G,MATCH(A17,单位卡分表!A:A,0)),IF(B17=2,INDEX(技能卡分表!G:G,MATCH(A17,技能卡分表!A:A,0)),0)) -> 3 | E17: =IF(B17=1,INDEX(单位卡分表!H:H,MATCH(A17,单位卡分表!A:A,0)),IF(B17=2,INDEX(技能卡分表!H:H,MATCH(A17,技能卡分表!A:A,0)),0)) -> 2 | F17: =IF(B17=1,INDEX(单位卡分表!P:P,MATCH(A17,单位卡分表!A:A,0)),IF(B17=2,INDEX(技能卡分表!P:P,MATCH(A17,技能卡分表!A:A,0)),0)) -> 指定位置，召唤一道雷电，对最近的敌方单位造成一次{0}点电击伤害 | G17: =IF(B17=1,INDEX(单位卡分表!Q:Q,MATCH(A17,单位卡分表!A:A,0)),IF(B17=2,INDEX(技能卡分表!Q:Q,MATCH(A17,技能卡分表!A:A,0)),"")) -> 隐藏效果，打出时若是雨天，则将天气转化成雷雨天
A18: 20031 | B18: 2 | C18: =IF(B18=1,INDEX(单位卡分表!B:B,MATCH(A18,单位卡分表!A:A,0)),IF(B18=2,INDEX(技能卡分表!B:B,MATCH(A18,技能卡分表!A:A,0)),0)) -> 滋水 | D18: =IF(B18=1,INDEX(单位卡分表!G:G,MATCH(A18,单位卡分表!A:A,0)),IF(B18=2,INDEX(技能卡分表!G:G,MATCH(A18,技能卡分表!A:A,0)),0)) -> 3 | E18: =IF(B18=1,INDEX(单位卡分表!H:H,MATCH(A18,单位卡分表!A:A,0)),IF(B18=2,INDEX(技能卡分表!H:H,MATCH(A18,技能卡分表!A:A,0)),0)) -> 1 | F18: =IF(B18=1,INDEX(单位卡分表!P:P,MATCH(A18,单位卡分表!A:A,0)),IF(B18=2,INDEX(技能卡分表!P:P,MATCH(A18,技能卡分表!A:A,0)),0)) -> 对触碰的首个敌方单位造成{0}点伤害，并赋予潮湿状态 | G18: =IF(B18=1,INDEX(单位卡分表!Q:Q,MATCH(A18,单位卡分表!A:A,0)),IF(B18=2,INDEX(技能卡分表!Q:Q,MATCH(A18,技能卡分表!A:A,0)),"")) -> 凑数技能，水瓶娘滋水，对碰到的我方也会赋予潮湿
A19: 20038 | B19: 2 | C19: =IF(B19=1,INDEX(单位卡分表!B:B,MATCH(A19,单位卡分表!A:A,0)),IF(B19=2,INDEX(技能卡分表!B:B,MATCH(A19,技能卡分表!A:A,0)),0)) -> 飞砖 | D19: =IF(B19=1,INDEX(单位卡分表!G:G,MATCH(A19,单位卡分表!A:A,0)),IF(B19=2,INDEX(技能卡分表!G:G,MATCH(A19,技能卡分表!A:A,0)),0)) -> 2 | E19: =IF(B19=1,INDEX(单位卡分表!H:H,MATCH(A19,单位卡分表!A:A,0)),IF(B19=2,INDEX(技能卡分表!H:H,MATCH(A19,技能卡分表!A:A,0)),0)) -> 2 | F19: =IF(B19=1,INDEX(单位卡分表!P:P,MATCH(A19,单位卡分表!A:A,0)),IF(B19=2,INDEX(技能卡分表!P:P,MATCH(A19,技能卡分表!A:A,0)),0)) -> 碰到首个敌方单位时，对其造成{0}点伤害并眩晕{1}层 | G19: =IF(B19=1,INDEX(单位卡分表!Q:Q,MATCH(A19,单位卡分表!A:A,0)),IF(B19=2,INDEX(技能卡分表!Q:Q,MATCH(A19,技能卡分表!A:A,0)),"")) -> 眩晕技能ID{2}
A20: 20044 | B20: 2 | C20: =IF(B20=1,INDEX(单位卡分表!B:B,MATCH(A20,单位卡分表!A:A,0)),IF(B20=2,INDEX(技能卡分表!B:B,MATCH(A20,技能卡分表!A:A,0)),0)) -> 胡乱抓挠 | D20: =IF(B20=1,INDEX(单位卡分表!G:G,MATCH(A20,单位卡分表!A:A,0)),IF(B20=2,INDEX(技能卡分表!G:G,MATCH(A20,技能卡分表!A:A,0)),0)) -> 4 | E20: =IF(B20=1,INDEX(单位卡分表!H:H,MATCH(A20,单位卡分表!A:A,0)),IF(B20=2,INDEX(技能卡分表!H:H,MATCH(A20,技能卡分表!A:A,0)),0)) -> 2 | F20: =IF(B20=1,INDEX(单位卡分表!P:P,MATCH(A20,单位卡分表!A:A,0)),IF(B20=2,INDEX(技能卡分表!P:P,MATCH(A20,技能卡分表!A:A,0)),0)) -> 对随机敌方单位造成{0}次{1}点伤害，同一敌方单位每被击中一次，该伤害增加{2}% | G20: =IF(B20=1,INDEX(单位卡分表!Q:Q,MATCH(A20,单位卡分表!A:A,0)),IF(B20=2,INDEX(技能卡分表!Q:Q,MATCH(A20,技能卡分表!A:A,0)),"")) -> 克制单体随从的教程牌，不同单位独立计算重复次数，每次伤害增加为先加后乘
A21: 20048 | B21: 2 | C21: =IF(B21=1,INDEX(单位卡分表!B:B,MATCH(A21,单位卡分表!A:A,0)),IF(B21=2,INDEX(技能卡分表!B:B,MATCH(A21,技能卡分表!A:A,0)),0)) -> 超电磁炮 | D21: =IF(B21=1,INDEX(单位卡分表!G:G,MATCH(A21,单位卡分表!A:A,0)),IF(B21=2,INDEX(技能卡分表!G:G,MATCH(A21,技能卡分表!A:A,0)),0)) -> 4 | E21: =IF(B21=1,INDEX(单位卡分表!H:H,MATCH(A21,单位卡分表!A:A,0)),IF(B21=2,INDEX(技能卡分表!H:H,MATCH(A21,技能卡分表!A:A,0)),0)) -> 3 | F21: =IF(B21=1,INDEX(单位卡分表!P:P,MATCH(A21,单位卡分表!A:A,0)),IF(B21=2,INDEX(技能卡分表!P:P,MATCH(A21,技能卡分表!A:A,0)),0)) -> 场景穿透，对敌方单位造成{0}点电击伤害 | G21: =IF(B21=1,INDEX(单位卡分表!Q:Q,MATCH(A21,单位卡分表!A:A,0)),IF(B21=2,INDEX(技能卡分表!Q:Q,MATCH(A21,技能卡分表!A:A,0)),"")) -> 和巨雷枪效果一致，包括引起雷雨，蔓延伤害这些，隐藏参数宽度{1}，增加对经过的场景物件的伤害
A22: 20012 | B22: 2 | C22: =IF(B22=1,INDEX(单位卡分表!B:B,MATCH(A22,单位卡分表!A:A,0)),IF(B22=2,INDEX(技能卡分表!B:B,MATCH(A22,技能卡分表!A:A,0)),0)) -> 弹射锯片 | D22: =IF(B22=1,INDEX(单位卡分表!G:G,MATCH(A22,单位卡分表!A:A,0)),IF(B22=2,INDEX(技能卡分表!G:G,MATCH(A22,技能卡分表!A:A,0)),0)) -> 4 | E22: =IF(B22=1,INDEX(单位卡分表!H:H,MATCH(A22,单位卡分表!A:A,0)),IF(B22=2,INDEX(技能卡分表!H:H,MATCH(A22,技能卡分表!A:A,0)),0)) -> 5 | F22: =IF(B22=1,INDEX(单位卡分表!P:P,MATCH(A22,单位卡分表!A:A,0)),IF(B22=2,INDEX(技能卡分表!P:P,MATCH(A22,技能卡分表!A:A,0)),0)) -> 穿透，造成{0}伤害，每穿透一个单位伤害增加{1}% | G22: =IF(B22=1,INDEX(单位卡分表!Q:Q,MATCH(A22,单位卡分表!A:A,0)),IF(B22=2,INDEX(技能卡分表!Q:Q,MATCH(A22,技能卡分表!A:A,0)),"")) -> 计算友方单位，先加后乘，隐藏参数最小伤害间隔{2}秒
A23: 10021 | B23: 1 | C23: =IF(B23=1,INDEX(单位卡分表!B:B,MATCH(A23,单位卡分表!A:A,0)),IF(B23=2,INDEX(技能卡分表!B:B,MATCH(A23,技能卡分表!A:A,0)),0)) -> 自动铅笔 追忆 | D23: =IF(B23=1,INDEX(单位卡分表!G:G,MATCH(A23,单位卡分表!A:A,0)),IF(B23=2,INDEX(技能卡分表!G:G,MATCH(A23,技能卡分表!A:A,0)),0)) -> 7 | E23: =IF(B23=1,INDEX(单位卡分表!H:H,MATCH(A23,单位卡分表!A:A,0)),IF(B23=2,INDEX(技能卡分表!H:H,MATCH(A23,技能卡分表!A:A,0)),0)) -> 3 | F23: =IF(B23=1,INDEX(单位卡分表!P:P,MATCH(A23,单位卡分表!A:A,0)),IF(B23=2,INDEX(技能卡分表!P:P,MATCH(A23,技能卡分表!A:A,0)),0)) -> 在场时：每有一个我方单位入场，对随机敌方单位造成{0}伤害 | G23: =IF(B23=1,INDEX(单位卡分表!Q:Q,MATCH(A23,单位卡分表!A:A,0)),IF(B23=2,INDEX(技能卡分表!Q:Q,MATCH(A23,技能卡分表!A:A,0)),"")) -> 0
A24: 20039 | B24: 2 | C24: =IF(B24=1,INDEX(单位卡分表!B:B,MATCH(A24,单位卡分表!A:A,0)),IF(B24=2,INDEX(技能卡分表!B:B,MATCH(A24,技能卡分表!A:A,0)),0)) -> 战术核武 | D24: =IF(B24=1,INDEX(单位卡分表!G:G,MATCH(A24,单位卡分表!A:A,0)),IF(B24=2,INDEX(技能卡分表!G:G,MATCH(A24,技能卡分表!A:A,0)),0)) -> 4 | E24: =IF(B24=1,INDEX(单位卡分表!H:H,MATCH(A24,单位卡分表!A:A,0)),IF(B24=2,INDEX(技能卡分表!H:H,MATCH(A24,技能卡分表!A:A,0)),0)) -> 4 | F24: =IF(B24=1,INDEX(单位卡分表!P:P,MATCH(A24,单位卡分表!A:A,0)),IF(B24=2,INDEX(技能卡分表!P:P,MATCH(A24,技能卡分表!A:A,0)),0)) -> 保留，对所有单位和场景物件造成{0}点伤害并点燃 | G24: =IF(B24=1,INDEX(单位卡分表!Q:Q,MATCH(A24,单位卡分表!A:A,0)),IF(B24=2,INDEX(技能卡分表!Q:Q,MATCH(A24,技能卡分表!A:A,0)),"")) -> 敌我双方都受伤，位置为战场中心，并且有力向周围，隐藏参数推动力{1}
A25: 10020 | B25: 1 | C25: =IF(B25=1,INDEX(单位卡分表!B:B,MATCH(A25,单位卡分表!A:A,0)),IF(B25=2,INDEX(技能卡分表!B:B,MATCH(A25,技能卡分表!A:A,0)),0)) -> 时钟 晨曦 | D25: =IF(B25=1,INDEX(单位卡分表!G:G,MATCH(A25,单位卡分表!A:A,0)),IF(B25=2,INDEX(技能卡分表!G:G,MATCH(A25,技能卡分表!A:A,0)),0)) -> 5 | E25: =IF(B25=1,INDEX(单位卡分表!H:H,MATCH(A25,单位卡分表!A:A,0)),IF(B25=2,INDEX(技能卡分表!H:H,MATCH(A25,技能卡分表!A:A,0)),0)) -> 3 | F25: =IF(B25=1,INDEX(单位卡分表!P:P,MATCH(A25,单位卡分表!A:A,0)),IF(B25=2,INDEX(技能卡分表!P:P,MATCH(A25,技能卡分表!A:A,0)),0)) -> 本局战斗：每打出一次，攻击力永久+{0} | G25: =IF(B25=1,INDEX(单位卡分表!Q:Q,MATCH(A25,单位卡分表!A:A,0)),IF(B25=2,INDEX(技能卡分表!Q:Q,MATCH(A25,技能卡分表!A:A,0)),"")) -> 0
... A31: 10023 | B31: 1 | C31: =IF(B31=1,INDEX(单位卡分表!B:B,MATCH(A31,单位卡分表!A:A,0)),IF(B31=2,INDEX(技能卡分表!B:B,MATCH(A31,技能卡分表!A:A,0)),0)) -> 牙膏 露洁 爱丽儿（Ariel 小美人鱼） | D31: =IF(B31=1,INDEX(单位卡分表!G:G,MATCH(A31,单位卡分表!A:A,0)),IF(B31=2,INDEX(技能卡分表!G:G,MATCH(A31,技能卡分表!A:A,0)),0)) -> 4 | E31: =IF(B31=1,INDEX(单位卡分表!H:H,MATCH(A31,单位卡分表!A:A,0)),IF(B31=2,INDEX(技能卡分表!H:H,MATCH(A31,技能卡分表!A:A,0)),0)) -> 4 | F31: =IF(B31=1,INDEX(单位卡分表!P:P,MATCH(A31,单位卡分表!A:A,0)),IF(B31=2,INDEX(技能卡分表!P:P,MATCH(A31,技能卡分表!A:A,0)),0)) -> 回合结束时：分裂出{0}个分裂体 | G31: =IF(B31=1,INDEX(单位卡分表!Q:Q,MATCH(A31,单位卡分表!A:A,0)),IF(B31=2,INDEX(技能卡分表!Q:Q,MATCH(A31,技能卡分表!A:A,0)),"")) -> 0

Sheet 卡牌数值表
C4: 一级ID | D4: 是否注释 | E4: 卡牌名 | F4: 技能效果 | G4: 效果备注 | H4: 特性ID | I4: 技能类型 | J4: 价格 | K4: 卡牌类型 | L4: 参考攻击 | M4: 参考生命 | N4: 发射速度 | O4: 体积 | P4: 质量 | Q4: 摩擦力 | R4: 空气摩擦力 | S4: 最长存在时间 | T4: 失效类型 | U4: 失效参数 | V4: 是否展示ICON | W4: 技能参数1 | X4: 技能参数2 | Y4: 技能参数3 | Z4: 技能参数4 | AA4: 技能参数5 | AB4: 技能参数6 | AC4: 技能参数7
C5: 10010 | E5: =IF(LEFT(C5,1)="1",IFERROR(INDEX(单位卡分表!B:B,MATCH(C5,单位卡分表!A:A,0)),"未找到"),IF(LEFT(C5,1)="2",IFERROR(INDEX(技能卡分表!B:B,MATCH(C5,技能卡分表!A:A,0)),"未找到"),IF(LEFT(C5,1)="3",IFERROR(INDEX('永久加成分表（废弃）'!B:B,MATCH(C5,'永久加成分表（废弃）'!A:A,0)),"未找到"),IF(LEFT(C5,1)="4",IFERROR(INDEX(组件分表!C:C,MATCH(VALUE(LEFT(C5,4)),组件分表!A:A,0)),"未找到"),"不匹配")))) -> 电吉他 和鸣 | F5: =IF(LEFT(C5,1)="1",IFERROR(INDEX(单位卡分表!P:P,MATCH(C5,单位卡分表!A:A,0)),"未找到"),IF(LEFT(C5,1)="2",IFERROR(INDEX(技能卡分表!P:P,MATCH(C5,技能卡分表!A:A,0)),"未找到"),IF(LEFT(C5,1)="3",IFERROR(INDEX('永久加成分表（废弃）'!N:N,MATCH(C5,'永久加成分表（废弃）'!A:A,0)),"未找到"),IF(LEFT(C5,1)="4",IFERROR(INDEX(组件分表!L:L,MATCH(VALUE(LEFT(C5,4)),组件分表!A:A,0)),"未找到"),"不匹配")))) -> 回合结束时：我方每有一个在场单位，为我方英雄永久+{0}生命 | G5: =IF(LEFT(C5,1)="1",IFERROR(INDEX(单位卡分表!Q:Q,MATCH(C5,单位卡分表!A:A,0)),"未找到"),IF(LEFT(C5,1)="2",IFERROR(INDEX(技能卡分表!Q:Q,MATCH(C5,技能卡分表!A:A,0)),"未找到"),IF(LEFT(C5,1)="3",IFERROR(INDEX('永久加成分表（废弃）'!O:O,MATCH(C5,'永久加成分表（废弃）'!A:A,0)),"未找到"),IF(LEFT(C5,1)="4",IFERROR(INDEX(组件分表!S:S,MATCH(VALUE(LEFT(C5,4)),组件分表!A:A,0)),"未找到"),"不匹配")))) -> 注意统一以造成的实际伤害论，打到1血单位，算造成1伤害 | H5: =C5*10+1 -> 100101 | I5: =IF(LEFT(C5,1)="1",IFERROR(IF(INDEX(单位卡分表!AG:AG,MATCH(C5,单位卡分表!A:A,0))=0,"",INDEX(单位卡分表!AG:AG,MATCH(C5,单位卡分表!A:A,0))),"未找到"),IF(LEFT(C5,1)="2",IFERROR(IF(INDEX(技能卡分表!AG:AG,MATCH(C5,技能卡分表!A:A,0))=0,"",INDEX(技能卡分表!AG:AG,MATCH(C5,技能卡分表!A:A,0))),"未找到"),IF(LEFT(C5,1)="3",IFERROR(IF(INDEX('永久加成分表（废弃）'!AF:AF,MATCH(C5,'永久加成分表（废弃）'!A:A,0))=0,"",INDEX('永久加成分表（废弃）'!AF:AF,MATCH(C5,'永久加成分表（废弃）'!A:A,0))),"未找到"),IF(LEFT(C5,1)="4",IFERROR(IF(INDEX(组件分表!R:R,MATCH(VALUE(LEFT(C5,4)),组件分表!A:A,0))=0,"",INDEX(组件分表!R:R,MATCH(VALUE(LEFT(C5,4)),组件分表!A:A,0))),"未找到"),"不匹配")))) -> CollisionCauseDamage2RandomEnemy | K5: =IF(LEFT(C5,1)="1",IFERROR(CHOOSE(MATCH(INDEX(单位卡分表!C:C,MATCH(C5,单位卡分表!A:A,0)),{1,4,6},0),"单位卡","英雄卡","雇佣兵卡"),""),"") -> 单位卡 | L5: 5 | M5: 30 | N5: 13.6 | O5: 0.65 | P5: 0.12 | Q5: 1.66 | R5: 1.47 | T5: =IFERROR(IF(LEFT(C5,1)="1",IF(INDEX(单位卡分表!AE:AE,MATCH(C5,单位卡分表!A:A,0))=0,"",INDEX(单位卡分表!AE:AE,MATCH(C5,单位卡分表!A:A,0))),IF(LEFT(C5,1)="2",IF(INDEX(技能卡分表!AE:AE,MATCH(C5,技能卡分表!A:A,0))=0,"",INDEX(技能卡分表!AE:AE,MATCH(C5,技能卡分表!A:A,0))),IF(LEFT(C5,1)="4",IF(INDEX(组件分表!W:W,MATCH(VALUE(LEFT(C5,4)),组件分表!A:A,0))=0,"",INDEX(组件分表!W:W,MATCH(VALUE(LEFT(C5,4)),组件分表!A:A,0))),""))),"") | U5: =IFERROR(IF(LEFT(C5,1)="1",IF(INDEX(单位卡分表!AF:AF,MATCH(C5,单位卡分表!A:A,0))=0,"",INDEX(单位卡分表!AF:AF,MATCH(C5,单位卡分表!A:A,0))),IF(LEFT(C5,1)="2",IF(INDEX(技能卡分表!AF:AF,MATCH(C5,技能卡分表!A:A,0))=0,"",INDEX(技能卡分表!AF:AF,MATCH(C5,技能卡分表!A:A,0))),IF(LEFT(C5,1)="4",IF(INDEX(组件分表!X:X,MATCH(VALUE(LEFT(C5,4)),组件分表!A:A,0))=0,"",INDEX(组件分表!X:X,MATCH(VALUE(LEFT(C5,4)),组件分表!A:A,0))),""))),"") | V5: FALSE | W5: 8
C6: 10011 | E6: =IF(LEFT(C6,1)="1",IFERROR(INDEX(单位卡分表!B:B,MATCH(C6,单位卡分表!A:A,0)),"未找到"),IF(LEFT(C6,1)="2",IFERROR(INDEX(技能卡分表!B:B,MATCH(C6,技能卡分表!A:A,0)),"未找到"),IF(LEFT(C6,1)="3",IFERROR(INDEX('永久加成分表（废弃）'!B:B,MATCH(C6,'永久加成分表（废弃）'!A:A,0)),"未找到"),IF(LEFT(C6,1)="4",IFERROR(INDEX(组件分表!C:C,MATCH(VALUE(LEFT(C6,4)),组件分表!A:A,0)),"未找到"),"不匹配")))) -> 纸巾 缠缠 | F6: =IF(LEFT(C6,1)="1",IFERROR(INDEX(单位卡分表!P:P,MATCH(C6,单位卡分表!A:A,0)),"未找到"),IF(LEFT(C6,1)="2",IFERROR(INDEX(技能卡分表!P:P,MATCH(C6,技能卡分表!A:A,0)),"未找到"),IF(LEFT(C6,1)="3",IFERROR(INDEX('永久加成分表（废弃）'!N:N,MATCH(C6,'永久加成分表（废弃）'!A:A,0)),"未找到"),IF(LEFT(C6,1)="4",IFERROR(INDEX(组件分表!L:L,MATCH(VALUE(LEFT(C6,4)),组件分表!A:A,0)),"未找到"),"不匹配")))) -> 对同一敌方单位每多碰撞一次，伤害增加{0}% | G6: =IF(LEFT(C6,1)="1",IFERROR(INDEX(单位卡分表!Q:Q,MATCH(C6,单位卡分表!A:A,0)),"未找到"),IF(LEFT(C6,1)="2",IFERROR(INDEX(技能卡分表!Q:Q,MATCH(C6,技能卡分表!A:A,0)),"未找到"),IF(LEFT(C6,1)="3",IFERROR(INDEX('永久加成分表（废弃）'!O:O,MATCH(C6,'永久加成分表（废弃）'!A:A,0)),"未找到"),IF(LEFT(C6,1)="4",IFERROR(INDEX(组件分表!S:S,MATCH(VALUE(LEFT(C6,4)),组件分表!A:A,0)),"未找到"),"不匹配")))) -> 可以加上标记，伤害向上取整，先加后乘。每回合最多触发{1}次 | H6: =C6*10+1 -> 100111 | I6: =IF(LEFT(C6,1)="1",IFERROR(IF(INDEX(单位卡分表!AG:AG,MATCH(C6,单位卡分表!A:A,0))=0,"",INDEX(单位卡分表!AG:AG,MATCH(C6,单位卡分表!A:A,0))),"未找到"),IF(LEFT(C6,1)="2",IFERROR(IF(INDEX(技能卡分表!AG:AG,MATCH(C6,技能卡分表!A:A,0))=0,"",INDEX(技能卡分表!AG:AG,MATCH(C6,技能卡分表!A:A,0))),"未找到"),IF(LEFT(C6,1)="3",IFERROR(IF(INDEX('永久加成分表（废弃）'!AF:AF,MATCH(C6,'永久加成分表（废弃）'!A:A,0))=0,"",INDEX('永久加成分表（废弃）'!AF:AF,MATCH(C6,'永久加成分表（废弃）'!A:A,0))),"未找到"),IF(LEFT(C6,1)="4",IFERROR(IF(INDEX(组件分表!R:R,MATCH(VALUE(LEFT(C6,4)),组件分表!A:A,0))=0,"",INDEX(组件分表!R:R,MATCH(VALUE(LEFT(C6,4)),组件分表!A:A,0))),"未找到"),"不匹配")))) -> CauseDamageByCollisionTimes | K6: =IF(LEFT(C6,1)="1",IFERROR(CHOOSE(MATCH(INDEX(单位卡分表!C:C,MATCH(C6,单位卡分表!A:A,0)),{1,4,6},0),"单位卡","英雄卡","雇佣兵卡"),""),"") -> 雇佣兵卡 | L6: 8 | M6: 1 | N6: 11.4 | O6: 0.5 | P6: 0.1 | Q6: 0.44 | R6: 1.47 | T6: =IFERROR(IF(LEFT(C6,1)="1",IF(INDEX(单位卡分表!AE:AE,MATCH(C6,单位卡分表!A:A,0))=0,"",INDEX(单位卡分表!AE:AE,MATCH(C6,单位卡分表!A:A,0))),IF(LEFT(C6,1)="2",IF(INDEX(技能卡分表!AE:AE,MATCH(C6,技能卡分表!A:A,0))=0,"",INDEX(技能卡分表!AE:AE,MATCH(C6,技能卡分表!A:A,0))),IF(LEFT(C6,1)="4",IF(INDEX(组件分表!W:W,MATCH(VALUE(LEFT(C6,4)),组件分表!A:A,0))=0,"",INDEX(组件分表!W:W,MATCH(VALUE(LEFT(C6,4)),组件分表!A:A,0))),""))),"") | U6: =IFERROR(IF(LEFT(C6,1)="1",IF(INDEX(单位卡分表!AF:AF,MATCH(C6,单位卡分表!A:A,0))=0,"",INDEX(单位卡分表!AF:AF,MATCH(C6,单位卡分表!A:A,0))),IF(LEFT(C6,1)="2",IF(INDEX(技能卡分表!AF:AF,MATCH(C6,技能卡分表!A:A,0))=0,"",INDEX(技能卡分表!AF:AF,MATCH(C6,技能卡分表!A:A,0))),IF(LEFT(C6,1)="4",IF(INDEX(组件分表!X:X,MATCH(VALUE(LEFT(C6,4)),组件分表!A:A,0))=0,"",INDEX(组件分表!X:X,MATCH(VALUE(LEFT(C6,4)),组件分表!A:A,0))),""))),"") | V6: FALSE | W6: 50 | X6: 100
C7: 10012 | E7: =IF(LEFT(C7,1)="1",IFERROR(INDEX(单位卡分表!B:B,MATCH(C7,单位卡分表!A:A,0)),"未找到"),IF(LEFT(C7,1)="2",IFERROR(INDEX(技能卡分表!B:B,MATCH(C7,技能卡分表!A:A,0)),"未找到"),IF(LEFT(C7,1)="3",IFERROR(INDEX('永久加成分表（废弃）'!B:B,MATCH(C7,'永久加成分表（废弃）'!A:A,0)),"未找到"),IF(LEFT(C7,1)="4",IFERROR(INDEX(组件分表!C:C,MATCH(VALUE(LEFT(C7,4)),组件分表!A:A,0)),"未找到"),"不匹配")))) -> 摩托 赤狸 塞琳娜 | F7: =IF(LEFT(C7,1)="1",IFERROR(INDEX(单位卡分表!P:P,MATCH(C7,单位卡分表!A:A,0)),"未找到"),IF(LEFT(C7,1)="2",IFERROR(INDEX(技能卡分表!P:P,MATCH(C7,技能卡分表!A:A,0)),"未找到"),IF(LEFT(C7,1)="3",IFERROR(INDEX('永久加成分表（废弃）'!N:N,MATCH(C7,'永久加成分表（废弃）'!A:A,0)),"未找到"),IF(LEFT(C7,1)="4",IFERROR(INDEX(组件分表!L:L,MATCH(VALUE(LEFT(C7,4)),组件分表!A:A,0)),"未找到"),"不匹配")))) -> 首次碰撞友方时，对其施加推力 | G7: =IF(LEFT(C7,1)="1",IFERROR(INDEX(单位卡分表!Q:Q,MATCH(C7,单位卡分表!A:A,0)),"未找到"),IF(LEFT(C7,1)="2",IFERROR(INDEX(技能卡分表!Q:Q,MATCH(C7,技能卡分表!A:A,0)),"未找到"),IF(LEFT(C7,1)="3",IFERROR(INDEX('永久加成分表（废弃）'!O:O,MATCH(C7,'永久加成分表（废弃）'!A:A,0)),"未找到"),IF(LEFT(C7,1)="4",IFERROR(INDEX(组件分表!S:S,MATCH(VALUE(LEFT(C7,4)),组件分表!A:A,0)),"未找到"),"不匹配")))) -> 隐藏推力{0} | H7: =C7*10+1 -> 100121 | I7: =IF(LEFT(C7,1)="1",IFERROR(IF(INDEX(单位卡分表!AG:AG,MATCH(C7,单位卡分表!A:A,0))=0,"",INDEX(单位卡分表!AG:AG,MATCH(C7,单位卡分表!A:A,0))),"未找到"),IF(LEFT(C7,1)="2",IFERROR(IF(INDEX(技能卡分表!AG:AG,MATCH(C7,技能卡分表!A:A,0))=0,"",INDEX(技能卡分表!AG:AG,MATCH(C7,技能卡分表!A:A,0))),"未找到"),IF(LEFT(C7,1)="3",IFERROR(IF(INDEX('永久加成分表（废弃）'!AF:AF,MATCH(C7,'永久加成分表（废弃）'!A:A,0))=0,"",INDEX('永久加成分表（废弃）'!AF:AF,MATCH(C7,'永久加成分表（废弃）'!A:A,0))),"未找到"),IF(LEFT(C7,1)="4",IFERROR(IF(INDEX(组件分表!R:R,MATCH(VALUE(LEFT(C7,4)),组件分表!A:A,0))=0,"",INDEX(组件分表!R:R,MATCH(VALUE(LEFT(C7,4)),组件分表!A:A,0))),"未找到"),"不匹配")))) -> CollisionHeroAddForceOnce | K7: =IF(LEFT(C7,1)="1",IFERROR(CHOOSE(MATCH(INDEX(单位卡分表!C:C,MATCH(C7,单位卡分表!A:A,0)),{1,4,6},0),"单位卡","英雄卡","雇佣兵卡"),""),"") -> 雇佣兵卡 | L7: 8 | M7: 1 | N7: 11.4 | O7: 0.5 | P7: 0.1 | Q7: 0.44 | R7: 1.47 | T7: =IFERROR(IF(LEFT(C7,1)="1",IF(INDEX(单位卡分表!AE:AE,MATCH(C7,单位卡分表!A:A,0))=0,"",INDEX(单位卡分表!AE:AE,MATCH(C7,单位卡分表!A:A,0))),IF(LEFT(C7,1)="2",IF(INDEX(技能卡分表!AE:AE,MATCH(C7,技能卡分表!A:A,0))=0,"",INDEX(技能卡分表!AE:AE,MATCH(C7,技能卡分表!A:A,0))),IF(LEFT(C7,1)="4",IF(INDEX(组件分表!W:W,MATCH(VALUE(LEFT(C7,4)),组件分表!A:A,0))=0,"",INDEX(组件分表!W:W,MATCH(VALUE(LEFT(C7,4)),组件分表!A:A,0))),""))),"") -> Times | U7: =IFERROR(IF(LEFT(C7,1)="1",IF(INDEX(单位卡分表!AF:AF,MATCH(C7,单位卡分表!A:A,0))=0,"",INDEX(单位卡分表!AF:AF,MATCH(C7,单位卡分表!A:A,0))),IF(LEFT(C7,1)="2",IF(INDEX(技能卡分表!AF:AF,MATCH(C7,技能卡分表!A:A,0))=0,"",INDEX(技能卡分表!AF:AF,MATCH(C7,技能卡分表!A:A,0))),IF(LEFT(C7,1)="4",IF(INDEX(组件分表!X:X,MATCH(VALUE(LEFT(C7,4)),组件分表!A:A,0))=0,"",INDEX(组件分表!X:X,MATCH(VALUE(LEFT(C7,4)),组件分表!A:A,0))),""))),"") -> 1 | V7: FALSE | W7: 6
C8: 10013 | E8: =IF(LEFT(C8,1)="1",IFERROR(INDEX(单位卡分表!B:B,MATCH(C8,单位卡分表!A:A,0)),"未找到"),IF(LEFT(C8,1)="2",IFERROR(INDEX(技能卡分表!B:B,MATCH(C8,技能卡分表!A:A,0)),"未找到"),IF(LEFT(C8,1)="3",IFERROR(INDEX('永久加成分表（废弃）'!B:B,MATCH(C8,'永久加成分表（废弃）'!A:A,0)),"未找到"),IF(LEFT(C8,1)="4",IFERROR(INDEX(组件分表!C:C,MATCH(VALUE(LEFT(C8,4)),组件分表!A:A,0)),"未找到"),"不匹配")))) -> 雨伞 守心 布洛莉Brolly | F8: =IF(LEFT(C8,1)="1",IFERROR(INDEX(单位卡分表!P:P,MATCH(C8,单位卡分表!A:A,0)),"未找到"),IF(LEFT(C8,1)="2",IFERROR(INDEX(技能卡分表!P:P,MATCH(C8,技能卡分表!A:A,0)),"未找到"),IF(LEFT(C8,1)="3",IFERROR(INDEX('永久加成分表（废弃）'!N:N,MATCH(C8,'永久加成分表（废弃）'!A:A,0)),"未找到"),IF(LEFT(C8,1)="4",IFERROR(INDEX(组件分表!L:L,MATCH(VALUE(LEFT(C8,4)),组件分表!A:A,0)),"未找到"),"不匹配")))) -> 碰撞友方时，为其添加圣盾 | G8: =IF(LEFT(C8,1)="1",IFERROR(INDEX(单位卡分表!Q:Q,MATCH(C8,单位卡分表!A:A,0)),"未找到"),IF(LEFT(C8,1)="2",IFERROR(INDEX(技能卡分表!Q:Q,MATCH(C8,技能卡分表!A:A,0)),"未找到"),IF(LEFT(C8,1)="3",IFERROR(INDEX('永久加成分表（废弃）'!O:O,MATCH(C8,'永久加成分表（废弃）'!A:A,0)),"未找到"),IF(LEFT(C8,1)="4",IFERROR(INDEX(组件分表!S:S,MATCH(VALUE(LEFT(C8,4)),组件分表!A:A,0)),"未找到"),"不匹配")))) -> 隐藏触发上限{0}次 | H8: =C8*10+1 -> 100131 | I8: =IF(LEFT(C8,1)="1",IFERROR(IF(INDEX(单位卡分表!AG:AG,MATCH(C8,单位卡分表!A:A,0))=0,"",INDEX(单位卡分表!AG:AG,MATCH(C8,单位卡分表!A:A,0))),"未找到"),IF(LEFT(C8,1)="2",IFERROR(IF(INDEX(技能卡分表!AG:AG,MATCH(C8,技能卡分表!A:A,0))=0,"",INDEX(技能卡分表!AG:AG,MATCH(C8,技能卡分表!A:A,0))),"未找到"),IF(LEFT(C8,1)="3",IFERROR(IF(INDEX('永久加成分表（废弃）'!AF:AF,MATCH(C8,'永久加成分表（废弃）'!A:A,0))=0,"",INDEX('永久加成分表（废弃）'!AF:AF,MATCH(C8,'永久加成分表（废弃）'!A:A,0))),"未找到"),IF(LEFT(C8,1)="4",IFERROR(IF(INDEX(组件分表!R:R,MATCH(VALUE(LEFT(C8,4)),组件分表!A:A,0))=0,"",INDEX(组件分表!R:R,MATCH(VALUE(LEFT(C8,4)),组件分表!A:A,0))),"未找到"),"不匹配")))) -> AddShieldToCollisionTeammate | K8: =IF(LEFT(C8,1)="1",IFERROR(CHOOSE(MATCH(INDEX(单位卡分表!C:C,MATCH(C8,单位卡分表!A:A,0)),{1,4,6},0),"单位卡","英雄卡","雇佣兵卡"),""),"") -> 雇佣兵卡 | L8: 3 | M8: 1 | N8: 11.4 | O8: 0.5 | P8: 0.1 | Q8: 0.44 | R8: 1.47 | T8: =IFERROR(IF(LEFT(C8,1)="1",IF(INDEX(单位卡分表!AE:AE,MATCH(C8,单位卡分表!A:A,0))=0,"",INDEX(单位卡分表!AE:AE,MATCH(C8,单位卡分表!A:A,0))),IF(LEFT(C8,1)="2",IF(INDEX(技能卡分表!AE:AE,MATCH(C8,技能卡分表!A:A,0))=0,"",INDEX(技能卡分表!AE:AE,MATCH(C8,技能卡分表!A:A,0))),IF(LEFT(C8,1)="4",IF(INDEX(组件分表!W:W,MATCH(VALUE(LEFT(C8,4)),组件分表!A:A,0))=0,"",INDEX(组件分表!W:W,MATCH(VALUE(LEFT(C8,4)),组件分表!A:A,0))),""))),"") | U8: =IFERROR(IF(LEFT(C8,1)="1",IF(INDEX(单位卡分表!AF:AF,MATCH(C8,单位卡分表!A:A,0))=0,"",INDEX(单位卡分表!AF:AF,MATCH(C8,单位卡分表!A:A,0))),IF(LEFT(C8,1)="2",IF(INDEX(技能卡分表!AF:AF,MATCH(C8,技能卡分表!A:A,0))=0,"",INDEX(技能卡分表!AF:AF,MATCH(C8,技能卡分表!A:A,0))),IF(LEFT(C8,1)="4",IF(INDEX(组件分表!X:X,MATCH(VALUE(LEFT(C8,4)),组件分表!A:A,0))=0,"",INDEX(组件分表!X:X,MATCH(VALUE(LEFT(C8,4)),组件分表!A:A,0))),""))),"") | V8: FALSE | W8: 100
C9: 10014 | E9: =IF(LEFT(C9,1)="1",IFERROR(INDEX(单位卡分表!B:B,MATCH(C9,单位卡分表!A:A,0)),"未找到"),IF(LEFT(C9,1)="2",IFERROR(INDEX(技能卡分表!B:B,MATCH(C9,技能卡分表!A:A,0)),"未找到"),IF(LEFT(C9,1)="3",IFERROR(INDEX('永久加成分表（废弃）'!B:B,MATCH(C9,'永久加成分表（废弃）'!A:A,0)),"未找到"),IF(LEFT(C9,1)="4",IFERROR(INDEX(组件分表!C:C,MATCH(VALUE(LEFT(C9,4)),组件分表!A:A,0)),"未找到"),"不匹配")))) -> 茶壶 灵愈 波西娅Potsia | F9: =IF(LEFT(C9,1)="1",IFERROR(INDEX(单位卡分表!P:P,MATCH(C9,单位卡分表!A:A,0)),"未找到"),IF(LEFT(C9,1)="2",IFERROR(INDEX(技能卡分表!P:P,MATCH(C9,技能卡分表!A:A,0)),"未找到"),IF(LEFT(C9,1)="3",IFERROR(INDEX('永久加成分表（废弃）'!N:N,MATCH(C9,'永久加成分表（废弃）'!A:A,0)),"未找到"),IF(LEFT(C9,1)="4",IFERROR(INDEX(组件分表!L:L,MATCH(VALUE(LEFT(C9,4)),组件分表!A:A,0)),"未找到"),"不匹配")))) -> 碰撞友方时，为其恢复{0}点生命 | G9: =IF(LEFT(C9,1)="1",IFERROR(INDEX(单位卡分表!Q:Q,MATCH(C9,单位卡分表!A:A,0)),"未找到"),IF(LEFT(C9,1)="2",IFERROR(INDEX(技能卡分表!Q:Q,MATCH(C9,技能卡分表!A:A,0)),"未找到"),IF(LEFT(C9,1)="3",IFERROR(INDEX('永久加成分表（废弃）'!O:O,MATCH(C9,'永久加成分表（废弃）'!A:A,0)),"未找到"),IF(LEFT(C9,1)="4",IFERROR(INDEX(组件分表!S:S,MATCH(VALUE(LEFT(C9,4)),组件分表!A:A,0)),"未找到"),"不匹配")))) -> 敌方回合也生效。隐藏触发上限{1}次 | H9: =C9*10+1 -> 100141 | I9: =IF(LEFT(C9,1)="1",IFERROR(IF(INDEX(单位卡分表!AG:AG,MATCH(C9,单位卡分表!A:A,0))=0,"",INDEX(单位卡分表!AG:AG,MATCH(C9,单位卡分表!A:A,0))),"未找到"),IF(LEFT(C9,1)="2",IFERROR(IF(INDEX(技能卡分表!AG:AG,MATCH(C9,技能卡分表!A:A,0))=0,"",INDEX(技能卡分表!AG:AG,MATCH(C9,技能卡分表!A:A,0))),"未找到"),IF(LEFT(C9,1)="3",IFERROR(IF(INDEX('永久加成分表（废弃）'!AF:AF,MATCH(C9,'永久加成分表（废弃）'!A:A,0))=0,"",INDEX('永久加成分表（废弃）'!AF:AF,MATCH(C9,'永久加成分表（废弃）'!A:A,0))),"未找到"),IF(LEFT(C9,1)="4",IFERROR(IF(INDEX(组件分表!R:R,MATCH(VALUE(LEFT(C9,4)),组件分表!A:A,0))=0,"",INDEX(组件分表!R:R,MATCH(VALUE(LEFT(C9,4)),组件分表!A:A,0))),"未找到"),"不匹配")))) -> CollisionTeammateRecoverHp | K9: =IF(LEFT(C9,1)="1",IFERROR(CHOOSE(MATCH(INDEX(单位卡分表!C:C,MATCH(C9,单位卡分表!A:A,0)),{1,4,6},0),"单位卡","英雄卡","雇佣兵卡"),""),"") -> 雇佣兵卡 | L9: 1 | M9: 1 | N9: 11.4 | O9: 0.5 | P9: 0.1 | Q9: 0.44 | R9: 1.47 | T9: =IFERROR(IF(LEFT(C9,1)="1",IF(INDEX(单位卡分表!AE:AE,MATCH(C9,单位卡分表!A:A,0))=0,"",INDEX(单位卡分表!AE:AE,MATCH(C9,单位卡分表!A:A,0))),IF(LEFT(C9,1)="2",IF(INDEX(技能卡分表!AE:AE,MATCH(C9,技能卡分表!A:A,0))=0,"",INDEX(技能卡分表!AE:AE,MATCH(C9,技能卡分表!A:A,0))),IF(LEFT(C9,1)="4",IF(INDEX(组件分表!W:W,MATCH(VALUE(LEFT(C9,4)),组件分表!A:A,0))=0,"",INDEX(组件分表!W:W,MATCH(VALUE(LEFT(C9,4)),组件分表!A:A,0))),""))),"") | U9: =IFERROR(IF(LEFT(C9,1)="1",IF(INDEX(单位卡分表!AF:AF,MATCH(C9,单位卡分表!A:A,0))=0,"",INDEX(单位卡分表!AF:AF,MATCH(C9,单位卡分表!A:A,0))),IF(LEFT(C9,1)="2",IF(INDEX(技能卡分表!AF:AF,MATCH(C9,技能卡分表!A:A,0))=0,"",INDEX(技能卡分表!AF:AF,MATCH(C9,技能卡分表!A:A,0))),IF(LEFT(C9,1)="4",IF(INDEX(组件分表!X:X,MATCH(VALUE(LEFT(C9,4)),组件分表!A:A,0))=0,"",INDEX(组件分表!X:X,MATCH(VALUE(LEFT(C9,4)),组件分表!A:A,0))),""))),"") | V9: FALSE | W9: 20 | X9: 100
C10: 10015 | E10: =IF(LEFT(C10,1)="1",IFERROR(INDEX(单位卡分表!B:B,MATCH(C10,单位卡分表!A:A,0)),"未找到"),IF(LEFT(C10,1)="2",IFERROR(INDEX(技能卡分表!B:B,MATCH(C10,技能卡分表!A:A,0)),"未找到"),IF(LEFT(C10,1)="3",IFERROR(INDEX('永久加成分表（废弃）'!B:B,MATCH(C10,'永久加成分表（废弃）'!A:A,0)),"未找到"),IF(LEFT(C10,1)="4",IFERROR(INDEX(组件分表!C:C,MATCH(VALUE(LEFT(C10,4)),组件分表!A:A,0)),"未找到"),"不匹配")))) -> 留声机 回音 玛利亚 | F10: =IF(LEFT(C10,1)="1",IFERROR(INDEX(单位卡分表!P:P,MATCH(C10,单位卡分表!A:A,0)),"未找到"),IF(LEFT(C10,1)="2",IFERROR(INDEX(技能卡分表!P:P,MATCH(C10,技能卡分表!A:A,0)),"未找到"),IF(LEFT(C10,1)="3",IFERROR(INDEX('永久加成分表（废弃）'!N:N,MATCH(C10,'永久加成分表（废弃）'!A:A,0)),"未找到"),IF(LEFT(C10,1)="4",IFERROR(INDEX(组件分表!L:L,MATCH(VALUE(LEFT(C10,4)),组件分表!A:A,0)),"未找到"),"不匹配")))) -> 回合结束时：对随机敌方单位造成{0}点伤害，每有{1}连击，伤害+{2} | G10: =IF(LEFT(C10,1)="1",IFERROR(INDEX(单位卡分表!Q:Q,MATCH(C10,单位卡分表!A:A,0)),"未找到"),IF(LEFT(C10,1)="2",IFERROR(INDEX(技能卡分表!Q:Q,MATCH(C10,技能卡分表!A:A,0)),"未找到"),IF(LEFT(C10,1)="3",IFERROR(INDEX('永久加成分表（废弃）'!O:O,MATCH(C10,'永久加成分表（废弃）'!A:A,0)),"未找到"),IF(LEFT(C10,1)="4",IFERROR(INDEX(组件分表!S:S,MATCH(VALUE(LEFT(C10,4)),组件分表!A:A,0)),"未找到"),"不匹配")))) -> 0 | H10: =C10*10+1 -> 100151 | I10: =IF(LEFT(C10,1)="1",IFERROR(IF(INDEX(单位卡分表!AG:AG,MATCH(C10,单位卡分表!A:A,0))=0,"",INDEX(单位卡分表!AG:AG,MATCH(C10,单位卡分表!A:A,0))),"未找到"),IF(LEFT(C10,1)="2",IFERROR(IF(INDEX(技能卡分表!AG:AG,MATCH(C10,技能卡分表!A:A,0))=0,"",INDEX(技能卡分表!AG:AG,MATCH(C10,技能卡分表!A:A,0))),"未找到"),IF(LEFT(C10,1)="3",IFERROR(IF(INDEX('永久加成分表（废弃）'!AF:AF,MATCH(C10,'永久加成分表（废弃）'!A:A,0))=0,"",INDEX('永久加成分表（废弃）'!AF:AF,MATCH(C10,'永久加成分表（废弃）'!A:A,0))),"未找到"),IF(LEFT(C10,1)="4",IFERROR(IF(INDEX(组件分表!R:R,MATCH(VALUE(LEFT(C10,4)),组件分表!A:A,0))=0,"",INDEX(组件分表!R:R,MATCH(VALUE(LEFT(C10,4)),组件分表!A:A,0))),"未找到"),"不匹配")))) -> CausePercentAttackDamageByComboCounts | K10: =IF(LEFT(C10,1)="1",IFERROR(CHOOSE(MATCH(INDEX(单位卡分表!C:C,MATCH(C10,单位卡分表!A:A,0)),{1,4,6},0),"单位卡","英雄卡","雇佣兵卡"),""),"") -> 单位卡 | L10: 2 | M10: 40 | N10: 13.6 | O10: 0.65 | P10: 0.12 | Q10: 1.66 | R10: 1.47 | T10: =IFERROR(IF(LEFT(C10,1)="1",IF(INDEX(单位卡分表!AE:AE,MATCH(C10,单位卡分表!A:A,0))=0,"",INDEX(单位卡分表!AE:AE,MATCH(C10,单位卡分表!A:A,0))),IF(LEFT(C10,1)="2",IF(INDEX(技能卡分表!AE:AE,MATCH(C10,技能卡分表!A:A,0))=0,"",INDEX(技能卡分表!AE:AE,MATCH(C10,技能卡分表!A:A,0))),IF(LEFT(C10,1)="4",IF(INDEX(组件分表!W:W,MATCH(VALUE(LEFT(C10,4)),组件分表!A:A,0))=0,"",INDEX(组件分表!W:W,MATCH(VALUE(LEFT(C10,4)),组件分表!A:A,0))),""))),"") -> Times | U10: =IFERROR(IF(LEFT(C10,1)="1",IF(INDEX(单位卡分表!AF:AF,MATCH(C10,单位卡分表!A:A,0))=0,"",INDEX(单位卡分表!AF:AF,MATCH(C10,单位卡分表!A:A,0))),IF(LEFT(C10,1)="2",IF(INDEX(技能卡分表!AF:AF,MATCH(C10,技能卡分表!A:A,0))=0,"",INDEX(技能卡分表!AF:AF,MATCH(C10,技能卡分表!A:A,0))),IF(LEFT(C10,1)="4",IF(INDEX(组件分表!X:X,MATCH(VALUE(LEFT(C10,4)),组件分表!A:A,0))=0,"",INDEX(组件分表!X:X,MATCH(VALUE(LEFT(C10,4)),组件分表!A:A,0))),""))),"") -> 1 | V10: FALSE | W10: 6 | X10: 3 | Y10: 6
C11: 10016 | E11: =IF(LEFT(C11,1)="1",IFERROR(INDEX(单位卡分表!B:B,MATCH(C11,单位卡分表!A:A,0)),"未找到"),IF(LEFT(C11,1)="2",IFERROR(INDEX(技能卡分表!B:B,MATCH(C11,技能卡分表!A:A,0)),"未找到"),IF(LEFT(C11,1)="3",IFERROR(INDEX('永久加成分表（废弃）'!B:B,MATCH(C11,'永久加成分表（废弃）'!A:A,0)),"未找到"),IF(LEFT(C11,1)="4",IFERROR(INDEX(组件分表!C:C,MATCH(VALUE(LEFT(C11,4)),组件分表!A:A,0)),"未找到"),"不匹配")))) -> 电扇 彩虹 | F11: =IF(LEFT(C11,1)="1",IFERROR(INDEX(单位卡分表!P:P,MATCH(C11,单位卡分表!A:A,0)),"未找到"),IF(LEFT(C11,1)="2",IFERROR(INDEX(技能卡分表!P:P,MATCH(C11,技能卡分表!A:A,0)),"未找到"),IF(LEFT(C11,1)="3",IFERROR(INDEX('永久加成分表（废弃）'!N:N,MATCH(C11,'永久加成分表（废弃）'!A:A,0)),"未找到"),IF(LEFT(C11,1)="4",IFERROR(INDEX(组件分表!L:L,MATCH(VALUE(LEFT(C11,4)),组件分表!A:A,0)),"未找到"),"不匹配")))) -> 在场时：我方打出的卡牌发射速度增加{0}% | G11: =IF(LEFT(C11,1)="1",IFERROR(INDEX(单位卡分表!Q:Q,MATCH(C11,单位卡分表!A:A,0)),"未找到"),IF(LEFT(C11,1)="2",IFERROR(INDEX(技能卡分表!Q:Q,MATCH(C11,技能卡分表!A:A,0)),"未找到"),IF(LEFT(C11,1)="3",IFERROR(INDEX('永久加成分表（废弃）'!O:O,MATCH(C11,'永久加成分表（废弃）'!A:A,0)),"未找到"),IF(LEFT(C11,1)="4",IFERROR(INDEX(组件分表!S:S,MATCH(VALUE(LEFT(C11,4)),组件分表!A:A,0)),"未找到"),"不匹配")))) -> 可叠加，所有百分比加成，先加后乘，AddShootCardSpeedPercent | H11: =C11*10+1 -> 100161 | I11: =IF(LEFT(C11,1)="1",IFERROR(IF(INDEX(单位卡分表!AG:AG,MATCH(C11,单位卡分表!A:A,0))=0,"",INDEX(单位卡分表!AG:AG,MATCH(C11,单位卡分表!A:A,0))),"未找到"),IF(LEFT(C11,1)="2",IFERROR(IF(INDEX(技能卡分表!AG:AG,MATCH(C11,技能卡分表!A:A,0))=0,"",INDEX(技能卡分表!AG:AG,MATCH(C11,技能卡分表!A:A,0))),"未找到"),IF(LEFT(C11,1)="3",IFERROR(IF(INDEX('永久加成分表（废弃）'!AF:AF,MATCH(C11,'永久加成分表（废弃）'!A:A,0))=0,"",INDEX('永久加成分表（废弃）'!AF:AF,MATCH(C11,'永久加成分表（废弃）'!A:A,0))),"未找到"),IF(LEFT(C11,1)="4",IFERROR(IF(INDEX(组件分表!R:R,MATCH(VALUE(LEFT(C11,4)),组件分表!A:A,0))=0,"",INDEX(组件分表!R:R,MATCH(VALUE(LEFT(C11,4)),组件分表!A:A,0))),"未找到"),"不匹配")))) -> CreatureAddShootCardSpeed | K11: =IF(LEFT(C11,1)="1",IFERROR(CHOOSE(MATCH(INDEX(单位卡分表!C:C,MATCH(C11,单位卡分表!A:A,0)),{1,4,6},0),"单位卡","英雄卡","雇佣兵卡"),""),"") -> 单位卡 | L11: 5 | M11: 45 | N11: 13.6 | O11: 0.65 | P11: 0.12 | Q11: 1.66 | R11: 1.47 | T11: =IFERROR(IF(LEFT(C11,1)="1",IF(INDEX(单位卡分表!AE:AE,MATCH(C11,单位卡分表!A:A,0))=0,"",INDEX(单位卡分表!AE:AE,MATCH(C11,单位卡分表!A:A,0))),IF(LEFT(C11,1)="2",IF(INDEX(技能卡分表!AE:AE,MATCH(C11,技能卡分表!A:A,0))=0,"",INDEX(技能卡分表!AE:AE,MATCH(C11,技能卡分表!A:A,0))),IF(LEFT(C11,1)="4",IF(INDEX(组件分表!W:W,MATCH(VALUE(LEFT(C11,4)),组件分表!A:A,0))=0,"",INDEX(组件分表!W:W,MATCH(VALUE(LEFT(C11,4)),组件分表!A:A,0))),""))),"") | U11: =IFERROR(IF(LEFT(C11,1)="1",IF(INDEX(单位卡分表!AF:AF,MATCH(C11,单位卡分表!A:A,0))=0,"",INDEX(单位卡分表!AF:AF,MATCH(C11,单位卡分表!A:A,0))),IF(LEFT(C11,1)="2",IF(INDEX(技能卡分表!AF:AF,MATCH(C11,技能卡分表!A:A,0))=0,"",INDEX(技能卡分表!AF:AF,MATCH(C11,技能卡分表!A:A,0))),IF(LEFT(C11,1)="4",IF(INDEX(组件分表!X:X,MATCH(VALUE(LEFT(C11,4)),组件分表!A:A,0))=0,"",INDEX(组件分表!X:X,MATCH(VALUE(LEFT(C11,4)),组件分表!A:A,0))),""))),"") | V11: FALSE | W11: 30
C12: 10017 | E12: =IF(LEFT(C12,1)="1",IFERROR(INDEX(单位卡分表!B:B,MATCH(C12,单位卡分表!A:A,0)),"未找到"),IF(LEFT(C12,1)="2",IFERROR(INDEX(技能卡分表!B:B,MATCH(C12,技能卡分表!A:A,0)),"未找到"),IF(LEFT(C12,1)="3",IFERROR(INDEX('永久加成分表（废弃）'!B:B,MATCH(C12,'永久加成分表（废弃）'!A:A,0)),"未找到"),IF(LEFT(C12,1)="4",IFERROR(INDEX(组件分表!C:C,MATCH(VALUE(LEFT(C12,4)),组件分表!A:A,0)),"未找到"),"不匹配")))) -> 电池 欧姆 | F12: =IF(LEFT(C12,1)="1",IFERROR(INDEX(单位卡分表!P:P,MATCH(C12,单位卡分表!A:A,0)),"未找到"),IF(LEFT(C12,1)="2",IFERROR(INDEX(技能卡分表!P:P,MATCH(C12,技能卡分表!A:A,0)),"未找到"),IF(LEFT(C12,1)="3",IFERROR(INDEX('永久加成分表（废弃）'!N:N,MATCH(C12,'永久加成分表（废弃）'!A:A,0)),"未找到"),IF(LEFT(C12,1)="4",IFERROR(INDEX(组件分表!L:L,MATCH(VALUE(LEFT(C12,4)),组件分表!A:A,0)),"未找到"),"不匹配")))) -> 在场时：我方每获得{0}次连击数，额外获得{1}次连击 | G12: =IF(LEFT(C12,1)="1",IFERROR(INDEX(单位卡分表!Q:Q,MATCH(C12,单位卡分表!A:A,0)),"未找到"),IF(LEFT(C12,1)="2",IFERROR(INDEX(技能卡分表!Q:Q,MATCH(C12,技能卡分表!A:A,0)),"未找到"),IF(LEFT(C12,1)="3",IFERROR(INDEX('永久加成分表（废弃）'!O:O,MATCH(C12,'永久加成分表（废弃）'!A:A,0)),"未找到"),IF(LEFT(C12,1)="4",IFERROR(INDEX(组件分表!S:S,MATCH(VALUE(LEFT(C12,4)),组件分表!A:A,0)),"未找到"),"不匹配")))) -> 多个欧姆不叠加 | H12: =C12*10+1 -> 100171 | I12: =IF(LEFT(C12,1)="1",IFERROR(IF(INDEX(单位卡分表!AG:AG,MATCH(C12,单位卡分表!A:A,0))=0,"",INDEX(单位卡分表!AG:AG,MATCH(C12,单位卡分表!A:A,0))),"未找到"),IF(LEFT(C12,1)="2",IFERROR(IF(INDEX(技能卡分表!AG:AG,MATCH(C12,技能卡分表!A:A,0))=0,"",INDEX(技能卡分表!AG:AG,MATCH(C12,技能卡分表!A:A,0))),"未找到"),IF(LEFT(C12,1)="3",IFERROR(IF(INDEX('永久加成分表（废弃）'!AF:AF,MATCH(C12,'永久加成分表（废弃）'!A:A,0))=0,"",INDEX('永久加成分表（废弃）'!AF:AF,MATCH(C12,'永久加成分表（废弃）'!A:A,0))),"未找到"),IF(LEFT(C12,1)="4",IFERROR(IF(INDEX(组件分表!R:R,MATCH(VALUE(LEFT(C12,4)),组件分表!A:A,0))=0,"",INDEX(组件分表!R:R,MATCH(VALUE(LEFT(C12,4)),组件分表!A:A,0))),"未找到"),"不匹配")))) -> AddEnergyForHeroAtRoundOver | K12: =IF(LEFT(C12,1)="1",IFERROR(CHOOSE(MATCH(INDEX(单位卡分表!C:C,MATCH(C12,单位卡分表!A:A,0)),{1,4,6},0),"单位卡","英雄卡","雇佣兵卡"),""),"") -> 单位卡 | L12: 3 | M12: 60 | N12: 13.6 | O12: 0.65 | P12: 0.12 | Q12: 1.66 | R12: 1.47 | T12: =IFERROR(IF(LEFT(C12,1)="1",IF(INDEX(单位卡分表!AE:AE,MATCH(C12,单位卡分表!A:A,0))=0,"",INDEX(单位卡分表!AE:AE,MATCH(C12,单位卡分表!A:A,0))),IF(LEFT(C12,1)="2",IF(INDEX(技能卡分表!AE:AE,MATCH(C12,技能卡分表!A:A,0))=0,"",INDEX(技能卡分表!AE:AE,MATCH(C12,技能卡分表!A:A,0))),IF(LEFT(C12,1)="4",IF(INDEX(组件分表!W:W,MATCH(VALUE(LEFT(C12,4)),组件分表!A:A,0))=0,"",INDEX(组件分表!W:W,MATCH(VALUE(LEFT(C12,4)),组件分表!A:A,0))),""))),"") | U12: =IFERROR(IF(LEFT(C12,1)="1",IF(INDEX(单位卡分表!AF:AF,MATCH(C12,单位卡分表!A:A,0))=0,"",INDEX(单位卡分表!AF:AF,MATCH(C12,单位卡分表!A:A,0))),IF(LEFT(C12,1)="2",IF(INDEX(技能卡分表!AF:AF,MATCH(C12,技能卡分表!A:A,0))=0,"",INDEX(技能卡分表!AF:AF,MATCH(C12,技能卡分表!A:A,0))),IF(LEFT(C12,1)="4",IF(INDEX(组件分表!X:X,MATCH(VALUE(LEFT(C12,4)),组件分表!A:A,0))=0,"",INDEX(组件分表!X:X,MATCH(VALUE(LEFT(C12,4)),组件分表!A:A,0))),""))),"") | V12: FALSE | W12: 6 | X12: 2
C13: 10018 | E13: =IF(LEFT(C13,1)="1",IFERROR(INDEX(单位卡分表!B:B,MATCH(C13,单位卡分表!A:A,0)),"未找到"),IF(LEFT(C13,1)="2",IFERROR(INDEX(技能卡分表!B:B,MATCH(C13,技能卡分表!A:A,0)),"未找到"),IF(LEFT(C13,1)="3",IFERROR(INDEX('永久加成分表（废弃）'!B:B,MATCH(C13,'永久加成分表（废弃）'!A:A,0)),"未找到"),IF(LEFT(C13,1)="4",IFERROR(INDEX(组件分表!C:C,MATCH(VALUE(LEFT(C13,4)),组件分表!A:A,0)),"未找到"),"不匹配")))) -> 萨克斯 莉莉（Lily was here） | F13: =IF(LEFT(C13,1)="1",IFERROR(INDEX(单位卡分表!P:P,MATCH(C13,单位卡分表!A:A,0)),"未找到"),IF(LEFT(C13,1)="2",IFERROR(INDEX(技能卡分表!P:P,MATCH(C13,技能卡分表!A:A,0)),"未找到"),IF(LEFT(C13,1)="3",IFERROR(INDEX('永久加成分表（废弃）'!N:N,MATCH(C13,'永久加成分表（废弃）'!A:A,0)),"未找到"),IF(LEFT(C13,1)="4",IFERROR(INDEX(组件分表!L:L,MATCH(VALUE(LEFT(C13,4)),组件分表!A:A,0)),"未找到"),"不匹配")))) -> 我方回合：每有我方单位离场时，我方英雄回复{0}点生命 | G13: =IF(LEFT(C13,1)="1",IFERROR(INDEX(单位卡分表!Q:Q,MATCH(C13,单位卡分表!A:A,0)),"未找到"),IF(LEFT(C13,1)="2",IFERROR(INDEX(技能卡分表!Q:Q,MATCH(C13,技能卡分表!A:A,0)),"未找到"),IF(LEFT(C13,1)="3",IFERROR(INDEX('永久加成分表（废弃）'!O:O,MATCH(C13,'永久加成分表（废弃）'!A:A,0)),"未找到"),IF(LEFT(C13,1)="4",IFERROR(INDEX(组件分表!S:S,MATCH(VALUE(LEFT(C13,4)),组件分表!A:A,0)),"未找到"),"不匹配")))) -> （死亡，被吞噬，雇佣兵都算），被吞噬后，被吞噬单位死亡，只算一次离场（因为吞噬已经算离场了） | H13: =C13*10+1 -> 100181 | I13: =IF(LEFT(C13,1)="1",IFERROR(IF(INDEX(单位卡分表!AG:AG,MATCH(C13,单位卡分表!A:A,0))=0,"",INDEX(单位卡分表!AG:AG,MATCH(C13,单位卡分表!A:A,0))),"未找到"),IF(LEFT(C13,1)="2",IFERROR(IF(INDEX(技能卡分表!AG:AG,MATCH(C13,技能卡分表!A:A,0))=0,"",INDEX(技能卡分表!AG:AG,MATCH(C13,技能卡分表!A:A,0))),"未找到"),IF(LEFT(C13,1)="3",IFERROR(IF(INDEX('永久加成分表（废弃）'!AF:AF,MATCH(C13,'永久加成分表（废弃）'!A:A,0))=0,"",INDEX('永久加成分表（废弃）'!AF:AF,MATCH(C13,'永久加成分表（废弃）'!A:A,0))),"未找到"),IF(LEFT(C13,1)="4",IFERROR(IF(INDEX(组件分表!R:R,MATCH(VALUE(LEFT(C13,4)),组件分表!A:A,0))=0,"",INDEX(组件分表!R:R,MATCH(VALUE(LEFT(C13,4)),组件分表!A:A,0))),"未找到"),"不匹配")))) -> CauseDamageWhenKillEnemy | K13: =IF(LEFT(C13,1)="1",IFERROR(CHOOSE(MATCH(INDEX(单位卡分表!C:C,MATCH(C13,单位卡分表!A:A,0)),{1,4,6},0),"单位卡","英雄卡","雇佣兵卡"),""),"") -> 单位卡 | L13: 5 | M13: 42 | N13: 13.6 | O13: 0.65 | P13: 0.12 | Q13: 1.66 | R13: 1.47 | T13: =IFERROR(IF(LEFT(C13,1)="1",IF(INDEX(单位卡分表!AE:AE,MATCH(C13,单位卡分表!A:A,0))=0,"",INDEX(单位卡分表!AE:AE,MATCH(C13,单位卡分表!A:A,0))),IF(LEFT(C13,1)="2",IF(INDEX(技能卡分表!AE:AE,MATCH(C13,技能卡分表!A:A,0))=0,"",INDEX(技能卡分表!AE:AE,MATCH(C13,技能卡分表!A:A,0))),IF(LEFT(C13,1)="4",IF(INDEX(组件分表!W:W,MATCH(VALUE(LEFT(C13,4)),组件分表!A:A,0))=0,"",INDEX(组件分表!W:W,MATCH(VALUE(LEFT(C13,4)),组件分表!A:A,0))),""))),"") | U13: =IFERROR(IF(LEFT(C13,1)="1",IF(INDEX(单位卡分表!AF:AF,MATCH(C13,单位卡分表!A:A,0))=0,"",INDEX(单位卡分表!AF:AF,MATCH(C13,单位卡分表!A:A,0))),IF(LEFT(C13,1)="2",IF(INDEX(技能卡分表!AF:AF,MATCH(C13,技能卡分表!A:A,0))=0,"",INDEX(技能卡分表!AF:AF,MATCH(C13,技能卡分表!A:A,0))),IF(LEFT(C13,1)="4",IF(INDEX(组件分表!X:X,MATCH(VALUE(LEFT(C13,4)),组件分表!A:A,0))=0,"",INDEX(组件分表!X:X,MATCH(VALUE(LEFT(C13,4)),组件分表!A:A,0))),""))),"") | V13: FALSE | W13: 10
C14: 10019 | E14: =IF(LEFT(C14,1)="1",IFERROR(INDEX(单位卡分表!B:B,MATCH(C14,单位卡分表!A:A,0)),"未找到"),IF(LEFT(C14,1)="2",IFERROR(INDEX(技能卡分表!B:B,MATCH(C14,技能卡分表!A:A,0)),"未找到"),IF(LEFT(C14,1)="3",IFERROR(INDEX('永久加成分表（废弃）'!B:B,MATCH(C14,'永久加成分表（废弃）'!A:A,0)),"未找到"),IF(LEFT(C14,1)="4",IFERROR(INDEX(组件分表!C:C,MATCH(VALUE(LEFT(C14,4)),组件分表!A:A,0)),"未找到"),"不匹配")))) -> 电池 焦耳 | F14: =IF(LEFT(C14,1)="1",IFERROR(INDEX(单位卡分表!P:P,MATCH(C14,单位卡分表!A:A,0)),"未找到"),IF(LEFT(C14,1)="2",IFERROR(INDEX(技能卡分表!P:P,MATCH(C14,技能卡分表!A:A,0)),"未找到"),IF(LEFT(C14,1)="3",IFERROR(INDEX('永久加成分表（废弃）'!N:N,MATCH(C14,'永久加成分表（废弃）'!A:A,0)),"未找到"),IF(LEFT(C14,1)="4",IFERROR(INDEX(组件分表!L:L,MATCH(VALUE(LEFT(C14,4)),组件分表!A:A,0)),"未找到"),"不匹配")))) -> 在场时：我方所有爆炸伤害增加{0}% | G14: =IF(LEFT(C14,1)="1",IFERROR(INDEX(单位卡分表!Q:Q,MATCH(C14,单位卡分表!A:A,0)),"未找到"),IF(LEFT(C14,1)="2",IFERROR(INDEX(技能卡分表!Q:Q,MATCH(C14,技能卡分表!A:A,0)),"未找到"),IF(LEFT(C14,1)="3",IFERROR(INDEX('永久加成分表（废弃）'!O:O,MATCH(C14,'永久加成分表（废弃）'!A:A,0)),"未找到"),IF(LEFT(C14,1)="4",IFERROR(INDEX(组件分表!S:S,MATCH(VALUE(LEFT(C14,4)),组件分表!A:A,0)),"未找到"),"不匹配")))) -> 0 | H14: =C14*10+1 -> 100191 | I14: =IF(LEFT(C14,1)="1",IFERROR(IF(INDEX(单位卡分表!AG:AG,MATCH(C14,单位卡分表!A:A,0))=0,"",INDEX(单位卡分表!AG:AG,MATCH(C14,单位卡分表!A:A,0))),"未找到"),IF(LEFT(C14,1)="2",IFERROR(IF(INDEX(技能卡分表!AG:AG,MATCH(C14,技能卡分表!A:A,0))=0,"",INDEX(技能卡分表!AG:AG,MATCH(C14,技能卡分表!A:A,0))),"未找到"),IF(LEFT(C14,1)="3",IFERROR(IF(INDEX('永久加成分表（废弃）'!AF:AF,MATCH(C14,'永久加成分表（废弃）'!A:A,0))=0,"",INDEX('永久加成分表（废弃）'!AF:AF,MATCH(C14,'永久加成分表（废弃）'!A:A,0))),"未找到"),IF(LEFT(C14,1)="4",IFERROR(IF(INDEX(组件分表!R:R,MATCH(VALUE(LEFT(C14,4)),组件分表!A:A,0))=0,"",INDEX(组件分表!R:R,MATCH(VALUE(LEFT(C14,4)),组件分表!A:A,0))),"未找到"),"不匹配")))) -> AddEnergyWhenKillEnemy | K14: =IF(LEFT(C14,1)="1",IFERROR(CHOOSE(MATCH(INDEX(单位卡分表!C:C,MATCH(C14,单位卡分表!A:A,0)),{1,4,6},0),"单位卡","英雄卡","雇佣兵卡"),""),"") -> 单位卡 | L14: 6 | M14: 36 | N14: 13.6 | O14: 0.65 | P14: 0.12 | Q14: 1.66 | R14: 1.47 | T14: =IFERROR(IF(LEFT(C14,1)="1",IF(INDEX(单位卡分表!AE:AE,MATCH(C14,单位卡分表!A:A,0))=0,"",INDEX(单位卡分表!AE:AE,MATCH(C14,单位卡分表!A:A,0))),IF(LEFT(C14,1)="2",IF(INDEX(技能卡分表!AE:AE,MATCH(C14,技能卡分表!A:A,0))=0,"",INDEX(技能卡分表!AE:AE,MATCH(C14,技能卡分表!A:A,0))),IF(LEFT(C14,1)="4",IF(INDEX(组件分表!W:W,MATCH(VALUE(LEFT(C14,4)),组件分表!A:A,0))=0,"",INDEX(组件分表!W:W,MATCH(VALUE(LEFT(C14,4)),组件分表!A:A,0))),""))),"") | U14: =IFERROR(IF(LEFT(C14,1)="1",IF(INDEX(单位卡分表!AF:AF,MATCH(C14,单位卡分表!A:A,0))=0,"",INDEX(单位卡分表!AF:AF,MATCH(C14,单位卡分表!A:A,0))),IF(LEFT(C14,1)="2",IF(INDEX(技能卡分表!AF:AF,MATCH(C14,技能卡分表!A:A,0))=0,"",INDEX(技能卡分表!AF:AF,MATCH(C14,技能卡分表!A:A,0))),IF(LEFT(C14,1)="4",IF(INDEX(组件分表!X:X,MATCH(VALUE(LEFT(C14,4)),组件分表!A:A,0))=0,"",INDEX(组件分表!X:X,MATCH(VALUE(LEFT(C14,4)),组件分表!A:A,0))),""))),"") | V14: FALSE | W14: 200
